Workbook

Sheet Costo Rosquete
E1: Precio Local | F1: Costo MP | G1: Costo EM | H1: Costo MO
E2: =IFERROR(O36,"") -> 1253.9205 | F2: =IFERROR(H25,"") -> 869.70131 | G2: =IFERROR(H26,"") -> 15.670689 | H2: =IFERROR(H28,"") -> 72.614729
A4: ROSQUETE CHOCOLATE PASTELERO REAL 800G
A5: ESTRUCTURA DE COSTOS
F6: Fecha: | H6: =TODAY() -> 45938
A7: UNIDADES | B7: MATERIA PRIMA SEMIELABORADOS | C7: UNIDADES | D7: UND MEDIDA | E7: COSTO UNITARIO | F7: TOTAL COSTO | G7: % PREC. DEFINIDO | H7: CODIGOS
A8: 1500 | B8: =IFERROR(VLOOKUP($H8,[1]SEMIELABORADOS!$A$2:$J$500,2,0),"") -> MEZCLA ENGRASE MOLDES (29800g) | C8: =+A8 -> 1500 | D8: =IFERROR(VLOOKUP($H8,[1]SEMIELABORADOS!$A$2:$J$500,4,0),"") -> GRAMO | E8: =IFERROR(VLOOKUP($H8,[1]SEMIELABORADOS!$A$2:$J$500,6,0),"") -> 0.86845386 | F8: =IFERROR(E8*C8,"") -> 1302.6808 | G8: =IFERROR(F8/$F$38,"") -> 0.02320995 | H8: 95720
A9: 48100 | B9: =IFERROR(VLOOKUP($H9,[1]SEMIELABORADOS!$A$2:$J$500,2,0),"") -> BATIDO P/ROSQUETE CHOCOLATE BUCCA (11475g) | C9: =+A9 -> 48100 | D9: =IFERROR(VLOOKUP($H9,[1]SEMIELABORADOS!$A$2:$J$500,4,0),"") -> GRAMO | E9: =IFERROR(VLOOKUP($H9,[1]SEMIELABORADOS!$A$2:$J$500,6,0),"") -> 1.0577837 | F9: =IFERROR(E9*C9,"") -> 50879.398 | G9: =IFERROR(F9/$F$38,"") -> 0.90652163 | H9: 96296
A11: UNIDADES | B11: EMPAQUE | C11: UNIDADES | D11: UND MEDIDA | E11: COSTO UNITARIO | F11: TOTAL COSTO | G11: % PREC. DEFINIDO | H11: CODIGOS
A12: 15 | B12: =IFERROR(VLOOKUP($H12,'[1]EMP PLANTA'!$A$2:$F$500,2,0),"") -> BOLSA TRANSPARENTE 56X96X1.80 | C12: =+A12 -> 15 | D12: =IFERROR(VLOOKUP($H12,'[1]EMP PLANTA'!$A$2:$F$500,5,0),"") -> UND | E12: =IFERROR(VLOOKUP($H12,'[1]EMP PLANTA'!$A$2:$F$500,6,0),"") -> 50 | F12: =IFERROR(E12*C12,"") -> 750 | G12: =IFERROR(F12/$F$38,"") -> 0.0133628 | H12: 1950928
A13: 15 | B13: =IFERROR(VLOOKUP($H13,'[1]EMP PLANTA'!$A$2:$F$500,2,0),"") -> ETIQUETA BLANCA 2 5/8X1 15/16 PRE BLANCA | C13: =+A13 -> 15 | D13: =IFERROR(VLOOKUP($H13,'[1]EMP PLANTA'!$A$2:$F$500,5,0),"") -> UND | E13: =IFERROR(VLOOKUP($H13,'[1]EMP PLANTA'!$A$2:$F$500,6,0),"") -> 2.276 | F13: =IFERROR(E13*C13,"") -> 34.14 | G13: =IFERROR(F13/$F$38,"") -> 0.00060827466 | H13: 0702123
A14: 15 | B14: =IFERROR(VLOOKUP($H14,'[1]EMP PLANTA'!$A$2:$F$500,2,0),"") -> ETIQ.FECHA VENCIMIENTO BLANCO | C14: =+A14 -> 15 | D14: =IFERROR(VLOOKUP($H14,'[1]EMP PLANTA'!$A$2:$F$500,5,0),"") -> UND | E14: =IFERROR(VLOOKUP($H14,'[1]EMP PLANTA'!$A$2:$F$500,6,0),"") -> 0.22878 | F14: =IFERROR(E14*C14,"") -> 3.4317 | G14: =IFERROR(F14/$F$38,"") -> 6.1142828e-05 | H14: 0702007
A16: UNIDADES | B16: EMPAQUE SEMIELABORADOS | C16: UNIDADES | D16: UND MEDIDA | E16: COSTO UNITARIO | F16: TOTAL COSTO | G16: % PREC. DEFINIDO | H16: CODIGOS
A17: =+A8 -> 1500 | B17: EMPAQUE ENGRASE MOLDES PLANTA | C17: =+A17 -> 1500 | D17: N/A | E17: =IFERROR(VLOOKUP($H17,[1]SEMIELABORADOS!$A$2:$J$500,8,0),"") -> 0.011341301 | F17: =IFERROR(E17*C17,"") -> 17.011951 | G17: =IFERROR(F17/$F$37,"") -> 0.0086795668 | H17: 95720
A18: =+A9 -> 48100 | B18: EMPAQUE ENGRASE MOLDES PLANTA | C18: =+A18 -> 48100 | D18: N/A | E18: =IFERROR(VLOOKUP($H18,[1]SEMIELABORADOS!$A$2:$J$500,8,0),"") -> 0.0028203258 | F18: =IFERROR(E18*C18,"") -> 135.65767 | G18: =IFERROR(F18/$F$37,"") -> 0.069213098 | H18: 96296
A20: UNIDADES | B20: MODI | C20: UNIDADES | E20: COSTO UNITARIO | F20: TOTAL COSTO | G20: % PREC. DEFINIDO | H20: CODIGOS
A21: =+A8 -> 1500 | B21: MODIENGRASE MOLDES | C21: =+A21 -> 1500 | D21: N/A | E21: =IFERROR(VLOOKUP($H21,[1]SEMIELABORADOS!$A$2:$J$500,10,0),"") -> 0.055369128 | F21: =IFERROR(C21*E21,"") -> 83.053691 | G21: =IFERROR(F21/$F$38,"") -> 0.0014797732 | H21: 95720
A22: =+A9 -> 48100 | B22: MODIENGRASE MOLDES | C22: =+A22 -> 48100 | D22: N/A | E22: =IFERROR(VLOOKUP($H22,[1]SEMIELABORADOS!$A$2:$J$500,10,0),"") -> 0.048104575 | F22: =IFERROR(C22*E22,"") -> 2313.8301 | G22: =IFERROR(F22/$F$38,"") -> 0.041225665 | H22: 96296
A23: 1 | B23: MODI PREPARACION | C23: =+A23 -> 1 | D23: N/A | E23: =+F37 -> 1960 | F23: =IFERROR(C23*E23,"") -> 1960 | G23: =IFERROR(F23/$F$38,"") -> 0.034921451
B25: TOTAL MATERIA PRIMA | F25: =SUM(F8:F9) -> 52182.079 | G25: =+F25/$F$38 -> 0.92973158 | H25: =+F25/$D$32 -> 869.70131
B26: TOTAL EMPAQUE | F26: =SUM(F12:F14,F17:F18) -> 940.24132 | G26: =+F26/$F$38 -> 0.016752342 | H26: =+F26/$D$32 -> 15.670689 | K26: TOTAL MATERIA PRIMA + EMPAQUE | O26: =+F27 -> 53122.32
B27: TOTAL MATERIAS P. + EMPAQUES | F27: =+F25+F26 -> 53122.32 | G27: =+F27/$F$38 -> 0.94648392 | H27: =+F27/$D$32 -> 885.372 | L27: MODI PLANTA | O27: =+F28 -> 4356.8838
C28: TOTAL MODI | F28: =SUM(F21:F23) -> 4356.8838 | G28: =+F28/$F$38 -> 0.077626888 | H28: =+F28/$D$32 -> 72.614729 | L28: DESECHO | N28: 0.02 | O28: =+(O26+O27)*N28 -> 1149.5841
L29: GAF | N29: =230%*0.85 -> 1.955 | O29: =+O27*N29 -> 8517.7077
B30: GRAMOS | D30: 48000 | M30: COSTO PLANTA | O30: =SUM(O26:O29) -> 67146.496
B31: PESO POR UNIDAD | D31: 800 | L31: LOGISTICA | N31: 0.25 | O31: =+($O$27+$O$29)*N31 -> 3218.6479
B32: UNIDADES TOTALES | D32: =+D30/D31 -> 60 | M32: ADMINISTRACION | N32: 0.1 | O32: =+($O$27+$O$29)*N32 -> 1287.4592
B33: UNIDAD EMPAQUE | D33: UND | L33: COSTO TOTAL | O33: =SUM(O30:O32) -> 71652.603
E34: S/ COSTO | F34: TOTAL | L34: TRANSFERENCIA | N34: 0.05 | O34: =+O33*N34 -> 3582.6301
B35: TOTAL MATERIAS P. + EMPAQUES | E35: =+F35/F35 -> 1 | F35: =SUM(F27) -> 53122.32 | G35: =+F35/$F$38 -> 0.94648392 | K35: PRECIO DE VENTA PLANTA A LOCAL | O35: =SUM(O33:O34) -> 75235.233 | P35: GR
B36: DESECHOS Y PERDIDAS | E36: 0.02 | F36: =+F25*E36 -> 1043.6416 | G36: =+F36/$F$38 -> 0.018594632 | L36: UNIDAD | O36: =+O35/D32 -> 1253.9205 | P36: =+O36/D31 -> 1.5674007
B37: MANO OBRA DIRECTA | D37: 35 | E37: 56 | F37: =+E37*D37 -> 1960 | G37: =+F37/$F$38 -> 0.034921451
B38: TOTAL COSTO PLANTA | F38: =SUM(F35:F37) -> 56125.962 | G38: =+F38/$F$38 -> 1
B40: COSTO POR GRAMO
B41: TOTAL COSTO MATERIA PRIMA | C41: =+F25 -> 52182.079 | D41: =+D30 -> 48000 | E41: =+C41/D41 -> 1.0871266
B43: TOTAL COSTO UNIDAD MP+DESECHO+EMPAQUE | C43: =SUM(F35:F36) -> 54165.962 | D43: =+D30 -> 48000 | E43: =+C43/D43 -> 1.1284575
B45: TOTAL MODI PREPARACION POR GRAMO | C45: =+F37 -> 1960 | D45: =+D30 -> 48000 | E45: =+C45/D45 -> 0.040833333
B46: TOTAL MODI POR GRAMO | C46: =+F28 -> 4356.8838 | D46: =+D45 -> 48000 | E46: =+C46/D46 -> 0.090768412
B48: TOTAL EMPAQUE POR GRAMO | C48: =+F26 -> 940.24132 | D48: =+D46 -> 48000 | E48: =+C48/D48 -> 0.019588361
B50: TOTAL GRAMO MP+MODI | E50: =+E41+E46 -> 1.1778951
B52: COSTO POR UNIDAD
B53: TOTAL COSTO MATERIA PRIMA | C53: =+C41 -> 52182.079 | D53: =+D32 -> 60 | E53: =+C53/D53 -> 869.70131
B55: TOTAL COSTO UNIDAD MP+DESECHO+EMPAQUE | C55: =+C43 -> 54165.962 | D55: =+D32 -> 60 | E55: =+C55/D55 -> 902.76603
B57: TOTAL MODI POR GRAMO | C57: =+C45 -> 1960 | D57: =+D32 -> 60 | E57: =+C57/D57 -> 32.666667
B58: TOTAL MODI POR GRAMO | C58: =+C46 -> 4356.8838 | D58: =+D57 -> 60 | E58: =+C58/D58 -> 72.614729

Sheet Hoja1
C1: SERVICIOS DE PASTELERIA S.A. | H1: CÓDIGO: | I1: ESP-RE-FIF-006
C2: ESPECIFICACION DE RECETA | H2: REVISIÓN: | I2: 02
C3: PTI00033 Torta Chocolate(1100g) 10 porc FAS (porcionada) | H3: FECHA DE APROBACIÓN: | I3: 45609
C4: Elaborado | D4: Javier Tong, Chef
C5: Aprobado | D5: Esteban Cartin, Gte Manufactura
A6: AREA QUE PRODUCE: | D6: Figuras | G6: AREA QUE EMPACA: | I6: Figuras
A7: # Código | B7: # Código Netsuite | C7: Descripción del ingrediente | D7: Marca | E7: Unidad Internacional | G7: Medida alternativa | I7: Costo - Referencia
E8: Cantidad | F8: Unidad medida | G8: Cantidad | H8: Unidad medida | I8: Colones
C9: Ensamble
A10: 907000291 | B10: SE00441 | C10: ROSQUETE EASY CHOCOLATE BC 800G | D10: FAS | E10: 755 | F10: g
A11: 11700002 | B11: MP10176 | C11: DULCE DE LECHE SUAVE F2 ( 5 KG ) | D11: LA CIABATTA | E11: 285 | F11: g | H11: 1 TAZA
A12: 95718 | B12: SE00024 | C12: CREMA CHANTILLY CHOCO (SPOON-IND)(24875g) | D12: FAS | E12: 100 | F12: g
A13: 11400027 | B13: MP10006 | C13: CREMA BETTERCREAM DOBLE CHOCO (UND:4 K) | D13: RICHS | E13: 20 | F13: g
B14: MP10709 | C14: SPRINKLES CHOCO | E14: 10 | F14: g
C20: Decoración
C26: Empaque
A27: 51400015 | B27: EM10023 | C27: QUEQUERA CHILENA (CAJA:50 UND) | D27: EXPORT PMT | E27: 1 | F27: ud
A28: 1950692 | B28: EM10008 | C28: ORLA CARTON 10" DORADA UND | D28: ESTUARDO | E28: 1 | F28: ud
A29: 1950772 | B29: EM10090 | C29: PAPEL ENCERADO 12 X 10 (CAJA) | D29: LOGAN | E29: 2 | F29: ud
A30: 703020 | B30: EM10248 | C30: CINTA ADHESIVA TRANSPARENTE 2*100 MTS | D30: MAYCA | E30: 30 | F30: cm
A31: 0702069 | B31: EM10002 | C31: ETIQ.BLANCA 1 1/4 * 3/4 | D31: ETIPLAS | E31: 1 | F31: ud
A32: 701096 | B32: EM10124 | C32: Etiqueta Blanca R-153 | D32: ETIPLAS | E32: 1 | F32: ud
A33: 702123 | B33: EM10011 | C33: ETIQUETA BLANCA 2 5/8X1 15/16 | E33: 1 | F33: ud
A34: 1952871 | B34: EM10062 | C34: CAJA PRALINE UND | E34: 1 | F34: ud
A35: 703020 | B35: EM10248 | C35: CINTA ADHESIVA TRANSPARENTE 2*100 MTS | D35: MAYCA | E35: 100 | F35: cm
D38: Cantidad | E38: Unidad
A39: PESO TOTAL OBTENIDO | D39: 1100 | E39: g | F39: Tiempo de Horneo:
A40: TIEMPO TOTAL DE PREPARACION | D40: 9 | E40: min | F40: Horno:
A41: CANTIDAD DE PORCIONES OBTENIDAS | D41: 1 | E41: ud | F41: Temperatura de Horneo:
A42: PESO DE CADA PORCIÓN | D42: 1100 | E42: g | F42: Otros
A43: MERMA | D43: 70 | E43: g
A44: PROCEDIMIENTO DE PREPARACION DE LA RECETA
A45: 1- Hacer un corte transversal al rosquete por la mitad, colocar 1/2 rosquete en la orla, pegado con dulce de leche.
A46: 2- Distribuir 1 tazas de manjar en el rosquete y colocar la otra mitad del rosquete.
A47: 3- Tapizar la torta con crema de chocolate y peinar los costados. Colcoar Sirope de chocolate en la superficie y con ayuda de una espatula formar un espiral en toda la superficie
A48: 5- Porcionar en 10
A49: 6- Cortar el papel encerado en 6 rectangulos (1ro por la mitas y de cada mitad cortar 3 cuadros), doblar por la mitad e introducir uno en cada porcion.
A50: 7- Distribuir el cofetti de chocolate en el borde de las porciones.
A51: 8- Tapar y etiquetar con nombre, fecha de vencimiento en congelado , etiqueta con dia juliano.
A52: 9.- Introducir en caja Praline, etiquetar con nombre, fecha vencimiento en congelado, # juliano
A56: CONTROL DE CAMBIOS
A57: Revision #2: Cambio en el codigo de los palitos de chocolate.

Sheet costo
E1: Precio Local | F1: Costo MP | G1: Costo EM | H1: Costo MO
E2: =IFERROR(O71,"") -> 5439.3879 | F2: =IFERROR(H62,"") -> 1799.7911 | G2: =IFERROR(H63,"") -> 1603.4645 | H2: =IFERROR(H65,"") -> 707.00745
A5: ESTRUCTURA DE COSTOS
F6: Fecha: | H6: =TODAY() -> 45938
A7: UNIDADES | B7: DESCRIPCION MAT.PRIMA | C7: UNIDADES | D7: UND MEDIDA | E7: COSTO UNITARIO | F7: TOTAL COSTO | G7: % PREC. DEFINIDO | H7: CODIGOS
A8: 285 | B8: =IFERROR(VLOOKUP(H8,'[2]Consolidado MP Planta'!$A$2:$M$823,3,0),"") -> DULCE LECHE LA CIABATA (UND:5 K ) | C8: =+A8 -> 285 | D8: =IFERROR(VLOOKUP(H8,'[2]Consolidado MP Planta'!$A$2:$M$823,13,0),"") -> Gramos | E8: =IFERROR(VLOOKUP(H8,'[2]Consolidado MP Planta'!$A$2:$M$823,12,0),"") -> 1.685 | F8: =IFERROR(C8*E8,"") -> 480.225 | G8: =IFERROR(F8/$F$75,"") -> 0.12206261 | H8: 11700002
A9: 40 | B9: =IFERROR(VLOOKUP(H9,'[2]Consolidado MP Planta'!$A$2:$M$823,3,0),"") -> SIROPE CHOCOLATE HERSHEY (UND:24 ONZ) | C9: =+A9 -> 40 | D9: Gramos | E9: 3.16 | F9: =IFERROR(C9*E9,"") -> 126.4 | G9: =IFERROR(F9/$F$75,"") -> 0.032128095 | H9: 1010047
A10: 10 | B10: =IFERROR(VLOOKUP(H10,'[2]Consolidado MP Planta'!$A$2:$M$823,3,0),"") -> CONFITE PALITO CHOCOLATE (PAQ:680 G) | C10: =+A10 -> 10 | D10: =IFERROR(VLOOKUP(H10,'[2]Consolidado MP Planta'!$A$2:$M$823,13,0),"") -> Gramos | E10: =IFERROR(VLOOKUP(H10,'[2]Consolidado MP Planta'!$A$2:$M$823,12,0),"") -> 2.9014706 | F10: =IFERROR(C10*E10,"") -> 29.014706 | G10: =IFERROR(F10/$F$75,"") -> 0.0073748989 | H10: 10700008
B11: =IFERROR(VLOOKUP(H11,'[2]Consolidado MP Planta'!$A$2:$M$823,3,0),"") | C11: =+A11 -> 0 | D11: =IFERROR(VLOOKUP(H11,'[2]Consolidado MP Planta'!$A$2:$M$823,13,0),"") | E11: =IFERROR(VLOOKUP(H11,'[2]Consolidado MP Planta'!$A$2:$M$823,12,0),"") | F11: =IFERROR(C11*E11,"") | G11: =IFERROR(F11/$F$75,"")
B12: =IFERROR(VLOOKUP(H12,'[2]Consolidado MP Planta'!$A$2:$M$823,3,0),"") | C12: =+A12 -> 0 | D12: =IFERROR(VLOOKUP(H12,'[2]Consolidado MP Planta'!$A$2:$M$823,13,0),"") | E12: =IFERROR(VLOOKUP(H12,'[2]Consolidado MP Planta'!$A$2:$M$823,12,0),"") | F12: =IFERROR(C12*E12,"") | G12: =IFERROR(F12/$F$75,"")
B13: =IFERROR(VLOOKUP(H13,'[2]Consolidado MP Planta'!$A$2:$M$823,3,0),"") | C13: =+A13 -> 0 | D13: =IFERROR(VLOOKUP(H13,'[2]Consolidado MP Planta'!$A$2:$M$823,13,0),"") | E13: =IFERROR(VLOOKUP(H13,'[2]Consolidado MP Planta'!$A$2:$M$823,12,0),"") | F13: =IFERROR(C13*E13,"") | G13: =IFERROR(F13/$F$75,"")
B14: =IFERROR(VLOOKUP(H14,'[2]Consolidado MP Planta'!$A$2:$M$823,3,0),"") | C14: =+A14 -> 0 | D14: =IFERROR(VLOOKUP(H14,'[2]Consolidado MP Planta'!$A$2:$M$823,13,0),"") | E14: =IFERROR(VLOOKUP(H14,'[2]Consolidado MP Planta'!$A$2:$M$823,12,0),"") | F14: =IFERROR(C14*E14,"") | G14: =IFERROR(F14/$F$75,"")
B15: =IFERROR(VLOOKUP(H15,'[3]ARTICULOS MP PLANTA'!$A$2:$G$589,2,0),"")
A16: UNIDADES | B16: MATERIA PRIMA SEMIELABORADOS | C16: UNIDADES | D16: UND MEDIDA | E16: COSTO UNITARIO | F16: TOTAL COSTO | G16: % PREC. DEFINIDO | H16: CODIGOS
A17: 1 | B17: =IFERROR(VLOOKUP(H17,[2]SEMIELABORADOS!$A$2:$M$6000,2,0),"") -> ROSQUETE CHOCOLATE BUCCA 800 g | C17: =+A17 -> 1 | D17: =IFERROR(VLOOKUP(H17,[2]SEMIELABORADOS!$A$2:$M$6000,6,0),"") -> Und | E17: =IFERROR(VLOOKUP(H17,[2]SEMIELABORADOS!$A$2:$H$65536,8,0),"") -> 892.79828 | F17: =IFERROR(E17*C17,"") -> 892.79828 | G17: =IFERROR(F17/$F$75,"") -> 0.22692965 | H17: 907000226
A18: 100 | B18: =IFERROR(VLOOKUP(H18,[2]SEMIELABORADOS!$A$2:$M$6000,2,0),"") -> CREMA CHANTILLY CHOCO SPOON KILO | C18: =+A18 -> 100 | D18: =IFERROR(VLOOKUP(H18,[2]SEMIELABORADOS!$A$2:$M$6000,6,0),"") -> Gramo | E18: =IFERROR(VLOOKUP(H18,[2]SEMIELABORADOS!$A$2:$H$65536,8,0),"") -> 2.7135307 | F18: =IFERROR(E18*C18,"") -> 271.35307 | G18: =IFERROR(F18/$F$75,"") -> 0.06897197 | H18: 95718
B19: =IFERROR(VLOOKUP(H19,[2]SEMIELABORADOS!$A$2:$M$6000,2,0),"") | C19: =+A19 -> 0 | D19: =IFERROR(VLOOKUP(H19,[2]SEMIELABORADOS!$A$2:$M$6000,6,0),"") | E19: =IFERROR(VLOOKUP(H19,[2]SEMIELABORADOS!$A$2:$H$65536,8,0),"") | F19: =IFERROR(E19*C19,"") | G19: =IFERROR(F19/$F$75,"")
B20: =IFERROR(VLOOKUP(H20,[2]SEMIELABORADOS!$A$2:$M$6000,2,0),"") | C20: =+A20 -> 0 | D20: =IFERROR(VLOOKUP(H20,[2]SEMIELABORADOS!$A$2:$M$6000,6,0),"") | E20: =IFERROR(VLOOKUP(H20,[2]SEMIELABORADOS!$A$2:$H$65536,8,0),"") | F20: =IFERROR(E20*C20,"") | G20: =IFERROR(F20/$F$75,"")
B21: =IFERROR(VLOOKUP(H21,[2]SEMIELABORADOS!$A$2:$M$6000,2,0),"") | C21: =+A21 -> 0 | D21: =IFERROR(VLOOKUP(H21,[2]SEMIELABORADOS!$A$2:$M$6000,6,0),"") | E21: =IFERROR(VLOOKUP(H21,[2]SEMIELABORADOS!$A$2:$H$65536,8,0),"") | F21: =IFERROR(E21*C21,"") | G21: =IFERROR(F21/$F$75,"")
B22: =IFERROR(VLOOKUP(H22,[2]SEMIELABORADOS!$A$2:$M$6000,2,0),"") | C22: =+A22 -> 0 | D22: =IFERROR(VLOOKUP(H22,[2]SEMIELABORADOS!$A$2:$M$6000,6,0),"") | E22: =IFERROR(VLOOKUP(H22,[2]SEMIELABORADOS!$A$2:$H$65536,8,0),"") | F22: =IFERROR(E22*C22,"") | G22: =IFERROR(F22/$F$75,"")
B23: =IFERROR(VLOOKUP(H23,[2]SEMIELABORADOS!$A$2:$M$6000,2,0),"") | C23: =+A23 -> 0 | D23: =IFERROR(VLOOKUP(H23,[2]SEMIELABORADOS!$A$2:$M$6000,6,0),"") | E23: =IFERROR(VLOOKUP(H23,[2]SEMIELABORADOS!$A$2:$H$65536,8,0),"") | F23: =IFERROR(E23*C23,"") | G23: =IFERROR(F23/$F$75,"")
B24: =IFERROR(VLOOKUP(H24,[2]SEMIELABORADOS!$A$2:$M$6000,2,0),"") | C24: =+A24 -> 0 | D24: =IFERROR(VLOOKUP(H24,[2]SEMIELABORADOS!$A$2:$M$6000,6,0),"") | E24: =IFERROR(VLOOKUP(H24,[2]SEMIELABORADOS!$A$2:$H$65536,8,0),"") | F24: =IFERROR(E24*C24,"") | G24: =IFERROR(F24/$F$75,"")
A26: UNIDADES | B26: EMPAQUE | C26: UNIDADES | D26: UND MEDIDA | E26: COSTO UNITARIO | F26: TOTAL COSTO | G26: % PREC. DEFINIDO | H26: CODIGOS
A27: 1 | B27: =IFERROR(VLOOKUP(H27,'[2]Consolidado MP Planta'!$A$2:$M$823,3,0),"") -> QUEQUERA CHILENA (CAJA:50 UND) | C27: =+A27 -> 1 | D27: =IFERROR(VLOOKUP(H27,'[2]Consolidado MP Planta'!$A$2:$M$823,13,0),"") -> Und | E27: =IFERROR(VLOOKUP(H27,'[2]Consolidado MP Planta'!$A$2:$M$823,12,0),"") -> 827.06 | F27: =IFERROR(C27*E27,"") -> 827.06 | G27: =IFERROR(F27/$F$75,"") -> 0.21022043 | H27: 51400015
A28: 1 | B28: =IFERROR(VLOOKUP(H28,'[2]Consolidado MP Planta'!$A$2:$M$823,3,0),"") -> ORLA CARTON 10" DORADA (UND) | C28: =+A28 -> 1 | D28: =IFERROR(VLOOKUP(H28,'[2]Consolidado MP Planta'!$A$2:$M$823,13,0),"") -> Und | E28: =IFERROR(VLOOKUP(H28,'[2]Consolidado MP Planta'!$A$2:$M$823,12,0),"") -> 137 | F28: =IFERROR(C28*E28,"") -> 137 | G28: =IFERROR(F28/$F$75,"") -> 0.034822381 | H28: 1950692
A29: 2 | B29: =IFERROR(VLOOKUP(H29,'[2]Consolidado MP Planta'!$A$2:$M$823,3,0),"") -> PAPEL ENCERADO 10X10 (CAJA) | C29: =+A29 -> 2 | D29: =IFERROR(VLOOKUP(H29,'[2]Consolidado MP Planta'!$A$2:$M$823,13,0),"") -> Und | E29: =IFERROR(VLOOKUP(H29,'[2]Consolidado MP Planta'!$A$2:$M$823,12,0),"") -> 10.642 | F29: =IFERROR(C29*E29,"") -> 21.284 | G29: =IFERROR(F29/$F$75,"") -> 0.0054099238 | H29: 1950772
A30: 30 | B30: =IFERROR(VLOOKUP(H30,'[2]Consolidado MP Planta'!$A$2:$M$823,3,0),"") -> CINTA ADHESIVA TRANSPARENT 2*100 M (UND) | C30: =+A30 -> 30 | D30: =IFERROR(VLOOKUP(H30,'[2]Consolidado MP Planta'!$A$2:$M$823,13,0),"") -> Cm | E30: =IFERROR(VLOOKUP(H30,'[2]Consolidado MP Planta'!$A$2:$M$823,12,0),"") -> 0.175 | F30: =IFERROR(C30*E30,"") -> 5.25 | G30: =IFERROR(F30/$F$75,"") -> 0.0013344343 | H30: 703020
A31: 1 | B31: =IFERROR(VLOOKUP(H31,'[2]Consolidado MP Planta'!$A$2:$M$823,3,0),"") -> ETIQUETA BLANCA R-153 (UND) | C31: =+A31 -> 1 | D31: =IFERROR(VLOOKUP(H31,'[2]Consolidado MP Planta'!$A$2:$M$823,13,0),"") -> Und | E31: =IFERROR(VLOOKUP(H31,'[2]Consolidado MP Planta'!$A$2:$M$823,12,0),"") -> 0.39 | F31: =IFERROR(C31*E31,"") -> 0.39 | G31: =IFERROR(F31/$F$75,"") -> 9.9129406e-05 | H31: 701096
A32: 1 | B32: =IFERROR(VLOOKUP(H32,'[2]Consolidado MP Planta'!$A$2:$M$823,3,0),"") -> ETIQ.FECHA VENCIMIENTO AMARILLO (ROLLO) | C32: =+A32 -> 1 | D32: =IFERROR(VLOOKUP(H32,'[2]Consolidado MP Planta'!$A$2:$M$823,13,0),"") -> Und | E32: =IFERROR(VLOOKUP(H32,'[2]Consolidado MP Planta'!$A$2:$M$823,12,0),"") -> 0.33333333 | F32: =IFERROR(C32*E32,"") -> 0.33333333 | G32: =IFERROR(F32/$F$75,"") -> 8.4725988e-05 | H32: 0702006
A33: 1 | B33: =IFERROR(VLOOKUP(H33,'[2]Consolidado MP Planta'!$A$2:$M$823,3,0),"") -> ETIQUETA BLANCA 2 5/8X1 15/16 (UND) | C33: =+A33 -> 1 | D33: =IFERROR(VLOOKUP(H33,'[2]Consolidado MP Planta'!$A$2:$M$823,13,0),"") -> Und | E33: =IFERROR(VLOOKUP(H33,'[2]Consolidado MP Planta'!$A$2:$M$823,12,0),"") -> 2.128 | F33: =IFERROR(C33*E33,"") -> 2.128 | G33: =IFERROR(F33/$F$75,"") -> 0.00054089071 | H33: 0702123
A34: 1 | B34: =IFERROR(VLOOKUP(H34,'[2]Consolidado MP Planta'!$A$2:$M$823,3,0),"") -> CAJA PRALINE (UND) | C34: =+A34 -> 1 | D34: Und | E34: =IFERROR(VLOOKUP(H34,'[2]Consolidado MP Planta'!$A$2:$M$823,12,0),"") -> 576 | F34: =IFERROR(C34*E34,"") -> 576 | G34: =IFERROR(F34/$F$75,"") -> 0.14640651 | H34: 1952871
A35: 1 | B35: =IFERROR(VLOOKUP(H35,'[2]Consolidado MP Planta'!$A$2:$M$823,3,0),"") -> ETIQUETA BLANCA R-153 (UND) | C35: =+A35 -> 1 | D35: =IFERROR(VLOOKUP(H35,'[2]Consolidado MP Planta'!$A$2:$M$823,13,0),"") -> Und | E35: =IFERROR(VLOOKUP(H35,'[2]Consolidado MP Planta'!$A$2:$M$823,12,0),"") -> 0.39 | F35: =IFERROR(C35*E35,"") -> 0.39 | G35: =IFERROR(F35/$F$75,"") -> 9.9129406e-05 | H35: 701096
A36: 1 | B36: =IFERROR(VLOOKUP(H36,'[2]Consolidado MP Planta'!$A$2:$M$823,3,0),"") -> ETIQ.FECHA VENCIMIENTO AMARILLO (ROLLO) | C36: =+A36 -> 1 | D36: =IFERROR(VLOOKUP(H36,'[2]Consolidado MP Planta'!$A$2:$M$823,13,0),"") -> Und | E36: =IFERROR(VLOOKUP(H36,'[2]Consolidado MP Planta'!$A$2:$M$823,12,0),"") -> 0.33333333 | F36: =IFERROR(C36*E36,"") -> 0.33333333 | G36: =IFERROR(F36/$F$75,"") -> 8.4725988e-05 | H36: 0702006
A37: 1 | B37: =IFERROR(VLOOKUP(H37,'[2]Consolidado MP Planta'!$A$2:$M$823,3,0),"") -> ETIQUETA BLANCA 2 5/8X1 15/16 (UND) | C37: =+A37 -> 1 | D37: =IFERROR(VLOOKUP(H37,'[2]Consolidado MP Planta'!$A$2:$M$823,13,0),"") -> Und | E37: =IFERROR(VLOOKUP(H37,'[2]Consolidado MP Planta'!$A$2:$M$823,12,0),"") -> 2.128 | F37: =IFERROR(C37*E37,"") -> 2.128 | G37: =IFERROR(F37/$F$75,"") -> 0.00054089071 | H37: 0702123
A38: 100 | B38: =IFERROR(VLOOKUP(H38,'[2]Consolidado MP Planta'!$A$2:$M$823,3,0),"") -> CINTA ADHESIVA TRANSPARENT 2*100 M (UND) | C38: =+A38 -> 100 | D38: =IFERROR(VLOOKUP(H38,'[2]Consolidado MP Planta'!$A$2:$M$823,13,0),"") -> Cm | E38: =IFERROR(VLOOKUP(H38,'[2]Consolidado MP Planta'!$A$2:$M$823,12,0),"") -> 0.175 | F38: =IFERROR(C38*E38,"") -> 17.5 | G38: =IFERROR(F38/$F$75,"") -> 0.0044481144 | H38: 703020
B39: =IFERROR(VLOOKUP(H39,'[2]Consolidado MP Planta'!$A$2:$M$823,3,0),"") | C39: =+A39 -> 0 | D39: =IFERROR(VLOOKUP(H39,'[2]Consolidado MP Planta'!$A$2:$M$823,13,0),"") | E39: =IFERROR(VLOOKUP(H39,'[2]Consolidado MP Planta'!$A$2:$M$823,12,0),"") | F39: =IFERROR(C39*E39,"") | G39: =IFERROR(F39/$F$75,"")
B40: =IFERROR(VLOOKUP(H40,'[2]Consolidado MP Planta'!$A$2:$M$823,3,0),"") | C40: =+A40 -> 0 | D40: =IFERROR(VLOOKUP(H40,'[2]Consolidado MP Planta'!$A$2:$M$823,13,0),"") | E40: =IFERROR(VLOOKUP(H40,'[2]Consolidado MP Planta'!$A$2:$M$823,12,0),"") | F40: =IFERROR(C40*E40,"") | G40: =IFERROR(F40/$F$75,"")
B41: =IFERROR(VLOOKUP(H41,'[2]Consolidado MP Planta'!$A$2:$M$823,3,0),"") | C41: =+A41 -> 0 | D41: =IFERROR(VLOOKUP(H41,'[2]Consolidado MP Planta'!$A$2:$M$823,13,0),"") | E41: =IFERROR(VLOOKUP(H41,'[2]Consolidado MP Planta'!$A$2:$M$823,12,0),"") | F41: =IFERROR(C41*E41,"") | G41: =IFERROR(F41/$F$75,"")
A43: UNIDADES | B43: EMPAQUE SEMIELABORADOS | C43: UNIDADES | D43: UND MEDIDA | E43: COSTO UNITARIO | F43: TOTAL COSTO | G43: % PREC. DEFINIDO | H43: CODIGOS
A44: =+A17 -> 1 | B44: =IFERROR(VLOOKUP(H44,[2]SEMIELABORADOS!$A$2:$M$6000,2,0),"") -> ROSQUETE CHOCOLATE BUCCA 800 g | C44: =+A44 -> 1 | D44: =IFERROR(VLOOKUP(H44,[2]SEMIELABORADOS!$A$2:$M$6000,6,0),"") -> Und | E44: =IFERROR(VLOOKUP(H44,[2]SEMIELABORADOS!$A$2:$M$65536,10,0),"") -> 13.659299 | F44: =IFERROR(E44*C44,"") -> 13.659299 | G44: =IFERROR(F44/$F$75,"") -> 0.0034718927 | H44: 907000226
A45: =+A18 -> 100 | B45: =IFERROR(VLOOKUP(H45,[2]SEMIELABORADOS!$A$2:$M$6000,2,0),"") -> CREMA CHANTILLY CHOCO SPOON KILO | C45: =+A45 -> 100 | D45: =IFERROR(VLOOKUP(H45,[2]SEMIELABORADOS!$A$2:$M$6000,6,0),"") -> Gramo | E45: =IFERROR(VLOOKUP(H45,[2]SEMIELABORADOS!$A$2:$M$65536,10,0),"") -> 8.512e-05 | F45: =IFERROR(E45*C45,"") -> 0.008512 | G45: =IFERROR(F45/$F$75,"") -> 2.1635628e-06 | H45: 95718
A46: =+A19 -> 0 | B46: =IFERROR(VLOOKUP(H46,[2]SEMIELABORADOS!$A$2:$M$6000,2,0),"") | C46: =+A46 -> 0 | D46: =IFERROR(VLOOKUP(H46,[2]SEMIELABORADOS!$A$2:$M$6000,6,0),"") | E46: =IFERROR(VLOOKUP(H46,[2]SEMIELABORADOS!$A$2:$M$65536,10,0),"") | F46: =IFERROR(E46*C46,"") | G46: =IFERROR(F46/$F$75,"")
A47: =+A20 -> 0 | B47: =IFERROR(VLOOKUP(H47,[2]SEMIELABORADOS!$A$2:$M$6000,2,0),"") | C47: =+A47 -> 0 | D47: =IFERROR(VLOOKUP(H47,[2]SEMIELABORADOS!$A$2:$M$6000,6,0),"") | E47: =IFERROR(VLOOKUP(H47,[2]SEMIELABORADOS!$A$2:$M$65536,10,0),"") | F47: =IFERROR(E47*C47,"") | G47: =IFERROR(F47/$F$75,"")
A48: =+A21 -> 0 | B48: =IFERROR(VLOOKUP(H48,[2]SEMIELABORADOS!$A$2:$M$6000,2,0),"") | C48: =+A48 -> 0 | D48: =IFERROR(VLOOKUP(H48,[2]SEMIELABORADOS!$A$2:$M$6000,6,0),"") | E48: =IFERROR(VLOOKUP(H48,[2]SEMIELABORADOS!$A$2:$M$65536,10,0),"") | F48: =IFERROR(E48*C48,"") | G48: =IFERROR(F48/$F$75,"")
A49: =+A22 -> 0 | B49: =IFERROR(VLOOKUP(H49,[2]SEMIELABORADOS!$A$2:$M$6000,2,0),"") | C49: =+A49 -> 0 | D49: =IFERROR(VLOOKUP(H49,[2]SEMIELABORADOS!$A$2:$M$6000,6,0),"") | E49: =IFERROR(VLOOKUP(H49,[2]SEMIELABORADOS!$A$2:$M$65536,10,0),"") | F49: =IFERROR(E49*C49,"") | G49: =IFERROR(F49/$F$75,"")
A50: =+A23 -> 0 | B50: =IFERROR(VLOOKUP(H50,[2]SEMIELABORADOS!$A$2:$M$6000,2,0),"") | C50: =+A50 -> 0 | D50: =IFERROR(VLOOKUP(H50,[2]SEMIELABORADOS!$A$2:$M$6000,6,0),"") | E50: =IFERROR(VLOOKUP(H50,[2]SEMIELABORADOS!$A$2:$M$65536,10,0),"") | F50: =IFERROR(E50*C50,"") | G50: =IFERROR(F50/$F$75,"")
A52: UNIDADES | B52: MODI | C52: UNIDADES | D52: UND MEDIDA | E52: COSTO UNITARIO | F52: TOTAL COSTO | G52: % PREC. DEFINIDO | H52: CODIGOS
A53: =+A44 -> 1 | B53: =IFERROR(VLOOKUP(H53,[2]SEMIELABORADOS!$A$2:$M$6000,2,0),"") -> ROSQUETE CHOCOLATE BUCCA 800 g | C53: =+A53 -> 1 | D53: =IFERROR(VLOOKUP(H53,[2]SEMIELABORADOS!$A$2:$M$6000,6,0),"") -> Und | E53: =IFERROR(VLOOKUP(H53,[2]SEMIELABORADOS!$A$2:$M$65536,12,0),"") -> 163.16236 | F53: =IFERROR(E53*C53,"") -> 163.16236 | G53: =IFERROR(F53/$F$75,"") -> 0.041472278 | H53: 907000226
A54: =+A45 -> 100 | B54: =IFERROR(VLOOKUP(H54,[2]SEMIELABORADOS!$A$2:$M$6000,2,0),"") -> CREMA CHANTILLY CHOCO SPOON KILO | C54: =+A54 -> 100 | D54: =IFERROR(VLOOKUP(H54,[2]SEMIELABORADOS!$A$2:$M$6000,6,0),"") -> Gramo | E54: =IFERROR(VLOOKUP(H54,[2]SEMIELABORADOS!$A$2:$M$65536,12,0),"") -> 0.48845084 | F54: =IFERROR(E54*C54,"") -> 48.845084 | G54: =IFERROR(F54/$F$75,"") -> 0.012415344 | H54: 95718
A55: =+A46 -> 0 | B55: =IFERROR(VLOOKUP(H55,[2]SEMIELABORADOS!$A$2:$M$6000,2,0),"") | C55: =+A55 -> 0 | D55: =IFERROR(VLOOKUP(H55,[2]SEMIELABORADOS!$A$2:$M$6000,6,0),"") | E55: =IFERROR(VLOOKUP(H55,[2]SEMIELABORADOS!$A$2:$M$65536,12,0),"") | F55: =IFERROR(E55*C55,"") | G55: =IFERROR(F55/$F$75,"")
A56: =+A47 -> 0 | B56: =IFERROR(VLOOKUP(H56,[2]SEMIELABORADOS!$A$2:$M$6000,2,0),"") | C56: =+A56 -> 0 | D56: =IFERROR(VLOOKUP(H56,[2]SEMIELABORADOS!$A$2:$M$6000,6,0),"") | E56: =IFERROR(VLOOKUP(H56,[2]SEMIELABORADOS!$A$2:$M$65536,12,0),"") | F56: =IFERROR(E56*C56,"") | G56: =IFERROR(F56/$F$75,"")
A57: =+A48 -> 0 | B57: =IFERROR(VLOOKUP(H57,[2]SEMIELABORADOS!$A$2:$M$6000,2,0),"") | C57: =+A57 -> 0 | D57: =IFERROR(VLOOKUP(H57,[2]SEMIELABORADOS!$A$2:$M$6000,6,0),"") | E57: =IFERROR(VLOOKUP(H57,[2]SEMIELABORADOS!$A$2:$M$65536,12,0),"") | F57: =IFERROR(E57*C57,"") | G57: =IFERROR(F57/$F$75,"")
A58: =+A49 -> 0 | B58: =IFERROR(VLOOKUP(H58,[2]SEMIELABORADOS!$A$2:$M$6000,2,0),"") | C58: =+A58 -> 0 | D58: =IFERROR(VLOOKUP(H58,[2]SEMIELABORADOS!$A$2:$M$6000,6,0),"") | E58: =IFERROR(VLOOKUP(H58,[2]SEMIELABORADOS!$A$2:$M$65536,12,0),"") | F58: =IFERROR(E58*C58,"") | G58: =IFERROR(F58/$F$75,"")
A59: =+A50 -> 0 | B59: =IFERROR(VLOOKUP(H59,[2]SEMIELABORADOS!$A$2:$M$6000,2,0),"") | C59: =+A59 -> 0 | D59: =IFERROR(VLOOKUP(H59,[2]SEMIELABORADOS!$A$2:$M$6000,6,0),"") | E59: =IFERROR(VLOOKUP(H59,[2]SEMIELABORADOS!$A$2:$M$65536,12,0),"") | F59: =IFERROR(E59*C59,"") | G59: =IFERROR(F59/$F$75,"")
A60: 1 | B60: MODI PREPARACION | C60: =+A60 -> 1 | D60: N/A | E60: =+F74 -> 495 | F60: =IFERROR(C60*E60,"") -> 495 | G60: =IFERROR(F60/$F$75,"") -> 0.12581809
B62: TOTAL MATERIA PRIMA | F62: =SUM(F8:F14,F17:F24) -> 1799.7911 | G62: =+F62/$F$75 -> 0.45746723 | H62: =+F62/$D$69 -> 1799.7911
B63: TOTAL EMPAQUE | F63: =SUM(F27:F41,F44:F50) -> 1603.4645 | G63: =+F63/$F$75 -> 0.40756534 | H63: =+F63/$D$69 -> 1603.4645 | K63: TOTAL MATERIA PRIMA + EMPAQUE | O63: =+F64 -> 3403.2555
B64: TOTAL MATERIAS P. + EMPAQUES | F64: =+F62+F63 -> 3403.2555 | G64: =+F64/$F$75 -> 0.86503256 | H64: =+F64/$D$69 -> 3403.2555 | L64: MODI PLANTA | O64: =+F65 -> 707.00745
C65: TOTAL MODI | F65: =SUM(F53:F60) -> 707.00745 | G65: =+F65/$F$75 -> 0.17970571 | H65: =+F65/$D$69 -> 707.00745 | M65: DESECHO | N65: 0.01 | O65: =O63*N65 -> 34.032555
M66: COSTO PLANTA | O66: =SUM(O63:O65) -> 4144.2955
B67: GRAMOS | D67: 1100 | M67: % MK | N67: 0.25 | O67: =+O66*N67 -> 1036.0739
B68: PESO POR UNIDAD | D68: 1100 | M68: COSTO PLANTA | O68: =SUM(O66:O67) -> 5180.3694
B69: UNIDADES TOTALES | D69: =+D67/D68 -> 1 | L69: TRANSFERENCIA | N69: 0.05 | O69: =+O68*N69 -> 259.01847
B70: UNIDAD MEDIDA | D70: UND | K70: PRECIO DE VENTA PLANTA A LOCAL | O70: =SUM(O68:O69) -> 5439.3879 | P70: GR
E71: S/ COSTO | F71: TOTAL | L71: UNIDAD | O71: =+O70/D69 -> 5439.3879 | P71: =+O71/D68 -> 4.9448981
B72: TOTAL MATERIAS P. + EMPAQUES | E72: =+F72/F72 -> 1 | F72: =SUM(F64) -> 3403.2555 | G72: =+F72/$F$75 -> 0.86503256
B73: DESECHOS Y PERDIDAS | E73: 0.02 | F73: =+F62*E73 -> 35.995821 | G73: =+F73/$F$75 -> 0.0091493445
B74: MANO OBRA DIRECTA | D74: 9 | E74: 55 | F74: =+E74*D74 -> 495 | G74: =+F74/$F$75 -> 0.12581809
B75: TOTAL COSTO PLANTA | F75: =SUM(F72:F74) -> 3934.2514 | G75: =+F75/$F$75 -> 1
B77: COSTO POR GRAMO
B78: TOTAL COSTO MATERIA PRIMA | C78: =+F62 -> 1799.7911 | D78: =+D67 -> 1100 | E78: =+C78/D78 -> 1.6361737
B80: TOTAL COSTO UNIDAD MP+DESECHO+EMPAQUE | C80: =SUM(F72:F73) -> 3439.2514 | D80: =+D67 -> 1100 | E80: =+C80/D80 -> 3.1265921
B82: TOTAL MODI PREPARACION POR GRAMO | C82: =+F74 -> 495 | D82: =+D67 -> 1100 | E82: =+C82/D82 -> 0.45
B83: TOTAL MODI POR GRAMO | C83: =+F65 -> 707.00745 | D83: =+D82 -> 1100 | E83: =+C83/D83 -> 0.64273404
B85: TOTAL EMPAQUE POR GRAMO | C85: =+F63 -> 1603.4645 | D85: =+D83 -> 1100 | E85: =+C85/D85 -> 1.457695
B87: TOTAL GRAMO MP+MODI | E87: =+E78+E83 -> 2.2789077
B89: COSTO POR UNIDAD
B90: TOTAL COSTO MATERIA PRIMA | C90: =+C78 -> 1799.7911 | D90: =+D69 -> 1 | E90: =+C90/D90 -> 1799.7911
B92: TOTAL COSTO UNIDAD MP+DESECHO+EMPAQUE | C92: =+C80 -> 3439.2514 | D92: =+D69 -> 1 | E92: =+C92/D92 -> 3439.2514
B94: TOTAL MODI POR GRAMO | C94: =+C82 -> 495 | D94: =+D69 -> 1 | E94: =+C94/D94 -> 495
B95: TOTAL MODI POR GRAMO | C95: =+C83 -> 707.00745 | D95: =+D94 -> 1 | E95: =+C95/D95 -> 707.00745

Sheet PRECIO-1
B2: ESTRUCTURA DE COSTOS
B3: INDUSTRIA
F4: Fecha:
B5: UNIDAD | C5: DESCRIPCION MAT.PRIMA | D5: UNIDAD | E5: COSTO UNITARIO | F5: TOTAL COSTO | G5: % PREC. DEFINIDO | H5: CÓDIGOS
B6: 1 | C6: TORTA CHOCO PORCIONADA 8 PORC | D6: =+B6 -> 1 | E6: =+costo!H62 -> 1799.7911 | F6: =+D6*E6 -> 1799.7911 | G6: =+F6/$F$23 -> 0.34175793 | H6: SPOON
B8: UNIDAD | C8: EMPAQUE | D8: UNIDAD | E8: COSTO UNITARIO | F8: TOTAL COSTO | G8: % PREC. DEFINIDO | H8: CÓDIGOS
B9: 1 | C9: EMPAQUE PLANTA | D9: =+B9 -> 1 | E9: =+costo!H63 -> 1603.4645 | F9: =+D9*E9 -> 1603.4645 | G9: =+F9/$F$23 -> 0.30447796 | H9: PLANTA
C11: TOTAL MATERIA PRIMA | F11: =SUM(F6) -> 1799.7911 | G11: =+F11/$F$23 -> 0.34175793
C12: TOTAL EMPAQUE | F12: =SUM(F9) -> 1603.4645 | G12: =+F12/$F$23 -> 0.30447796
C13: TOTAL MATERIA PRIMA + EMPAQUE | F13: =SUM(F11:F12) -> 3403.2555 | G13: =+F13/$F$23 -> 0.64623589
B15: TOTAL MATERIA PRIMA + EMPAQUE | E15: Planta | F15: =+F13 -> 3403.2555 | G15: =+F15/$F$23 -> 0.64623589
C16: MODI PLANTA | F16: =+costo!H65 -> 707.00745 | G16: =+F16/$F$23 -> 0.13425192
C17: DESECHO | E17: 0 | F17: =+(F15+F16)*E17 -> 0 | G17: =+F17/$F$23 -> 0
C18: GAF | E18: 0 | F18: =+F16*E18 -> 0 | G18: =+F18/$F$23 -> 0
F19: =SUM(F15:F18) -> 4110.263 | G19: =+F19/$F$21 -> 0.8
C20: % MK | E20: 0.25 | F20: =+F19*E20 -> 1027.5657 | G20: =+F20/$F$23 -> 0.19512195
C21: COSTO PLANTA | F21: =SUM(F19:F20) -> 5137.8287 | G21: =+F21/$F$23 -> 0.97560976
C22: TRANSFERENCIA | E22: 0.025 | F22: =+F21*E22 -> 128.44572 | G22: =+F22/$F$23 -> 0.024390244
C23: PRECIO DE VENTA PLANTA A LOCAL | F23: =SUM(F21:F22) -> 5266.2744 | G23: =+F23/$F$23 -> 1
C27: PRECIO DE VENTA PLANTA A LOCAL | F27: =+F23 -> 5266.2744
C28: CAMIONES | D28: LOGISTICA | E28: 0.1 | F28: =+F27*E28 -> 526.62744 | G28: Costo | H28: % Margen
C29: COSTO TOTAL | F29: =SUM(F27:F28) -> 5792.9019 | G29: =+F29/$F$31 -> 0.68965517 | H29: =1-(F29/F31) -> 0.31034483
C30: MARK UP LOCAL | E30: 0.45 | F30: =+F29*E30 -> 2606.8059
C31: PRECIO VENTA SIN IMP | F31: =SUM(F29:F30) -> 8399.7077
C32: PRECIO VENTA IVI | E32: 0.13 | F32: =+F31*(1+E32) -> 9491.6697
C34: MARGEN SUPERMERCADO | E34: 0.65 | F34: =+F31/0.65 -> 12922.627
C35: PRECIO IVI | E35: 0.13 | F35: =+F34*1.13 -> 14602.569
A37: Esteban Ramírez S. / Costos

Sheet Costo Ensamble 
E1: Precio Local | F1: Costo MP | G1: Costo EM | H1: Costo MO
E2: =IFERROR(O59,"") -> 4096.3494 | F2: =IFERROR(H50,"") -> 1652.6411 | G2: =IFERROR(H51,"") -> 875.49103 | H2: =IFERROR(H53,"") -> 567.61473
A4: PASTEL CHOCOLATE INDUSTRIA PORCIONADO
A5: ESTRUCTURA DE COSTOS
F6: Fecha: | H6: =TODAY() -> 45938
A7: UNIDADES | B7: DESCRIPCION MAT.PRIMA | C7: UNIDADES | D7: UND MEDIDA | E7: COSTO UNITARIO | F7: TOTAL COSTO | G7: % PREC. DEFINIDO | H7: CODIGOS
A8: 285 | B8: =IFERROR(VLOOKUP($H8,'[1]MP PLANTA'!$A$2:$F$500,2,0),"") -> DULCE DE LECHE SUAVE F2 ( 5 KG ) | C8: =+A8 -> 285 | D8: =IFERROR(VLOOKUP($H8,'[1]MP PLANTA'!$A$2:$F$500,5,0),"") -> Gramo | E8: =IFERROR(VLOOKUP($H8,'[1]MP PLANTA'!$A$2:$F$500,6,0),"") -> 1.359981 | F8: =IFERROR(C8*E8,"") -> 387.59458 | G8: =IFERROR(F8/$F$63,"") -> 0.12682302 | H8: 0310143
A9: 40 | B9: =IFERROR(VLOOKUP($H9,'[1]MP PLANTA'!$A$2:$F$500,2,0),"") -> CHOCOLATE HERSHEYS SEMISWEET (2,5k) | C9: =+A9 -> 40 | D9: =IFERROR(VLOOKUP($H9,'[1]MP PLANTA'!$A$2:$F$500,5,0),"") -> Gramo | E9: =IFERROR(VLOOKUP($H9,'[1]MP PLANTA'!$A$2:$F$500,6,0),"") -> 4.778 | F9: =IFERROR(C9*E9,"") -> 191.12 | G9: =IFERROR(F9/$F$63,"") -> 0.062535483 | H9: 1210421
A10: 10 | B10: CONFITE CHOCOLATE CRUJIENTE | C10: =+A10 -> 10 | D10: Gramo | E10: 2.66 | F10: =IFERROR(C10*E10,"") -> 26.6 | G10: =IFERROR(F10/$F$63,"") -> 0.0087036618 | H10: 10700008
B11: =IFERROR(VLOOKUP($H11,'[1]MP PLANTA'!$A$2:$F$500,2,0),"") | C11: =+A11 -> 0 | D11: =IFERROR(VLOOKUP($H11,'[1]MP PLANTA'!$A$2:$F$500,5,0),"") | E11: =IFERROR(VLOOKUP($H11,'[1]MP PLANTA'!$A$2:$F$500,6,0),"") | F11: =IFERROR(C11*E11,"") | G11: =IFERROR(F11/$F$63,"")
B12: =IFERROR(VLOOKUP($H12,'[1]MP PLANTA'!$A$2:$F$500,2,0),"") | C12: =+A12 -> 0 | D12: =IFERROR(VLOOKUP($H12,'[1]MP PLANTA'!$A$2:$F$500,5,0),"") | E12: =IFERROR(VLOOKUP($H12,'[1]MP PLANTA'!$A$2:$F$500,6,0),"") | F12: =IFERROR(C12*E12,"") | G12: =IFERROR(F12/$F$63,"")
B13: =IFERROR(VLOOKUP($H13,'[1]MP PLANTA'!$A$2:$F$500,2,0),"") | C13: =+A13 -> 0 | D13: =IFERROR(VLOOKUP($H13,'[1]MP PLANTA'!$A$2:$F$500,5,0),"") | E13: =IFERROR(VLOOKUP($H13,'[1]MP PLANTA'!$A$2:$F$500,6,0),"") | F13: =IFERROR(C13*E13,"") | G13: =IFERROR(F13/$F$63,"")
A15: UNIDADES | B15: MATERIA PRIMA SEMIELABORADOS | C15: UNIDADES | D15: UND MEDIDA | E15: COSTO UNITARIO | F15: TOTAL COSTO | G15: % PREC. DEFINIDO | H15: CODIGOS
A16: 1 | B16: ROSQUETE CHOCOLATE BUCCA 800G | C16: =+A16 -> 1 | D16: UND | E16: =+'Costo Rosquete'!H25 -> 869.70131 | F16: =IFERROR(E16*C16,"") -> 869.70131 | G16: =IFERROR(F16/$F$63,"") -> 0.28457091
A17: 100 | B17: =IFERROR(VLOOKUP($H17,[1]SEMIELABORADOS!$A$1:$J$999,2,0),"") -> CREMA CHANTILLY CHOCO (SPOON-IND)(24875g) | C17: =+A17 -> 100 | D17: =IFERROR(VLOOKUP($H17,[1]SEMIELABORADOS!$A$1:$J$999,4,0),"") -> GRAMO | E17: =IFERROR(VLOOKUP($H17,[1]SEMIELABORADOS!$A$1:$J$999,6,0),"") -> 1.7762516 | F17: =IFERROR(E17*C17,"") -> 177.62516 | G17: =IFERROR(F17/$F$63,"") -> 0.058119899 | H17: 95718
B18: =IFERROR(VLOOKUP($H18,[1]SEMIELABORADOS!$A$1:$J$999,2,0),"") | C18: =+A18 -> 0 | D18: =IFERROR(VLOOKUP($H18,[1]SEMIELABORADOS!$A$1:$J$999,4,0),"") | E18: =IFERROR(VLOOKUP($H18,[1]SEMIELABORADOS!$A$1:$J$999,6,0),"") | F18: =IFERROR(E18*C18,"") | G18: =IFERROR(F18/$F$63,"")
B19: =IFERROR(VLOOKUP($H19,[1]SEMIELABORADOS!$A$1:$J$999,2,0),"") | C19: =+A19 -> 0 | D19: =IFERROR(VLOOKUP($H19,[1]SEMIELABORADOS!$A$1:$J$999,4,0),"") | E19: =IFERROR(VLOOKUP($H19,[1]SEMIELABORADOS!$A$1:$J$999,6,0),"") | F19: =IFERROR(E19*C19,"") | G19: =IFERROR(F19/$F$63,"")
A21: UNIDADES | B21: EMPAQUE | C21: UNIDADES | D21: UND MEDIDA | E21: COSTO UNITARIO | F21: TOTAL COSTO | G21: % PREC. DEFINIDO | H21: CODIGOS
A22: 4 | B22: =IFERROR(VLOOKUP($H22,'[1]EMP PLANTA'!$A$2:$F$500,2,0),"") -> PAPEL ENCERADO 12 X 10 (CAJA) | C22: =+A22 -> 4 | D22: =IFERROR(VLOOKUP($H22,'[1]EMP PLANTA'!$A$2:$F$500,5,0),"") -> UND | E22: =IFERROR(VLOOKUP($H22,'[1]EMP PLANTA'!$A$2:$F$500,6,0),"") -> 7.070446 | F22: =IFERROR(E22*C22,"") -> 28.281784 | G22: =IFERROR(F22/$F$63,"") -> 0.0092539505 | H22: 1950772
A23: 1 | B23: =IFERROR(VLOOKUP($H23,'[1]EMP PLANTA'!$A$2:$F$500,2,0),"") -> ORLA CARTON 10" DORADA (100 * PAQ) | C23: =+A23 -> 1 | D23: =IFERROR(VLOOKUP($H23,'[1]EMP PLANTA'!$A$2:$F$500,5,0),"") -> UND | E23: =IFERROR(VLOOKUP($H23,'[1]EMP PLANTA'!$A$2:$F$500,6,0),"") -> 99.497 | F23: =IFERROR(E23*C23,"") -> 99.497 | G23: =IFERROR(F23/$F$63,"") -> 0.032555949 | H23: 1950692
A24: 1 | B24: QUEQUERA CHILENA (CAJA:50 UND) | C24: =+A24 -> 1 | D24: UND | E24: 256.3 | F24: =IFERROR(E24*C24,"") -> 256.3 | G24: =IFERROR(F24/$F$63,"") -> 0.083862727 | H24: 51400015
A25: 1 | B25: =IFERROR(VLOOKUP($H25,'[1]EMP PLANTA'!$A$2:$F$500,2,0),"") | C25: =+A25 -> 1 | D25: =IFERROR(VLOOKUP($H25,'[1]EMP PLANTA'!$A$2:$F$500,5,0),"") | E25: =IFERROR(VLOOKUP($H25,'[1]EMP PLANTA'!$A$2:$F$500,6,0),"") | F25: =IFERROR(E25*C25,"") | G25: =IFERROR(F25/$F$63,"")
A26: 1 | B26: =IFERROR(VLOOKUP($H26,'[1]EMP PLANTA'!$A$2:$F$500,2,0),"") | C26: =+A26 -> 1 | D26: =IFERROR(VLOOKUP($H26,'[1]EMP PLANTA'!$A$2:$F$500,5,0),"") | E26: =IFERROR(VLOOKUP($H26,'[1]EMP PLANTA'!$A$2:$F$500,6,0),"") | F26: =IFERROR(E26*C26,"") | G26: =IFERROR(F26/$F$63,"")
A27: 1 | B27: =IFERROR(VLOOKUP($H27,'[1]EMP PLANTA'!$A$2:$F$500,2,0),"") -> ETIQ.BLANCA 1 1/4 * 3/4 | C27: =+A27 -> 1 | D27: =IFERROR(VLOOKUP($H27,'[1]EMP PLANTA'!$A$2:$F$500,5,0),"") -> UND | E27: =IFERROR(VLOOKUP($H27,'[1]EMP PLANTA'!$A$2:$F$500,6,0),"") -> 0.616 | F27: =IFERROR(E27*C27,"") -> 0.616 | G27: =IFERROR(F27/$F$63,"") -> 0.00020155848 | H27: 0702069
A28: 30 | B28: CINTA ADHESIVA TRANSPARENTE 2*100 MTS | C28: =+A28 -> 30 | D28: CM | E28: 0.15 | F28: =IFERROR(E28*C28,"") -> 4.5 | G28: =IFERROR(F28/$F$63,"") -> 0.001472424 | H28: 703020
A29: 1 | B29: =IFERROR(VLOOKUP($H29,'[1]EMP PLANTA'!$A$2:$F$500,2,0),"") -> ETIQ.FECHA VENCIMIENTO BLANCO | C29: =+A29 -> 1 | D29: =IFERROR(VLOOKUP($H29,'[1]EMP PLANTA'!$A$2:$F$500,5,0),"") -> UND | E29: =IFERROR(VLOOKUP($H29,'[1]EMP PLANTA'!$A$2:$F$500,6,0),"") -> 0.22878 | F29: =IFERROR(E29*C29,"") -> 0.22878 | G29: =IFERROR(F29/$F$63,"") -> 7.4858036e-05 | H29: 0702007
A30: 1 | B30: =IFERROR(VLOOKUP($H30,'[1]EMP PLANTA'!$A$2:$F$500,2,0),"") -> ETIQUETA BLANCA 2 5/8X1 15/16 PRE BLANCA | C30: =+A30 -> 1 | D30: =IFERROR(VLOOKUP($H30,'[1]EMP PLANTA'!$A$2:$F$500,5,0),"") -> UND | E30: =IFERROR(VLOOKUP($H30,'[1]EMP PLANTA'!$A$2:$F$500,6,0),"") -> 2.276 | F30: =IFERROR(E30*C30,"") -> 2.276 | G30: =IFERROR(F30/$F$63,"") -> 0.00074471934 | H30: 0702123
A31: 1 | B31: CAJA PRALINE UND | C31: =+A31 -> 1 | D31: UND | E31: 450 | F31: =IFERROR(E31*C31,"") -> 450 | G31: =IFERROR(F31/$F$63,"") -> 0.1472424 | H31: 1952871
A32: 1 | B32: =IFERROR(VLOOKUP($H32,'[1]EMP PLANTA'!$A$2:$F$500,2,0),"") -> ETIQ.BLANCA 1 1/4 * 3/4 | C32: =+A32 -> 1 | D32: =IFERROR(VLOOKUP($H32,'[1]EMP PLANTA'!$A$2:$F$500,5,0),"") -> UND | E32: =IFERROR(VLOOKUP($H32,'[1]EMP PLANTA'!$A$2:$F$500,6,0),"") -> 0.616 | F32: =IFERROR(E32*C32,"") -> 0.616 | G32: =IFERROR(F32/$F$63,"") -> 0.00020155848 | H32: 0702069
A33: 1 | B33: =IFERROR(VLOOKUP($H33,'[1]EMP PLANTA'!$A$2:$F$500,2,0),"") -> ETIQ.FECHA VENCIMIENTO BLANCO | C33: =+A33 -> 1 | D33: =IFERROR(VLOOKUP($H33,'[1]EMP PLANTA'!$A$2:$F$500,5,0),"") -> UND | E33: =IFERROR(VLOOKUP($H33,'[1]EMP PLANTA'!$A$2:$F$500,6,0),"") -> 0.22878 | F33: =IFERROR(E33*C33,"") -> 0.22878 | G33: =IFERROR(F33/$F$63,"") -> 7.4858036e-05 | H33: 0702007
A34: 1 | B34: =IFERROR(VLOOKUP($H34,'[1]EMP PLANTA'!$A$2:$F$500,2,0),"") -> ETIQUETA BLANCA 2 5/8X1 15/16 PRE BLANCA | C34: =+A34 -> 1 | D34: =IFERROR(VLOOKUP($H34,'[1]EMP PLANTA'!$A$2:$F$500,5,0),"") -> UND | E34: =IFERROR(VLOOKUP($H34,'[1]EMP PLANTA'!$A$2:$F$500,6,0),"") -> 2.276 | F34: =IFERROR(E34*C34,"") -> 2.276 | G34: =IFERROR(F34/$F$63,"") -> 0.00074471934 | H34: 0702123
A35: 100 | B35: CINTA ADHESIVA TRANSPARENTE 2*100 MTS | C35: =+A35 -> 100 | D35: CM | E35: 0.15 | F35: =IFERROR(E35*C35,"") -> 15 | G35: =IFERROR(F35/$F$63,"") -> 0.00490808 | H35: 703020
A37: UNIDADES | B37: EMPAQUE SEMIELABORADOS | C37: UNIDADES | D37: UND MEDIDA | E37: COSTO UNITARIO | F37: TOTAL COSTO | G37: % PREC. DEFINIDO | H37: CODIGOS
A38: =+A16 -> 1 | B38: ROSQUETE CHOCOLATE PASTELERO REAL 900g | C38: =+A38 -> 1 | D38: N/A | E38: =+'Costo Rosquete'!H26 -> 15.670689 | F38: =IFERROR(E38*C38,"") -> 15.670689 | G38: =IFERROR(F38/$F$62,"") -> 0.031657957
A39: =+A17 -> 100 | C39: =+A39 -> 100 | D39: N/A | E39: =IFERROR(VLOOKUP($H39,[1]SEMIELABORADOS!$A$1:$J$999,8,0),"") | F39: =IFERROR(E39*C39,"") | G39: =IFERROR(F39/$F$62,"")
A40: =+A18 -> 0 | C40: =+A40 -> 0 | D40: N/A | E40: =IFERROR(VLOOKUP($H40,[1]SEMIELABORADOS!$A$1:$J$999,8,0),"") | F40: =IFERROR(E40*C40,"") | G40: =IFERROR(F40/$F$62,"")
A41: =+A19 -> 0 | C41: =+A41 -> 0 | D41: N/A | E41: =IFERROR(VLOOKUP($H41,[1]SEMIELABORADOS!$A$1:$J$999,8,0),"") | F41: =IFERROR(E41*C41,"") | G41: =IFERROR(F41/$F$62,"")
A43: UNIDADES | B43: MODI | C43: UNIDADES | E43: COSTO UNITARIO | F43: TOTAL COSTO | G43: % PREC. DEFINIDO | H43: CODIGOS
A44: =+A16 -> 1 | B44: ROSQUETE CHOCOLATE PASTELERO REAL 900g | C44: =+A44 -> 1 | D44: N/A | E44: =+'Costo Rosquete'!H28 -> 72.614729 | F44: =IFERROR(C44*E44,"") -> 72.614729 | G44: =IFERROR(F44/$F$63,"") -> 0.023759927
A45: =+A17 -> 100 | C45: =+A45 -> 100 | D45: N/A | E45: =IFERROR(VLOOKUP($H45,[1]SEMIELABORADOS!$A$1:$J$999,10,0),"") | F45: =IFERROR(C45*E45,"") | G45: =IFERROR(F45/$F$63,"")
A46: =+A18 -> 0 | C46: =+A46 -> 0 | D46: N/A | E46: =IFERROR(VLOOKUP($H46,[1]SEMIELABORADOS!$A$1:$J$999,10,0),"") | F46: =IFERROR(C46*E46,"") | G46: =IFERROR(F46/$F$63,"")
A47: =+A19 -> 0 | C47: =+A47 -> 0 | D47: N/A | E47: =IFERROR(VLOOKUP($H47,[1]SEMIELABORADOS!$A$1:$J$999,10,0),"") | F47: =IFERROR(C47*E47,"") | G47: =IFERROR(F47/$F$63,"")
A48: 1 | B48: MODI PREPARACION | C48: =+A48 -> 1 | D48: N/A | E48: =+F62 -> 495 | F48: =IFERROR(C48*E48,"") -> 495 | G48: =IFERROR(F48/$F$63,"") -> 0.16196664
B50: TOTAL MATERIA PRIMA | F50: =SUM(F8:F13,F16:F19) -> 1652.6411 | G50: =+F50/$F$63 -> 0.54075297 | H50: =+F50/$D$57 -> 1652.6411
B51: TOTAL EMPAQUE | F51: =SUM(F22:F35,F38:F41) -> 875.49103 | G51: =+F51/$F$63 -> 0.28646533 | H51: =+F51/$D$57 -> 875.49103 | K51: TOTAL MATERIA PRIMA + EMPAQUE | O51: =+F52 -> 2528.1321
B52: TOTAL MATERIAS P. + EMPAQUES | F52: =+F50+F51 -> 2528.1321 | G52: =+F52/$F$63 -> 0.8272183 | H52: =+F52/$D$57 -> 2528.1321 | L52: MODI PLANTA | O52: =+F53 -> 567.61473
C53: TOTAL MODI | F53: =SUM(F44:F48) -> 567.61473 | G53: =+F53/$F$63 -> 0.18572657 | H53: =+F53/$D$57 -> 567.61473 | M53: DESECHO | N53: 0.01 | O53: =O51*N53 -> 25.281321
M54: COSTO PLANTA | O54: =SUM(O51:O53) -> 3121.0281
B55: GRAMOS | D55: 1100 | M55: % MK | N55: 0.25 | O55: =+O54*N55 -> 780.25703
B56: PESO POR UNIDAD | D56: 1100 | M56: COSTO PLANTA | O56: =SUM(O54:O55) -> 3901.2852
B57: UNIDADES TOTALES | D57: =+D55/D56 -> 1 | L57: TRANSFERENCIA | N57: 0.05 | O57: =+O56*N57 -> 195.06426
B58: UNIDAD MEDIDA | D58: UND | K58: PRECIO DE VENTA PLANTA A LOCAL | O58: =SUM(O56:O57) -> 4096.3494 | P58: GR
E59: S/ COSTO | F59: TOTAL | L59: UNIDAD | O59: =+O58/D57 -> 4096.3494 | P59: =+O59/D56 -> 3.723954
B60: TOTAL MATERIAS P. + EMPAQUES | E60: =+F60/F60 -> 1 | F60: =SUM(F52) -> 2528.1321 | G60: =+F60/$F$63 -> 0.8272183
B61: DESECHOS Y PERDIDAS | E61: 0.02 | F61: =+F50*E61 -> 33.052821 | G61: =+F61/$F$63 -> 0.010815059
B62: MANO OBRA DIRECTA | D62: 9 | E62: 55 | F62: =+E62*D62 -> 495 | G62: =+F62/$F$63 -> 0.16196664
B63: TOTAL COSTO PLANTA | F63: =SUM(F60:F62) -> 3056.1849 | G63: =+F63/$F$63 -> 1
B65: COSTO POR GRAMO
B66: TOTAL COSTO MATERIA PRIMA | C66: =+F50 -> 1652.6411 | D66: =+D55 -> 1100 | E66: =+C66/D66 -> 1.502401
B68: TOTAL COSTO UNIDAD MP+DESECHO+EMPAQUE | C68: =SUM(F60:F61) -> 2561.1849 | D68: =+D55 -> 1100 | E68: =+C68/D68 -> 2.3283499
B70: TOTAL MODI PREPARACION POR GRAMO | C70: =+F62 -> 495 | D70: =+D55 -> 1100 | E70: =+C70/D70 -> 0.45
B71: TOTAL MODI POR GRAMO | C71: =+F53 -> 567.61473 | D71: =+D70 -> 1100 | E71: =+C71/D71 -> 0.51601339
B73: TOTAL EMPAQUE POR GRAMO | C73: =+F51 -> 875.49103 | D73: =+D71 -> 1100 | E73: =+C73/D73 -> 0.79590094
B75: TOTAL GRAMO MP+MODI | E75: =+E66+E71 -> 2.0184144
B77: COSTO POR UNIDAD
B78: TOTAL COSTO MATERIA PRIMA | C78: =+C66 -> 1652.6411 | D78: =+D57 -> 1 | E78: =+C78/D78 -> 1652.6411
B80: TOTAL COSTO UNIDAD MP+DESECHO+EMPAQUE | C80: =+C68 -> 2561.1849 | D80: =+D57 -> 1 | E80: =+C80/D80 -> 2561.1849
B82: TOTAL MODI POR GRAMO | C82: =+C70 -> 495 | D82: =+D57 -> 1 | E82: =+C82/D82 -> 495
B83: TOTAL MODI POR GRAMO | C83: =+C71 -> 567.61473 | D83: =+D82 -> 1 | E83: =+C83/D83 -> 567.61473

Sheet Precio
B2: ESTRUCTURA DE COSTOS
B3: INDUSTRIA
F4: Fecha:
B5: UNIDAD | C5: DESCRIPCION MAT.PRIMA | D5: UNIDAD | E5: COSTO UNITARIO | F5: TOTAL COSTO | G5: % PREC. DEFINIDO | H5: CÓDIGOS
B6: 1 | C6: Torta chocolate porcionada | D6: =+B6 -> 1 | E6: =+'Costo Ensamble '!H50 -> 1652.6411 | F6: =+D6*E6 -> 1652.6411 | G6: =+F6/$F$23 -> 0.41665752 | H6: SPOON
B8: UNIDAD | C8: EMPAQUE | D8: UNIDAD | E8: COSTO UNITARIO | F8: TOTAL COSTO | G8: % PREC. DEFINIDO | H8: CÓDIGOS
B9: 1 | C9: EMPAQUE PLANTA | D9: =+B9 -> 1 | E9: =+'Costo Ensamble '!H51 -> 875.49103 | F9: =+D9*E9 -> 875.49103 | G9: =+F9/$F$23 -> 0.22072544 | H9: PLANTA
C11: TOTAL MATERIA PRIMA | F11: =SUM(F6) -> 1652.6411 | G11: =+F11/$F$23 -> 0.41665752
C12: TOTAL EMPAQUE | F12: =SUM(F9) -> 875.49103 | G12: =+F12/$F$23 -> 0.22072544
C13: TOTAL MATERIA PRIMA + EMPAQUE | F13: =SUM(F11:F12) -> 2528.1321 | G13: =+F13/$F$23 -> 0.63738296
B15: TOTAL MATERIA PRIMA + EMPAQUE | E15: Planta | F15: =+F13 -> 2528.1321 | G15: =+F15/$F$23 -> 0.63738296
C16: MODI PLANTA | F16: =+'Costo Ensamble '!H53 -> 567.61473 | G16: =+F16/$F$23 -> 0.14310485
C17: DESECHO | E17: 0 | F17: =+(F15+F16)*E17 -> 0 | G17: =+F17/$F$23 -> 0
C18: GAF | E18: 0 | F18: =+F16*E18 -> 0 | G18: =+F18/$F$23 -> 0
F19: =SUM(F15:F18) -> 3095.7468 | G19: =+F19/$F$21 -> 0.8
C20: % MK | E20: 0.25 | F20: =+F19*E20 -> 773.9367 | G20: =+F20/$F$23 -> 0.19512195
C21: COSTO PLANTA | F21: =SUM(F19:F20) -> 3869.6835 | G21: =+F21/$F$23 -> 0.97560976
C22: TRANSFERENCIA | E22: 0.025 | F22: =+F21*E22 -> 96.742088 | G22: =+F22/$F$23 -> 0.024390244
C23: PRECIO DE VENTA PLANTA A LOCAL | F23: =SUM(F21:F22) -> 3966.4256 | G23: =+F23/$F$23 -> 1
C27: PRECIO DE VENTA PLANTA A LOCAL | F27: =+F23 -> 3966.4256
C28: CAMIONES | D28: LOGISTICA | E28: 0.1 | F28: =+F27*E28 -> 396.64256 | G28: Costo | H28: % Margen
C29: COSTO TOTAL | F29: =SUM(F27:F28) -> 4363.0682 | G29: =+F29/$F$31 -> 0.68965517 | H29: =1-(F29/F31) -> 0.31034483
C30: MARK UP LOCAL | E30: 0.45 | F30: =+F29*E30 -> 1963.3807
C31: PRECIO VENTA SIN IMP | F31: =SUM(F29:F30) -> 6326.4489
C32: PRECIO VENTA IVI | E32: 0.13 | F32: =+F31*(1+E32) -> 7148.8872
C34: MARGEN SUPERMERCADO | E34: 0.65 | F34: =+F31/0.65 -> 9732.9982
C35: PRECIO IVI | E35: 0.13 | F35: =+F34*1.13 -> 10998.288
A37: Esteban Ramírez S. / Costos
