Workbook

Sheet Enmsable LOCALES
C1: SERVICIOS DE PASTELERIA S.A. | H1: CÓDIGO:
C2: ESPECIFICACION DE RECETA | H2: REVISIÓN:
C3: Postre de chocolate Cadbury LOCALES | H3: m
C4: Elaborado | D4: Jose Brizuela Lopez , chef
C5: Aprobado | D5: Esteban Cartin, Gte Manufactura
A7: AREA QUE PRODUCE: | D7: Postres | G7: AREA QUE EMPACA: | I7: Postres
A8: # Código | B8: # Codigo Netsuite | C8: Descripción del ingrediente | D8: Marca | G8: Medida alternativa | I8: Costo - Referencia
E9: Cantidad | F9: Unidad medida | G9: Cantidad | H9: Unidad medida | I9: Colones
C10: Emsamble
A11: 907000268 | B11: SE00345 | C11: Rosquete Chocolate 400 grs Spoon | D11: FAS | E11: 168 | F11: g
C12: DISCO MOUSSE CHOCOLATE | D12: FAS | E12: 440 | F12: g | G12: 1 | H12: UNIDAD
C13: Semillas de Cadbury | D13: FAS | E13: 80 | F13: g | H13: 1/4 Taza
C14: Mousse de pastelera | D14: FAS | E14: 400 | F14: g
C16: Decoracion
A17: 20100163 | B17: SE00337 | C17: Empaque Fudge De Chocolate | D17: FAS | E17: 50 | F17: g | G17: COLOCHO BOQUILLA 103
C18: Fudge Liquido | D18: FAS | E18: 70 | F18: g | J18: No hay receta
A19: 1210398 | B19: MP10384 | C19: Trozos Chocolate Oscuro | D19: FAS | E19: 35 | F19: g | G19: 6 ud
C20: Cuadros de Cadbury | D20: FAS | E20: 50 | F20: g | G20: 1/2 barra (6 pares)
C22: EMPAQUE
A23: 11400066 | B23: MP10007 | C23: Manjar Leche Condensada | E23: 10 | F23: g
A24: 51400021 | B24: EM10021 | C24: Quequera Red C/Base Alta 9" | D24: FAS | E24: 1 | F24: ud
A25: 1950693 | B25: EM10020 | C25: Orla #9 Dorada | D25: FAS | E25: 1 | F25: ud
A26: 0702069 | B26: EM10002 | C26: Etiq.Blanca 1 1/4 * 3/4 | E26: 1 | F26: ud
A27: 701096 | B27: EM10124 | C27: ETIQUETA BLANCA R-153 (UND) | D27: Cemusa | E27: 1 | F27: ud
A28: 702123 | B28: EM10011 | C28: ETIQUETA BLANCA 2 5/8X1 15/16 (UND) | D28: Etiplast | E28: 1 | F28: ud
D33: Cantidad | E33: Unidad
A34: PESO TOTAL OBTENIDO | D34: 1120 | E34: g | F34: Tiempo de Horneo:
A35: TIEMPO TOTAL DE PREPARACION | D35: 5 | E35: min | F35: Horno:
A36: CANTIDAD DE PORCIONES OBTENIDAS | D36: 1 | E36: ud | F36: Temperatura de Horneo:
A37: PESO DE CADA PORCIÓN | D37: =D34 -> 1120 | E37: g | F37: Otros
A38: MERMA | D38: =SUM(E11:E20)-D34 -> 173 | E38: g
A39: PROCEDIMIENTO DE PREPARACION DE LA RECETA
A40: 1, Agregar medio Rosquete de Chocolate Dawn de 400 g en un molde 22 cm Desmoldable.
A41: 2, Agregar las semillas toceadas, Agregar el disco de mousse de chocolate y colocarla en el Centro del Rosquete Grande
A42: 3, Agregar la mousse de crema pastelera dejar que corte al menos por 6 horas en refrigeraicon y dezmoldar y pegar con manjar a la orla.
A43: 4, Decorar con la Boquilla # 103 a los Borde con el Fudge Cholate Fas, Agregar el Fudge Liquido en el centro y Agregar los Trozos de Chocolate intercalando con los pares de chocolate cadbury
A44: 5, Tapar y etiquetar
A45: CONTROL DE CAMBIOS

Sheet Ensamble locales 2
C1: SERVICIOS DE PASTELERIA S.A. | H1: CÓDIGO:
C2: ESPECIFICACION DE RECETA | H2: REVISIÓN:
C3: Postre de chocolate Cadbury y arandanos rojos LOCALES | H3: m
C4: Elaborado | D4: Jose Brizuela Lopez , chef
C5: Aprobado | D5: Esteban Cartin, Gte Manufactura
A7: AREA QUE PRODUCE: | D7: Postres | G7: AREA QUE EMPACA: | I7: Postres
A8: # Código | B8: # Codigo Netsuite | C8: Descripción del ingrediente | D8: Marca | G8: Medida alternativa | I8: Costo - Referencia
E9: Cantidad | F9: Unidad medida | G9: Cantidad | H9: Unidad medida | I9: Colones
C10: Emsamble
A11: 907000268 | B11: SE00345 | C11: Rosquete Chocolate 400 grs Spoon | D11: FAS | E11: 168 | F11: g
C12: DISCO MOUSSE CHOCOLATE | D12: FAS | E12: 440 | F12: g | G12: 1 | H12: UNIDAD
C13: Semillas de Cadbury | D13: FAS | E13: 80 | F13: g | H13: 1/4 Taza
C14: Mousse de pastelera | D14: FAS | E14: 400 | F14: g
C16: Decoracion
A17: 20100163 | B17: SE00337 | C17: Empaque Fudge De Chocolate | D17: FAS | E17: 50 | F17: g | G17: COLOCHO BOQUILLA 103
C18: Fudge Liquido | D18: FAS | E18: 70 | F18: g
C19: Empaque Relleno Arandanos Rojos | D19: FAS | E19: 80 | F19: g | G19: Espejo en el centro
A20: 1210398 | B20: MP10384 | C20: Trozos Chocolate Oscuro | D20: FAS | E20: 35 | F20: g | G20: 6 ud
C21: Cuadros de Cadbury | D21: FAS | E21: 50 | F21: g | G21: 1/2 barra (6 pares)
C23: EMPAQUE
A24: 11400066 | B24: MP10007 | C24: Manjar Leche Condensada | E24: 10 | F24: g
A25: 51400021 | B25: EM10021 | C25: Quequera Red C/Base Alta 9" | D25: FAS | E25: 1 | F25: ud
A26: 1950693 | B26: EM10020 | C26: Orla #9 Dorada | D26: FAS | E26: 1 | F26: ud
A27: 0702069 | B27: EM10002 | C27: Etiq.Blanca 1 1/4 * 3/4 | E27: 1 | F27: ud
A28: 701096 | B28: EM10124 | C28: ETIQUETA BLANCA R-153 (UND) | D28: Cemusa | E28: 1 | F28: ud
A29: 702123 | B29: EM10011 | C29: ETIQUETA BLANCA 2 5/8X1 15/16 (UND) | D29: Etiplast | E29: 1 | F29: ud
D34: Cantidad | E34: Unidad
A35: PESO TOTAL OBTENIDO | D35: 1120 | E35: g | F35: Tiempo de Horneo:
A36: TIEMPO TOTAL DE PREPARACION | D36: 5 | E36: min | F36: Horno:
A37: CANTIDAD DE PORCIONES OBTENIDAS | D37: 1 | E37: ud | F37: Temperatura de Horneo:
A38: PESO DE CADA PORCIÓN | D38: 1120 | E38: g | F38: Otros
A39: MERMA | D39: 253 | E39: g
A40: PROCEDIMIENTO DE PREPARACION DE LA RECETA
A41: 1, Agregar medio Rosquete de Chocolate Dawn de 400 g en un molde 22 cm Desmoldable.
A42: 2, Agregar las semillas toceadas, Agregar el disco de mousse de chocolate y colocarla en el Centro del Rosquete Grande
A43: 3, Agregar la mousse de crema pastelera dejar que corte al menos por 6 horas en refrigeraicon y dezmoldar y pegar con manjar a la orla.
A44: 4, Decorar con la Boquilla # 103 a los Borde con el Fudge Cholate Fas, Agregar relleno de arandanos en el centro y hace run espejo, Agregar el Fudge Liquido en el borde y Agregar los Trozos de Chocolate intercalando con los pares de chocolate cadbury
A45: 5, Tapar y etiquetar
A46: CONTROL DE CAMBIOS

Sheet Ensamble 3
C1: SERVICIOS DE PASTELERIA S.A. | H1: CÓDIGO:
C2: ESPECIFICACION DE RECETA | H2: REVISIÓN:
C3: Postre de chocolate Cadbury y arandanos rojos LOCALES | H3: m
C4: Elaborado | D4: Jose Brizuela Lopez , chef
C5: Aprobado | D5: Esteban Cartin, Gte Manufactura
A7: AREA QUE PRODUCE: | D7: Postres | G7: AREA QUE EMPACA: | I7: Postres
A8: # Código | B8: # Codigo Netsuite | C8: Descripción del ingrediente | D8: Marca | G8: Medida alternativa | I8: Costo - Referencia
E9: Cantidad | F9: Unidad medida | G9: Cantidad | H9: Unidad medida | I9: Colones
C10: Emsamble
A11: 907000268 | B11: SE00345 | C11: Rosquete Chocolate 400 grs Spoon | D11: FAS | E11: 168 | F11: g
C12: DISCO MOUSSE CHOCOLATE | D12: FAS | E12: 340 | F12: g | G12: 1 | H12: UNIDAD
C13: Semillas de Cadbury | D13: FAS | E13: 50 | F13: g
C14: Mousse de pastelera | D14: FAS | E14: 350 | F14: g
C16: Decoracion
A17: 20100163 | B17: SE00337 | C17: Empaque Fudge De Chocolate | D17: FAS | E17: 50 | F17: g | G17: COLOCHO BOQUILLA 103
C18: Fudge Liquido | D18: FAS | E18: 50 | F18: g
C19: Empaque Relleno Arandanos Rojos | D19: FAS | E19: 60 | F19: g | G19: Espejo en el centro
C20: Cuadros de Cadbury | D20: FAS | E20: 25 | F20: g | G20: 1/4 barra (3 pares)
C22: EMPAQUE
A23: 11400066 | B23: MP10007 | C23: Manjar Leche Condensada | E23: 10 | F23: g
A24: 51400021 | B24: EM10021 | C24: Quequera Red C/Base Alta 9" | D24: FAS | E24: 1 | F24: ud
A25: 1950693 | B25: EM10020 | C25: Orla #9 Dorada | D25: FAS | E25: 1 | F25: ud
A26: 0702069 | B26: EM10002 | C26: Etiq.Blanca 1 1/4 * 3/4 | E26: 1 | F26: ud
A27: 701096 | B27: EM10124 | C27: ETIQUETA BLANCA R-153 (UND) | D27: Cemusa | E27: 1 | F27: ud
A28: 702123 | B28: EM10011 | C28: ETIQUETA BLANCA 2 5/8X1 15/16 (UND) | D28: Etiplast | E28: 1 | F28: ud
D33: Cantidad | E33: Unidad
A34: PESO TOTAL OBTENIDO | D34: 900 | E34: g | F34: Tiempo de Horneo:
A35: TIEMPO TOTAL DE PREPARACION | D35: 5 | E35: min | F35: Horno:
A36: CANTIDAD DE PORCIONES OBTENIDAS | D36: 1 | E36: ud | F36: Temperatura de Horneo:
A37: PESO DE CADA PORCIÓN | D37: 900 | E37: g | F37: Otros
A38: MERMA | D38: 253 | E38: g
A39: PROCEDIMIENTO DE PREPARACION DE LA RECETA
A40: 1, Agregar medio Rosquete de Chocolate Dawn de 400 g en un molde 22 cm Desmoldable.
A41: 2, Agregar las semillas toceadas, Agregar el disco de mousse de chocolate y colocarla en el Centro del Rosquete Grande
A42: 3, Agregar la mousse de crema pastelera dejar que corte al menos por 6 horas en refrigeraicon y dezmoldar y pegar con manjar a la orla.
A43: 4, Decorar con la Boquilla # 103 a los Borde con el Fudge Cholate Fas, Agregar relleno de arandanos en el centro y hace run espejo, Agregar el Fudge Liquido en el borde y Agregar los pares de chocolate cadbury
A44: 5, Tapar y etiquetar
A45: CONTROL DE CAMBIOS

Sheet Costo Ensamble locales
E1: Precio Local | F1: Costo MP | G1: Costo EM | H1: Costo MO
E2: =IFERROR(O68,"") -> 5773.4875 | F2: =IFERROR(H59,"") -> 4020.6054 | G2: =IFERROR(H60,"") -> 487.86875 | H2: =IFERROR(H62,"") -> 648.45223
A5: ESTRUCTURA DE COSTOS
F6: Fecha: | H6: =TODAY() -> 45776
A7: UNIDADES | B7: DESCRIPCION MAT.PRIMA | C7: UNIDADES | D7: UND MEDIDA | E7: COSTO UNITARIO | F7: TOTAL COSTO | G7: % PREC. DEFINIDO | H7: CODIGOS
A8: 0 | B8: Trozos Chocolate Oscuro | C8: =+A8 -> 0 | D8: =IFERROR(VLOOKUP(H8,'[1]Consolidado MP Planta'!$A$2:$M$823,13,0),"") | E8: 11.5 | F8: =IFERROR(C8*E8,"") -> 0 | G8: =IFERROR(F8/$F$72,"") -> 0 | H8: 1210398
A9: 25 | B9: Cuadros de Cadbury | C9: =+A9 -> 25 | D9: =IFERROR(VLOOKUP(H9,'[1]Consolidado MP Planta'!$A$2:$M$823,13,0),"") | E9: 10.48 | F9: =IFERROR(C9*E9,"") -> 262 | G9: =IFERROR(F9/$F$72,"") -> 0.053536185 | M9: Precio cadbury estimado mas x menos
A10: 10 | B10: Manjar Leche Condensada | C10: =+A10 -> 10 | D10: =IFERROR(VLOOKUP(H10,'[1]Consolidado MP Planta'!$A$2:$M$823,13,0),"") | E10: 2.56 | F10: =IFERROR(C10*E10,"") -> 25.6 | G10: =IFERROR(F10/$F$72,"") -> 0.0052310165 | H10: 11400066
B11: =IFERROR(VLOOKUP(H11,'[1]Consolidado MP Planta'!$A$2:$M$823,3,0),"") | C11: =+A11 -> 0 | D11: =IFERROR(VLOOKUP(H11,'[1]Consolidado MP Planta'!$A$2:$M$823,13,0),"") | E11: =IFERROR(VLOOKUP(H11,'[1]Consolidado MP Planta'!$A$2:$M$823,12,0),"") | F11: =IFERROR(C11*E11,"") | G11: =IFERROR(F11/$F$72,"")
B12: =IFERROR(VLOOKUP(H12,'[1]Consolidado MP Planta'!$A$2:$M$823,3,0),"") | C12: =+A12 -> 0 | D12: =IFERROR(VLOOKUP(H12,'[1]Consolidado MP Planta'!$A$2:$M$823,13,0),"") | E12: =IFERROR(VLOOKUP(H12,'[1]Consolidado MP Planta'!$A$2:$M$823,12,0),"") | F12: =IFERROR(C12*E12,"") | G12: =IFERROR(F12/$F$72,"")
B13: =IFERROR(VLOOKUP(H13,'[1]Consolidado MP Planta'!$A$2:$M$823,3,0),"") | C13: =+A13 -> 0 | D13: =IFERROR(VLOOKUP(H13,'[1]Consolidado MP Planta'!$A$2:$M$823,13,0),"") | E13: =IFERROR(VLOOKUP(H13,'[1]Consolidado MP Planta'!$A$2:$M$823,12,0),"") | F13: =IFERROR(C13*E13,"") | G13: =IFERROR(F13/$F$72,"")
B14: =IFERROR(VLOOKUP(H14,'[1]Consolidado MP Planta'!$A$2:$M$823,3,0),"") | C14: =+A14 -> 0 | D14: =IFERROR(VLOOKUP(H14,'[1]Consolidado MP Planta'!$A$2:$M$823,13,0),"") | E14: =IFERROR(VLOOKUP(H14,'[1]Consolidado MP Planta'!$A$2:$M$823,12,0),"") | F14: =IFERROR(C14*E14,"") | G14: =IFERROR(F14/$F$72,"")
B15: =IFERROR(VLOOKUP(H15,'[2]ARTICULOS MP PLANTA'!$A$2:$G$589,2,0),"")
A16: UNIDADES | B16: MATERIA PRIMA SEMIELABORADOS | C16: UNIDADES | D16: UND MEDIDA | E16: COSTO UNITARIO | F16: TOTAL COSTO | G16: % PREC. DEFINIDO | H16: CODIGOS
A17: 0.5 | B17: Rosquete Chocolate 400 grs Spoon | C17: =+A17 -> 0.5 | D17: und | E17: 517.65 | F17: =IFERROR(E17*C17,"") -> 258.825 | G17: =IFERROR(F17/$F$72,"") -> 0.052887416 | H17: 907000268
A18: 1 | B18: DISCO MOUSSE CHOCOLATE | C18: =+A18 -> 1 | D18: =IFERROR(VLOOKUP(H18,[1]SEMIELABORADOS!$A$2:$M$6000,6,0),"") | E18: =+'Costo disco'!H53 -> 1467.2327 | F18: =IFERROR(E18*C18,"") -> 1467.2327 | G18: =IFERROR(F18/$F$72,"") -> 0.29980931
A19: 50 | B19: Semillas de Cadbury | C19: =+A19 -> 50 | D19: =IFERROR(VLOOKUP(H19,[1]SEMIELABORADOS!$A$2:$M$6000,6,0),"") | E19: =+'costo semillas Cadbury'!E69 -> 3.9676 | F19: =IFERROR(E19*C19,"") -> 198.38 | G19: =IFERROR(F19/$F$72,"") -> 0.040536291
A20: 350 | B20: Mousse de pastelera | C20: =+A20 -> 350 | D20: =IFERROR(VLOOKUP(H20,[1]SEMIELABORADOS!$A$2:$M$6000,6,0),"") | E20: =+'Costo Mousse pastelera'!E69 -> 2.6250455 | F20: =IFERROR(E20*C20,"") -> 918.76593 | G20: =IFERROR(F20/$F$72,"") -> 0.18773749 | M20: =6*24 -> 144 | N20: =+M20*100 -> 14400 | O20: =12*24 -> 288 | P20: =+O20*42 -> 12096
A21: 50 | B21: Empaque Fudge De Chocolate | C21: =+A21 -> 50 | D21: =IFERROR(VLOOKUP(H21,[1]SEMIELABORADOS!$A$2:$M$6000,6,0),"") | E21: 2.34 | F21: =IFERROR(E21*C21,"") -> 117 | G21: =IFERROR(F21/$F$72,"") -> 0.02390738 | H21: 20100163 | N21: =150452/N20 -> 10.448056 | P21: =158763/P20 -> 13.125248
A22: 50 | B22: Fudge Liquido | C22: =+A22 -> 50 | D22: =IFERROR(VLOOKUP(H22,[1]SEMIELABORADOS!$A$2:$M$6000,6,0),"") | E22: 3.5 | F22: =IFERROR(E22*C22,"") -> 175 | G22: =IFERROR(F22/$F$72,"") -> 0.035758902
A23: 60 | B23: Empaque Relleno Arandanos Rojos | C23: =+A23 -> 60 | D23: =IFERROR(VLOOKUP(H23,[1]SEMIELABORADOS!$A$2:$M$6000,6,0),"") | E23: =+'Costo Empaque Relleno Arand'!E69 -> 6.6233641 | F23: =IFERROR(E23*C23,"") -> 397.40185 | G23: =IFERROR(F23/$F$72,"") -> 0.081203736
A24: 60 | B24: Galleta Oreo Bañada Chocolate Blanco | C24: =+A24 -> 60 | D24: =IFERROR(VLOOKUP(H24,[1]SEMIELABORADOS!$A$2:$M$6000,6,0),"") | E24: 3.34 | F24: =IFERROR(E24*C24,"") -> 200.4 | G24: =IFERROR(F24/$F$72,"") -> 0.040949051 | H24: 902000176
A26: UNIDADES | B26: EMPAQUE | C26: UNIDADES | D26: UND MEDIDA | E26: COSTO UNITARIO | F26: TOTAL COSTO | G26: % PREC. DEFINIDO | H26: CODIGOS
A27: 1 | B27: =IFERROR(VLOOKUP(H27,'[1]Consolidado MP Planta'!$A$2:$M$823,3,0),"") -> QUEQUERA RED C/BASE ALTA 9" (CAJA:100 U) | C27: =+A27 -> 1 | D27: =IFERROR(VLOOKUP(H27,'[1]Consolidado MP Planta'!$A$2:$M$823,13,0),"") -> Und | E27: 342.24 | F27: =IFERROR(C27*E27,"") -> 342.24 | G27: =IFERROR(F27/$F$72,"") -> 0.069932152 | H27: 51400021
A28: 1 | B28: =IFERROR(VLOOKUP(H28,'[1]Consolidado MP Planta'!$A$2:$M$823,3,0),"") -> ORLA #9 DORADA (UND) | C28: =+A28 -> 1 | D28: =IFERROR(VLOOKUP(H28,'[1]Consolidado MP Planta'!$A$2:$M$823,13,0),"") -> Und | E28: =IFERROR(VLOOKUP(H28,'[1]Consolidado MP Planta'!$A$2:$M$823,12,0),"") -> 135 | F28: =IFERROR(C28*E28,"") -> 135 | G28: =IFERROR(F28/$F$72,"") -> 0.027585439 | H28: 1950693
A29: 1 | B29: =IFERROR(VLOOKUP(H29,'[1]Consolidado MP Planta'!$A$2:$M$823,3,0),"") -> ETIQ.BLANCA 1 1/4 * 3/4 (UND) | C29: =+A29 -> 1 | D29: =IFERROR(VLOOKUP(H29,'[1]Consolidado MP Planta'!$A$2:$M$823,13,0),"") -> Und | E29: =IFERROR(VLOOKUP(H29,'[1]Consolidado MP Planta'!$A$2:$M$823,12,0),"") -> 0.58 | F29: =IFERROR(C29*E29,"") -> 0.58 | G29: =IFERROR(F29/$F$72,"") -> 0.00011851522 | H29: 0702069
A30: 1 | B30: =IFERROR(VLOOKUP(H30,'[1]Consolidado MP Planta'!$A$2:$M$823,3,0),"") -> ETIQUETA BLANCA R-153 (UND) | C30: =+A30 -> 1 | D30: =IFERROR(VLOOKUP(H30,'[1]Consolidado MP Planta'!$A$2:$M$823,13,0),"") -> Und | E30: =IFERROR(VLOOKUP(H30,'[1]Consolidado MP Planta'!$A$2:$M$823,12,0),"") -> 0.39 | F30: =IFERROR(C30*E30,"") -> 0.39 | G30: =IFERROR(F30/$F$72,"") -> 7.9691267e-05 | H30: 701096
A31: 1 | B31: =IFERROR(VLOOKUP(H31,'[1]Consolidado MP Planta'!$A$2:$M$823,3,0),"") -> ETIQUETA BLANCA 2 5/8X1 15/16 (UND) | C31: =+A31 -> 1 | D31: =IFERROR(VLOOKUP(H31,'[1]Consolidado MP Planta'!$A$2:$M$823,13,0),"") -> Und | E31: =IFERROR(VLOOKUP(H31,'[1]Consolidado MP Planta'!$A$2:$M$823,12,0),"") -> 2.128 | F31: =IFERROR(C31*E31,"") -> 2.128 | G31: =IFERROR(F31/$F$72,"") -> 0.00043482825 | H31: 0702123
B32: =IFERROR(VLOOKUP(H32,'[1]Consolidado MP Planta'!$A$2:$M$823,3,0),"") | C32: =+A32 -> 0 | D32: =IFERROR(VLOOKUP(H32,'[1]Consolidado MP Planta'!$A$2:$M$823,13,0),"") | E32: =IFERROR(VLOOKUP(H32,'[1]Consolidado MP Planta'!$A$2:$M$823,12,0),"") | F32: =IFERROR(C32*E32,"") | G32: =IFERROR(F32/$F$72,"")
B33: =IFERROR(VLOOKUP(H33,'[1]Consolidado MP Planta'!$A$2:$M$823,3,0),"") | C33: =+A33 -> 0 | D33: =IFERROR(VLOOKUP(H33,'[1]Consolidado MP Planta'!$A$2:$M$823,13,0),"") | E33: =IFERROR(VLOOKUP(H33,'[1]Consolidado MP Planta'!$A$2:$M$823,12,0),"") | F33: =IFERROR(C33*E33,"") | G33: =IFERROR(F33/$F$72,"")
B34: =IFERROR(VLOOKUP(H34,'[1]Consolidado MP Planta'!$A$2:$M$823,3,0),"") | C34: =+A34 -> 0 | D34: =IFERROR(VLOOKUP(H34,'[1]Consolidado MP Planta'!$A$2:$M$823,13,0),"") | E34: =IFERROR(VLOOKUP(H34,'[1]Consolidado MP Planta'!$A$2:$M$823,12,0),"") | F34: =IFERROR(C34*E34,"") | G34: =IFERROR(F34/$F$72,"")
B35: =IFERROR(VLOOKUP(H35,'[1]Consolidado MP Planta'!$A$2:$M$823,3,0),"") | C35: =+A35 -> 0 | D35: =IFERROR(VLOOKUP(H35,'[1]Consolidado MP Planta'!$A$2:$M$823,13,0),"") | E35: =IFERROR(VLOOKUP(H35,'[1]Consolidado MP Planta'!$A$2:$M$823,12,0),"") | F35: =IFERROR(C35*E35,"") | G35: =IFERROR(F35/$F$72,"")
B36: =IFERROR(VLOOKUP(H36,'[1]Consolidado MP Planta'!$A$2:$M$823,3,0),"") | C36: =+A36 -> 0 | D36: =IFERROR(VLOOKUP(H36,'[1]Consolidado MP Planta'!$A$2:$M$823,13,0),"") | E36: =IFERROR(VLOOKUP(H36,'[1]Consolidado MP Planta'!$A$2:$M$823,12,0),"") | F36: =IFERROR(C36*E36,"") | G36: =IFERROR(F36/$F$72,"")
A38: UNIDADES | B38: EMPAQUE SEMIELABORADOS | C38: UNIDADES | D38: UND MEDIDA | E38: COSTO UNITARIO | F38: TOTAL COSTO | G38: % PREC. DEFINIDO | H38: CODIGOS
A39: =+A17 -> 0.5 | B39: Rosquete Chocolate 400 grs Spoon | C39: =+A39 -> 0.5 | D39: =IFERROR(VLOOKUP(H39,[1]SEMIELABORADOS!$A$2:$M$6000,6,0),"") | E39: 5.29 | F39: =IFERROR(E39*C39,"") -> 2.645 | G39: =IFERROR(F39/$F$72,"") -> 0.00054047026 | H39: 907000268
A40: =+A18 -> 1 | B40: DISCO MOUSSE CHOCOLATE | C40: =+A40 -> 1 | D40: =IFERROR(VLOOKUP(H40,[1]SEMIELABORADOS!$A$2:$M$6000,6,0),"") | E40: =+'Costo disco'!H54 -> 2.4662564 | F40: =IFERROR(E40*C40,"") -> 2.4662564 | G40: =IFERROR(F40/$F$72,"") -> 0.00050394641
A41: =+A19 -> 50 | B41: Semillas de Cadbury | C41: =+A41 -> 50 | D41: =IFERROR(VLOOKUP(H41,[1]SEMIELABORADOS!$A$2:$M$6000,6,0),"") | E41: =+'costo semillas Cadbury'!E76 -> 0.0049747048 | F41: =IFERROR(E41*C41,"") -> 0.24873524 | G41: =IFERROR(F41/$F$72,"") -> 5.0825709e-05
A42: =+A20 -> 350 | B42: Mousse de pastelera | C42: =+A42 -> 350 | D42: =IFERROR(VLOOKUP(H42,[1]SEMIELABORADOS!$A$2:$M$6000,6,0),"") | E42: =+'Costo Mousse pastelera'!E76 -> 0 | F42: =IFERROR(E42*C42,"") -> 0 | G42: =IFERROR(F42/$F$72,"") -> 0
A43: =+A21 -> 50 | B43: Empaque Fudge De Chocolate | C43: =+A43 -> 50 | D43: =IFERROR(VLOOKUP(H43,[1]SEMIELABORADOS!$A$2:$M$6000,6,0),"") | E43: 0.01 | F43: =IFERROR(E43*C43,"") -> 0.5 | G43: =IFERROR(F43/$F$72,"") -> 0.00010216829
A44: =+A22 -> 50 | B44: Fudge Liquido | C44: =+A44 -> 50 | D44: =IFERROR(VLOOKUP(H44,[1]SEMIELABORADOS!$A$2:$M$6000,6,0),"") | E44: 0.01 | F44: =IFERROR(E44*C44,"") -> 0.5 | G44: =IFERROR(F44/$F$72,"") -> 0.00010216829
A45: =+A23 -> 60 | B45: Empaque Relleno Arandanos Rojos | C45: =+A45 -> 60 | D45: =IFERROR(VLOOKUP(H45,[1]SEMIELABORADOS!$A$2:$M$6000,6,0),"") | E45: =+'Costo Empaque Relleno Arand'!E76 -> 0.019512564 | F45: =IFERROR(E45*C45,"") -> 1.1707539 | G45: =IFERROR(F45/$F$72,"") -> 0.00023922784
A46: =+A24 -> 60 | B46: Galleta Oreo Bañada Chocolate Blanco | C46: =+A46 -> 60 | D46: =IFERROR(VLOOKUP(H46,[1]SEMIELABORADOS!$A$2:$M$6000,6,0),"") | E46: 0 | F46: =IFERROR(E46*C46,"") -> 0 | G46: =IFERROR(F46/$F$72,"") -> 0
A48: UNIDADES | B48: MODI | C48: UNIDADES | D48: UND MEDIDA | E48: COSTO UNITARIO | F48: TOTAL COSTO | G48: % PREC. DEFINIDO | H48: CODIGOS
A49: =+A39 -> 0.5 | B49: Rosquete Chocolate 400 grs Spoon | C49: =+A49 -> 0.5 | D49: =IFERROR(VLOOKUP(H49,[1]SEMIELABORADOS!$A$2:$M$6000,6,0),"") | E49: 33.34 | F49: =IFERROR(E49*C49,"") -> 16.67 | G49: =IFERROR(F49/$F$72,"") -> 0.0034062908 | H49: 907000268
A50: =+A40 -> 1 | B50: DISCO MOUSSE CHOCOLATE | C50: =+A50 -> 1 | D50: =IFERROR(VLOOKUP(H50,[1]SEMIELABORADOS!$A$2:$M$6000,6,0),"") | E50: =+'Costo disco'!H56 -> 247.75827 | F50: =IFERROR(E50*C50,"") -> 247.75827 | G50: =IFERROR(F50/$F$72,"") -> 0.050626078
A51: =+A41 -> 50 | B51: Semillas de Cadbury | C51: =+A51 -> 50 | D51: =IFERROR(VLOOKUP(H51,[1]SEMIELABORADOS!$A$2:$M$6000,6,0),"") | E51: =+'costo semillas Cadbury'!E74 -> 0.122 | F51: =IFERROR(E51*C51,"") -> 6.1 | G51: =IFERROR(F51/$F$72,"") -> 0.0012464532
A52: =+A42 -> 350 | B52: Mousse de pastelera | C52: =+A52 -> 350 | D52: =IFERROR(VLOOKUP(H52,[1]SEMIELABORADOS!$A$2:$M$6000,6,0),"") | E52: =+'Costo Mousse pastelera'!E74 -> 0.1403 | F52: =IFERROR(E52*C52,"") -> 49.105 | G52: =IFERROR(F52/$F$72,"") -> 0.010033948
A53: =+A43 -> 50 | B53: Empaque Fudge De Chocolate | C53: =+A53 -> 50 | D53: =IFERROR(VLOOKUP(H53,[1]SEMIELABORADOS!$A$2:$M$6000,6,0),"") | E53: 0.09 | F53: =IFERROR(E53*C53,"") -> 4.5 | G53: =IFERROR(F53/$F$72,"") -> 0.00091951462
A54: =+A44 -> 50 | B54: Fudge Liquido | C54: =+A54 -> 50 | D54: =IFERROR(VLOOKUP(H54,[1]SEMIELABORADOS!$A$2:$M$6000,6,0),"") | E54: 0.09 | F54: =IFERROR(E54*C54,"") -> 4.5 | G54: =IFERROR(F54/$F$72,"") -> 0.00091951462
A55: =+A45 -> 60 | B55: Empaque Relleno Arandanos Rojos | C55: =+A55 -> 60 | D55: =IFERROR(VLOOKUP(H55,[1]SEMIELABORADOS!$A$2:$M$6000,6,0),"") | E55: =+'Costo Empaque Relleno Arand'!E74 -> 0.09698268 | F55: =IFERROR(E55*C55,"") -> 5.8189608 | G55: =IFERROR(F55/$F$72,"") -> 0.0011890266
A56: =+A46 -> 60 | B56: Galleta Oreo Bañada Chocolate Blanco | C56: =+A56 -> 60 | D56: =IFERROR(VLOOKUP(H56,[1]SEMIELABORADOS!$A$2:$M$6000,6,0),"") | E56: 0.15 | F56: =IFERROR(E56*C56,"") -> 9 | G56: =IFERROR(F56/$F$72,"") -> 0.0018390292
A57: 1 | B57: MODI PREPARACION | C57: =+A57 -> 1 | D57: N/A | E57: =+F71 -> 305 | F57: =IFERROR(C57*E57,"") -> 305 | G57: =IFERROR(F57/$F$72,"") -> 0.062322658
B59: TOTAL MATERIA PRIMA | F59: =SUM(F8:F14,F17:F24) -> 4020.6054 | G59: =+F59/$F$72 -> 0.82155677 | H59: =+F59/$D$66 -> 4020.6054
B60: TOTAL EMPAQUE | F60: =SUM(F27:F36,F39:F46) -> 487.86875 | G60: =+F60/$F$72 -> 0.099689432 | H60: =+F60/$D$66 -> 487.86875 | K60: TOTAL MATERIA PRIMA + EMPAQUE | O60: =+F61 -> 4508.4742
B61: TOTAL MATERIAS P. + EMPAQUES | F61: =+F59+F60 -> 4508.4742 | G61: =+F61/$F$72 -> 0.92124621 | H61: =+F61/$D$66 -> 4508.4742 | M61: MODI PLANTA | O61: =+H62 -> 648.45223
C62: TOTAL MODI | F62: =SUM(F49:F57) -> 648.45223 | G62: =+F62/$F$72 -> 0.13250251 | H62: =+F62/$D$66 -> 648.45223 | M62: DESECHO | O62: =O60*N62 -> 0
M63: COSTO PLANTA | O63: =SUM(O60:O62) -> 5156.9264
B64: GRAMOS | D64: 950 | H64: =+H62/61 -> 10.630364 | M64: % GIF | O64: =+H65 -> 616.56114
B65: PESO POR UNIDAD | D65: 950 | H65: =+H64*58 -> 616.56114 | M65: COSTO PLANTA | O65: =SUM(O63:O64) -> 5773.4875
B66: UNIDADES TOTALES | D66: =+D64/D65 -> 1 | O66: =+O65*N66 -> 0
B67: UNIDAD MEDIDA | K67: PRECIO DE VENTA PLANTA A LOCAL | O67: =SUM(O65:O66) -> 5773.4875 | P67: GR
E68: S/ COSTO | F68: TOTAL | L68: UNIDAD | O68: =+O67/D66 -> 5773.4875 | P68: =+O68/D65 -> 6.0773553
B69: TOTAL MATERIAS P. + EMPAQUES | E69: =+F69/F69 -> 1 | F69: =SUM(F61) -> 4508.4742 | G69: =+F69/$F$72 -> 0.92124621
B70: DESECHOS Y PERDIDAS | E70: 0.02 | F70: =+F59*E70 -> 80.412109 | G70: =+F70/$F$72 -> 0.016431135
B71: MANO OBRA DIRECTA | D71: 5 | E71: 61 | F71: =+E71*D71 -> 305 | G71: =+F71/$F$72 -> 0.062322658
B72: TOTAL COSTO PLANTA | F72: =SUM(F69:F71) -> 4893.8863 | G72: =+F72/$F$72 -> 1 | M72: MODI 61 COLONES X MIN
M73: Gf 58 colones min
B74: COSTO POR GRAMO | M74: ,
B75: TOTAL COSTO MATERIA PRIMA | C75: =+F59 -> 4020.6054 | D75: =+D64 -> 950 | E75: =+C75/D75 -> 4.2322162
B77: TOTAL COSTO UNIDAD MP+DESECHO+EMPAQUE | C77: =SUM(F69:F70) -> 4588.8863 | D77: =+D64 -> 950 | E77: =+C77/D77 -> 4.8304066
B79: TOTAL MODI PREPARACION POR GRAMO | C79: =+F71 -> 305 | D79: =+D64 -> 950 | E79: =+C79/D79 -> 0.32105263
B80: TOTAL MODI POR GRAMO | C80: =+F62 -> 648.45223 | D80: =+D79 -> 950 | E80: =+C80/D80 -> 0.68258129
B82: TOTAL EMPAQUE POR GRAMO | C82: =+F60 -> 487.86875 | D82: =+D80 -> 950 | E82: =+C82/D82 -> 0.51354605
B84: TOTAL GRAMO MP+MODI | E84: =+E75+E80 -> 4.9147975
B86: COSTO POR UNIDAD
B87: TOTAL COSTO MATERIA PRIMA | C87: =+C75 -> 4020.6054 | D87: =+D66 -> 1 | E87: =+C87/D87 -> 4020.6054
B89: TOTAL COSTO UNIDAD MP+DESECHO+EMPAQUE | C89: =+C77 -> 4588.8863 | D89: =+D66 -> 1 | E89: =+C89/D89 -> 4588.8863
B91: TOTAL MODI POR GRAMO | C91: =+C79 -> 305 | D91: =+D66 -> 1 | E91: =+C91/D91 -> 305
B92: TOTAL MODI POR GRAMO | C92: =+C80 -> 648.45223 | D92: =+D91 -> 1 | E92: =+C92/D92 -> 648.45223

Sheet Emsamble IND
C1: SERVICIOS DE PASTELERIA S.A. | H1: CÓDIGO:
C2: ESPECIFICACION DE RECETA | H2: REVISIÓN:
C3: Postre de chocolate Cadbury INDUSTRIA | H3: m
C4: Elaborado | D4: Jose Brizuela Lopez , chef
C5: Aprobado | D5: Esteban Cartin, Gte Manufactura
A7: AREA QUE PRODUCE: | D7: Postres | G7: AREA QUE EMPACA: | I7: Postres
A8: # Código | B8: # Codigo Netsuite | C8: Descripción del ingrediente | D8: Marca | G8: Medida alternativa | I8: Costo - Referencia
E9: Cantidad | F9: Unidad medida | G9: Cantidad | H9: Unidad medida | I9: Colones
C10: Emsamble
A11: 907000268 | B11: SE00345 | C11: Rosquete Chocolate 400 grs Spoon | D11: FAS | E11: 168 | F11: g
C12: DISCO MOUSSE CHOCOLATE | D12: FAS | E12: 440 | F12: g | G12: 1 | H12: UNIDAD
C13: Semillas de Cadbury | D13: FAS | E13: 80 | F13: g | H13: 1/4 Taza
C14: Mousse de pastelera | D14: FAS | E14: 400 | F14: g
C16: Decoracion
A17: 20100163 | B17: SE00337 | C17: Empaque Fudge De Chocolate | D17: FAS | E17: 50 | F17: g | G17: COLOCHO BOQUILLA 103
C18: Fudge Liquido | D18: FAS | E18: 70 | F18: g
A19: 1210398 | B19: MP10384 | C19: Trozos Chocolate Oscuro | D19: FAS | E19: 35 | F19: g | G19: 6 ud
C20: Cuadros de Cadbury | D20: FAS | E20: 50 | F20: g | G20: 1/2 barra (6 pares)
C22: EMPAQUE
A23: 11400066 | B23: MP10007 | C23: Manjar Leche Condensada | E23: 10 | F23: g
A24: 51400021 | B24: EM10021 | C24: Quequera Red C/Base Alta 9" | D24: FAS | E24: 1 | F24: ud
A25: 1950693 | B25: EM10020 | C25: Orla #9 Dorada | D25: FAS | E25: 1 | F25: ud
A26: 0702069 | B26: EM10002 | C26: Etiq.Blanca 1 1/4 * 3/4 | E26: 1 | F26: ud
A27: 701096 | B27: EM10124 | C27: ETIQUETA BLANCA R-153 (UND) | D27: Cemusa | E27: 1 | F27: ud
A28: 702123 | B28: EM10011 | C28: ETIQUETA BLANCA 2 5/8X1 15/16 (UND) | D28: Etiplast | E28: 1 | F28: ud
A29: 60100120 | B29: EM10314 | C29: Etiqueta Edicion Especial | E29: 1 | F29: ud
D33: Cantidad | E33: Unidad
A34: PESO TOTAL OBTENIDO | D34: 1120 | E34: g | F34: Tiempo de Horneo:
A35: TIEMPO TOTAL DE PREPARACION | D35: 5 | E35: min | F35: Horno:
A36: CANTIDAD DE PORCIONES OBTENIDAS | D36: 1 | E36: ud | F36: Temperatura de Horneo:
A37: PESO DE CADA PORCIÓN | D37: =D34 -> 1120 | E37: g | F37: Otros
A38: MERMA | D38: =SUM(E11:E20)-D34 -> 173 | E38: g
A39: PROCEDIMIENTO DE PREPARACION DE LA RECETA
A40: 1, Agregar medio Rosquete de Chocolate Dawn de 400 g en un molde 22 cm Desmoldable.
A41: 2, Agregar las semillas toceadas, Agregar el disco de mousse de chocolate y colocarla en el Centro del Rosquete Grande
A42: 3, Agregar la mousse de crema pastelera dejar que corte al menos por 6 horas en refrigeraicon y dezmoldar y pegar con manjar a la orla.
A43: 4, Decorar con la Boquilla # 103 a los Borde con el Fudge Cholate Fas, Agregar el Fudge Liquido en el centro y Agregar los Trozos de Chocolate intercalando con los pares de chocolate cadbury
A44: 5, Tapar y etiquetar
A45: CONTROL DE CAMBIOS

Sheet Ensamble Industria 2
C1: SERVICIOS DE PASTELERIA S.A. | H1: CÓDIGO:
C2: ESPECIFICACION DE RECETA | H2: REVISIÓN:
C3: Postre de chocolate Cadbury y arandanos rojos INDUSTRIA | H3: m
C4: Elaborado | D4: Jose Brizuela Lopez , chef
C5: Aprobado | D5: Esteban Cartin, Gte Manufactura
A7: AREA QUE PRODUCE: | D7: Postres | G7: AREA QUE EMPACA: | I7: Postres
A8: # Código | B8: # Codigo Netsuite | C8: Descripción del ingrediente | D8: Marca | G8: Medida alternativa | I8: Costo - Referencia
E9: Cantidad | F9: Unidad medida | G9: Cantidad | H9: Unidad medida | I9: Colones
C10: Emsamble
A11: 907000268 | B11: SE00345 | C11: Rosquete Chocolate 400 grs Spoon | D11: FAS | E11: 168 | F11: g | G11: 0.5 | H11: Unidad
C12: DISCO MOUSSE CHOCOLATE | D12: FAS | E12: 340 | F12: g | G12: 1 | H12: UNIDAD
C13: Semillas de Cadbury | D13: FAS | E13: 50 | F13: g | H13: 1/4 Taza
C14: Mousse de pastelera | D14: FAS | E14: 350 | F14: g
C16: Decoracion
A17: 20100163 | B17: SE00337 | C17: Empaque Fudge De Chocolate | D17: FAS | E17: 50 | F17: g | G17: COLOCHO BOQUILLA 103
C18: Fudge Liquido | D18: FAS | E18: 50 | F18: g
C19: Empaque Relleno Arandanos Rojos | D19: FAS | E19: 60 | F19: g | G19: Espejo en el centro
C20: Cuadros de Cadbury | D20: FAS | E20: 25 | F20: g | G20: 1/2 barra (6 pares)
C22: EMPAQUE
A23: 11400066 | B23: MP10007 | C23: Manjar Leche Condensada | E23: 10 | F23: g
A24: 51400021 | B24: EM10021 | C24: Quequera Red C/Base Alta 9" | D24: FAS | E24: 1 | F24: ud
A25: 1950693 | B25: EM10020 | C25: Orla #9 Dorada | D25: FAS | E25: 1 | F25: ud
A26: 0702069 | B26: EM10002 | C26: Etiq.Blanca 1 1/4 * 3/4 | E26: 1 | F26: ud
A27: 701096 | B27: EM10124 | C27: ETIQUETA BLANCA R-153 (UND) | D27: Cemusa | E27: 1 | F27: ud
A28: 702123 | B28: EM10011 | C28: ETIQUETA BLANCA 2 5/8X1 15/16 (UND) | D28: Etiplast | E28: 1 | F28: ud
A29: 60100120 | B29: EM10314 | C29: Etiqueta Edicion Especial | E29: 1 | F29: ud
D33: Cantidad | E33: Unidad
A34: PESO TOTAL OBTENIDO | D34: 900 | E34: g | F34: Tiempo de Horneo:
A35: TIEMPO TOTAL DE PREPARACION | D35: 5 | E35: min | F35: Horno:
A36: CANTIDAD DE PORCIONES OBTENIDAS | D36: 1 | E36: ud | F36: Temperatura de Horneo:
A37: PESO DE CADA PORCIÓN | D37: 900 | E37: g | F37: Otros
A38: MERMA | D38: 253 | E38: g
A39: PROCEDIMIENTO DE PREPARACION DE LA RECETA
A40: 1, Agregar medio Rosquete de Chocolate Dawn de 400 g en un molde 22 cm Desmoldable.
A41: 2, Agregar las semillas toceadas, Agregar el disco de mousse de chocolate y colocarla en el Centro del Rosquete Grande
A42: 3, Agregar la mousse de crema pastelera dejar que corte al menos por 6 horas en refrigeraicon y dezmoldar y pegar con manjar a la orla.
A43: 4, Decorar con la Boquilla # 103 a los Borde con el Fudge Cholate Fas, Agregar relleno de arandanos en el centro y hace run espejo, Agregar el Fudge Liquido en el borde y Agregar los Trozos de Chocolate intercalando con los pares de chocolate cadbury
A44: 5, Tapar y etiquetar
A45: CONTROL DE CAMBIOS

Sheet Costo Ensamble Industria 
E1: Precio Local | F1: Costo MP | G1: Costo EM | H1: Costo MO
E2: =IFERROR(O68,"") -> 5883.4875 | F2: =IFERROR(H59,"") -> 4020.6054 | G2: =IFERROR(H60,"") -> 597.86875 | H2: =IFERROR(H62,"") -> 648.45223
A5: ESTRUCTURA DE COSTOS
F6: Fecha: | H6: =TODAY() -> 45776
A7: UNIDADES | B7: DESCRIPCION MAT.PRIMA | C7: UNIDADES | D7: UND MEDIDA | E7: COSTO UNITARIO | F7: TOTAL COSTO | G7: % PREC. DEFINIDO | H7: CODIGOS
A8: 0 | B8: Trozos Chocolate Oscuro | C8: =+A8 -> 0 | D8: =IFERROR(VLOOKUP(H8,'[1]Consolidado MP Planta'!$A$2:$M$823,13,0),"") | E8: 11.5 | F8: =IFERROR(C8*E8,"") -> 0 | G8: =IFERROR(F8/$F$72,"") -> 0 | H8: 1210398
A9: 25 | B9: Cuadros de Cadbury | C9: =+A9 -> 25 | D9: =IFERROR(VLOOKUP(H9,'[1]Consolidado MP Planta'!$A$2:$M$823,13,0),"") | E9: 10.48 | F9: =IFERROR(C9*E9,"") -> 262 | G9: =IFERROR(F9/$F$72,"") -> 0.052359303 | M9: Precio cadbury estimado mas x menos
A10: 10 | B10: Manjar Leche Condensada | C10: =+A10 -> 10 | D10: =IFERROR(VLOOKUP(H10,'[1]Consolidado MP Planta'!$A$2:$M$823,13,0),"") | E10: 2.56 | F10: =IFERROR(C10*E10,"") -> 25.6 | G10: =IFERROR(F10/$F$72,"") -> 0.0051160235 | H10: 11400066
B11: =IFERROR(VLOOKUP(H11,'[1]Consolidado MP Planta'!$A$2:$M$823,3,0),"") | C11: =+A11 -> 0 | D11: =IFERROR(VLOOKUP(H11,'[1]Consolidado MP Planta'!$A$2:$M$823,13,0),"") | E11: =IFERROR(VLOOKUP(H11,'[1]Consolidado MP Planta'!$A$2:$M$823,12,0),"") | F11: =IFERROR(C11*E11,"") | G11: =IFERROR(F11/$F$72,"")
B12: =IFERROR(VLOOKUP(H12,'[1]Consolidado MP Planta'!$A$2:$M$823,3,0),"") | C12: =+A12 -> 0 | D12: =IFERROR(VLOOKUP(H12,'[1]Consolidado MP Planta'!$A$2:$M$823,13,0),"") | E12: =IFERROR(VLOOKUP(H12,'[1]Consolidado MP Planta'!$A$2:$M$823,12,0),"") | F12: =IFERROR(C12*E12,"") | G12: =IFERROR(F12/$F$72,"")
B13: =IFERROR(VLOOKUP(H13,'[1]Consolidado MP Planta'!$A$2:$M$823,3,0),"") | C13: =+A13 -> 0 | D13: =IFERROR(VLOOKUP(H13,'[1]Consolidado MP Planta'!$A$2:$M$823,13,0),"") | E13: =IFERROR(VLOOKUP(H13,'[1]Consolidado MP Planta'!$A$2:$M$823,12,0),"") | F13: =IFERROR(C13*E13,"") | G13: =IFERROR(F13/$F$72,"")
B14: =IFERROR(VLOOKUP(H14,'[1]Consolidado MP Planta'!$A$2:$M$823,3,0),"") | C14: =+A14 -> 0 | D14: =IFERROR(VLOOKUP(H14,'[1]Consolidado MP Planta'!$A$2:$M$823,13,0),"") | E14: =IFERROR(VLOOKUP(H14,'[1]Consolidado MP Planta'!$A$2:$M$823,12,0),"") | F14: =IFERROR(C14*E14,"") | G14: =IFERROR(F14/$F$72,"")
B15: =IFERROR(VLOOKUP(H15,'[2]ARTICULOS MP PLANTA'!$A$2:$G$589,2,0),"")
A16: UNIDADES | B16: MATERIA PRIMA SEMIELABORADOS | C16: UNIDADES | D16: UND MEDIDA | E16: COSTO UNITARIO | F16: TOTAL COSTO | G16: % PREC. DEFINIDO | H16: CODIGOS
A17: 0.5 | B17: Rosquete Chocolate 400 grs Spoon | C17: =+A17 -> 0.5 | D17: und | E17: 517.65 | F17: =IFERROR(E17*C17,"") -> 258.825 | G17: =IFERROR(F17/$F$72,"") -> 0.051724796 | H17: 907000268
A18: 1 | B18: DISCO MOUSSE CHOCOLATE | C18: =+A18 -> 1 | D18: =IFERROR(VLOOKUP(H18,[1]SEMIELABORADOS!$A$2:$M$6000,6,0),"") | E18: =+'Costo disco'!H53 -> 1467.2327 | F18: =IFERROR(E18*C18,"") -> 1467.2327 | G18: =IFERROR(F18/$F$72,"") -> 0.29321863
A19: 50 | B19: Semillas de Cadbury | C19: =+A19 -> 50 | D19: =IFERROR(VLOOKUP(H19,[1]SEMIELABORADOS!$A$2:$M$6000,6,0),"") | E19: =+'costo semillas Cadbury'!E69 -> 3.9676 | F19: =IFERROR(E19*C19,"") -> 198.38 | G19: =IFERROR(F19/$F$72,"") -> 0.039645185
A20: 350 | B20: Mousse de pastelera | C20: =+A20 -> 350 | D20: =IFERROR(VLOOKUP(H20,[1]SEMIELABORADOS!$A$2:$M$6000,6,0),"") | E20: =+'Costo Mousse pastelera'!E69 -> 2.6250455 | F20: =IFERROR(E20*C20,"") -> 918.76593 | G20: =IFERROR(F20/$F$72,"") -> 0.18361047 | M20: =6*24 -> 144 | N20: =+M20*100 -> 14400 | O20: =12*24 -> 288 | P20: =+O20*42 -> 12096
A21: 50 | B21: Empaque Fudge De Chocolate | C21: =+A21 -> 50 | D21: =IFERROR(VLOOKUP(H21,[1]SEMIELABORADOS!$A$2:$M$6000,6,0),"") | E21: 2.34 | F21: =IFERROR(E21*C21,"") -> 117 | G21: =IFERROR(F21/$F$72,"") -> 0.023381826 | H21: 20100163 | N21: =150452/N20 -> 10.448056 | P21: =158763/P20 -> 13.125248
A22: 50 | B22: Fudge Liquido | C22: =+A22 -> 50 | D22: =IFERROR(VLOOKUP(H22,[1]SEMIELABORADOS!$A$2:$M$6000,6,0),"") | E22: 3.5 | F22: =IFERROR(E22*C22,"") -> 175 | G22: =IFERROR(F22/$F$72,"") -> 0.034972817
A23: 60 | B23: Empaque Relleno Arandanos Rojos | C23: =+A23 -> 60 | D23: =IFERROR(VLOOKUP(H23,[1]SEMIELABORADOS!$A$2:$M$6000,6,0),"") | E23: =+'Costo Empaque Relleno Arand'!E69 -> 6.6233641 | F23: =IFERROR(E23*C23,"") -> 397.40185 | G23: =IFERROR(F23/$F$72,"") -> 0.079418641
A24: 60 | B24: Galleta Oreo Bañada Chocolate Blanco | C24: =+A24 -> 60 | D24: =IFERROR(VLOOKUP(H24,[1]SEMIELABORADOS!$A$2:$M$6000,6,0),"") | E24: 3.34 | F24: =IFERROR(E24*C24,"") -> 200.4 | G24: =IFERROR(F24/$F$72,"") -> 0.040048872 | H24: 902000176
A26: UNIDADES | B26: EMPAQUE | C26: UNIDADES | D26: UND MEDIDA | E26: COSTO UNITARIO | F26: TOTAL COSTO | G26: % PREC. DEFINIDO | H26: CODIGOS
A27: 1 | B27: =IFERROR(VLOOKUP(H27,'[1]Consolidado MP Planta'!$A$2:$M$823,3,0),"") -> QUEQUERA RED C/BASE ALTA 9" (CAJA:100 U) | C27: =+A27 -> 1 | D27: =IFERROR(VLOOKUP(H27,'[1]Consolidado MP Planta'!$A$2:$M$823,13,0),"") -> Und | E27: 342.24 | F27: =IFERROR(C27*E27,"") -> 342.24 | G27: =IFERROR(F27/$F$72,"") -> 0.06839484 | H27: 51400021
A28: 1 | B28: =IFERROR(VLOOKUP(H28,'[1]Consolidado MP Planta'!$A$2:$M$823,3,0),"") -> ORLA #9 DORADA (UND) | C28: =+A28 -> 1 | D28: =IFERROR(VLOOKUP(H28,'[1]Consolidado MP Planta'!$A$2:$M$823,13,0),"") -> Und | E28: =IFERROR(VLOOKUP(H28,'[1]Consolidado MP Planta'!$A$2:$M$823,12,0),"") -> 135 | F28: =IFERROR(C28*E28,"") -> 135 | G28: =IFERROR(F28/$F$72,"") -> 0.02697903 | H28: 1950693
A29: 1 | B29: =IFERROR(VLOOKUP(H29,'[1]Consolidado MP Planta'!$A$2:$M$823,3,0),"") -> ETIQ.BLANCA 1 1/4 * 3/4 (UND) | C29: =+A29 -> 1 | D29: =IFERROR(VLOOKUP(H29,'[1]Consolidado MP Planta'!$A$2:$M$823,13,0),"") -> Und | E29: =IFERROR(VLOOKUP(H29,'[1]Consolidado MP Planta'!$A$2:$M$823,12,0),"") -> 0.58 | F29: =IFERROR(C29*E29,"") -> 0.58 | G29: =IFERROR(F29/$F$72,"") -> 0.00011590991 | H29: 0702069
A30: 1 | B30: =IFERROR(VLOOKUP(H30,'[1]Consolidado MP Planta'!$A$2:$M$823,3,0),"") -> ETIQUETA BLANCA R-153 (UND) | C30: =+A30 -> 1 | D30: =IFERROR(VLOOKUP(H30,'[1]Consolidado MP Planta'!$A$2:$M$823,13,0),"") -> Und | E30: =IFERROR(VLOOKUP(H30,'[1]Consolidado MP Planta'!$A$2:$M$823,12,0),"") -> 0.39 | F30: =IFERROR(C30*E30,"") -> 0.39 | G30: =IFERROR(F30/$F$72,"") -> 7.7939421e-05 | H30: 701096
A31: 1 | B31: =IFERROR(VLOOKUP(H31,'[1]Consolidado MP Planta'!$A$2:$M$823,3,0),"") -> ETIQUETA BLANCA 2 5/8X1 15/16 (UND) | C31: =+A31 -> 1 | D31: =IFERROR(VLOOKUP(H31,'[1]Consolidado MP Planta'!$A$2:$M$823,13,0),"") -> Und | E31: =IFERROR(VLOOKUP(H31,'[1]Consolidado MP Planta'!$A$2:$M$823,12,0),"") -> 2.128 | F31: =IFERROR(C31*E31,"") -> 2.128 | G31: =IFERROR(F31/$F$72,"") -> 0.00042526946 | H31: 0702123
A32: 1 | B32: Etiqueta Edicion Especial | C32: =+A32 -> 1 | D32: Und | E32: 110 | F32: =IFERROR(C32*E32,"") -> 110 | G32: =IFERROR(F32/$F$72,"") -> 0.021982914 | H32: 60100120
B33: =IFERROR(VLOOKUP(H33,'[1]Consolidado MP Planta'!$A$2:$M$823,3,0),"") | C33: =+A33 -> 0 | D33: =IFERROR(VLOOKUP(H33,'[1]Consolidado MP Planta'!$A$2:$M$823,13,0),"") | E33: =IFERROR(VLOOKUP(H33,'[1]Consolidado MP Planta'!$A$2:$M$823,12,0),"") | F33: =IFERROR(C33*E33,"") | G33: =IFERROR(F33/$F$72,"")
B34: =IFERROR(VLOOKUP(H34,'[1]Consolidado MP Planta'!$A$2:$M$823,3,0),"") | C34: =+A34 -> 0 | D34: =IFERROR(VLOOKUP(H34,'[1]Consolidado MP Planta'!$A$2:$M$823,13,0),"") | E34: =IFERROR(VLOOKUP(H34,'[1]Consolidado MP Planta'!$A$2:$M$823,12,0),"") | F34: =IFERROR(C34*E34,"") | G34: =IFERROR(F34/$F$72,"")
B35: =IFERROR(VLOOKUP(H35,'[1]Consolidado MP Planta'!$A$2:$M$823,3,0),"") | C35: =+A35 -> 0 | D35: =IFERROR(VLOOKUP(H35,'[1]Consolidado MP Planta'!$A$2:$M$823,13,0),"") | E35: =IFERROR(VLOOKUP(H35,'[1]Consolidado MP Planta'!$A$2:$M$823,12,0),"") | F35: =IFERROR(C35*E35,"") | G35: =IFERROR(F35/$F$72,"")
B36: =IFERROR(VLOOKUP(H36,'[1]Consolidado MP Planta'!$A$2:$M$823,3,0),"") | C36: =+A36 -> 0 | D36: =IFERROR(VLOOKUP(H36,'[1]Consolidado MP Planta'!$A$2:$M$823,13,0),"") | E36: =IFERROR(VLOOKUP(H36,'[1]Consolidado MP Planta'!$A$2:$M$823,12,0),"") | F36: =IFERROR(C36*E36,"") | G36: =IFERROR(F36/$F$72,"")
A38: UNIDADES | B38: EMPAQUE SEMIELABORADOS | C38: UNIDADES | D38: UND MEDIDA | E38: COSTO UNITARIO | F38: TOTAL COSTO | G38: % PREC. DEFINIDO | H38: CODIGOS
A39: =+A17 -> 0.5 | B39: Rosquete Chocolate 400 grs Spoon | C39: =+A39 -> 0.5 | D39: =IFERROR(VLOOKUP(H39,[1]SEMIELABORADOS!$A$2:$M$6000,6,0),"") | E39: 5.29 | F39: =IFERROR(E39*C39,"") -> 2.645 | G39: =IFERROR(F39/$F$72,"") -> 0.00052858915 | H39: 907000268
A40: =+A18 -> 1 | B40: DISCO MOUSSE CHOCOLATE | C40: =+A40 -> 1 | D40: =IFERROR(VLOOKUP(H40,[1]SEMIELABORADOS!$A$2:$M$6000,6,0),"") | E40: =+'Costo disco'!H54 -> 2.4662564 | F40: =IFERROR(E40*C40,"") -> 2.4662564 | G40: =IFERROR(F40/$F$72,"") -> 0.0004928682
A41: =+A19 -> 50 | B41: Semillas de Cadbury | C41: =+A41 -> 50 | D41: =IFERROR(VLOOKUP(H41,[1]SEMIELABORADOS!$A$2:$M$6000,6,0),"") | E41: =+'costo semillas Cadbury'!E76 -> 0.0049747048 | F41: =IFERROR(E41*C41,"") -> 0.24873524 | G41: =IFERROR(F41/$F$72,"") -> 4.9708411e-05
A42: =+A20 -> 350 | B42: Mousse de pastelera | C42: =+A42 -> 350 | D42: =IFERROR(VLOOKUP(H42,[1]SEMIELABORADOS!$A$2:$M$6000,6,0),"") | E42: =+'Costo Mousse pastelera'!E76 -> 0 | F42: =IFERROR(E42*C42,"") -> 0 | G42: =IFERROR(F42/$F$72,"") -> 0
A43: =+A21 -> 50 | B43: Empaque Fudge De Chocolate | C43: =+A43 -> 50 | D43: =IFERROR(VLOOKUP(H43,[1]SEMIELABORADOS!$A$2:$M$6000,6,0),"") | E43: 0.01 | F43: =IFERROR(E43*C43,"") -> 0.5 | G43: =IFERROR(F43/$F$72,"") -> 9.9922335e-05
A44: =+A22 -> 50 | B44: Fudge Liquido | C44: =+A44 -> 50 | D44: =IFERROR(VLOOKUP(H44,[1]SEMIELABORADOS!$A$2:$M$6000,6,0),"") | E44: 0.01 | F44: =IFERROR(E44*C44,"") -> 0.5 | G44: =IFERROR(F44/$F$72,"") -> 9.9922335e-05
A45: =+A23 -> 60 | B45: Empaque Relleno Arandanos Rojos | C45: =+A45 -> 60 | D45: =IFERROR(VLOOKUP(H45,[1]SEMIELABORADOS!$A$2:$M$6000,6,0),"") | E45: =+'Costo Empaque Relleno Arand'!E76 -> 0.019512564 | F45: =IFERROR(E45*C45,"") -> 1.1707539 | G45: =IFERROR(F45/$F$72,"") -> 0.00023396892
A46: =+A24 -> 60 | B46: Galleta Oreo Bañada Chocolate Blanco | C46: =+A46 -> 60 | D46: =IFERROR(VLOOKUP(H46,[1]SEMIELABORADOS!$A$2:$M$6000,6,0),"") | E46: 0 | F46: =IFERROR(E46*C46,"") -> 0 | G46: =IFERROR(F46/$F$72,"") -> 0
A48: UNIDADES | B48: MODI | C48: UNIDADES | D48: UND MEDIDA | E48: COSTO UNITARIO | F48: TOTAL COSTO | G48: % PREC. DEFINIDO | H48: CODIGOS
A49: =+A39 -> 0.5 | B49: Rosquete Chocolate 400 grs Spoon | C49: =+A49 -> 0.5 | D49: =IFERROR(VLOOKUP(H49,[1]SEMIELABORADOS!$A$2:$M$6000,6,0),"") | E49: 33.34 | F49: =IFERROR(E49*C49,"") -> 16.67 | G49: =IFERROR(F49/$F$72,"") -> 0.0033314106 | H49: 907000268
A50: =+A40 -> 1 | B50: DISCO MOUSSE CHOCOLATE | C50: =+A50 -> 1 | D50: =IFERROR(VLOOKUP(H50,[1]SEMIELABORADOS!$A$2:$M$6000,6,0),"") | E50: =+'Costo disco'!H56 -> 247.75827 | F50: =IFERROR(E50*C50,"") -> 247.75827 | G50: =IFERROR(F50/$F$72,"") -> 0.049513169
A51: =+A41 -> 50 | B51: Semillas de Cadbury | C51: =+A51 -> 50 | D51: =IFERROR(VLOOKUP(H51,[1]SEMIELABORADOS!$A$2:$M$6000,6,0),"") | E51: =+'costo semillas Cadbury'!E74 -> 0.122 | F51: =IFERROR(E51*C51,"") -> 6.1 | G51: =IFERROR(F51/$F$72,"") -> 0.0012190525
A52: =+A42 -> 350 | B52: Mousse de pastelera | C52: =+A52 -> 350 | D52: =IFERROR(VLOOKUP(H52,[1]SEMIELABORADOS!$A$2:$M$6000,6,0),"") | E52: =+'Costo Mousse pastelera'!E74 -> 0.1403 | F52: =IFERROR(E52*C52,"") -> 49.105 | G52: =IFERROR(F52/$F$72,"") -> 0.0098133725
A53: =+A43 -> 50 | B53: Empaque Fudge De Chocolate | C53: =+A53 -> 50 | D53: =IFERROR(VLOOKUP(H53,[1]SEMIELABORADOS!$A$2:$M$6000,6,0),"") | E53: 0.09 | F53: =IFERROR(E53*C53,"") -> 4.5 | G53: =IFERROR(F53/$F$72,"") -> 0.00089930101
A54: =+A44 -> 50 | B54: Fudge Liquido | C54: =+A54 -> 50 | D54: =IFERROR(VLOOKUP(H54,[1]SEMIELABORADOS!$A$2:$M$6000,6,0),"") | E54: 0.09 | F54: =IFERROR(E54*C54,"") -> 4.5 | G54: =IFERROR(F54/$F$72,"") -> 0.00089930101
A55: =+A45 -> 60 | B55: Empaque Relleno Arandanos Rojos | C55: =+A55 -> 60 | D55: =IFERROR(VLOOKUP(H55,[1]SEMIELABORADOS!$A$2:$M$6000,6,0),"") | E55: =+'Costo Empaque Relleno Arand'!E74 -> 0.09698268 | F55: =IFERROR(E55*C55,"") -> 5.8189608 | G55: =IFERROR(F55/$F$72,"") -> 0.0011628883
A56: =+A46 -> 60 | B56: Galleta Oreo Bañada Chocolate Blanco | C56: =+A56 -> 60 | D56: =IFERROR(VLOOKUP(H56,[1]SEMIELABORADOS!$A$2:$M$6000,6,0),"") | E56: 0.15 | F56: =IFERROR(E56*C56,"") -> 9 | G56: =IFERROR(F56/$F$72,"") -> 0.001798602
A57: 1 | B57: MODI PREPARACION | C57: =+A57 -> 1 | D57: N/A | E57: =+F71 -> 305 | F57: =IFERROR(C57*E57,"") -> 305 | G57: =IFERROR(F57/$F$72,"") -> 0.060952624
B59: TOTAL MATERIA PRIMA | F59: =SUM(F8:F14,F17:F24) -> 4020.6054 | G59: =+F59/$F$72 -> 0.80349656 | H59: =+F59/$D$66 -> 4020.6054
B60: TOTAL EMPAQUE | F60: =SUM(F27:F36,F39:F46) -> 597.86875 | G60: =+F60/$F$72 -> 0.11948088 | H60: =+F60/$D$66 -> 597.86875 | K60: TOTAL MATERIA PRIMA + EMPAQUE | O60: =+F61 -> 4618.4742
B61: TOTAL MATERIAS P. + EMPAQUES | F61: =+F59+F60 -> 4618.4742 | G61: =+F61/$F$72 -> 0.92297744 | H61: =+F61/$D$66 -> 4618.4742 | M61: MODI PLANTA | O61: =+H62 -> 648.45223
C62: TOTAL MODI | F62: =SUM(F49:F57) -> 648.45223 | G62: =+F62/$F$72 -> 0.12958972 | H62: =+F62/$D$66 -> 648.45223 | M62: DESECHO | O62: =O60*N62 -> 0
M63: COSTO PLANTA | O63: =SUM(O60:O62) -> 5266.9264
B64: GRAMOS | D64: 950 | H64: =+H62/61 -> 10.630364 | M64: % GIF | O64: =+H65 -> 616.56114
B65: PESO POR UNIDAD | D65: 950 | H65: =+H64*58 -> 616.56114 | M65: COSTO PLANTA | O65: =SUM(O63:O64) -> 5883.4875
B66: UNIDADES TOTALES | D66: =+D64/D65 -> 1 | O66: =+O65*N66 -> 0
B67: UNIDAD MEDIDA | K67: PRECIO DE VENTA PLANTA A LOCAL | O67: =SUM(O65:O66) -> 5883.4875 | P67: GR
E68: S/ COSTO | F68: TOTAL | L68: UNIDAD | O68: =+O67/D66 -> 5883.4875 | P68: =+O68/D65 -> 6.1931448
B69: TOTAL MATERIAS P. + EMPAQUES | E69: =+F69/F69 -> 1 | F69: =SUM(F61) -> 4618.4742 | G69: =+F69/$F$72 -> 0.92297744
B70: DESECHOS Y PERDIDAS | E70: 0.02 | F70: =+F59*E70 -> 80.412109 | G70: =+F70/$F$72 -> 0.016069931
B71: MANO OBRA DIRECTA | D71: 5 | E71: 61 | F71: =+E71*D71 -> 305 | G71: =+F71/$F$72 -> 0.060952624
B72: TOTAL COSTO PLANTA | F72: =SUM(F69:F71) -> 5003.8863 | G72: =+F72/$F$72 -> 1 | M72: MODI 61 COLONES X MIN
M73: Gf 58 colones min
B74: COSTO POR GRAMO | M74: ,
B75: TOTAL COSTO MATERIA PRIMA | C75: =+F59 -> 4020.6054 | D75: =+D64 -> 950 | E75: =+C75/D75 -> 4.2322162
B77: TOTAL COSTO UNIDAD MP+DESECHO+EMPAQUE | C77: =SUM(F69:F70) -> 4698.8863 | D77: =+D64 -> 950 | E77: =+C77/D77 -> 4.9461961
B79: TOTAL MODI PREPARACION POR GRAMO | C79: =+F71 -> 305 | D79: =+D64 -> 950 | E79: =+C79/D79 -> 0.32105263
B80: TOTAL MODI POR GRAMO | C80: =+F62 -> 648.45223 | D80: =+D79 -> 950 | E80: =+C80/D80 -> 0.68258129
B82: TOTAL EMPAQUE POR GRAMO | C82: =+F60 -> 597.86875 | D82: =+D80 -> 950 | E82: =+C82/D82 -> 0.62933552
B84: TOTAL GRAMO MP+MODI | E84: =+E75+E80 -> 4.9147975
B86: COSTO POR UNIDAD
B87: TOTAL COSTO MATERIA PRIMA | C87: =+C75 -> 4020.6054 | D87: =+D66 -> 1 | E87: =+C87/D87 -> 4020.6054
B89: TOTAL COSTO UNIDAD MP+DESECHO+EMPAQUE | C89: =+C77 -> 4698.8863 | D89: =+D66 -> 1 | E89: =+C89/D89 -> 4698.8863
B91: TOTAL MODI POR GRAMO | C91: =+C79 -> 305 | D91: =+D66 -> 1 | E91: =+C91/D91 -> 305
B92: TOTAL MODI POR GRAMO | C92: =+C80 -> 648.45223 | D92: =+D91 -> 1 | E92: =+C92/D92 -> 648.45223

Sheet costo semillas Cadbury
E1: Precio Local | F1: Costo MP | G1: Costo EM | H1: Costo MO
E2: =IFERROR(O62,"") -> 42105.747 | F2: =IFERROR(H53,"") -> 39676 | G2: =IFERROR(H54,"") -> 49.747048 | H2: =IFERROR(H56,"") -> 1220
A5: ESTRUCTURA DE COSTOS
F6: Fecha: | H6: =TODAY() -> 45776
A7: UNIDADES | B7: DESCRIPCION MAT.PRIMA | C7: UNIDADES | D7: UND MEDIDA | E7: COSTO UNITARIO | F7: TOTAL COSTO | G7: % PREC. DEFINIDO | H7: CODIGOS
A8: 2600 | B8: Cobertura Chocolate Leche | C8: =+A8 -> 2600 | D8: =IFERROR(VLOOKUP(H8,'[1]Consolidado MP Planta'!$A$2:$M$823,13,0),"") -> Gramos | E8: 4.4 | F8: =IFERROR(C8*E8,"") -> 11440 | G8: =IFERROR(F8/$F$66,"") -> 0.27408244 | H8: 1210386
A9: 2600 | B9: Chocolate Semi Amargo 54% | C9: =+A9 -> 2600 | D9: Gramos | E9: 4.4 | F9: =IFERROR(C9*E9,"") -> 11440 | G9: =IFERROR(F9/$F$66,"") -> 0.27408244 | H9: 10100331
A10: 2600 | B10: Pasas | C10: =+A10 -> 2600 | D10: Gramos | E10: 1.47 | F10: =IFERROR(C10*E10,"") -> 3822 | G10: =IFERROR(F10/$F$66,"") -> 0.09156845 | H10: 5105009
A11: 2600 | B11: Almendra Entera | C11: =+A11 -> 2600 | D11: Gramos | E11: 4.99 | F11: =IFERROR(C11*E11,"") -> 12974 | G11: =IFERROR(F11/$F$66,"") -> 0.3108344 | H11: 11900029
B12: =IFERROR(VLOOKUP(H12,'[1]Consolidado MP Planta'!$A$2:$M$823,3,0),"") | C12: =+A12 -> 0 | D12: =IFERROR(VLOOKUP(H12,'[1]Consolidado MP Planta'!$A$2:$M$823,13,0),"") | E12: =IFERROR(VLOOKUP(H12,'[1]Consolidado MP Planta'!$A$2:$M$823,12,0),"") | F12: =IFERROR(C12*E12,"") | G12: =IFERROR(F12/$F$66,"")
B13: =IFERROR(VLOOKUP(H13,'[1]Consolidado MP Planta'!$A$2:$M$823,3,0),"") | C13: =+A13 -> 0 | D13: =IFERROR(VLOOKUP(H13,'[1]Consolidado MP Planta'!$A$2:$M$823,13,0),"") | E13: =IFERROR(VLOOKUP(H13,'[1]Consolidado MP Planta'!$A$2:$M$823,12,0),"") | F13: =IFERROR(C13*E13,"") | G13: =IFERROR(F13/$F$66,"")
B14: =IFERROR(VLOOKUP(H14,'[1]Consolidado MP Planta'!$A$2:$M$823,3,0),"") | C14: =+A14 -> 0 | D14: =IFERROR(VLOOKUP(H14,'[1]Consolidado MP Planta'!$A$2:$M$823,13,0),"") | E14: =IFERROR(VLOOKUP(H14,'[1]Consolidado MP Planta'!$A$2:$M$823,12,0),"") | F14: =IFERROR(C14*E14,"") | G14: =IFERROR(F14/$F$66,"")
B15: =IFERROR(VLOOKUP(H15,'[2]ARTICULOS MP PLANTA'!$A$2:$G$589,2,0),"")
A16: UNIDADES | B16: MATERIA PRIMA SEMIELABORADOS | C16: UNIDADES | D16: UND MEDIDA | E16: COSTO UNITARIO | F16: TOTAL COSTO | G16: % PREC. DEFINIDO | H16: CODIGOS
B17: =IFERROR(VLOOKUP(H17,[1]SEMIELABORADOS!$A$2:$M$6000,2,0),"") | C17: =+A17 -> 0 | D17: =IFERROR(VLOOKUP(H17,[1]SEMIELABORADOS!$A$2:$M$6000,6,0),"") | E17: =IFERROR(VLOOKUP(H17,[1]SEMIELABORADOS!$A$2:$H$65536,8,0),"") | F17: =IFERROR(E17*C17,"") | G17: =IFERROR(F17/$F$66,"")
B18: =IFERROR(VLOOKUP(H18,[1]SEMIELABORADOS!$A$2:$M$6000,2,0),"") | C18: =+A18 -> 0 | D18: =IFERROR(VLOOKUP(H18,[1]SEMIELABORADOS!$A$2:$M$6000,6,0),"") | E18: =IFERROR(VLOOKUP(H18,[1]SEMIELABORADOS!$A$2:$H$65536,8,0),"") | F18: =IFERROR(E18*C18,"") | G18: =IFERROR(F18/$F$66,"")
B19: =IFERROR(VLOOKUP(H19,[1]SEMIELABORADOS!$A$2:$M$6000,2,0),"") | C19: =+A19 -> 0 | D19: =IFERROR(VLOOKUP(H19,[1]SEMIELABORADOS!$A$2:$M$6000,6,0),"") | E19: =IFERROR(VLOOKUP(H19,[1]SEMIELABORADOS!$A$2:$H$65536,8,0),"") | F19: =IFERROR(E19*C19,"") | G19: =IFERROR(F19/$F$66,"")
B20: =IFERROR(VLOOKUP(H20,[1]SEMIELABORADOS!$A$2:$M$6000,2,0),"") | C20: =+A20 -> 0 | D20: =IFERROR(VLOOKUP(H20,[1]SEMIELABORADOS!$A$2:$M$6000,6,0),"") | E20: =IFERROR(VLOOKUP(H20,[1]SEMIELABORADOS!$A$2:$H$65536,8,0),"") | F20: =IFERROR(E20*C20,"") | G20: =IFERROR(F20/$F$66,"")
B21: =IFERROR(VLOOKUP(H21,[1]SEMIELABORADOS!$A$2:$M$6000,2,0),"") | C21: =+A21 -> 0 | D21: =IFERROR(VLOOKUP(H21,[1]SEMIELABORADOS!$A$2:$M$6000,6,0),"") | E21: =IFERROR(VLOOKUP(H21,[1]SEMIELABORADOS!$A$2:$H$65536,8,0),"") | F21: =IFERROR(E21*C21,"") | G21: =IFERROR(F21/$F$66,"")
B22: =IFERROR(VLOOKUP(H22,[1]SEMIELABORADOS!$A$2:$M$6000,2,0),"") | C22: =+A22 -> 0 | D22: =IFERROR(VLOOKUP(H22,[1]SEMIELABORADOS!$A$2:$M$6000,6,0),"") | E22: =IFERROR(VLOOKUP(H22,[1]SEMIELABORADOS!$A$2:$H$65536,8,0),"") | F22: =IFERROR(E22*C22,"") | G22: =IFERROR(F22/$F$66,"")
B23: =IFERROR(VLOOKUP(H23,[1]SEMIELABORADOS!$A$2:$M$6000,2,0),"") | C23: =+A23 -> 0 | D23: =IFERROR(VLOOKUP(H23,[1]SEMIELABORADOS!$A$2:$M$6000,6,0),"") | E23: =IFERROR(VLOOKUP(H23,[1]SEMIELABORADOS!$A$2:$H$65536,8,0),"") | F23: =IFERROR(E23*C23,"") | G23: =IFERROR(F23/$F$66,"")
B24: =IFERROR(VLOOKUP(H24,[1]SEMIELABORADOS!$A$2:$M$6000,2,0),"") | C24: =+A24 -> 0 | D24: =IFERROR(VLOOKUP(H24,[1]SEMIELABORADOS!$A$2:$M$6000,6,0),"") | E24: =IFERROR(VLOOKUP(H24,[1]SEMIELABORADOS!$A$2:$H$65536,8,0),"") | F24: =IFERROR(E24*C24,"") | G24: =IFERROR(F24/$F$66,"")
A26: UNIDADES | B26: EMPAQUE | C26: UNIDADES | D26: UND MEDIDA | E26: COSTO UNITARIO | F26: TOTAL COSTO | G26: % PREC. DEFINIDO | H26: CODIGOS
A27: 1 | B27: =IFERROR(VLOOKUP(H27,'[1]Consolidado MP Planta'!$A$2:$M$823,3,0),"") -> BOLSA 17x25 TRANSP KILO | C27: =+A27 -> 1 | D27: =IFERROR(VLOOKUP(H27,'[1]Consolidado MP Planta'!$A$2:$M$823,13,0),"") -> Und | E27: =IFERROR(VLOOKUP(H27,'[1]Consolidado MP Planta'!$A$2:$M$823,12,0),"") -> 47.619048 | F27: =IFERROR(C27*E27,"") -> 47.619048 | G27: =IFERROR(F27/$F$66,"") -> 0.0011408693 | H27: 1950708
A28: 1 | B28: =IFERROR(VLOOKUP(H28,'[1]Consolidado MP Planta'!$A$2:$M$823,3,0),"") -> ETIQUETA BLANCA 2 5/8X1 15/16 (UND) | C28: =+A28 -> 1 | D28: =IFERROR(VLOOKUP(H28,'[1]Consolidado MP Planta'!$A$2:$M$823,13,0),"") -> Und | E28: =IFERROR(VLOOKUP(H28,'[1]Consolidado MP Planta'!$A$2:$M$823,12,0),"") -> 2.128 | F28: =IFERROR(C28*E28,"") -> 2.128 | G28: =IFERROR(F28/$F$66,"") -> 5.0983166e-05 | H28: 0702123
B29: =IFERROR(VLOOKUP(H29,'[1]Consolidado MP Planta'!$A$2:$M$823,3,0),"") | C29: =+A29 -> 0 | D29: =IFERROR(VLOOKUP(H29,'[1]Consolidado MP Planta'!$A$2:$M$823,13,0),"") | E29: =IFERROR(VLOOKUP(H29,'[1]Consolidado MP Planta'!$A$2:$M$823,12,0),"") | F29: =IFERROR(C29*E29,"") | G29: =IFERROR(F29/$F$66,"")
B30: =IFERROR(VLOOKUP(H30,'[1]Consolidado MP Planta'!$A$2:$M$823,3,0),"") | C30: =+A30 -> 0 | D30: =IFERROR(VLOOKUP(H30,'[1]Consolidado MP Planta'!$A$2:$M$823,13,0),"") | E30: =IFERROR(VLOOKUP(H30,'[1]Consolidado MP Planta'!$A$2:$M$823,12,0),"") | F30: =IFERROR(C30*E30,"") | G30: =IFERROR(F30/$F$66,"")
B31: =IFERROR(VLOOKUP(H31,'[1]Consolidado MP Planta'!$A$2:$M$823,3,0),"") | C31: =+A31 -> 0 | D31: =IFERROR(VLOOKUP(H31,'[1]Consolidado MP Planta'!$A$2:$M$823,13,0),"") | E31: =IFERROR(VLOOKUP(H31,'[1]Consolidado MP Planta'!$A$2:$M$823,12,0),"") | F31: =IFERROR(C31*E31,"") | G31: =IFERROR(F31/$F$66,"")
B32: =IFERROR(VLOOKUP(H32,'[1]Consolidado MP Planta'!$A$2:$M$823,3,0),"") | C32: =+A32 -> 0 | D32: =IFERROR(VLOOKUP(H32,'[1]Consolidado MP Planta'!$A$2:$M$823,13,0),"") | E32: =IFERROR(VLOOKUP(H32,'[1]Consolidado MP Planta'!$A$2:$M$823,12,0),"") | F32: =IFERROR(C32*E32,"") | G32: =IFERROR(F32/$F$66,"")
A34: UNIDADES | B34: EMPAQUE SEMIELABORADOS | C34: UNIDADES | D34: UND MEDIDA | E34: COSTO UNITARIO | F34: TOTAL COSTO | G34: % PREC. DEFINIDO | H34: CODIGOS
A35: =+A17 -> 0 | B35: =IFERROR(VLOOKUP(H35,[1]SEMIELABORADOS!$A$2:$M$6000,2,0),"") | C35: =+A35 -> 0 | D35: =IFERROR(VLOOKUP(H35,[1]SEMIELABORADOS!$A$2:$M$6000,6,0),"") | E35: =IFERROR(VLOOKUP(H35,[1]SEMIELABORADOS!$A$2:$M$65536,10,0),"") | F35: =IFERROR(E35*C35,"") | G35: =IFERROR(F35/$F$66,"")
A36: =+A18 -> 0 | B36: =IFERROR(VLOOKUP(H36,[1]SEMIELABORADOS!$A$2:$M$6000,2,0),"") | C36: =+A36 -> 0 | D36: =IFERROR(VLOOKUP(H36,[1]SEMIELABORADOS!$A$2:$M$6000,6,0),"") | E36: =IFERROR(VLOOKUP(H36,[1]SEMIELABORADOS!$A$2:$M$65536,10,0),"") | F36: =IFERROR(E36*C36,"") | G36: =IFERROR(F36/$F$66,"")
A37: =+A19 -> 0 | B37: =IFERROR(VLOOKUP(H37,[1]SEMIELABORADOS!$A$2:$M$6000,2,0),"") | C37: =+A37 -> 0 | D37: =IFERROR(VLOOKUP(H37,[1]SEMIELABORADOS!$A$2:$M$6000,6,0),"") | E37: =IFERROR(VLOOKUP(H37,[1]SEMIELABORADOS!$A$2:$M$65536,10,0),"") | F37: =IFERROR(E37*C37,"") | G37: =IFERROR(F37/$F$66,"")
A38: =+A20 -> 0 | B38: =IFERROR(VLOOKUP(H38,[1]SEMIELABORADOS!$A$2:$M$6000,2,0),"") | C38: =+A38 -> 0 | D38: =IFERROR(VLOOKUP(H38,[1]SEMIELABORADOS!$A$2:$M$6000,6,0),"") | E38: =IFERROR(VLOOKUP(H38,[1]SEMIELABORADOS!$A$2:$M$65536,10,0),"") | F38: =IFERROR(E38*C38,"") | G38: =IFERROR(F38/$F$66,"")
A39: =+A21 -> 0 | B39: =IFERROR(VLOOKUP(H39,[1]SEMIELABORADOS!$A$2:$M$6000,2,0),"") | C39: =+A39 -> 0 | D39: =IFERROR(VLOOKUP(H39,[1]SEMIELABORADOS!$A$2:$M$6000,6,0),"") | E39: =IFERROR(VLOOKUP(H39,[1]SEMIELABORADOS!$A$2:$M$65536,10,0),"") | F39: =IFERROR(E39*C39,"") | G39: =IFERROR(F39/$F$66,"")
A40: =+A22 -> 0 | B40: =IFERROR(VLOOKUP(H40,[1]SEMIELABORADOS!$A$2:$M$6000,2,0),"") | C40: =+A40 -> 0 | D40: =IFERROR(VLOOKUP(H40,[1]SEMIELABORADOS!$A$2:$M$6000,6,0),"") | E40: =IFERROR(VLOOKUP(H40,[1]SEMIELABORADOS!$A$2:$M$65536,10,0),"") | F40: =IFERROR(E40*C40,"") | G40: =IFERROR(F40/$F$66,"")
A41: =+A23 -> 0 | B41: =IFERROR(VLOOKUP(H41,[1]SEMIELABORADOS!$A$2:$M$6000,2,0),"") | C41: =+A41 -> 0 | D41: =IFERROR(VLOOKUP(H41,[1]SEMIELABORADOS!$A$2:$M$6000,6,0),"") | E41: =IFERROR(VLOOKUP(H41,[1]SEMIELABORADOS!$A$2:$M$65536,10,0),"") | F41: =IFERROR(E41*C41,"") | G41: =IFERROR(F41/$F$66,"")
A43: UNIDADES | B43: MODI | C43: UNIDADES | D43: UND MEDIDA | E43: COSTO UNITARIO | F43: TOTAL COSTO | G43: % PREC. DEFINIDO | H43: CODIGOS
A44: =+A35 -> 0 | B44: =IFERROR(VLOOKUP(H44,[1]SEMIELABORADOS!$A$2:$M$6000,2,0),"") | C44: =+A44 -> 0 | D44: =IFERROR(VLOOKUP(H44,[1]SEMIELABORADOS!$A$2:$M$6000,6,0),"") | E44: =IFERROR(VLOOKUP(H44,[1]SEMIELABORADOS!$A$2:$M$65536,12,0),"") | F44: =IFERROR(E44*C44,"") | G44: =IFERROR(F44/$F$66,"")
A45: =+A36 -> 0 | B45: =IFERROR(VLOOKUP(H45,[1]SEMIELABORADOS!$A$2:$M$6000,2,0),"") | C45: =+A45 -> 0 | D45: =IFERROR(VLOOKUP(H45,[1]SEMIELABORADOS!$A$2:$M$6000,6,0),"") | E45: =IFERROR(VLOOKUP(H45,[1]SEMIELABORADOS!$A$2:$M$65536,12,0),"") | F45: =IFERROR(E45*C45,"") | G45: =IFERROR(F45/$F$66,"")
A46: =+A37 -> 0 | B46: =IFERROR(VLOOKUP(H46,[1]SEMIELABORADOS!$A$2:$M$6000,2,0),"") | C46: =+A46 -> 0 | D46: =IFERROR(VLOOKUP(H46,[1]SEMIELABORADOS!$A$2:$M$6000,6,0),"") | E46: =IFERROR(VLOOKUP(H46,[1]SEMIELABORADOS!$A$2:$M$65536,12,0),"") | F46: =IFERROR(E46*C46,"") | G46: =IFERROR(F46/$F$66,"")
A47: =+A38 -> 0 | B47: =IFERROR(VLOOKUP(H47,[1]SEMIELABORADOS!$A$2:$M$6000,2,0),"") | C47: =+A47 -> 0 | D47: =IFERROR(VLOOKUP(H47,[1]SEMIELABORADOS!$A$2:$M$6000,6,0),"") | E47: =IFERROR(VLOOKUP(H47,[1]SEMIELABORADOS!$A$2:$M$65536,12,0),"") | F47: =IFERROR(E47*C47,"") | G47: =IFERROR(F47/$F$66,"")
A48: =+A39 -> 0 | B48: =IFERROR(VLOOKUP(H48,[1]SEMIELABORADOS!$A$2:$M$6000,2,0),"") | C48: =+A48 -> 0 | D48: =IFERROR(VLOOKUP(H48,[1]SEMIELABORADOS!$A$2:$M$6000,6,0),"") | E48: =IFERROR(VLOOKUP(H48,[1]SEMIELABORADOS!$A$2:$M$65536,12,0),"") | F48: =IFERROR(E48*C48,"") | G48: =IFERROR(F48/$F$66,"")
A49: =+A40 -> 0 | B49: =IFERROR(VLOOKUP(H49,[1]SEMIELABORADOS!$A$2:$M$6000,2,0),"") | C49: =+A49 -> 0 | D49: =IFERROR(VLOOKUP(H49,[1]SEMIELABORADOS!$A$2:$M$6000,6,0),"") | E49: =IFERROR(VLOOKUP(H49,[1]SEMIELABORADOS!$A$2:$M$65536,12,0),"") | F49: =IFERROR(E49*C49,"") | G49: =IFERROR(F49/$F$66,"")
A50: =+A41 -> 0 | B50: =IFERROR(VLOOKUP(H50,[1]SEMIELABORADOS!$A$2:$M$6000,2,0),"") | C50: =+A50 -> 0 | D50: =IFERROR(VLOOKUP(H50,[1]SEMIELABORADOS!$A$2:$M$6000,6,0),"") | E50: =IFERROR(VLOOKUP(H50,[1]SEMIELABORADOS!$A$2:$M$65536,12,0),"") | F50: =IFERROR(E50*C50,"") | G50: =IFERROR(F50/$F$66,"")
A51: 1 | B51: MODI PREPARACION | C51: =+A51 -> 1 | D51: N/A | E51: =+F65 -> 1220 | F51: =IFERROR(C51*E51,"") -> 1220 | G51: =IFERROR(F51/$F$66,"") -> 0.029229071
B53: TOTAL MATERIA PRIMA | F53: =SUM(F8:F14,F17:F24) -> 39676 | G53: =+F53/$F$66 -> 0.95056772 | H53: =+F53/$D$60 -> 39676
B54: TOTAL EMPAQUE | F54: =SUM(F27:F32,F35:F41) -> 49.747048 | G54: =+F54/$F$66 -> 0.0011918524 | H54: =+F54/$D$60 -> 49.747048 | K54: TOTAL MATERIA PRIMA + EMPAQUE | O54: =+F55 -> 39725.747
B55: TOTAL MATERIAS P. + EMPAQUES | F55: =+F53+F54 -> 39725.747 | G55: =+F55/$F$66 -> 0.95175957 | H55: =+F55/$D$60 -> 39725.747 | M55: MODI PLANTA | O55: =+H56 -> 1220
C56: TOTAL MODI | F56: =SUM(F44:F51) -> 1220 | G56: =+F56/$F$66 -> 0.029229071 | H56: =+F56/$D$60 -> 1220 | M56: DESECHO | O56: =O54*N56 -> 0
M57: COSTO PLANTA | O57: =SUM(O54:O56) -> 40945.747
B58: GRAMOS | D58: 10000 | H58: =+H56/61 -> 20 | M58: % GIF | O58: =+H59 -> 1160
B59: PESO POR UNIDAD | D59: 10000 | H59: =+H58*58 -> 1160 | M59: COSTO PLANTA | O59: =SUM(O57:O58) -> 42105.747
B60: UNIDADES TOTALES | D60: =+D58/D59 -> 1 | O60: =+O59*N60 -> 0
B61: UNIDAD MEDIDA | K61: PRECIO DE VENTA PLANTA A LOCAL | O61: =SUM(O59:O60) -> 42105.747 | P61: GR
E62: S/ COSTO | F62: TOTAL | L62: UNIDAD | O62: =+O61/D60 -> 42105.747 | P62: =+O62/D59 -> 4.2105747
B63: TOTAL MATERIAS P. + EMPAQUES | E63: =+F63/F63 -> 1 | F63: =SUM(F55) -> 39725.747 | G63: =+F63/$F$66 -> 0.95175957
B64: DESECHOS Y PERDIDAS | E64: 0.02 | F64: =+F53*E64 -> 793.52 | G64: =+F64/$F$66 -> 0.019011354
B65: MANO OBRA DIRECTA | D65: 20 | E65: 61 | F65: =+E65*D65 -> 1220 | G65: =+F65/$F$66 -> 0.029229071
B66: TOTAL COSTO PLANTA | F66: =SUM(F63:F65) -> 41739.267 | G66: =+F66/$F$66 -> 1 | M66: MODI 61 COLONES X MIN
M67: Gf 58 colones min
B68: COSTO POR GRAMO | M68: ,
B69: TOTAL COSTO MATERIA PRIMA | C69: =+F53 -> 39676 | D69: =+D58 -> 10000 | E69: =+C69/D69 -> 3.9676
B71: TOTAL COSTO UNIDAD MP+DESECHO+EMPAQUE | C71: =SUM(F63:F64) -> 40519.267 | D71: =+D58 -> 10000 | E71: =+C71/D71 -> 4.0519267
B73: TOTAL MODI PREPARACION POR GRAMO | C73: =+F65 -> 1220 | D73: =+D58 -> 10000 | E73: =+C73/D73 -> 0.122
B74: TOTAL MODI POR GRAMO | C74: =+F56 -> 1220 | D74: =+D73 -> 10000 | E74: =+C74/D74 -> 0.122
B76: TOTAL EMPAQUE POR GRAMO | C76: =+F54 -> 49.747048 | D76: =+D74 -> 10000 | E76: =+C76/D76 -> 0.0049747048
B78: TOTAL GRAMO MP+MODI | E78: =+E69+E74 -> 4.0896
B80: COSTO POR UNIDAD
B81: TOTAL COSTO MATERIA PRIMA | C81: =+C69 -> 39676 | D81: =+D60 -> 1 | E81: =+C81/D81 -> 39676
B83: TOTAL COSTO UNIDAD MP+DESECHO+EMPAQUE | C83: =+C71 -> 40519.267 | D83: =+D60 -> 1 | E83: =+C83/D83 -> 40519.267
B85: TOTAL MODI POR GRAMO | C85: =+C73 -> 1220 | D85: =+D60 -> 1 | E85: =+C85/D85 -> 1220
B86: TOTAL MODI POR GRAMO | C86: =+C74 -> 1220 | D86: =+D85 -> 1 | E86: =+C86/D86 -> 1220

Sheet Hoja1
C1: SERVICIOS DE PASTELERIA S.A. | H1: CÓDIGO: | I1: ESP-RE-COCS-082
C2: ESPECIFICACION DE RECETA | H2: REVISIÓN: | I2: 01
C3: SE00601 RELLENO ARANDANOS ROJOS | H3: FECHA DE APROBACIÓN: | I3: 45617
C4: Elaborado | D4: Javier Tong, Chef
C5: Aprobado | D5: Esteban Cartin, Gte Manufactura
A6: AREA QUE PRODUCE: | D6: Cocina | G6: AREA QUE EMPACA: | I6: Cocina
A7: # Código | B7: # Código Netsuite | C7: Descripción del ingrediente | D7: Marca | E7: Unidad Internacional | G7: Medida alternativa | I7: Costo - Referencia
E8: Cantidad | F8: Unidad medida | G8: Cantidad | H8: Unidad medida | I8: Colones
C9: Ensamble
B10: MP10688 | C10: ARANDANOS CONGELADOS ROJOS | D10: SYSCO | E10: 7142 | F10: g
B11: MP10689 | C11: ARANDANOS DESHIDRATADOS MFS | D11: MFS | E11: 2857 | F11: g
A12: 90100131 | B12: SE00016 | C12: EMPAQUE AZUCAR INDUSTRIAL | E12: 2857 | F12: g
A13: 1100022 | B13: MP10043 | C13: GELATINA PURA | E13: 30 | F13: g
A14: 90100129 | B14: SE00014 | C14: EMPAQUE ALMIDON MODIFICADO | E14: 200 | F14: g
A15: 1212410 | B15: MP10008 | C15: PRESERVANTE 1047S | E15: 10 | F15: g
A16: 10415 | C16: AGUA POTABLE (PLANTA) | D16: FAS | E16: 1000 | F16: g
A17: 10415 | C17: AGUA POTABLE (PLANTA) | D17: FAS | E17: 1600 | F17: g
C24: Decoración
C32: Empaque
A33: 512000003 | B33: EM10252 | C33: PLÁSTICO AUTOADERIBLE 1/ 12*2000 | E33: 1 | F33: ud
D45: Cantidad | E45: Unidad
A46: PESO TOTAL OBTENIDO | D46: 13000 | E46: g | F46: Tiempo de Horneo:
A47: TIEMPO TOTAL DE PREPARACION | D47: 10 | E47: min | F47: Horno:
A48: CANTIDAD DE PORCIONES OBTENIDAS | D48: 1 | E48: g | F48: Temperatura de Horneo:
A49: PESO DE CADA PORCIÓN | D49: 1 | E49: g | F49: Otros
A50: MERMA | D50: 2696 | E50: g
A51: PROCEDIMIENTO DE PREPARACION DE LA RECETA
A52: 1.- Colocar el Arandano deshidratado y Azucar y 1000 gramos de agua
A53: 2.-Cocinar a fuego medio y agregar 500 gramos de arandanos congelados, mover cada 5 minutos, para evitar que el relleno se pegue en el fondo de la olla.
A54: 3.- Una vez que el relleno este hirviendo agregar el restante de arandanos congelados, agregar el almidon disuelto en el agua
A55: 4.- Una Vez que el relleno hirvio agregar la gelatina Hidratada
A56: 5.-Hervir hasta que el relleno este bien espeso y con la textura deseada.
A57: 6.-Enfriar, cubir con plastico y rotular.
A58: 7-No mover mucho para que no se desbarate los arandanos
A60: CONTROL DE CAMBIOS

Sheet costo relleno arandanos
E1: Precio Local | F1: Costo MP | G1: Costo EM | H1: Costo MO
E2: =IFERROR(O62,"") -> 67985.659 | F2: =IFERROR(H53,"") -> 66233.641 | G2: =IFERROR(H54,"") -> 98.060883 | H2: =IFERROR(H56,"") -> 847.8268
A5: ESTRUCTURA DE COSTOS
F6: Fecha: | H6: =TODAY() -> 45776
A7: UNIDADES | B7: DESCRIPCION MAT.PRIMA | C7: UNIDADES | D7: UND MEDIDA | E7: COSTO UNITARIO | F7: TOTAL COSTO | G7: % PREC. DEFINIDO | H7: CODIGOS
A8: 7142 | B8: Arandanos Congelados Rojos | C8: =+A8 -> 7142 | D8: Gramos | E8: 7.03 | F8: =IFERROR(C8*E8,"") -> 50208.26 | G8: =IFERROR(F8/$F$66,"") -> 0.7354757
A9: 2857 | B9: Arandanos Deshidratados MFS | C9: =+A9 -> 2857 | D9: Gramos | E9: 4.74 | F9: =IFERROR(C9*E9,"") -> 13542.18 | G9: =IFERROR(F9/$F$66,"") -> 0.19837262
A10: 57 | B10: Gelatina Pura | C10: =+A10 -> 57 | D10: Gramos | E10: 13 | F10: =IFERROR(C10*E10,"") -> 741 | G10: =IFERROR(F10/$F$66,"") -> 0.010854539 | H10: 1100022
B11: =IFERROR(VLOOKUP(H11,'[1]Consolidado MP Planta'!$A$2:$M$823,3,0),"") | C11: =+A11 -> 0 | D11: =IFERROR(VLOOKUP(H11,'[1]Consolidado MP Planta'!$A$2:$M$823,13,0),"") | E11: =IFERROR(VLOOKUP(H11,'[1]Consolidado MP Planta'!$A$2:$M$823,12,0),"") | F11: =IFERROR(C11*E11,"") | G11: =IFERROR(F11/$F$66,"")
B12: =IFERROR(VLOOKUP(H12,'[1]Consolidado MP Planta'!$A$2:$M$823,3,0),"") | C12: =+A12 -> 0 | D12: =IFERROR(VLOOKUP(H12,'[1]Consolidado MP Planta'!$A$2:$M$823,13,0),"") | E12: =IFERROR(VLOOKUP(H12,'[1]Consolidado MP Planta'!$A$2:$M$823,12,0),"") | F12: =IFERROR(C12*E12,"") | G12: =IFERROR(F12/$F$66,"")
B13: =IFERROR(VLOOKUP(H13,'[1]Consolidado MP Planta'!$A$2:$M$823,3,0),"") | C13: =+A13 -> 0 | D13: =IFERROR(VLOOKUP(H13,'[1]Consolidado MP Planta'!$A$2:$M$823,13,0),"") | E13: =IFERROR(VLOOKUP(H13,'[1]Consolidado MP Planta'!$A$2:$M$823,12,0),"") | F13: =IFERROR(C13*E13,"") | G13: =IFERROR(F13/$F$66,"")
B14: =IFERROR(VLOOKUP(H14,'[1]Consolidado MP Planta'!$A$2:$M$823,3,0),"") | C14: =+A14 -> 0 | D14: =IFERROR(VLOOKUP(H14,'[1]Consolidado MP Planta'!$A$2:$M$823,13,0),"") | E14: =IFERROR(VLOOKUP(H14,'[1]Consolidado MP Planta'!$A$2:$M$823,12,0),"") | F14: =IFERROR(C14*E14,"") | G14: =IFERROR(F14/$F$66,"")
B15: =IFERROR(VLOOKUP(H15,'[2]ARTICULOS MP PLANTA'!$A$2:$G$589,2,0),"")
A16: UNIDADES | B16: MATERIA PRIMA SEMIELABORADOS | C16: UNIDADES | D16: UND MEDIDA | E16: COSTO UNITARIO | F16: TOTAL COSTO | G16: % PREC. DEFINIDO | H16: CODIGOS
A17: 2857 | B17: =IFERROR(VLOOKUP(H17,[1]SEMIELABORADOS!$A$2:$M$6000,2,0),"") -> AZUCAR BLANCO INDUSTRIAL KILO | C17: =+A17 -> 2857 | D17: =IFERROR(VLOOKUP(H17,[1]SEMIELABORADOS!$A$2:$M$6000,6,0),"") -> Gramo | E17: =IFERROR(VLOOKUP(H17,[1]SEMIELABORADOS!$A$2:$H$65536,8,0),"") -> 0.39034 | F17: =IFERROR(E17*C17,"") -> 1115.2014 | G17: =IFERROR(F17/$F$66,"") -> 0.016336027 | H17: 90100131
A18: 285 | B18: =IFERROR(VLOOKUP(H18,[1]SEMIELABORADOS!$A$2:$M$6000,2,0),"") -> EMPAQUE ALMIDON MODIFICADO KILO | C18: =+A18 -> 285 | D18: =IFERROR(VLOOKUP(H18,[1]SEMIELABORADOS!$A$2:$M$6000,6,0),"") -> Gramo | E18: 2.2 | F18: =IFERROR(E18*C18,"") -> 627 | G18: =IFERROR(F18/$F$66,"") -> 0.0091846095 | H18: 90100129
B19: =IFERROR(VLOOKUP(H19,[1]SEMIELABORADOS!$A$2:$M$6000,2,0),"") | C19: =+A19 -> 0 | D19: =IFERROR(VLOOKUP(H19,[1]SEMIELABORADOS!$A$2:$M$6000,6,0),"") | E19: =IFERROR(VLOOKUP(H19,[1]SEMIELABORADOS!$A$2:$H$65536,8,0),"") | F19: =IFERROR(E19*C19,"") | G19: =IFERROR(F19/$F$66,"")
B20: =IFERROR(VLOOKUP(H20,[1]SEMIELABORADOS!$A$2:$M$6000,2,0),"") | C20: =+A20 -> 0 | D20: =IFERROR(VLOOKUP(H20,[1]SEMIELABORADOS!$A$2:$M$6000,6,0),"") | E20: =IFERROR(VLOOKUP(H20,[1]SEMIELABORADOS!$A$2:$H$65536,8,0),"") | F20: =IFERROR(E20*C20,"") | G20: =IFERROR(F20/$F$66,"")
B21: =IFERROR(VLOOKUP(H21,[1]SEMIELABORADOS!$A$2:$M$6000,2,0),"") | C21: =+A21 -> 0 | D21: =IFERROR(VLOOKUP(H21,[1]SEMIELABORADOS!$A$2:$M$6000,6,0),"") | E21: =IFERROR(VLOOKUP(H21,[1]SEMIELABORADOS!$A$2:$H$65536,8,0),"") | F21: =IFERROR(E21*C21,"") | G21: =IFERROR(F21/$F$66,"")
B22: =IFERROR(VLOOKUP(H22,[1]SEMIELABORADOS!$A$2:$M$6000,2,0),"") | C22: =+A22 -> 0 | D22: =IFERROR(VLOOKUP(H22,[1]SEMIELABORADOS!$A$2:$M$6000,6,0),"") | E22: =IFERROR(VLOOKUP(H22,[1]SEMIELABORADOS!$A$2:$H$65536,8,0),"") | F22: =IFERROR(E22*C22,"") | G22: =IFERROR(F22/$F$66,"")
B23: =IFERROR(VLOOKUP(H23,[1]SEMIELABORADOS!$A$2:$M$6000,2,0),"") | C23: =+A23 -> 0 | D23: =IFERROR(VLOOKUP(H23,[1]SEMIELABORADOS!$A$2:$M$6000,6,0),"") | E23: =IFERROR(VLOOKUP(H23,[1]SEMIELABORADOS!$A$2:$H$65536,8,0),"") | F23: =IFERROR(E23*C23,"") | G23: =IFERROR(F23/$F$66,"")
B24: =IFERROR(VLOOKUP(H24,[1]SEMIELABORADOS!$A$2:$M$6000,2,0),"") | C24: =+A24 -> 0 | D24: =IFERROR(VLOOKUP(H24,[1]SEMIELABORADOS!$A$2:$M$6000,6,0),"") | E24: =IFERROR(VLOOKUP(H24,[1]SEMIELABORADOS!$A$2:$H$65536,8,0),"") | F24: =IFERROR(E24*C24,"") | G24: =IFERROR(F24/$F$66,"")
A26: UNIDADES | B26: EMPAQUE | C26: UNIDADES | D26: UND MEDIDA | E26: COSTO UNITARIO | F26: TOTAL COSTO | G26: % PREC. DEFINIDO | H26: CODIGOS
A27: 0 | B27: =IFERROR(VLOOKUP(H27,'[1]Consolidado MP Planta'!$A$2:$M$823,3,0),"") | C27: =+A27 -> 0 | D27: =IFERROR(VLOOKUP(H27,'[1]Consolidado MP Planta'!$A$2:$M$823,13,0),"") | E27: =IFERROR(VLOOKUP(H27,'[1]Consolidado MP Planta'!$A$2:$M$823,12,0),"") | F27: =IFERROR(C27*E27,"") | G27: =IFERROR(F27/$F$66,"")
B28: =IFERROR(VLOOKUP(H28,'[1]Consolidado MP Planta'!$A$2:$M$823,3,0),"") | C28: =+A28 -> 0 | D28: =IFERROR(VLOOKUP(H28,'[1]Consolidado MP Planta'!$A$2:$M$823,13,0),"") | E28: =IFERROR(VLOOKUP(H28,'[1]Consolidado MP Planta'!$A$2:$M$823,12,0),"") | F28: =IFERROR(C28*E28,"") | G28: =IFERROR(F28/$F$66,"")
B29: =IFERROR(VLOOKUP(H29,'[1]Consolidado MP Planta'!$A$2:$M$823,3,0),"") | C29: =+A29 -> 0 | D29: =IFERROR(VLOOKUP(H29,'[1]Consolidado MP Planta'!$A$2:$M$823,13,0),"") | E29: =IFERROR(VLOOKUP(H29,'[1]Consolidado MP Planta'!$A$2:$M$823,12,0),"") | F29: =IFERROR(C29*E29,"") | G29: =IFERROR(F29/$F$66,"")
B30: =IFERROR(VLOOKUP(H30,'[1]Consolidado MP Planta'!$A$2:$M$823,3,0),"") | C30: =+A30 -> 0 | D30: =IFERROR(VLOOKUP(H30,'[1]Consolidado MP Planta'!$A$2:$M$823,13,0),"") | E30: =IFERROR(VLOOKUP(H30,'[1]Consolidado MP Planta'!$A$2:$M$823,12,0),"") | F30: =IFERROR(C30*E30,"") | G30: =IFERROR(F30/$F$66,"")
B31: =IFERROR(VLOOKUP(H31,'[1]Consolidado MP Planta'!$A$2:$M$823,3,0),"") | C31: =+A31 -> 0 | D31: =IFERROR(VLOOKUP(H31,'[1]Consolidado MP Planta'!$A$2:$M$823,13,0),"") | E31: =IFERROR(VLOOKUP(H31,'[1]Consolidado MP Planta'!$A$2:$M$823,12,0),"") | F31: =IFERROR(C31*E31,"") | G31: =IFERROR(F31/$F$66,"")
B32: =IFERROR(VLOOKUP(H32,'[1]Consolidado MP Planta'!$A$2:$M$823,3,0),"") | C32: =+A32 -> 0 | D32: =IFERROR(VLOOKUP(H32,'[1]Consolidado MP Planta'!$A$2:$M$823,13,0),"") | E32: =IFERROR(VLOOKUP(H32,'[1]Consolidado MP Planta'!$A$2:$M$823,12,0),"") | F32: =IFERROR(C32*E32,"") | G32: =IFERROR(F32/$F$66,"")
A34: UNIDADES | B34: EMPAQUE SEMIELABORADOS | C34: UNIDADES | D34: UND MEDIDA | E34: COSTO UNITARIO | F34: TOTAL COSTO | G34: % PREC. DEFINIDO | H34: CODIGOS
A35: =+A17 -> 2857 | B35: =IFERROR(VLOOKUP(H35,[1]SEMIELABORADOS!$A$2:$M$6000,2,0),"") -> AZUCAR BLANCO INDUSTRIAL KILO | C35: =+A35 -> 2857 | D35: =IFERROR(VLOOKUP(H35,[1]SEMIELABORADOS!$A$2:$M$6000,6,0),"") -> Gramo | E35: =IFERROR(VLOOKUP(H35,[1]SEMIELABORADOS!$A$2:$M$65536,10,0),"") -> 0.033330522 | F35: =IFERROR(E35*C35,"") -> 95.225301 | G35: =IFERROR(F35/$F$66,"") -> 0.0013949078 | H35: 90100131
A36: =+A18 -> 285 | B36: =IFERROR(VLOOKUP(H36,[1]SEMIELABORADOS!$A$2:$M$6000,2,0),"") -> EMPAQUE ALMIDON MODIFICADO KILO | C36: =+A36 -> 285 | D36: =IFERROR(VLOOKUP(H36,[1]SEMIELABORADOS!$A$2:$M$6000,6,0),"") -> Gramo | E36: =IFERROR(VLOOKUP(H36,[1]SEMIELABORADOS!$A$2:$M$65536,10,0),"") -> 0.0099494095 | F36: =IFERROR(E36*C36,"") -> 2.8355817 | G36: =IFERROR(F36/$F$66,"") -> 4.1537019e-05 | H36: 90100129
A37: =+A19 -> 0 | B37: =IFERROR(VLOOKUP(H37,[1]SEMIELABORADOS!$A$2:$M$6000,2,0),"") | C37: =+A37 -> 0 | D37: =IFERROR(VLOOKUP(H37,[1]SEMIELABORADOS!$A$2:$M$6000,6,0),"") | E37: =IFERROR(VLOOKUP(H37,[1]SEMIELABORADOS!$A$2:$M$65536,10,0),"") | F37: =IFERROR(E37*C37,"") | G37: =IFERROR(F37/$F$66,"")
A38: =+A20 -> 0 | B38: =IFERROR(VLOOKUP(H38,[1]SEMIELABORADOS!$A$2:$M$6000,2,0),"") | C38: =+A38 -> 0 | D38: =IFERROR(VLOOKUP(H38,[1]SEMIELABORADOS!$A$2:$M$6000,6,0),"") | E38: =IFERROR(VLOOKUP(H38,[1]SEMIELABORADOS!$A$2:$M$65536,10,0),"") | F38: =IFERROR(E38*C38,"") | G38: =IFERROR(F38/$F$66,"")
A39: =+A21 -> 0 | B39: =IFERROR(VLOOKUP(H39,[1]SEMIELABORADOS!$A$2:$M$6000,2,0),"") | C39: =+A39 -> 0 | D39: =IFERROR(VLOOKUP(H39,[1]SEMIELABORADOS!$A$2:$M$6000,6,0),"") | E39: =IFERROR(VLOOKUP(H39,[1]SEMIELABORADOS!$A$2:$M$65536,10,0),"") | F39: =IFERROR(E39*C39,"") | G39: =IFERROR(F39/$F$66,"")
A40: =+A22 -> 0 | B40: =IFERROR(VLOOKUP(H40,[1]SEMIELABORADOS!$A$2:$M$6000,2,0),"") | C40: =+A40 -> 0 | D40: =IFERROR(VLOOKUP(H40,[1]SEMIELABORADOS!$A$2:$M$6000,6,0),"") | E40: =IFERROR(VLOOKUP(H40,[1]SEMIELABORADOS!$A$2:$M$65536,10,0),"") | F40: =IFERROR(E40*C40,"") | G40: =IFERROR(F40/$F$66,"")
A41: =+A23 -> 0 | B41: =IFERROR(VLOOKUP(H41,[1]SEMIELABORADOS!$A$2:$M$6000,2,0),"") | C41: =+A41 -> 0 | D41: =IFERROR(VLOOKUP(H41,[1]SEMIELABORADOS!$A$2:$M$6000,6,0),"") | E41: =IFERROR(VLOOKUP(H41,[1]SEMIELABORADOS!$A$2:$M$65536,10,0),"") | F41: =IFERROR(E41*C41,"") | G41: =IFERROR(F41/$F$66,"")
A43: UNIDADES | B43: MODI | C43: UNIDADES | D43: UND MEDIDA | E43: COSTO UNITARIO | F43: TOTAL COSTO | G43: % PREC. DEFINIDO | H43: CODIGOS
A44: =+A35 -> 2857 | B44: =IFERROR(VLOOKUP(H44,[1]SEMIELABORADOS!$A$2:$M$6000,2,0),"") -> AZUCAR BLANCO INDUSTRIAL KILO | C44: =+A44 -> 2857 | D44: =IFERROR(VLOOKUP(H44,[1]SEMIELABORADOS!$A$2:$M$6000,6,0),"") -> Gramo | E44: =IFERROR(VLOOKUP(H44,[1]SEMIELABORADOS!$A$2:$M$65536,12,0),"") -> 0.076260694 | F44: =IFERROR(E44*C44,"") -> 217.8768 | G44: =IFERROR(F44/$F$66,"") -> 0.0031915684 | H44: 90100131
A45: =+A36 -> 285 | B45: =IFERROR(VLOOKUP(H45,[1]SEMIELABORADOS!$A$2:$M$6000,2,0),"") -> EMPAQUE ALMIDON MODIFICADO KILO | C45: =+A45 -> 285 | D45: =IFERROR(VLOOKUP(H45,[1]SEMIELABORADOS!$A$2:$M$6000,6,0),"") -> Gramo | E45: 0.07 | F45: =IFERROR(E45*C45,"") -> 19.95 | G45: =IFERROR(F45/$F$66,"") -> 0.00029223758 | H45: 90100129
A46: =+A37 -> 0 | B46: =IFERROR(VLOOKUP(H46,[1]SEMIELABORADOS!$A$2:$M$6000,2,0),"") | C46: =+A46 -> 0 | D46: =IFERROR(VLOOKUP(H46,[1]SEMIELABORADOS!$A$2:$M$6000,6,0),"") | E46: =IFERROR(VLOOKUP(H46,[1]SEMIELABORADOS!$A$2:$M$65536,12,0),"") | F46: =IFERROR(E46*C46,"") | G46: =IFERROR(F46/$F$66,"")
A47: =+A38 -> 0 | B47: =IFERROR(VLOOKUP(H47,[1]SEMIELABORADOS!$A$2:$M$6000,2,0),"") | C47: =+A47 -> 0 | D47: =IFERROR(VLOOKUP(H47,[1]SEMIELABORADOS!$A$2:$M$6000,6,0),"") | E47: =IFERROR(VLOOKUP(H47,[1]SEMIELABORADOS!$A$2:$M$65536,12,0),"") | F47: =IFERROR(E47*C47,"") | G47: =IFERROR(F47/$F$66,"")
A48: =+A39 -> 0 | B48: =IFERROR(VLOOKUP(H48,[1]SEMIELABORADOS!$A$2:$M$6000,2,0),"") | C48: =+A48 -> 0 | D48: =IFERROR(VLOOKUP(H48,[1]SEMIELABORADOS!$A$2:$M$6000,6,0),"") | E48: =IFERROR(VLOOKUP(H48,[1]SEMIELABORADOS!$A$2:$M$65536,12,0),"") | F48: =IFERROR(E48*C48,"") | G48: =IFERROR(F48/$F$66,"")
A49: =+A40 -> 0 | B49: =IFERROR(VLOOKUP(H49,[1]SEMIELABORADOS!$A$2:$M$6000,2,0),"") | C49: =+A49 -> 0 | D49: =IFERROR(VLOOKUP(H49,[1]SEMIELABORADOS!$A$2:$M$6000,6,0),"") | E49: =IFERROR(VLOOKUP(H49,[1]SEMIELABORADOS!$A$2:$M$65536,12,0),"") | F49: =IFERROR(E49*C49,"") | G49: =IFERROR(F49/$F$66,"")
A50: =+A41 -> 0 | B50: =IFERROR(VLOOKUP(H50,[1]SEMIELABORADOS!$A$2:$M$6000,2,0),"") | C50: =+A50 -> 0 | D50: =IFERROR(VLOOKUP(H50,[1]SEMIELABORADOS!$A$2:$M$6000,6,0),"") | E50: =IFERROR(VLOOKUP(H50,[1]SEMIELABORADOS!$A$2:$M$65536,12,0),"") | F50: =IFERROR(E50*C50,"") | G50: =IFERROR(F50/$F$66,"")
A51: 1 | B51: MODI PREPARACION | C51: =+A51 -> 1 | D51: N/A | E51: =+F65 -> 610 | F51: =IFERROR(C51*E51,"") -> 610 | G51: =IFERROR(F51/$F$66,"") -> 0.008935585
B53: TOTAL MATERIA PRIMA | F53: =SUM(F8:F14,F17:F24) -> 66233.641 | G53: =+F53/$F$66 -> 0.9702235 | H53: =+F53/$D$60 -> 66233.641
B54: TOTAL EMPAQUE | F54: =SUM(F27:F32,F35:F41) -> 98.060883 | G54: =+F54/$F$66 -> 0.0014364448 | H54: =+F54/$D$60 -> 98.060883 | K54: TOTAL MATERIA PRIMA + EMPAQUE | O54: =+F55 -> 66331.702
B55: TOTAL MATERIAS P. + EMPAQUES | F55: =+F53+F54 -> 66331.702 | G55: =+F55/$F$66 -> 0.97165994 | H55: =+F55/$D$60 -> 66331.702 | M55: MODI PLANTA | O55: =+H56 -> 847.8268
C56: TOTAL MODI | F56: =SUM(F44:F51) -> 847.8268 | G56: =+F56/$F$66 -> 0.012419391 | H56: =+F56/$D$60 -> 847.8268 | M56: DESECHO | O56: =O54*N56 -> 0
M57: COSTO PLANTA | O57: =SUM(O54:O56) -> 67179.529
B58: GRAMOS | D58: 10000 | H58: =+H56/61 -> 13.8988 | M58: % GIF | O58: =+H59 -> 806.1304
B59: PESO POR UNIDAD | D59: 10000 | H59: =+H58*58 -> 806.1304 | M59: COSTO PLANTA | O59: =SUM(O57:O58) -> 67985.659
B60: UNIDADES TOTALES | D60: =+D58/D59 -> 1 | O60: =+O59*N60 -> 0
B61: UNIDAD MEDIDA | K61: PRECIO DE VENTA PLANTA A LOCAL | O61: =SUM(O59:O60) -> 67985.659 | P61: GR
E62: S/ COSTO | F62: TOTAL | L62: UNIDAD | O62: =+O61/D60 -> 67985.659 | P62: =+O62/D59 -> 6.7985659
B63: TOTAL MATERIAS P. + EMPAQUES | E63: =+F63/F63 -> 1 | F63: =SUM(F55) -> 66331.702 | G63: =+F63/$F$66 -> 0.97165994
B64: DESECHOS Y PERDIDAS | E64: 0.02 | F64: =+F53*E64 -> 1324.6728 | G64: =+F64/$F$66 -> 0.01940447
B65: MANO OBRA DIRECTA | D65: 10 | E65: 61 | F65: =+E65*D65 -> 610 | G65: =+F65/$F$66 -> 0.008935585
B66: TOTAL COSTO PLANTA | F66: =SUM(F63:F65) -> 68266.375 | G66: =+F66/$F$66 -> 1 | M66: MODI 61 COLONES X MIN
M67: Gf 58 colones min
B68: COSTO POR GRAMO | M68: ,
B69: TOTAL COSTO MATERIA PRIMA | C69: =+F53 -> 66233.641 | D69: =+D58 -> 10000 | E69: =+C69/D69 -> 6.6233641
B71: TOTAL COSTO UNIDAD MP+DESECHO+EMPAQUE | C71: =SUM(F63:F64) -> 67656.375 | D71: =+D58 -> 10000 | E71: =+C71/D71 -> 6.7656375
B73: TOTAL MODI PREPARACION POR GRAMO | C73: =+F65 -> 610 | D73: =+D58 -> 10000 | E73: =+C73/D73 -> 0.061
B74: TOTAL MODI POR GRAMO | C74: =+F56 -> 847.8268 | D74: =+D73 -> 10000 | E74: =+C74/D74 -> 0.08478268
B76: TOTAL EMPAQUE POR GRAMO | C76: =+F54 -> 98.060883 | D76: =+D74 -> 10000 | E76: =+C76/D76 -> 0.0098060883
B78: TOTAL GRAMO MP+MODI | E78: =+E69+E74 -> 6.7081468
B80: COSTO POR UNIDAD
B81: TOTAL COSTO MATERIA PRIMA | C81: =+C69 -> 66233.641 | D81: =+D60 -> 1 | E81: =+C81/D81 -> 66233.641
B83: TOTAL COSTO UNIDAD MP+DESECHO+EMPAQUE | C83: =+C71 -> 67656.375 | D83: =+D60 -> 1 | E83: =+C83/D83 -> 67656.375
B85: TOTAL MODI POR GRAMO | C85: =+C73 -> 610 | D85: =+D60 -> 1 | E85: =+C85/D85 -> 610
B86: TOTAL MODI POR GRAMO | C86: =+C74 -> 847.8268 | D86: =+D85 -> 1 | E86: =+C86/D86 -> 847.8268

Sheet Costo Empaque Relleno Arand
E1: Precio Local | F1: Costo MP | G1: Costo EM | H1: Costo MO
E2: =IFERROR(O62,"") -> 34160.362 | F2: =IFERROR(H53,"") -> 33116.821 | G2: =IFERROR(H54,"") -> 97.562822 | H2: =IFERROR(H56,"") -> 484.9134
A5: ESTRUCTURA DE COSTOS
F6: Fecha: | H6: =TODAY() -> 45776
A7: UNIDADES | B7: DESCRIPCION MAT.PRIMA | C7: UNIDADES | D7: UND MEDIDA | E7: COSTO UNITARIO | F7: TOTAL COSTO | G7: % PREC. DEFINIDO | H7: CODIGOS
B8: =IFERROR(VLOOKUP(H8,'[1]Consolidado MP Planta'!$A$2:$M$823,3,0),"") | C8: =+A8 -> 0 | D8: =IFERROR(VLOOKUP(H8,'[1]Consolidado MP Planta'!$A$2:$M$823,13,0),"") | E8: =IFERROR(VLOOKUP(H8,'[1]Consolidado MP Planta'!$A$2:$M$823,12,0),"") | F8: =IFERROR(C8*E8,"") | G8: =IFERROR(F8/$F$66,"")
B9: =IFERROR(VLOOKUP(H9,'[1]Consolidado MP Planta'!$A$2:$M$823,3,0),"") | C9: =+A9 -> 0 | D9: =IFERROR(VLOOKUP(H9,'[1]Consolidado MP Planta'!$A$2:$M$823,13,0),"") | E9: =IFERROR(VLOOKUP(H9,'[1]Consolidado MP Planta'!$A$2:$M$823,12,0),"") | F9: =IFERROR(C9*E9,"") | G9: =IFERROR(F9/$F$66,"")
B10: =IFERROR(VLOOKUP(H10,'[1]Consolidado MP Planta'!$A$2:$M$823,3,0),"") | C10: =+A10 -> 0 | D10: =IFERROR(VLOOKUP(H10,'[1]Consolidado MP Planta'!$A$2:$M$823,13,0),"") | E10: =IFERROR(VLOOKUP(H10,'[1]Consolidado MP Planta'!$A$2:$M$823,12,0),"") | F10: =IFERROR(C10*E10,"") | G10: =IFERROR(F10/$F$66,"")
B11: =IFERROR(VLOOKUP(H11,'[1]Consolidado MP Planta'!$A$2:$M$823,3,0),"") | C11: =+A11 -> 0 | D11: =IFERROR(VLOOKUP(H11,'[1]Consolidado MP Planta'!$A$2:$M$823,13,0),"") | E11: =IFERROR(VLOOKUP(H11,'[1]Consolidado MP Planta'!$A$2:$M$823,12,0),"") | F11: =IFERROR(C11*E11,"") | G11: =IFERROR(F11/$F$66,"")
B12: =IFERROR(VLOOKUP(H12,'[1]Consolidado MP Planta'!$A$2:$M$823,3,0),"") | C12: =+A12 -> 0 | D12: =IFERROR(VLOOKUP(H12,'[1]Consolidado MP Planta'!$A$2:$M$823,13,0),"") | E12: =IFERROR(VLOOKUP(H12,'[1]Consolidado MP Planta'!$A$2:$M$823,12,0),"") | F12: =IFERROR(C12*E12,"") | G12: =IFERROR(F12/$F$66,"")
B13: =IFERROR(VLOOKUP(H13,'[1]Consolidado MP Planta'!$A$2:$M$823,3,0),"") | C13: =+A13 -> 0 | D13: =IFERROR(VLOOKUP(H13,'[1]Consolidado MP Planta'!$A$2:$M$823,13,0),"") | E13: =IFERROR(VLOOKUP(H13,'[1]Consolidado MP Planta'!$A$2:$M$823,12,0),"") | F13: =IFERROR(C13*E13,"") | G13: =IFERROR(F13/$F$66,"")
B14: =IFERROR(VLOOKUP(H14,'[1]Consolidado MP Planta'!$A$2:$M$823,3,0),"") | C14: =+A14 -> 0 | D14: =IFERROR(VLOOKUP(H14,'[1]Consolidado MP Planta'!$A$2:$M$823,13,0),"") | E14: =IFERROR(VLOOKUP(H14,'[1]Consolidado MP Planta'!$A$2:$M$823,12,0),"") | F14: =IFERROR(C14*E14,"") | G14: =IFERROR(F14/$F$66,"")
B15: =IFERROR(VLOOKUP(H15,'[2]ARTICULOS MP PLANTA'!$A$2:$G$589,2,0),"")
A16: UNIDADES | B16: MATERIA PRIMA SEMIELABORADOS | C16: UNIDADES | D16: UND MEDIDA | E16: COSTO UNITARIO | F16: TOTAL COSTO | G16: % PREC. DEFINIDO | H16: CODIGOS
A17: 5000 | B17: RELLENO ARANDANOS ROJOS | C17: =+A17 -> 5000 | D17: =IFERROR(VLOOKUP(H17,[1]SEMIELABORADOS!$A$2:$M$6000,6,0),"") | E17: =+'costo relleno arandanos'!E69 -> 6.6233641 | F17: =IFERROR(E17*C17,"") -> 33116.821 | G17: =IFERROR(F17/$F$66,"") -> 0.9758116
B18: =IFERROR(VLOOKUP(H18,[1]SEMIELABORADOS!$A$2:$M$6000,2,0),"") | C18: =+A18 -> 0 | D18: =IFERROR(VLOOKUP(H18,[1]SEMIELABORADOS!$A$2:$M$6000,6,0),"") | E18: =IFERROR(VLOOKUP(H18,[1]SEMIELABORADOS!$A$2:$H$65536,8,0),"") | F18: =IFERROR(E18*C18,"") | G18: =IFERROR(F18/$F$66,"")
B19: =IFERROR(VLOOKUP(H19,[1]SEMIELABORADOS!$A$2:$M$6000,2,0),"") | C19: =+A19 -> 0 | D19: =IFERROR(VLOOKUP(H19,[1]SEMIELABORADOS!$A$2:$M$6000,6,0),"") | E19: =IFERROR(VLOOKUP(H19,[1]SEMIELABORADOS!$A$2:$H$65536,8,0),"") | F19: =IFERROR(E19*C19,"") | G19: =IFERROR(F19/$F$66,"")
B20: =IFERROR(VLOOKUP(H20,[1]SEMIELABORADOS!$A$2:$M$6000,2,0),"") | C20: =+A20 -> 0 | D20: =IFERROR(VLOOKUP(H20,[1]SEMIELABORADOS!$A$2:$M$6000,6,0),"") | E20: =IFERROR(VLOOKUP(H20,[1]SEMIELABORADOS!$A$2:$H$65536,8,0),"") | F20: =IFERROR(E20*C20,"") | G20: =IFERROR(F20/$F$66,"")
B21: =IFERROR(VLOOKUP(H21,[1]SEMIELABORADOS!$A$2:$M$6000,2,0),"") | C21: =+A21 -> 0 | D21: =IFERROR(VLOOKUP(H21,[1]SEMIELABORADOS!$A$2:$M$6000,6,0),"") | E21: =IFERROR(VLOOKUP(H21,[1]SEMIELABORADOS!$A$2:$H$65536,8,0),"") | F21: =IFERROR(E21*C21,"") | G21: =IFERROR(F21/$F$66,"")
B22: =IFERROR(VLOOKUP(H22,[1]SEMIELABORADOS!$A$2:$M$6000,2,0),"") | C22: =+A22 -> 0 | D22: =IFERROR(VLOOKUP(H22,[1]SEMIELABORADOS!$A$2:$M$6000,6,0),"") | E22: =IFERROR(VLOOKUP(H22,[1]SEMIELABORADOS!$A$2:$H$65536,8,0),"") | F22: =IFERROR(E22*C22,"") | G22: =IFERROR(F22/$F$66,"")
B23: =IFERROR(VLOOKUP(H23,[1]SEMIELABORADOS!$A$2:$M$6000,2,0),"") | C23: =+A23 -> 0 | D23: =IFERROR(VLOOKUP(H23,[1]SEMIELABORADOS!$A$2:$M$6000,6,0),"") | E23: =IFERROR(VLOOKUP(H23,[1]SEMIELABORADOS!$A$2:$H$65536,8,0),"") | F23: =IFERROR(E23*C23,"") | G23: =IFERROR(F23/$F$66,"")
B24: =IFERROR(VLOOKUP(H24,[1]SEMIELABORADOS!$A$2:$M$6000,2,0),"") | C24: =+A24 -> 0 | D24: =IFERROR(VLOOKUP(H24,[1]SEMIELABORADOS!$A$2:$M$6000,6,0),"") | E24: =IFERROR(VLOOKUP(H24,[1]SEMIELABORADOS!$A$2:$H$65536,8,0),"") | F24: =IFERROR(E24*C24,"") | G24: =IFERROR(F24/$F$66,"")
A26: UNIDADES | B26: EMPAQUE | C26: UNIDADES | D26: UND MEDIDA | E26: COSTO UNITARIO | F26: TOTAL COSTO | G26: % PREC. DEFINIDO | H26: CODIGOS
A27: 1 | B27: =IFERROR(VLOOKUP(H27,'[1]Consolidado MP Planta'!$A$2:$M$823,3,0),"") -> BOLSA 17x25 TRANSP KILO | C27: =+A27 -> 1 | D27: =IFERROR(VLOOKUP(H27,'[1]Consolidado MP Planta'!$A$2:$M$823,13,0),"") -> Und | E27: =IFERROR(VLOOKUP(H27,'[1]Consolidado MP Planta'!$A$2:$M$823,12,0),"") -> 47.619048 | F27: =IFERROR(C27*E27,"") -> 47.619048 | G27: =IFERROR(F27/$F$66,"") -> 0.0014031304 | H27: 1950708
A28: 1 | B28: =IFERROR(VLOOKUP(H28,'[1]Consolidado MP Planta'!$A$2:$M$823,3,0),"") -> ETIQ.BLANCA 1 1/4 * 3/4 (UND) | C28: =+A28 -> 1 | D28: =IFERROR(VLOOKUP(H28,'[1]Consolidado MP Planta'!$A$2:$M$823,13,0),"") -> Und | E28: =IFERROR(VLOOKUP(H28,'[1]Consolidado MP Planta'!$A$2:$M$823,12,0),"") -> 0.58 | F28: =IFERROR(C28*E28,"") -> 0.58 | G28: =IFERROR(F28/$F$66,"") -> 1.7090129e-05 | H28: 0702069
A29: 1 | B29: =IFERROR(VLOOKUP(H29,'[1]Consolidado MP Planta'!$A$2:$M$823,3,0),"") -> ETIQ.FECHA VENCIMIENTO BLANCO (ROLLO) | C29: =+A29 -> 1 | D29: =IFERROR(VLOOKUP(H29,'[1]Consolidado MP Planta'!$A$2:$M$823,13,0),"") -> Gramos | E29: =IFERROR(VLOOKUP(H29,'[1]Consolidado MP Planta'!$A$2:$M$823,12,0),"") -> 0.33333333 | F29: =IFERROR(C29*E29,"") -> 0.33333333 | G29: =IFERROR(F29/$F$66,"") -> 9.821913e-06 | H29: 0702007
B30: =IFERROR(VLOOKUP(H30,'[1]Consolidado MP Planta'!$A$2:$M$823,3,0),"") | C30: =+A30 -> 0 | D30: =IFERROR(VLOOKUP(H30,'[1]Consolidado MP Planta'!$A$2:$M$823,13,0),"") | E30: =IFERROR(VLOOKUP(H30,'[1]Consolidado MP Planta'!$A$2:$M$823,12,0),"") | F30: =IFERROR(C30*E30,"") | G30: =IFERROR(F30/$F$66,"")
B31: =IFERROR(VLOOKUP(H31,'[1]Consolidado MP Planta'!$A$2:$M$823,3,0),"") | C31: =+A31 -> 0 | D31: =IFERROR(VLOOKUP(H31,'[1]Consolidado MP Planta'!$A$2:$M$823,13,0),"") | E31: =IFERROR(VLOOKUP(H31,'[1]Consolidado MP Planta'!$A$2:$M$823,12,0),"") | F31: =IFERROR(C31*E31,"") | G31: =IFERROR(F31/$F$66,"")
B32: =IFERROR(VLOOKUP(H32,'[1]Consolidado MP Planta'!$A$2:$M$823,3,0),"") | C32: =+A32 -> 0 | D32: =IFERROR(VLOOKUP(H32,'[1]Consolidado MP Planta'!$A$2:$M$823,13,0),"") | E32: =IFERROR(VLOOKUP(H32,'[1]Consolidado MP Planta'!$A$2:$M$823,12,0),"") | F32: =IFERROR(C32*E32,"") | G32: =IFERROR(F32/$F$66,"")
A34: UNIDADES | B34: EMPAQUE SEMIELABORADOS | C34: UNIDADES | D34: UND MEDIDA | E34: COSTO UNITARIO | F34: TOTAL COSTO | G34: % PREC. DEFINIDO | H34: CODIGOS
A35: =+A17 -> 5000 | B35: RELLENO ARANDANOS ROJOS | C35: =+A35 -> 5000 | D35: =IFERROR(VLOOKUP(H35,[1]SEMIELABORADOS!$A$2:$M$6000,6,0),"") | E35: =+'costo relleno arandanos'!E76 -> 0.0098060883 | F35: =IFERROR(E35*C35,"") -> 49.030441 | G35: =IFERROR(F35/$F$66,"") -> 0.0014447182
A36: =+A18 -> 0 | B36: =IFERROR(VLOOKUP(H36,[1]SEMIELABORADOS!$A$2:$M$6000,2,0),"") | C36: =+A36 -> 0 | D36: =IFERROR(VLOOKUP(H36,[1]SEMIELABORADOS!$A$2:$M$6000,6,0),"") | E36: =IFERROR(VLOOKUP(H36,[1]SEMIELABORADOS!$A$2:$M$65536,10,0),"") | F36: =IFERROR(E36*C36,"") | G36: =IFERROR(F36/$F$66,"")
A37: =+A19 -> 0 | B37: =IFERROR(VLOOKUP(H37,[1]SEMIELABORADOS!$A$2:$M$6000,2,0),"") | C37: =+A37 -> 0 | D37: =IFERROR(VLOOKUP(H37,[1]SEMIELABORADOS!$A$2:$M$6000,6,0),"") | E37: =IFERROR(VLOOKUP(H37,[1]SEMIELABORADOS!$A$2:$M$65536,10,0),"") | F37: =IFERROR(E37*C37,"") | G37: =IFERROR(F37/$F$66,"")
A38: =+A20 -> 0 | B38: =IFERROR(VLOOKUP(H38,[1]SEMIELABORADOS!$A$2:$M$6000,2,0),"") | C38: =+A38 -> 0 | D38: =IFERROR(VLOOKUP(H38,[1]SEMIELABORADOS!$A$2:$M$6000,6,0),"") | E38: =IFERROR(VLOOKUP(H38,[1]SEMIELABORADOS!$A$2:$M$65536,10,0),"") | F38: =IFERROR(E38*C38,"") | G38: =IFERROR(F38/$F$66,"")
A39: =+A21 -> 0 | B39: =IFERROR(VLOOKUP(H39,[1]SEMIELABORADOS!$A$2:$M$6000,2,0),"") | C39: =+A39 -> 0 | D39: =IFERROR(VLOOKUP(H39,[1]SEMIELABORADOS!$A$2:$M$6000,6,0),"") | E39: =IFERROR(VLOOKUP(H39,[1]SEMIELABORADOS!$A$2:$M$65536,10,0),"") | F39: =IFERROR(E39*C39,"") | G39: =IFERROR(F39/$F$66,"")
A40: =+A22 -> 0 | B40: =IFERROR(VLOOKUP(H40,[1]SEMIELABORADOS!$A$2:$M$6000,2,0),"") | C40: =+A40 -> 0 | D40: =IFERROR(VLOOKUP(H40,[1]SEMIELABORADOS!$A$2:$M$6000,6,0),"") | E40: =IFERROR(VLOOKUP(H40,[1]SEMIELABORADOS!$A$2:$M$65536,10,0),"") | F40: =IFERROR(E40*C40,"") | G40: =IFERROR(F40/$F$66,"")
A41: =+A23 -> 0 | B41: =IFERROR(VLOOKUP(H41,[1]SEMIELABORADOS!$A$2:$M$6000,2,0),"") | C41: =+A41 -> 0 | D41: =IFERROR(VLOOKUP(H41,[1]SEMIELABORADOS!$A$2:$M$6000,6,0),"") | E41: =IFERROR(VLOOKUP(H41,[1]SEMIELABORADOS!$A$2:$M$65536,10,0),"") | F41: =IFERROR(E41*C41,"") | G41: =IFERROR(F41/$F$66,"")
A43: UNIDADES | B43: MODI | C43: UNIDADES | D43: UND MEDIDA | E43: COSTO UNITARIO | F43: TOTAL COSTO | G43: % PREC. DEFINIDO | H43: CODIGOS
A44: =+A35 -> 5000 | B44: RELLENO ARANDANOS ROJOS | C44: =+A44 -> 5000 | D44: =IFERROR(VLOOKUP(H44,[1]SEMIELABORADOS!$A$2:$M$6000,6,0),"") | E44: =+'costo relleno arandanos'!E74 -> 0.08478268 | F44: =IFERROR(E44*C44,"") -> 423.9134 | G44: =IFERROR(F44/$F$66,"") -> 0.012490922
A45: =+A36 -> 0 | B45: =IFERROR(VLOOKUP(H45,[1]SEMIELABORADOS!$A$2:$M$6000,2,0),"") | C45: =+A45 -> 0 | D45: =IFERROR(VLOOKUP(H45,[1]SEMIELABORADOS!$A$2:$M$6000,6,0),"") | E45: =IFERROR(VLOOKUP(H45,[1]SEMIELABORADOS!$A$2:$M$65536,12,0),"") | F45: =IFERROR(E45*C45,"") | G45: =IFERROR(F45/$F$66,"")
A46: =+A37 -> 0 | B46: =IFERROR(VLOOKUP(H46,[1]SEMIELABORADOS!$A$2:$M$6000,2,0),"") | C46: =+A46 -> 0 | D46: =IFERROR(VLOOKUP(H46,[1]SEMIELABORADOS!$A$2:$M$6000,6,0),"") | E46: =IFERROR(VLOOKUP(H46,[1]SEMIELABORADOS!$A$2:$M$65536,12,0),"") | F46: =IFERROR(E46*C46,"") | G46: =IFERROR(F46/$F$66,"")
A47: =+A38 -> 0 | B47: =IFERROR(VLOOKUP(H47,[1]SEMIELABORADOS!$A$2:$M$6000,2,0),"") | C47: =+A47 -> 0 | D47: =IFERROR(VLOOKUP(H47,[1]SEMIELABORADOS!$A$2:$M$6000,6,0),"") | E47: =IFERROR(VLOOKUP(H47,[1]SEMIELABORADOS!$A$2:$M$65536,12,0),"") | F47: =IFERROR(E47*C47,"") | G47: =IFERROR(F47/$F$66,"")
A48: =+A39 -> 0 | B48: =IFERROR(VLOOKUP(H48,[1]SEMIELABORADOS!$A$2:$M$6000,2,0),"") | C48: =+A48 -> 0 | D48: =IFERROR(VLOOKUP(H48,[1]SEMIELABORADOS!$A$2:$M$6000,6,0),"") | E48: =IFERROR(VLOOKUP(H48,[1]SEMIELABORADOS!$A$2:$M$65536,12,0),"") | F48: =IFERROR(E48*C48,"") | G48: =IFERROR(F48/$F$66,"")
A49: =+A40 -> 0 | B49: =IFERROR(VLOOKUP(H49,[1]SEMIELABORADOS!$A$2:$M$6000,2,0),"") | C49: =+A49 -> 0 | D49: =IFERROR(VLOOKUP(H49,[1]SEMIELABORADOS!$A$2:$M$6000,6,0),"") | E49: =IFERROR(VLOOKUP(H49,[1]SEMIELABORADOS!$A$2:$M$65536,12,0),"") | F49: =IFERROR(E49*C49,"") | G49: =IFERROR(F49/$F$66,"")
A50: =+A41 -> 0 | B50: =IFERROR(VLOOKUP(H50,[1]SEMIELABORADOS!$A$2:$M$6000,2,0),"") | C50: =+A50 -> 0 | D50: =IFERROR(VLOOKUP(H50,[1]SEMIELABORADOS!$A$2:$M$6000,6,0),"") | E50: =IFERROR(VLOOKUP(H50,[1]SEMIELABORADOS!$A$2:$M$65536,12,0),"") | F50: =IFERROR(E50*C50,"") | G50: =IFERROR(F50/$F$66,"")
A51: 1 | B51: MODI PREPARACION | C51: =+A51 -> 1 | D51: N/A | E51: =+F65 -> 61 | F51: =IFERROR(C51*E51,"") -> 61 | G51: =IFERROR(F51/$F$66,"") -> 0.0017974101
B53: TOTAL MATERIA PRIMA | F53: =SUM(F8:F14,F17:F24) -> 33116.821 | G53: =+F53/$F$66 -> 0.9758116 | H53: =+F53/$D$60 -> 33116.821
B54: TOTAL EMPAQUE | F54: =SUM(F27:F32,F35:F41) -> 97.562822 | G54: =+F54/$F$66 -> 0.0028747607 | H54: =+F54/$D$60 -> 97.562822 | K54: TOTAL MATERIA PRIMA + EMPAQUE | O54: =+F55 -> 33214.384
B55: TOTAL MATERIAS P. + EMPAQUES | F55: =+F53+F54 -> 33214.384 | G55: =+F55/$F$66 -> 0.97868636 | H55: =+F55/$D$60 -> 33214.384 | M55: MODI PLANTA | O55: =+H56 -> 484.9134
C56: TOTAL MODI | F56: =SUM(F44:F51) -> 484.9134 | G56: =+F56/$F$66 -> 0.014288332 | H56: =+F56/$D$60 -> 484.9134 | M56: DESECHO | O56: =O54*N56 -> 0
M57: COSTO PLANTA | O57: =SUM(O54:O56) -> 33699.297
B58: GRAMOS | D58: 5000 | H58: =+H56/61 -> 7.9494 | M58: % GIF | O58: =+H59 -> 461.0652
B59: PESO POR UNIDAD | D59: 5000 | H59: =+H58*58 -> 461.0652 | M59: COSTO PLANTA | O59: =SUM(O57:O58) -> 34160.362
B60: UNIDADES TOTALES | D60: =+D58/D59 -> 1 | O60: =+O59*N60 -> 0
B61: UNIDAD MEDIDA | K61: PRECIO DE VENTA PLANTA A LOCAL | O61: =SUM(O59:O60) -> 34160.362 | P61: GR
E62: S/ COSTO | F62: TOTAL | L62: UNIDAD | O62: =+O61/D60 -> 34160.362 | P62: =+O62/D59 -> 6.8320724
B63: TOTAL MATERIAS P. + EMPAQUES | E63: =+F63/F63 -> 1 | F63: =SUM(F55) -> 33214.384 | G63: =+F63/$F$66 -> 0.97868636
B64: DESECHOS Y PERDIDAS | E64: 0.02 | F64: =+F53*E64 -> 662.33641 | G64: =+F64/$F$66 -> 0.019516232
B65: MANO OBRA DIRECTA | D65: 1 | E65: 61 | F65: =+E65*D65 -> 61 | G65: =+F65/$F$66 -> 0.0017974101
B66: TOTAL COSTO PLANTA | F66: =SUM(F63:F65) -> 33937.72 | G66: =+F66/$F$66 -> 1 | M66: MODI 61 COLONES X MIN
M67: Gf 58 colones min
B68: COSTO POR GRAMO | M68: ,
B69: TOTAL COSTO MATERIA PRIMA | C69: =+F53 -> 33116.821 | D69: =+D58 -> 5000 | E69: =+C69/D69 -> 6.6233641
B71: TOTAL COSTO UNIDAD MP+DESECHO+EMPAQUE | C71: =SUM(F63:F64) -> 33876.72 | D71: =+D58 -> 5000 | E71: =+C71/D71 -> 6.775344
B73: TOTAL MODI PREPARACION POR GRAMO | C73: =+F65 -> 61 | D73: =+D58 -> 5000 | E73: =+C73/D73 -> 0.0122
B74: TOTAL MODI POR GRAMO | C74: =+F56 -> 484.9134 | D74: =+D73 -> 5000 | E74: =+C74/D74 -> 0.09698268
B76: TOTAL EMPAQUE POR GRAMO | C76: =+F54 -> 97.562822 | D76: =+D74 -> 5000 | E76: =+C76/D76 -> 0.019512564
B78: TOTAL GRAMO MP+MODI | E78: =+E69+E74 -> 6.7203468
B80: COSTO POR UNIDAD
B81: TOTAL COSTO MATERIA PRIMA | C81: =+C69 -> 33116.821 | D81: =+D60 -> 1 | E81: =+C81/D81 -> 33116.821
B83: TOTAL COSTO UNIDAD MP+DESECHO+EMPAQUE | C83: =+C71 -> 33876.72 | D83: =+D60 -> 1 | E83: =+C83/D83 -> 33876.72
B85: TOTAL MODI POR GRAMO | C85: =+C73 -> 61 | D85: =+D60 -> 1 | E85: =+C85/D85 -> 61
B86: TOTAL MODI POR GRAMO | C86: =+C74 -> 484.9134 | D86: =+D85 -> 1 | E86: =+C86/D86 -> 484.9134

Sheet Mousse Chocolate Interno
C1: SERVICIOS DE PASTELERIA S.A. | H1: CÓDIGO:
C2: ESPECIFICACION DE RECETA | H2: REVISIÓN:
C3: Mousse Chocolate Interno | H3: FECHA DE APROBACIÓN:
C4: Elaborado | D4: Jose Brizuela Lopez , chef
C5: Aprobado | D5: Esteban Cartin, Gte Manufactura
A7: AREA QUE PRODUCE: | D7: Postres | G7: AREA QUE EMPACA: | I7: Postres
A8: # Código | B8: # Codigo Netsuite | C8: Descripción del ingrediente | D8: Marca | G8: Medida alternativa | I8: Costo - Referencia
E9: Cantidad | F9: Unidad medida | G9: Cantidad | H9: Unidad medida | I9: Colones
A10: 1210386 | B10: MP10001 | C10: Cobertura Chocolate Leche | D10: FAS | E10: 1600 | F10: g | G10: Para Ganache
A11: 10100331 | B11: MP10492 | C11: Chocolate Semi Amargo 54% | D11: FAS | E11: 3300 | F11: g
A12: 11400031 | B12: MP10048 | C12: Crema Prestige Grand | D12: FAS | E12: 2500 | F12: g
A13: 11400031 | B13: MP10048 | C13: Crema Prestige Grand | D13: FAS | E13: 3300 | F13: g | G13: Para batir
D20: Cantidad | E20: Unidad
A21: PESO TOTAL OBTENIDO | D21: 10000 | E21: g | F21: Tiempo de Horneo:
A22: TIEMPO TOTAL DE PREPARACION | D22: 20 | E22: min | F22: Horno:
A23: CANTIDAD DE PORCIONES OBTENIDAS | D23: 1 | E23: ud | F23: Temperatura de Horneo:
A24: PESO DE CADA PORCIÓN | D24: =D21 -> 10000 | E24: g | F24: Otros
A25: MERMA | D25: =SUM(E10:E13)-D21 -> 700 | E25: g | F25: Rendimiento :
A26: PROCEDIMIENTO DE PREPARACION DE LA RECETA
A27: # 1 Derretir chocolate leche y chocolate amargo, junto al prestige en microndas o a baños maria.
A28: # 2 Montar la crema hasta punto Chantilly en la batidroa con ayuda del globo | J28: ¿¿
A29: # 3 Agregar la mezcla de chocolate y emzclar en veolicadd media por 3 min aprox, hasta homogeneo.
A30: # 4 Utilizar de inmeadito
A34: CONTROL DE CAMBIOS

Sheet Costo Mousse choco
E1: Precio Local | F1: Costo MP | G1: Costo EM | H1: Costo MO
E2: =IFERROR(O62,"") -> 46739.75 | F2: =IFERROR(H53,"") -> 44359.75 | G2: =IFERROR(H54,"") -> 0 | H2: =IFERROR(H56,"") -> 1220
A5: ESTRUCTURA DE COSTOS
F6: Fecha: | H6: =TODAY() -> 45776
A7: UNIDADES | B7: DESCRIPCION MAT.PRIMA | C7: UNIDADES | D7: UND MEDIDA | E7: COSTO UNITARIO | F7: TOTAL COSTO | G7: % PREC. DEFINIDO | H7: CODIGOS
A8: 0 | B8: =IFERROR(VLOOKUP(H8,'[1]Consolidado MP Planta'!$A$2:$M$823,3,0),"") -> COBERTURA CHOCOLATE LECHE (PAQ:5 K) | C8: =+A8 -> 0 | D8: =IFERROR(VLOOKUP(H8,'[1]Consolidado MP Planta'!$A$2:$M$823,13,0),"") -> Gramos | E8: =IFERROR(VLOOKUP(H8,'[1]Consolidado MP Planta'!$A$2:$M$823,12,0),"") -> 4.49 | F8: =IFERROR(C8*E8,"") -> 0 | G8: =IFERROR(F8/$F$66,"") -> 0 | H8: 1210386
A9: 3300 | B9: Chocolate Semi Amargo 54% | C9: =+A9 -> 3300 | D9: Gramos | E9: 4.4 | F9: =IFERROR(C9*E9,"") -> 14520 | G9: =IFERROR(F9/$F$66,"") -> 0.31248019 | H9: 10100331
A10: 2500 | B10: =IFERROR(VLOOKUP(H10,'[1]Consolidado MP Planta'!$A$2:$M$823,3,0),"") -> CREMA PRESTIGE GRAND (UND:4 K) * | C10: =+A10 -> 2500 | D10: =IFERROR(VLOOKUP(H10,'[1]Consolidado MP Planta'!$A$2:$M$823,13,0),"") -> Gramos | E10: =IFERROR(VLOOKUP(H10,'[1]Consolidado MP Planta'!$A$2:$M$823,12,0),"") -> 2.25375 | F10: =IFERROR(C10*E10,"") -> 5634.375 | G10: =IFERROR(F10/$F$66,"") -> 0.12125555 | H10: 11400031
A11: 3300 | B11: =IFERROR(VLOOKUP(H11,'[1]Consolidado MP Planta'!$A$2:$M$823,3,0),"") -> CREMA PRESTIGE GRAND (UND:4 K) * | C11: =+A11 -> 3300 | D11: =IFERROR(VLOOKUP(H11,'[1]Consolidado MP Planta'!$A$2:$M$823,13,0),"") -> Gramos | E11: =IFERROR(VLOOKUP(H11,'[1]Consolidado MP Planta'!$A$2:$M$823,12,0),"") -> 2.25375 | F11: =IFERROR(C11*E11,"") -> 7437.375 | G11: =IFERROR(F11/$F$66,"") -> 0.16005733 | H11: 11400031
A12: 1600 | B12: cadbury | C12: 1600 | E12: 10.48 | F12: 16768 | G12: 0.37171999
B13: =IFERROR(VLOOKUP(H13,'[1]Consolidado MP Planta'!$A$2:$M$823,3,0),"") | C13: =+A13 -> 0 | D13: =IFERROR(VLOOKUP(H13,'[1]Consolidado MP Planta'!$A$2:$M$823,13,0),"") | E13: =IFERROR(VLOOKUP(H13,'[1]Consolidado MP Planta'!$A$2:$M$823,12,0),"") | F13: =IFERROR(C13*E13,"") | G13: =IFERROR(F13/$F$66,"")
B14: =IFERROR(VLOOKUP(H14,'[1]Consolidado MP Planta'!$A$2:$M$823,3,0),"") | C14: =+A14 -> 0 | D14: =IFERROR(VLOOKUP(H14,'[1]Consolidado MP Planta'!$A$2:$M$823,13,0),"") | E14: =IFERROR(VLOOKUP(H14,'[1]Consolidado MP Planta'!$A$2:$M$823,12,0),"") | F14: =IFERROR(C14*E14,"") | G14: =IFERROR(F14/$F$66,"")
B15: =IFERROR(VLOOKUP(H15,'[2]ARTICULOS MP PLANTA'!$A$2:$G$589,2,0),"")
A16: UNIDADES | B16: MATERIA PRIMA SEMIELABORADOS | C16: UNIDADES | D16: UND MEDIDA | E16: COSTO UNITARIO | F16: TOTAL COSTO | G16: % PREC. DEFINIDO | H16: CODIGOS
B17: =IFERROR(VLOOKUP(H17,[1]SEMIELABORADOS!$A$2:$M$6000,2,0),"") | C17: =+A17 -> 0 | D17: =IFERROR(VLOOKUP(H17,[1]SEMIELABORADOS!$A$2:$M$6000,6,0),"") | E17: =IFERROR(VLOOKUP(H17,[1]SEMIELABORADOS!$A$2:$H$65536,8,0),"") | F17: =IFERROR(E17*C17,"") | G17: =IFERROR(F17/$F$66,"")
B18: =IFERROR(VLOOKUP(H18,[1]SEMIELABORADOS!$A$2:$M$6000,2,0),"") | C18: =+A18 -> 0 | D18: =IFERROR(VLOOKUP(H18,[1]SEMIELABORADOS!$A$2:$M$6000,6,0),"") | E18: =IFERROR(VLOOKUP(H18,[1]SEMIELABORADOS!$A$2:$H$65536,8,0),"") | F18: =IFERROR(E18*C18,"") | G18: =IFERROR(F18/$F$66,"")
B19: =IFERROR(VLOOKUP(H19,[1]SEMIELABORADOS!$A$2:$M$6000,2,0),"") | C19: =+A19 -> 0 | D19: =IFERROR(VLOOKUP(H19,[1]SEMIELABORADOS!$A$2:$M$6000,6,0),"") | E19: =IFERROR(VLOOKUP(H19,[1]SEMIELABORADOS!$A$2:$H$65536,8,0),"") | F19: =IFERROR(E19*C19,"") | G19: =IFERROR(F19/$F$66,"")
B20: =IFERROR(VLOOKUP(H20,[1]SEMIELABORADOS!$A$2:$M$6000,2,0),"") | C20: =+A20 -> 0 | D20: =IFERROR(VLOOKUP(H20,[1]SEMIELABORADOS!$A$2:$M$6000,6,0),"") | E20: =IFERROR(VLOOKUP(H20,[1]SEMIELABORADOS!$A$2:$H$65536,8,0),"") | F20: =IFERROR(E20*C20,"") | G20: =IFERROR(F20/$F$66,"")
B21: =IFERROR(VLOOKUP(H21,[1]SEMIELABORADOS!$A$2:$M$6000,2,0),"") | C21: =+A21 -> 0 | D21: =IFERROR(VLOOKUP(H21,[1]SEMIELABORADOS!$A$2:$M$6000,6,0),"") | E21: =IFERROR(VLOOKUP(H21,[1]SEMIELABORADOS!$A$2:$H$65536,8,0),"") | F21: =IFERROR(E21*C21,"") | G21: =IFERROR(F21/$F$66,"")
B22: =IFERROR(VLOOKUP(H22,[1]SEMIELABORADOS!$A$2:$M$6000,2,0),"") | C22: =+A22 -> 0 | D22: =IFERROR(VLOOKUP(H22,[1]SEMIELABORADOS!$A$2:$M$6000,6,0),"") | E22: =IFERROR(VLOOKUP(H22,[1]SEMIELABORADOS!$A$2:$H$65536,8,0),"") | F22: =IFERROR(E22*C22,"") | G22: =IFERROR(F22/$F$66,"")
B23: =IFERROR(VLOOKUP(H23,[1]SEMIELABORADOS!$A$2:$M$6000,2,0),"") | C23: =+A23 -> 0 | D23: =IFERROR(VLOOKUP(H23,[1]SEMIELABORADOS!$A$2:$M$6000,6,0),"") | E23: =IFERROR(VLOOKUP(H23,[1]SEMIELABORADOS!$A$2:$H$65536,8,0),"") | F23: =IFERROR(E23*C23,"") | G23: =IFERROR(F23/$F$66,"")
B24: =IFERROR(VLOOKUP(H24,[1]SEMIELABORADOS!$A$2:$M$6000,2,0),"") | C24: =+A24 -> 0 | D24: =IFERROR(VLOOKUP(H24,[1]SEMIELABORADOS!$A$2:$M$6000,6,0),"") | E24: =IFERROR(VLOOKUP(H24,[1]SEMIELABORADOS!$A$2:$H$65536,8,0),"") | F24: =IFERROR(E24*C24,"") | G24: =IFERROR(F24/$F$66,"")
A26: UNIDADES | B26: EMPAQUE | C26: UNIDADES | D26: UND MEDIDA | E26: COSTO UNITARIO | F26: TOTAL COSTO | G26: % PREC. DEFINIDO | H26: CODIGOS
A27: 0 | B27: =IFERROR(VLOOKUP(H27,'[1]Consolidado MP Planta'!$A$2:$M$823,3,0),"") | C27: =+A27 -> 0 | D27: =IFERROR(VLOOKUP(H27,'[1]Consolidado MP Planta'!$A$2:$M$823,13,0),"") | E27: =IFERROR(VLOOKUP(H27,'[1]Consolidado MP Planta'!$A$2:$M$823,12,0),"") | F27: =IFERROR(C27*E27,"") | G27: =IFERROR(F27/$F$66,"")
B28: =IFERROR(VLOOKUP(H28,'[1]Consolidado MP Planta'!$A$2:$M$823,3,0),"") | C28: =+A28 -> 0 | D28: =IFERROR(VLOOKUP(H28,'[1]Consolidado MP Planta'!$A$2:$M$823,13,0),"") | E28: =IFERROR(VLOOKUP(H28,'[1]Consolidado MP Planta'!$A$2:$M$823,12,0),"") | F28: =IFERROR(C28*E28,"") | G28: =IFERROR(F28/$F$66,"")
B29: =IFERROR(VLOOKUP(H29,'[1]Consolidado MP Planta'!$A$2:$M$823,3,0),"") | C29: =+A29 -> 0 | D29: =IFERROR(VLOOKUP(H29,'[1]Consolidado MP Planta'!$A$2:$M$823,13,0),"") | E29: =IFERROR(VLOOKUP(H29,'[1]Consolidado MP Planta'!$A$2:$M$823,12,0),"") | F29: =IFERROR(C29*E29,"") | G29: =IFERROR(F29/$F$66,"")
B30: =IFERROR(VLOOKUP(H30,'[1]Consolidado MP Planta'!$A$2:$M$823,3,0),"") | C30: =+A30 -> 0 | D30: =IFERROR(VLOOKUP(H30,'[1]Consolidado MP Planta'!$A$2:$M$823,13,0),"") | E30: =IFERROR(VLOOKUP(H30,'[1]Consolidado MP Planta'!$A$2:$M$823,12,0),"") | F30: =IFERROR(C30*E30,"") | G30: =IFERROR(F30/$F$66,"")
B31: =IFERROR(VLOOKUP(H31,'[1]Consolidado MP Planta'!$A$2:$M$823,3,0),"") | C31: =+A31 -> 0 | D31: =IFERROR(VLOOKUP(H31,'[1]Consolidado MP Planta'!$A$2:$M$823,13,0),"") | E31: =IFERROR(VLOOKUP(H31,'[1]Consolidado MP Planta'!$A$2:$M$823,12,0),"") | F31: =IFERROR(C31*E31,"") | G31: =IFERROR(F31/$F$66,"")
B32: =IFERROR(VLOOKUP(H32,'[1]Consolidado MP Planta'!$A$2:$M$823,3,0),"") | C32: =+A32 -> 0 | D32: =IFERROR(VLOOKUP(H32,'[1]Consolidado MP Planta'!$A$2:$M$823,13,0),"") | E32: =IFERROR(VLOOKUP(H32,'[1]Consolidado MP Planta'!$A$2:$M$823,12,0),"") | F32: =IFERROR(C32*E32,"") | G32: =IFERROR(F32/$F$66,"")
A34: UNIDADES | B34: EMPAQUE SEMIELABORADOS | C34: UNIDADES | D34: UND MEDIDA | E34: COSTO UNITARIO | F34: TOTAL COSTO | G34: % PREC. DEFINIDO | H34: CODIGOS
A35: =+A17 -> 0 | B35: =IFERROR(VLOOKUP(H35,[1]SEMIELABORADOS!$A$2:$M$6000,2,0),"") | C35: =+A35 -> 0 | D35: =IFERROR(VLOOKUP(H35,[1]SEMIELABORADOS!$A$2:$M$6000,6,0),"") | E35: =IFERROR(VLOOKUP(H35,[1]SEMIELABORADOS!$A$2:$M$65536,10,0),"") | F35: =IFERROR(E35*C35,"") | G35: =IFERROR(F35/$F$66,"")
A36: =+A18 -> 0 | B36: =IFERROR(VLOOKUP(H36,[1]SEMIELABORADOS!$A$2:$M$6000,2,0),"") | C36: =+A36 -> 0 | D36: =IFERROR(VLOOKUP(H36,[1]SEMIELABORADOS!$A$2:$M$6000,6,0),"") | E36: =IFERROR(VLOOKUP(H36,[1]SEMIELABORADOS!$A$2:$M$65536,10,0),"") | F36: =IFERROR(E36*C36,"") | G36: =IFERROR(F36/$F$66,"")
A37: =+A19 -> 0 | B37: =IFERROR(VLOOKUP(H37,[1]SEMIELABORADOS!$A$2:$M$6000,2,0),"") | C37: =+A37 -> 0 | D37: =IFERROR(VLOOKUP(H37,[1]SEMIELABORADOS!$A$2:$M$6000,6,0),"") | E37: =IFERROR(VLOOKUP(H37,[1]SEMIELABORADOS!$A$2:$M$65536,10,0),"") | F37: =IFERROR(E37*C37,"") | G37: =IFERROR(F37/$F$66,"")
A38: =+A20 -> 0 | B38: =IFERROR(VLOOKUP(H38,[1]SEMIELABORADOS!$A$2:$M$6000,2,0),"") | C38: =+A38 -> 0 | D38: =IFERROR(VLOOKUP(H38,[1]SEMIELABORADOS!$A$2:$M$6000,6,0),"") | E38: =IFERROR(VLOOKUP(H38,[1]SEMIELABORADOS!$A$2:$M$65536,10,0),"") | F38: =IFERROR(E38*C38,"") | G38: =IFERROR(F38/$F$66,"")
A39: =+A21 -> 0 | B39: =IFERROR(VLOOKUP(H39,[1]SEMIELABORADOS!$A$2:$M$6000,2,0),"") | C39: =+A39 -> 0 | D39: =IFERROR(VLOOKUP(H39,[1]SEMIELABORADOS!$A$2:$M$6000,6,0),"") | E39: =IFERROR(VLOOKUP(H39,[1]SEMIELABORADOS!$A$2:$M$65536,10,0),"") | F39: =IFERROR(E39*C39,"") | G39: =IFERROR(F39/$F$66,"")
A40: =+A22 -> 0 | B40: =IFERROR(VLOOKUP(H40,[1]SEMIELABORADOS!$A$2:$M$6000,2,0),"") | C40: =+A40 -> 0 | D40: =IFERROR(VLOOKUP(H40,[1]SEMIELABORADOS!$A$2:$M$6000,6,0),"") | E40: =IFERROR(VLOOKUP(H40,[1]SEMIELABORADOS!$A$2:$M$65536,10,0),"") | F40: =IFERROR(E40*C40,"") | G40: =IFERROR(F40/$F$66,"")
A41: =+A23 -> 0 | B41: =IFERROR(VLOOKUP(H41,[1]SEMIELABORADOS!$A$2:$M$6000,2,0),"") | C41: =+A41 -> 0 | D41: =IFERROR(VLOOKUP(H41,[1]SEMIELABORADOS!$A$2:$M$6000,6,0),"") | E41: =IFERROR(VLOOKUP(H41,[1]SEMIELABORADOS!$A$2:$M$65536,10,0),"") | F41: =IFERROR(E41*C41,"") | G41: =IFERROR(F41/$F$66,"")
A43: UNIDADES | B43: MODI | C43: UNIDADES | D43: UND MEDIDA | E43: COSTO UNITARIO | F43: TOTAL COSTO | G43: % PREC. DEFINIDO | H43: CODIGOS
A44: =+A35 -> 0 | B44: =IFERROR(VLOOKUP(H44,[1]SEMIELABORADOS!$A$2:$M$6000,2,0),"") | C44: =+A44 -> 0 | D44: =IFERROR(VLOOKUP(H44,[1]SEMIELABORADOS!$A$2:$M$6000,6,0),"") | E44: =IFERROR(VLOOKUP(H44,[1]SEMIELABORADOS!$A$2:$M$65536,12,0),"") | F44: =IFERROR(E44*C44,"") | G44: =IFERROR(F44/$F$66,"")
A45: =+A36 -> 0 | B45: =IFERROR(VLOOKUP(H45,[1]SEMIELABORADOS!$A$2:$M$6000,2,0),"") | C45: =+A45 -> 0 | D45: =IFERROR(VLOOKUP(H45,[1]SEMIELABORADOS!$A$2:$M$6000,6,0),"") | E45: =IFERROR(VLOOKUP(H45,[1]SEMIELABORADOS!$A$2:$M$65536,12,0),"") | F45: =IFERROR(E45*C45,"") | G45: =IFERROR(F45/$F$66,"")
A46: =+A37 -> 0 | B46: =IFERROR(VLOOKUP(H46,[1]SEMIELABORADOS!$A$2:$M$6000,2,0),"") | C46: =+A46 -> 0 | D46: =IFERROR(VLOOKUP(H46,[1]SEMIELABORADOS!$A$2:$M$6000,6,0),"") | E46: =IFERROR(VLOOKUP(H46,[1]SEMIELABORADOS!$A$2:$M$65536,12,0),"") | F46: =IFERROR(E46*C46,"") | G46: =IFERROR(F46/$F$66,"")
A47: =+A38 -> 0 | B47: =IFERROR(VLOOKUP(H47,[1]SEMIELABORADOS!$A$2:$M$6000,2,0),"") | C47: =+A47 -> 0 | D47: =IFERROR(VLOOKUP(H47,[1]SEMIELABORADOS!$A$2:$M$6000,6,0),"") | E47: =IFERROR(VLOOKUP(H47,[1]SEMIELABORADOS!$A$2:$M$65536,12,0),"") | F47: =IFERROR(E47*C47,"") | G47: =IFERROR(F47/$F$66,"")
A48: =+A39 -> 0 | B48: =IFERROR(VLOOKUP(H48,[1]SEMIELABORADOS!$A$2:$M$6000,2,0),"") | C48: =+A48 -> 0 | D48: =IFERROR(VLOOKUP(H48,[1]SEMIELABORADOS!$A$2:$M$6000,6,0),"") | E48: =IFERROR(VLOOKUP(H48,[1]SEMIELABORADOS!$A$2:$M$65536,12,0),"") | F48: =IFERROR(E48*C48,"") | G48: =IFERROR(F48/$F$66,"")
A49: =+A40 -> 0 | B49: =IFERROR(VLOOKUP(H49,[1]SEMIELABORADOS!$A$2:$M$6000,2,0),"") | C49: =+A49 -> 0 | D49: =IFERROR(VLOOKUP(H49,[1]SEMIELABORADOS!$A$2:$M$6000,6,0),"") | E49: =IFERROR(VLOOKUP(H49,[1]SEMIELABORADOS!$A$2:$M$65536,12,0),"") | F49: =IFERROR(E49*C49,"") | G49: =IFERROR(F49/$F$66,"")
A50: =+A41 -> 0 | B50: =IFERROR(VLOOKUP(H50,[1]SEMIELABORADOS!$A$2:$M$6000,2,0),"") | C50: =+A50 -> 0 | D50: =IFERROR(VLOOKUP(H50,[1]SEMIELABORADOS!$A$2:$M$6000,6,0),"") | E50: =IFERROR(VLOOKUP(H50,[1]SEMIELABORADOS!$A$2:$M$65536,12,0),"") | F50: =IFERROR(E50*C50,"") | G50: =IFERROR(F50/$F$66,"")
A51: 1 | B51: MODI PREPARACION | C51: =+A51 -> 1 | D51: N/A | E51: =+F65 -> 1220 | F51: =IFERROR(C51*E51,"") -> 1220 | G51: =IFERROR(F51/$F$66,"") -> 0.026255223
B53: TOTAL MATERIA PRIMA | F53: =SUM(F8:F14,F17:F24) -> 44359.75 | G53: =+F53/$F$66 -> 0.95465174 | H53: =+F53/$D$60 -> 44359.75
B54: TOTAL EMPAQUE | F54: =SUM(F27:F32,F35:F41) -> 0 | G54: =+F54/$F$66 -> 0 | H54: =+F54/$D$60 -> 0 | K54: TOTAL MATERIA PRIMA + EMPAQUE | O54: =+F55 -> 44359.75
B55: TOTAL MATERIAS P. + EMPAQUES | F55: =+F53+F54 -> 44359.75 | G55: =+F55/$F$66 -> 0.95465174 | H55: =+F55/$D$60 -> 44359.75 | M55: MODI PLANTA | O55: =+H56 -> 1220
C56: TOTAL MODI | F56: =SUM(F44:F51) -> 1220 | G56: =+F56/$F$66 -> 0.026255223 | H56: =+F56/$D$60 -> 1220 | M56: DESECHO | O56: =O54*N56 -> 0
M57: COSTO PLANTA | O57: =SUM(O54:O56) -> 45579.75
B58: GRAMOS | D58: 10000 | H58: =+H56/61 -> 20 | M58: % GIF | O58: =+H59 -> 1160
B59: PESO POR UNIDAD | D59: 10000 | H59: =+H58*58 -> 1160 | M59: COSTO PLANTA | O59: =SUM(O57:O58) -> 46739.75
B60: UNIDADES TOTALES | D60: =+D58/D59 -> 1 | O60: =+O59*N60 -> 0
B61: UNIDAD MEDIDA | K61: PRECIO DE VENTA PLANTA A LOCAL | O61: =SUM(O59:O60) -> 46739.75 | P61: GR
E62: S/ COSTO | F62: TOTAL | L62: UNIDAD | O62: =+O61/D60 -> 46739.75 | P62: =+O62/D59 -> 4.673975
B63: TOTAL MATERIAS P. + EMPAQUES | E63: =+F63/F63 -> 1 | F63: =SUM(F55) -> 44359.75 | G63: =+F63/$F$66 -> 0.95465174
B64: DESECHOS Y PERDIDAS | E64: 0.02 | F64: =+F53*E64 -> 887.195 | G64: =+F64/$F$66 -> 0.019093035
B65: MANO OBRA DIRECTA | D65: 20 | E65: 61 | F65: =+E65*D65 -> 1220 | G65: =+F65/$F$66 -> 0.026255223
B66: TOTAL COSTO PLANTA | F66: =SUM(F63:F65) -> 46466.945 | G66: =+F66/$F$66 -> 1 | M66: MODI 61 COLONES X MIN
M67: Gf 58 colones min
B68: COSTO POR GRAMO | M68: ,
B69: TOTAL COSTO MATERIA PRIMA | C69: =+F53 -> 44359.75 | D69: =+D58 -> 10000 | E69: =+C69/D69 -> 4.435975
B71: TOTAL COSTO UNIDAD MP+DESECHO+EMPAQUE | C71: =SUM(F63:F64) -> 45246.945 | D71: =+D58 -> 10000 | E71: =+C71/D71 -> 4.5246945
B73: TOTAL MODI PREPARACION POR GRAMO | C73: =+F65 -> 1220 | D73: =+D58 -> 10000 | E73: =+C73/D73 -> 0.122
B74: TOTAL MODI POR GRAMO | C74: =+F56 -> 1220 | D74: =+D73 -> 10000 | E74: =+C74/D74 -> 0.122
B76: TOTAL EMPAQUE POR GRAMO | C76: =+F54 -> 0 | D76: =+D74 -> 10000 | E76: =+C76/D76 -> 0
B78: TOTAL GRAMO MP+MODI | E78: =+E69+E74 -> 4.557975
B80: COSTO POR UNIDAD
B81: TOTAL COSTO MATERIA PRIMA | C81: =+C69 -> 44359.75 | D81: =+D60 -> 1 | E81: =+C81/D81 -> 44359.75
B83: TOTAL COSTO UNIDAD MP+DESECHO+EMPAQUE | C83: =+C71 -> 45246.945 | D83: =+D60 -> 1 | E83: =+C83/D83 -> 45246.945
B85: TOTAL MODI POR GRAMO | C85: =+C73 -> 1220 | D85: =+D60 -> 1 | E85: =+C85/D85 -> 1220
B86: TOTAL MODI POR GRAMO | C86: =+C74 -> 1220 | D86: =+D85 -> 1 | E86: =+C86/D86 -> 1220

Sheet Disco
C1: SERVICIOS DE PASTELERIA S.A. | H1: CÓDIGO:
C2: ESPECIFICACION DE RECETA | H2: REVISIÓN:
C3: Disco Mousse Chocolate | H3: m
C4: Elaborado | D4: Jose Brizuela Lopez , chef
C5: Aprobado | D5: Esteban Cartin, Gte Manufactura
A7: AREA QUE PRODUCE: | D7: Postres | G7: AREA QUE EMPACA: | I7: Postres
A8: # Código | B8: # Codigo Netsuite | C8: Descripción del ingrediente | D8: Marca | G8: Medida alternativa | I8: Costo - Referencia
E9: Cantidad | F9: Unidad medida | G9: Cantidad | H9: Unidad medida | I9: Colones
C10: Emsamble
A12: 907000317 | B12: SE00463 | C12: ROSQUETE CHOCOLATE DAWN 220g | D12: FAS | E12: 95 | F12: g | G12: 0,5 unidad
C13: Mousse Chocolate Interno | D13: FAS | E13: 200 | F13: g
C14: Empaque Relleno Arandanos Rojos | D14: FAS | E14: 150 | F14: g
D16: Cantidad | E16: Unidad
A17: PESO TOTAL OBTENIDO | D17: 440 | E17: g | F17: Tiempo de Horneo:
A18: TIEMPO TOTAL DE PREPARACION | D18: 3 | E18: min | F18: Horno:
A19: CANTIDAD DE PORCIONES OBTENIDAS | D19: 1 | E19: ud | F19: Temperatura de Horneo:
A20: PESO DE CADA PORCIÓN | D20: =D17 -> 440 | E20: g | F20: Otros
A21: MERMA | D21: =SUM(E12:E14)-D17 -> 5 | E21: g
A22: PROCEDIMIENTO DE PREPARACION DE LA RECETA
A23: # 1 Agregar el Rosquete pequeño en un molde desarmable pequeño de 15 cm por 9 altura.
A24: # 2 Agregar el Mousse Chocolate Interno , emparejar o alisar y agregar el relleno de arandanos rojos
A25: # 3 Dejar que Corte y Desmolde para usar
A29: CONTROL DE CAMBIOS

Sheet Costo disco
E1: Precio Local | F1: Costo MP | G1: Costo EM | H1: Costo MO
E2: =IFERROR(O62,"") -> 1953.0306 | F2: =IFERROR(H53,"") -> 1467.2327 | G2: =IFERROR(H54,"") -> 2.4662564 | H2: =IFERROR(H56,"") -> 247.75827
A5: ESTRUCTURA DE COSTOS
F6: Fecha: | H6: =TODAY() -> 45776
A7: UNIDADES | B7: DESCRIPCION MAT.PRIMA | C7: UNIDADES | D7: UND MEDIDA | E7: COSTO UNITARIO | F7: TOTAL COSTO | G7: % PREC. DEFINIDO | H7: CODIGOS
B8: =IFERROR(VLOOKUP(H8,'[1]Consolidado MP Planta'!$A$2:$M$823,3,0),"") | C8: =+A8 -> 0 | D8: =IFERROR(VLOOKUP(H8,'[1]Consolidado MP Planta'!$A$2:$M$823,13,0),"") | E8: =IFERROR(VLOOKUP(H8,'[1]Consolidado MP Planta'!$A$2:$M$823,12,0),"") | F8: =IFERROR(C8*E8,"") | G8: =IFERROR(F8/$F$66,"")
B9: =IFERROR(VLOOKUP(H9,'[1]Consolidado MP Planta'!$A$2:$M$823,3,0),"") | C9: =+A9 -> 0 | D9: =IFERROR(VLOOKUP(H9,'[1]Consolidado MP Planta'!$A$2:$M$823,13,0),"") | E9: =IFERROR(VLOOKUP(H9,'[1]Consolidado MP Planta'!$A$2:$M$823,12,0),"") | F9: =IFERROR(C9*E9,"") | G9: =IFERROR(F9/$F$66,"")
B10: =IFERROR(VLOOKUP(H10,'[1]Consolidado MP Planta'!$A$2:$M$823,3,0),"") | C10: =+A10 -> 0 | D10: =IFERROR(VLOOKUP(H10,'[1]Consolidado MP Planta'!$A$2:$M$823,13,0),"") | E10: =IFERROR(VLOOKUP(H10,'[1]Consolidado MP Planta'!$A$2:$M$823,12,0),"") | F10: =IFERROR(C10*E10,"") | G10: =IFERROR(F10/$F$66,"")
B11: =IFERROR(VLOOKUP(H11,'[1]Consolidado MP Planta'!$A$2:$M$823,3,0),"") | C11: =+A11 -> 0 | D11: =IFERROR(VLOOKUP(H11,'[1]Consolidado MP Planta'!$A$2:$M$823,13,0),"") | E11: =IFERROR(VLOOKUP(H11,'[1]Consolidado MP Planta'!$A$2:$M$823,12,0),"") | F11: =IFERROR(C11*E11,"") | G11: =IFERROR(F11/$F$66,"")
B12: =IFERROR(VLOOKUP(H12,'[1]Consolidado MP Planta'!$A$2:$M$823,3,0),"") | C12: =+A12 -> 0 | D12: =IFERROR(VLOOKUP(H12,'[1]Consolidado MP Planta'!$A$2:$M$823,13,0),"") | E12: =IFERROR(VLOOKUP(H12,'[1]Consolidado MP Planta'!$A$2:$M$823,12,0),"") | F12: =IFERROR(C12*E12,"") | G12: =IFERROR(F12/$F$66,"")
B13: =IFERROR(VLOOKUP(H13,'[1]Consolidado MP Planta'!$A$2:$M$823,3,0),"") | C13: =+A13 -> 0 | D13: =IFERROR(VLOOKUP(H13,'[1]Consolidado MP Planta'!$A$2:$M$823,13,0),"") | E13: =IFERROR(VLOOKUP(H13,'[1]Consolidado MP Planta'!$A$2:$M$823,12,0),"") | F13: =IFERROR(C13*E13,"") | G13: =IFERROR(F13/$F$66,"")
B14: =IFERROR(VLOOKUP(H14,'[1]Consolidado MP Planta'!$A$2:$M$823,3,0),"") | C14: =+A14 -> 0 | D14: =IFERROR(VLOOKUP(H14,'[1]Consolidado MP Planta'!$A$2:$M$823,13,0),"") | E14: =IFERROR(VLOOKUP(H14,'[1]Consolidado MP Planta'!$A$2:$M$823,12,0),"") | F14: =IFERROR(C14*E14,"") | G14: =IFERROR(F14/$F$66,"")
B15: =IFERROR(VLOOKUP(H15,'[2]ARTICULOS MP PLANTA'!$A$2:$G$589,2,0),"")
A16: UNIDADES | B16: MATERIA PRIMA SEMIELABORADOS | C16: UNIDADES | D16: UND MEDIDA | E16: COSTO UNITARIO | F16: TOTAL COSTO | G16: % PREC. DEFINIDO | H16: CODIGOS
A17: 0.5 | B17: ROSQUETE CHOCOLATE DAWN 220g | C17: =+A17 -> 0.5 | D17: UND | E17: 279 | F17: =IFERROR(E17*C17,"") -> 139.5 | G17: =IFERROR(F17/$F$66,"") -> 0.082934831 | H17: 907000317
A18: 150 | B18: Mousse Chocolate Interno | C18: =+A18 -> 150 | D18: Gramos | E18: =+'Costo Mousse choco'!E69 -> 4.435975 | F18: =IFERROR(E18*C18,"") -> 665.39625 | G18: =IFERROR(F18/$F$66,"") -> 0.395588
A19: 100 | B19: Empaque Relleno Arandanos Rojos | C19: =+A19 -> 100 | D19: Gramos | E19: =+'Costo Empaque Relleno Arand'!E69 -> 6.6233641 | F19: =IFERROR(E19*C19,"") -> 662.33641 | G19: =IFERROR(F19/$F$66,"") -> 0.39376888
B20: =IFERROR(VLOOKUP(H20,[1]SEMIELABORADOS!$A$2:$M$6000,2,0),"") | C20: =+A20 -> 0 | D20: =IFERROR(VLOOKUP(H20,[1]SEMIELABORADOS!$A$2:$M$6000,6,0),"") | E20: =IFERROR(VLOOKUP(H20,[1]SEMIELABORADOS!$A$2:$H$65536,8,0),"") | F20: =IFERROR(E20*C20,"") | G20: =IFERROR(F20/$F$66,"")
B21: =IFERROR(VLOOKUP(H21,[1]SEMIELABORADOS!$A$2:$M$6000,2,0),"") | C21: =+A21 -> 0 | D21: =IFERROR(VLOOKUP(H21,[1]SEMIELABORADOS!$A$2:$M$6000,6,0),"") | E21: =IFERROR(VLOOKUP(H21,[1]SEMIELABORADOS!$A$2:$H$65536,8,0),"") | F21: =IFERROR(E21*C21,"") | G21: =IFERROR(F21/$F$66,"")
B22: =IFERROR(VLOOKUP(H22,[1]SEMIELABORADOS!$A$2:$M$6000,2,0),"") | C22: =+A22 -> 0 | D22: =IFERROR(VLOOKUP(H22,[1]SEMIELABORADOS!$A$2:$M$6000,6,0),"") | E22: =IFERROR(VLOOKUP(H22,[1]SEMIELABORADOS!$A$2:$H$65536,8,0),"") | F22: =IFERROR(E22*C22,"") | G22: =IFERROR(F22/$F$66,"")
B23: =IFERROR(VLOOKUP(H23,[1]SEMIELABORADOS!$A$2:$M$6000,2,0),"") | C23: =+A23 -> 0 | D23: =IFERROR(VLOOKUP(H23,[1]SEMIELABORADOS!$A$2:$M$6000,6,0),"") | E23: =IFERROR(VLOOKUP(H23,[1]SEMIELABORADOS!$A$2:$H$65536,8,0),"") | F23: =IFERROR(E23*C23,"") | G23: =IFERROR(F23/$F$66,"")
B24: =IFERROR(VLOOKUP(H24,[1]SEMIELABORADOS!$A$2:$M$6000,2,0),"") | C24: =+A24 -> 0 | D24: =IFERROR(VLOOKUP(H24,[1]SEMIELABORADOS!$A$2:$M$6000,6,0),"") | E24: =IFERROR(VLOOKUP(H24,[1]SEMIELABORADOS!$A$2:$H$65536,8,0),"") | F24: =IFERROR(E24*C24,"") | G24: =IFERROR(F24/$F$66,"")
A26: UNIDADES | B26: EMPAQUE | C26: UNIDADES | D26: UND MEDIDA | E26: COSTO UNITARIO | F26: TOTAL COSTO | G26: % PREC. DEFINIDO | H26: CODIGOS
A27: 0 | B27: =IFERROR(VLOOKUP(H27,'[1]Consolidado MP Planta'!$A$2:$M$823,3,0),"") | C27: =+A27 -> 0 | D27: =IFERROR(VLOOKUP(H27,'[1]Consolidado MP Planta'!$A$2:$M$823,13,0),"") | E27: =IFERROR(VLOOKUP(H27,'[1]Consolidado MP Planta'!$A$2:$M$823,12,0),"") | F27: =IFERROR(C27*E27,"") | G27: =IFERROR(F27/$F$66,"")
B28: =IFERROR(VLOOKUP(H28,'[1]Consolidado MP Planta'!$A$2:$M$823,3,0),"") | C28: =+A28 -> 0 | D28: =IFERROR(VLOOKUP(H28,'[1]Consolidado MP Planta'!$A$2:$M$823,13,0),"") | E28: =IFERROR(VLOOKUP(H28,'[1]Consolidado MP Planta'!$A$2:$M$823,12,0),"") | F28: =IFERROR(C28*E28,"") | G28: =IFERROR(F28/$F$66,"")
B29: =IFERROR(VLOOKUP(H29,'[1]Consolidado MP Planta'!$A$2:$M$823,3,0),"") | C29: =+A29 -> 0 | D29: =IFERROR(VLOOKUP(H29,'[1]Consolidado MP Planta'!$A$2:$M$823,13,0),"") | E29: =IFERROR(VLOOKUP(H29,'[1]Consolidado MP Planta'!$A$2:$M$823,12,0),"") | F29: =IFERROR(C29*E29,"") | G29: =IFERROR(F29/$F$66,"")
B30: =IFERROR(VLOOKUP(H30,'[1]Consolidado MP Planta'!$A$2:$M$823,3,0),"") | C30: =+A30 -> 0 | D30: =IFERROR(VLOOKUP(H30,'[1]Consolidado MP Planta'!$A$2:$M$823,13,0),"") | E30: =IFERROR(VLOOKUP(H30,'[1]Consolidado MP Planta'!$A$2:$M$823,12,0),"") | F30: =IFERROR(C30*E30,"") | G30: =IFERROR(F30/$F$66,"")
B31: =IFERROR(VLOOKUP(H31,'[1]Consolidado MP Planta'!$A$2:$M$823,3,0),"") | C31: =+A31 -> 0 | D31: =IFERROR(VLOOKUP(H31,'[1]Consolidado MP Planta'!$A$2:$M$823,13,0),"") | E31: =IFERROR(VLOOKUP(H31,'[1]Consolidado MP Planta'!$A$2:$M$823,12,0),"") | F31: =IFERROR(C31*E31,"") | G31: =IFERROR(F31/$F$66,"")
B32: =IFERROR(VLOOKUP(H32,'[1]Consolidado MP Planta'!$A$2:$M$823,3,0),"") | C32: =+A32 -> 0 | D32: =IFERROR(VLOOKUP(H32,'[1]Consolidado MP Planta'!$A$2:$M$823,13,0),"") | E32: =IFERROR(VLOOKUP(H32,'[1]Consolidado MP Planta'!$A$2:$M$823,12,0),"") | F32: =IFERROR(C32*E32,"") | G32: =IFERROR(F32/$F$66,"")
A34: UNIDADES | B34: EMPAQUE SEMIELABORADOS | C34: UNIDADES | D34: UND MEDIDA | E34: COSTO UNITARIO | F34: TOTAL COSTO | G34: % PREC. DEFINIDO | H34: CODIGOS
A35: =+A17 -> 0.5 | B35: ROSQUETE CHOCOLATE DAWN 220g | C35: =+A35 -> 0.5 | D35: =IFERROR(VLOOKUP(H35,[1]SEMIELABORADOS!$A$2:$M$6000,6,0),"") | E35: 1.03 | F35: =IFERROR(E35*C35,"") -> 0.515 | G35: =IFERROR(F35/$F$66,"") -> 0.00030617518 | H35: 907000317
A36: =+A18 -> 150 | B36: Mousse Chocolate Interno | C36: =+A36 -> 150 | D36: =IFERROR(VLOOKUP(H36,[1]SEMIELABORADOS!$A$2:$M$6000,6,0),"") | E36: =+'Costo Mousse pastelera'!E76 -> 0 | F36: =IFERROR(E36*C36,"") -> 0 | G36: =IFERROR(F36/$F$66,"") -> 0
A37: =+A19 -> 100 | B37: Empaque Relleno Arandanos Rojos | C37: =+A37 -> 100 | D37: =IFERROR(VLOOKUP(H37,[1]SEMIELABORADOS!$A$2:$M$6000,6,0),"") | E37: =+'Costo Empaque Relleno Arand'!E76 -> 0.019512564 | F37: =IFERROR(E37*C37,"") -> 1.9512564 | G37: =IFERROR(F37/$F$66,"") -> 0.0011600511
A38: =+A20 -> 0 | B38: =IFERROR(VLOOKUP(H38,[1]SEMIELABORADOS!$A$2:$M$6000,2,0),"") | C38: =+A38 -> 0 | D38: =IFERROR(VLOOKUP(H38,[1]SEMIELABORADOS!$A$2:$M$6000,6,0),"") | E38: =IFERROR(VLOOKUP(H38,[1]SEMIELABORADOS!$A$2:$M$65536,10,0),"") | F38: =IFERROR(E38*C38,"") | G38: =IFERROR(F38/$F$66,"")
A39: =+A21 -> 0 | B39: =IFERROR(VLOOKUP(H39,[1]SEMIELABORADOS!$A$2:$M$6000,2,0),"") | C39: =+A39 -> 0 | D39: =IFERROR(VLOOKUP(H39,[1]SEMIELABORADOS!$A$2:$M$6000,6,0),"") | E39: =IFERROR(VLOOKUP(H39,[1]SEMIELABORADOS!$A$2:$M$65536,10,0),"") | F39: =IFERROR(E39*C39,"") | G39: =IFERROR(F39/$F$66,"")
A40: =+A22 -> 0 | B40: =IFERROR(VLOOKUP(H40,[1]SEMIELABORADOS!$A$2:$M$6000,2,0),"") | C40: =+A40 -> 0 | D40: =IFERROR(VLOOKUP(H40,[1]SEMIELABORADOS!$A$2:$M$6000,6,0),"") | E40: =IFERROR(VLOOKUP(H40,[1]SEMIELABORADOS!$A$2:$M$65536,10,0),"") | F40: =IFERROR(E40*C40,"") | G40: =IFERROR(F40/$F$66,"")
A41: =+A23 -> 0 | B41: =IFERROR(VLOOKUP(H41,'[1]Consolidado MP Planta'!$A$2:$M$823,3,0),"") | C41: =+A41 -> 0 | D41: =IFERROR(VLOOKUP(H41,[1]SEMIELABORADOS!$A$2:$M$6000,6,0),"") | E41: =IFERROR(VLOOKUP(H41,[1]SEMIELABORADOS!$A$2:$M$65536,10,0),"") | F41: =IFERROR(E41*C41,"") | G41: =IFERROR(F41/$F$66,"")
A43: UNIDADES | B43: MODI | C43: UNIDADES | D43: UND MEDIDA | E43: COSTO UNITARIO | F43: TOTAL COSTO | G43: % PREC. DEFINIDO | H43: CODIGOS
A44: =+A35 -> 0.5 | B44: ROSQUETE CHOCOLATE DAWN 220g | C44: =+A44 -> 0.5 | D44: =IFERROR(VLOOKUP(H44,[1]SEMIELABORADOS!$A$2:$M$6000,6,0),"") | E44: 68.03 | F44: =IFERROR(E44*C44,"") -> 34.015 | G44: =IFERROR(F44/$F$66,"") -> 0.020222425 | H44: 907000317
A45: =+A36 -> 150 | B45: Mousse Chocolate Interno | C45: =+A45 -> 150 | D45: =IFERROR(VLOOKUP(H45,[1]SEMIELABORADOS!$A$2:$M$6000,6,0),"") | E45: =+'Costo Mousse pastelera'!E74 -> 0.1403 | F45: =IFERROR(E45*C45,"") -> 21.045 | G45: =IFERROR(F45/$F$66,"") -> 0.012511566
A46: =+A37 -> 100 | B46: Empaque Relleno Arandanos Rojos | C46: =+A46 -> 100 | D46: =IFERROR(VLOOKUP(H46,[1]SEMIELABORADOS!$A$2:$M$6000,6,0),"") | E46: =+'Costo Empaque Relleno Arand'!E74 -> 0.09698268 | F46: =IFERROR(E46*C46,"") -> 9.698268 | G46: =IFERROR(F46/$F$66,"") -> 0.005765765
A47: =+A38 -> 0 | B47: =IFERROR(VLOOKUP(H47,[1]SEMIELABORADOS!$A$2:$M$6000,2,0),"") | C47: =+A47 -> 0 | D47: =IFERROR(VLOOKUP(H47,[1]SEMIELABORADOS!$A$2:$M$6000,6,0),"") | E47: =IFERROR(VLOOKUP(H47,[1]SEMIELABORADOS!$A$2:$M$65536,12,0),"") | F47: =IFERROR(E47*C47,"") | G47: =IFERROR(F47/$F$66,"")
A48: =+A39 -> 0 | B48: =IFERROR(VLOOKUP(H48,[1]SEMIELABORADOS!$A$2:$M$6000,2,0),"") | C48: =+A48 -> 0 | D48: =IFERROR(VLOOKUP(H48,[1]SEMIELABORADOS!$A$2:$M$6000,6,0),"") | E48: =IFERROR(VLOOKUP(H48,[1]SEMIELABORADOS!$A$2:$M$65536,12,0),"") | F48: =IFERROR(E48*C48,"") | G48: =IFERROR(F48/$F$66,"")
A49: =+A40 -> 0 | B49: =IFERROR(VLOOKUP(H49,[1]SEMIELABORADOS!$A$2:$M$6000,2,0),"") | C49: =+A49 -> 0 | D49: =IFERROR(VLOOKUP(H49,[1]SEMIELABORADOS!$A$2:$M$6000,6,0),"") | E49: =IFERROR(VLOOKUP(H49,[1]SEMIELABORADOS!$A$2:$M$65536,12,0),"") | F49: =IFERROR(E49*C49,"") | G49: =IFERROR(F49/$F$66,"")
A50: =+A41 -> 0 | B50: =IFERROR(VLOOKUP(H50,[1]SEMIELABORADOS!$A$2:$M$6000,2,0),"") | C50: =+A50 -> 0 | D50: =IFERROR(VLOOKUP(H50,[1]SEMIELABORADOS!$A$2:$M$6000,6,0),"") | E50: =IFERROR(VLOOKUP(H50,[1]SEMIELABORADOS!$A$2:$M$65536,12,0),"") | F50: =IFERROR(E50*C50,"") | G50: =IFERROR(F50/$F$66,"")
A51: 1 | B51: MODI PREPARACION | C51: =+A51 -> 1 | D51: N/A | E51: =+F65 -> 183 | F51: =IFERROR(C51*E51,"") -> 183 | G51: =IFERROR(F51/$F$66,"") -> 0.10879623
B53: TOTAL MATERIA PRIMA | F53: =SUM(F8:F14,F17:F24) -> 1467.2327 | G53: =+F53/$F$66 -> 0.87229171 | H53: =+F53/$D$60 -> 1467.2327
B54: TOTAL EMPAQUE | F54: =SUM(F27:F32,F35:F41) -> 2.4662564 | G54: =+F54/$F$66 -> 0.0014662263 | H54: =+F54/$D$60 -> 2.4662564 | K54: TOTAL MATERIA PRIMA + EMPAQUE | O54: =+F55 -> 1469.6989
B55: TOTAL MATERIAS P. + EMPAQUES | F55: =+F53+F54 -> 1469.6989 | G55: =+F55/$F$66 -> 0.87375794 | H55: =+F55/$D$60 -> 1469.6989 | M55: MODI PLANTA | O55: =+H56 -> 247.75827
C56: TOTAL MODI | F56: =SUM(F44:F51) -> 247.75827 | G56: =+F56/$F$66 -> 0.14729599 | H56: =+F56/$D$60 -> 247.75827 | M56: DESECHO | O56: =O54*N56 -> 0
M57: COSTO PLANTA | O57: =SUM(O54:O56) -> 1717.4572
B58: GRAMOS | D58: 340 | H58: =+H56/61 -> 4.061611 | M58: % GIF | O58: =+H59 -> 235.57344
B59: PESO POR UNIDAD | D59: 340 | H59: =+H58*58 -> 235.57344 | M59: COSTO PLANTA | O59: =SUM(O57:O58) -> 1953.0306
B60: UNIDADES TOTALES | D60: =+D58/D59 -> 1 | O60: =+O59*N60 -> 0
B61: UNIDAD MEDIDA | K61: PRECIO DE VENTA PLANTA A LOCAL | O61: =SUM(O59:O60) -> 1953.0306 | P61: GR
E62: S/ COSTO | F62: TOTAL | L62: UNIDAD | O62: =+O61/D60 -> 1953.0306 | P62: =+O62/D59 -> 5.7442077
B63: TOTAL MATERIAS P. + EMPAQUES | E63: =+F63/F63 -> 1 | F63: =SUM(F55) -> 1469.6989 | G63: =+F63/$F$66 -> 0.87375794
B64: DESECHOS Y PERDIDAS | E64: 0.02 | F64: =+F53*E64 -> 29.344653 | G64: =+F64/$F$66 -> 0.017445834
B65: MANO OBRA DIRECTA | D65: 3 | E65: 61 | F65: =+E65*D65 -> 183 | G65: =+F65/$F$66 -> 0.10879623
B66: TOTAL COSTO PLANTA | F66: =SUM(F63:F65) -> 1682.0436 | G66: =+F66/$F$66 -> 1 | M66: MODI 61 COLONES X MIN
M67: Gf 58 colones min
B68: COSTO POR GRAMO | M68: ,
B69: TOTAL COSTO MATERIA PRIMA | C69: =+F53 -> 1467.2327 | D69: =+D58 -> 340 | E69: =+C69/D69 -> 4.3153902
B71: TOTAL COSTO UNIDAD MP+DESECHO+EMPAQUE | C71: =SUM(F63:F64) -> 1499.0436 | D71: =+D58 -> 340 | E71: =+C71/D71 -> 4.4089517
B73: TOTAL MODI PREPARACION POR GRAMO | C73: =+F65 -> 183 | D73: =+D58 -> 340 | E73: =+C73/D73 -> 0.53823529
B74: TOTAL MODI POR GRAMO | C74: =+F56 -> 247.75827 | D74: =+D73 -> 340 | E74: =+C74/D74 -> 0.72870079
B76: TOTAL EMPAQUE POR GRAMO | C76: =+F54 -> 2.4662564 | D76: =+D74 -> 340 | E76: =+C76/D76 -> 0.0072536954
B78: TOTAL GRAMO MP+MODI | E78: =+E69+E74 -> 5.044091
B80: COSTO POR UNIDAD
B81: TOTAL COSTO MATERIA PRIMA | C81: =+C69 -> 1467.2327 | D81: =+D60 -> 1 | E81: =+C81/D81 -> 1467.2327
B83: TOTAL COSTO UNIDAD MP+DESECHO+EMPAQUE | C83: =+C71 -> 1499.0436 | D83: =+D60 -> 1 | E83: =+C83/D83 -> 1499.0436
B85: TOTAL MODI POR GRAMO | C85: =+C73 -> 183 | D85: =+D60 -> 1 | E85: =+C85/D85 -> 183
B86: TOTAL MODI POR GRAMO | C86: =+C74 -> 247.75827 | D86: =+D85 -> 1 | E86: =+C86/D86 -> 247.75827

Sheet Costo Mousse pastelera
E1: Precio Local | F1: Costo MP | G1: Costo EM | H1: Costo MO
E2: =IFERROR(O62,"") -> 28987.455 | F2: =IFERROR(H53,"") -> 26250.455 | G2: =IFERROR(H54,"") -> 0 | H2: =IFERROR(H56,"") -> 1403
A5: ESTRUCTURA DE COSTOS
F6: Fecha: | H6: =TODAY() -> 45776
A7: UNIDADES | B7: DESCRIPCION MAT.PRIMA | C7: UNIDADES | D7: UND MEDIDA | E7: COSTO UNITARIO | F7: TOTAL COSTO | G7: % PREC. DEFINIDO | H7: CODIGOS
A8: 3500 | B8: =IFERROR(VLOOKUP(H8,'[1]Consolidado MP Planta'!$A$2:$M$823,3,0),"") -> CREMA PRESTIGE GRAND (UND:4 K) * | C8: =+A8 -> 3500 | D8: =IFERROR(VLOOKUP(H8,'[1]Consolidado MP Planta'!$A$2:$M$823,13,0),"") -> Gramos | E8: =IFERROR(VLOOKUP(H8,'[1]Consolidado MP Planta'!$A$2:$M$823,12,0),"") -> 2.25375 | F8: =IFERROR(C8*E8,"") -> 7888.125 | G8: =IFERROR(F8/$F$66,"") -> 0.28804058 | H8: 11400031
A9: 100 | B9: Gelatina Pura | C9: =+A9 -> 100 | D9: Gramos | E9: 13.01 | F9: =IFERROR(C9*E9,"") -> 1301 | G9: =IFERROR(F9/$F$66,"") -> 0.047506955 | H9: 1100022
B10: =IFERROR(VLOOKUP(H10,'[1]Consolidado MP Planta'!$A$2:$M$823,3,0),"") | C10: =+A10 -> 0 | D10: =IFERROR(VLOOKUP(H10,'[1]Consolidado MP Planta'!$A$2:$M$823,13,0),"") | E10: =IFERROR(VLOOKUP(H10,'[1]Consolidado MP Planta'!$A$2:$M$823,12,0),"") | F10: =IFERROR(C10*E10,"") | G10: =IFERROR(F10/$F$66,"")
B11: =IFERROR(VLOOKUP(H11,'[1]Consolidado MP Planta'!$A$2:$M$823,3,0),"") | C11: =+A11 -> 0 | D11: =IFERROR(VLOOKUP(H11,'[1]Consolidado MP Planta'!$A$2:$M$823,13,0),"") | E11: =IFERROR(VLOOKUP(H11,'[1]Consolidado MP Planta'!$A$2:$M$823,12,0),"") | F11: =IFERROR(C11*E11,"") | G11: =IFERROR(F11/$F$66,"")
B12: =IFERROR(VLOOKUP(H12,'[1]Consolidado MP Planta'!$A$2:$M$823,3,0),"") | C12: =+A12 -> 0 | D12: =IFERROR(VLOOKUP(H12,'[1]Consolidado MP Planta'!$A$2:$M$823,13,0),"") | E12: =IFERROR(VLOOKUP(H12,'[1]Consolidado MP Planta'!$A$2:$M$823,12,0),"") | F12: =IFERROR(C12*E12,"") | G12: =IFERROR(F12/$F$66,"")
B13: =IFERROR(VLOOKUP(H13,'[1]Consolidado MP Planta'!$A$2:$M$823,3,0),"") | C13: =+A13 -> 0 | D13: =IFERROR(VLOOKUP(H13,'[1]Consolidado MP Planta'!$A$2:$M$823,13,0),"") | E13: =IFERROR(VLOOKUP(H13,'[1]Consolidado MP Planta'!$A$2:$M$823,12,0),"") | F13: =IFERROR(C13*E13,"") | G13: =IFERROR(F13/$F$66,"")
B14: =IFERROR(VLOOKUP(H14,'[1]Consolidado MP Planta'!$A$2:$M$823,3,0),"") | C14: =+A14 -> 0 | D14: =IFERROR(VLOOKUP(H14,'[1]Consolidado MP Planta'!$A$2:$M$823,13,0),"") | E14: =IFERROR(VLOOKUP(H14,'[1]Consolidado MP Planta'!$A$2:$M$823,12,0),"") | F14: =IFERROR(C14*E14,"") | G14: =IFERROR(F14/$F$66,"")
B15: =IFERROR(VLOOKUP(H15,'[2]ARTICULOS MP PLANTA'!$A$2:$G$589,2,0),"")
A16: UNIDADES | B16: MATERIA PRIMA SEMIELABORADOS | C16: UNIDADES | D16: UND MEDIDA | E16: COSTO UNITARIO | F16: TOTAL COSTO | G16: % PREC. DEFINIDO | H16: CODIGOS
A17: 6500 | B17: Crema Pastelera peruana | C17: =+A17 -> 6500 | D17: gramos | E17: =+'Costo Crema Past Peruana'!E69 -> 2.62482 | F17: =IFERROR(E17*C17,"") -> 17061.33 | G17: =IFERROR(F17/$F$66,"") -> 0.62300679
B18: =IFERROR(VLOOKUP(H18,[1]SEMIELABORADOS!$A$2:$M$6000,2,0),"") | C18: =+A18 -> 0 | D18: =IFERROR(VLOOKUP(H18,[1]SEMIELABORADOS!$A$2:$M$6000,6,0),"") | E18: =IFERROR(VLOOKUP(H18,[1]SEMIELABORADOS!$A$2:$H$65536,8,0),"") | F18: =IFERROR(E18*C18,"") | G18: =IFERROR(F18/$F$66,"")
B19: =IFERROR(VLOOKUP(H19,[1]SEMIELABORADOS!$A$2:$M$6000,2,0),"") | C19: =+A19 -> 0 | D19: =IFERROR(VLOOKUP(H19,[1]SEMIELABORADOS!$A$2:$M$6000,6,0),"") | E19: =IFERROR(VLOOKUP(H19,[1]SEMIELABORADOS!$A$2:$H$65536,8,0),"") | F19: =IFERROR(E19*C19,"") | G19: =IFERROR(F19/$F$66,"")
B20: =IFERROR(VLOOKUP(H20,[1]SEMIELABORADOS!$A$2:$M$6000,2,0),"") | C20: =+A20 -> 0 | D20: =IFERROR(VLOOKUP(H20,[1]SEMIELABORADOS!$A$2:$M$6000,6,0),"") | E20: =IFERROR(VLOOKUP(H20,[1]SEMIELABORADOS!$A$2:$H$65536,8,0),"") | F20: =IFERROR(E20*C20,"") | G20: =IFERROR(F20/$F$66,"")
B21: =IFERROR(VLOOKUP(H21,[1]SEMIELABORADOS!$A$2:$M$6000,2,0),"") | C21: =+A21 -> 0 | D21: =IFERROR(VLOOKUP(H21,[1]SEMIELABORADOS!$A$2:$M$6000,6,0),"") | E21: =IFERROR(VLOOKUP(H21,[1]SEMIELABORADOS!$A$2:$H$65536,8,0),"") | F21: =IFERROR(E21*C21,"") | G21: =IFERROR(F21/$F$66,"")
B22: =IFERROR(VLOOKUP(H22,[1]SEMIELABORADOS!$A$2:$M$6000,2,0),"") | C22: =+A22 -> 0 | D22: =IFERROR(VLOOKUP(H22,[1]SEMIELABORADOS!$A$2:$M$6000,6,0),"") | E22: =IFERROR(VLOOKUP(H22,[1]SEMIELABORADOS!$A$2:$H$65536,8,0),"") | F22: =IFERROR(E22*C22,"") | G22: =IFERROR(F22/$F$66,"")
B23: =IFERROR(VLOOKUP(H23,[1]SEMIELABORADOS!$A$2:$M$6000,2,0),"") | C23: =+A23 -> 0 | D23: =IFERROR(VLOOKUP(H23,[1]SEMIELABORADOS!$A$2:$M$6000,6,0),"") | E23: =IFERROR(VLOOKUP(H23,[1]SEMIELABORADOS!$A$2:$H$65536,8,0),"") | F23: =IFERROR(E23*C23,"") | G23: =IFERROR(F23/$F$66,"")
B24: =IFERROR(VLOOKUP(H24,[1]SEMIELABORADOS!$A$2:$M$6000,2,0),"") | C24: =+A24 -> 0 | D24: =IFERROR(VLOOKUP(H24,[1]SEMIELABORADOS!$A$2:$M$6000,6,0),"") | E24: =IFERROR(VLOOKUP(H24,[1]SEMIELABORADOS!$A$2:$H$65536,8,0),"") | F24: =IFERROR(E24*C24,"") | G24: =IFERROR(F24/$F$66,"")
A26: UNIDADES | B26: EMPAQUE | C26: UNIDADES | D26: UND MEDIDA | E26: COSTO UNITARIO | F26: TOTAL COSTO | G26: % PREC. DEFINIDO | H26: CODIGOS
A27: 0 | B27: =IFERROR(VLOOKUP(H27,'[1]Consolidado MP Planta'!$A$2:$M$823,3,0),"") | C27: =+A27 -> 0 | D27: =IFERROR(VLOOKUP(H27,'[1]Consolidado MP Planta'!$A$2:$M$823,13,0),"") | E27: =IFERROR(VLOOKUP(H27,'[1]Consolidado MP Planta'!$A$2:$M$823,12,0),"") | F27: =IFERROR(C27*E27,"") | G27: =IFERROR(F27/$F$66,"")
B28: =IFERROR(VLOOKUP(H28,'[1]Consolidado MP Planta'!$A$2:$M$823,3,0),"") | C28: =+A28 -> 0 | D28: =IFERROR(VLOOKUP(H28,'[1]Consolidado MP Planta'!$A$2:$M$823,13,0),"") | E28: =IFERROR(VLOOKUP(H28,'[1]Consolidado MP Planta'!$A$2:$M$823,12,0),"") | F28: =IFERROR(C28*E28,"") | G28: =IFERROR(F28/$F$66,"")
B29: =IFERROR(VLOOKUP(H29,'[1]Consolidado MP Planta'!$A$2:$M$823,3,0),"") | C29: =+A29 -> 0 | D29: =IFERROR(VLOOKUP(H29,'[1]Consolidado MP Planta'!$A$2:$M$823,13,0),"") | E29: =IFERROR(VLOOKUP(H29,'[1]Consolidado MP Planta'!$A$2:$M$823,12,0),"") | F29: =IFERROR(C29*E29,"") | G29: =IFERROR(F29/$F$66,"")
B30: =IFERROR(VLOOKUP(H30,'[1]Consolidado MP Planta'!$A$2:$M$823,3,0),"") | C30: =+A30 -> 0 | D30: =IFERROR(VLOOKUP(H30,'[1]Consolidado MP Planta'!$A$2:$M$823,13,0),"") | E30: =IFERROR(VLOOKUP(H30,'[1]Consolidado MP Planta'!$A$2:$M$823,12,0),"") | F30: =IFERROR(C30*E30,"") | G30: =IFERROR(F30/$F$66,"")
B31: =IFERROR(VLOOKUP(H31,'[1]Consolidado MP Planta'!$A$2:$M$823,3,0),"") | C31: =+A31 -> 0 | D31: =IFERROR(VLOOKUP(H31,'[1]Consolidado MP Planta'!$A$2:$M$823,13,0),"") | E31: =IFERROR(VLOOKUP(H31,'[1]Consolidado MP Planta'!$A$2:$M$823,12,0),"") | F31: =IFERROR(C31*E31,"") | G31: =IFERROR(F31/$F$66,"")
B32: =IFERROR(VLOOKUP(H32,'[1]Consolidado MP Planta'!$A$2:$M$823,3,0),"") | C32: =+A32 -> 0 | D32: =IFERROR(VLOOKUP(H32,'[1]Consolidado MP Planta'!$A$2:$M$823,13,0),"") | E32: =IFERROR(VLOOKUP(H32,'[1]Consolidado MP Planta'!$A$2:$M$823,12,0),"") | F32: =IFERROR(C32*E32,"") | G32: =IFERROR(F32/$F$66,"")
A34: UNIDADES | B34: EMPAQUE SEMIELABORADOS | C34: UNIDADES | D34: UND MEDIDA | E34: COSTO UNITARIO | F34: TOTAL COSTO | G34: % PREC. DEFINIDO | H34: CODIGOS
A35: =+A17 -> 6500 | B35: Crema Pastelera peruana | C35: =+A35 -> 6500 | D35: =IFERROR(VLOOKUP(H35,[1]SEMIELABORADOS!$A$2:$M$6000,6,0),"") | E35: =+'Costo Crema Past Peruana'!E76 -> 0 | F35: =IFERROR(E35*C35,"") -> 0 | G35: =IFERROR(F35/$F$66,"") -> 0
A36: =+A18 -> 0 | B36: =IFERROR(VLOOKUP(H36,[1]SEMIELABORADOS!$A$2:$M$6000,2,0),"") | C36: =+A36 -> 0 | D36: =IFERROR(VLOOKUP(H36,[1]SEMIELABORADOS!$A$2:$M$6000,6,0),"") | E36: =IFERROR(VLOOKUP(H36,[1]SEMIELABORADOS!$A$2:$M$65536,10,0),"") | F36: =IFERROR(E36*C36,"") | G36: =IFERROR(F36/$F$66,"")
A37: =+A19 -> 0 | B37: =IFERROR(VLOOKUP(H37,[1]SEMIELABORADOS!$A$2:$M$6000,2,0),"") | C37: =+A37 -> 0 | D37: =IFERROR(VLOOKUP(H37,[1]SEMIELABORADOS!$A$2:$M$6000,6,0),"") | E37: =IFERROR(VLOOKUP(H37,[1]SEMIELABORADOS!$A$2:$M$65536,10,0),"") | F37: =IFERROR(E37*C37,"") | G37: =IFERROR(F37/$F$66,"")
A38: =+A20 -> 0 | B38: =IFERROR(VLOOKUP(H38,[1]SEMIELABORADOS!$A$2:$M$6000,2,0),"") | C38: =+A38 -> 0 | D38: =IFERROR(VLOOKUP(H38,[1]SEMIELABORADOS!$A$2:$M$6000,6,0),"") | E38: =IFERROR(VLOOKUP(H38,[1]SEMIELABORADOS!$A$2:$M$65536,10,0),"") | F38: =IFERROR(E38*C38,"") | G38: =IFERROR(F38/$F$66,"")
A39: =+A21 -> 0 | B39: =IFERROR(VLOOKUP(H39,[1]SEMIELABORADOS!$A$2:$M$6000,2,0),"") | C39: =+A39 -> 0 | D39: =IFERROR(VLOOKUP(H39,[1]SEMIELABORADOS!$A$2:$M$6000,6,0),"") | E39: =IFERROR(VLOOKUP(H39,[1]SEMIELABORADOS!$A$2:$M$65536,10,0),"") | F39: =IFERROR(E39*C39,"") | G39: =IFERROR(F39/$F$66,"")
A40: =+A22 -> 0 | B40: =IFERROR(VLOOKUP(H40,[1]SEMIELABORADOS!$A$2:$M$6000,2,0),"") | C40: =+A40 -> 0 | D40: =IFERROR(VLOOKUP(H40,[1]SEMIELABORADOS!$A$2:$M$6000,6,0),"") | E40: =IFERROR(VLOOKUP(H40,[1]SEMIELABORADOS!$A$2:$M$65536,10,0),"") | F40: =IFERROR(E40*C40,"") | G40: =IFERROR(F40/$F$66,"")
A41: =+A23 -> 0 | B41: =IFERROR(VLOOKUP(H41,[1]SEMIELABORADOS!$A$2:$M$6000,2,0),"") | C41: =+A41 -> 0 | D41: =IFERROR(VLOOKUP(H41,[1]SEMIELABORADOS!$A$2:$M$6000,6,0),"") | E41: =IFERROR(VLOOKUP(H41,[1]SEMIELABORADOS!$A$2:$M$65536,10,0),"") | F41: =IFERROR(E41*C41,"") | G41: =IFERROR(F41/$F$66,"")
A43: UNIDADES | B43: MODI | C43: UNIDADES | D43: UND MEDIDA | E43: COSTO UNITARIO | F43: TOTAL COSTO | G43: % PREC. DEFINIDO | H43: CODIGOS
A44: =+A35 -> 6500 | B44: Crema Pastelera peruana | C44: =+A44 -> 6500 | D44: =IFERROR(VLOOKUP(H44,[1]SEMIELABORADOS!$A$2:$M$6000,6,0),"") | E44: =+'Costo Crema Past Peruana'!E74 -> 0.122 | F44: =IFERROR(E44*C44,"") -> 793 | G44: =IFERROR(F44/$F$66,"") -> 0.028956968
A45: =+A36 -> 0 | B45: =IFERROR(VLOOKUP(H45,[1]SEMIELABORADOS!$A$2:$M$6000,2,0),"") | C45: =+A45 -> 0 | D45: =IFERROR(VLOOKUP(H45,[1]SEMIELABORADOS!$A$2:$M$6000,6,0),"") | E45: =IFERROR(VLOOKUP(H45,[1]SEMIELABORADOS!$A$2:$M$65536,12,0),"") | F45: =IFERROR(E45*C45,"") | G45: =IFERROR(F45/$F$66,"")
A46: =+A37 -> 0 | B46: =IFERROR(VLOOKUP(H46,[1]SEMIELABORADOS!$A$2:$M$6000,2,0),"") | C46: =+A46 -> 0 | D46: =IFERROR(VLOOKUP(H46,[1]SEMIELABORADOS!$A$2:$M$6000,6,0),"") | E46: =IFERROR(VLOOKUP(H46,[1]SEMIELABORADOS!$A$2:$M$65536,12,0),"") | F46: =IFERROR(E46*C46,"") | G46: =IFERROR(F46/$F$66,"")
A47: =+A38 -> 0 | B47: =IFERROR(VLOOKUP(H47,[1]SEMIELABORADOS!$A$2:$M$6000,2,0),"") | C47: =+A47 -> 0 | D47: =IFERROR(VLOOKUP(H47,[1]SEMIELABORADOS!$A$2:$M$6000,6,0),"") | E47: =IFERROR(VLOOKUP(H47,[1]SEMIELABORADOS!$A$2:$M$65536,12,0),"") | F47: =IFERROR(E47*C47,"") | G47: =IFERROR(F47/$F$66,"")
A48: =+A39 -> 0 | B48: =IFERROR(VLOOKUP(H48,[1]SEMIELABORADOS!$A$2:$M$6000,2,0),"") | C48: =+A48 -> 0 | D48: =IFERROR(VLOOKUP(H48,[1]SEMIELABORADOS!$A$2:$M$6000,6,0),"") | E48: =IFERROR(VLOOKUP(H48,[1]SEMIELABORADOS!$A$2:$M$65536,12,0),"") | F48: =IFERROR(E48*C48,"") | G48: =IFERROR(F48/$F$66,"")
A49: =+A40 -> 0 | B49: =IFERROR(VLOOKUP(H49,[1]SEMIELABORADOS!$A$2:$M$6000,2,0),"") | C49: =+A49 -> 0 | D49: =IFERROR(VLOOKUP(H49,[1]SEMIELABORADOS!$A$2:$M$6000,6,0),"") | E49: =IFERROR(VLOOKUP(H49,[1]SEMIELABORADOS!$A$2:$M$65536,12,0),"") | F49: =IFERROR(E49*C49,"") | G49: =IFERROR(F49/$F$66,"")
A50: =+A41 -> 0 | B50: =IFERROR(VLOOKUP(H50,[1]SEMIELABORADOS!$A$2:$M$6000,2,0),"") | C50: =+A50 -> 0 | D50: =IFERROR(VLOOKUP(H50,[1]SEMIELABORADOS!$A$2:$M$6000,6,0),"") | E50: =IFERROR(VLOOKUP(H50,[1]SEMIELABORADOS!$A$2:$M$65536,12,0),"") | F50: =IFERROR(E50*C50,"") | G50: =IFERROR(F50/$F$66,"")
A51: 1 | B51: MODI PREPARACION | C51: =+A51 -> 1 | D51: N/A | E51: =+F65 -> 610 | F51: =IFERROR(C51*E51,"") -> 610 | G51: =IFERROR(F51/$F$66,"") -> 0.022274591
B53: TOTAL MATERIA PRIMA | F53: =SUM(F8:F14,F17:F24) -> 26250.455 | G53: =+F53/$F$66 -> 0.95855432 | H53: =+F53/$D$60 -> 26250.455
B54: TOTAL EMPAQUE | F54: =SUM(F27:F32,F35:F41) -> 0 | G54: =+F54/$F$66 -> 0 | H54: =+F54/$D$60 -> 0 | K54: TOTAL MATERIA PRIMA + EMPAQUE | O54: =+F55 -> 26250.455
B55: TOTAL MATERIAS P. + EMPAQUES | F55: =+F53+F54 -> 26250.455 | G55: =+F55/$F$66 -> 0.95855432 | H55: =+F55/$D$60 -> 26250.455 | M55: MODI PLANTA | O55: =+H56 -> 1403
C56: TOTAL MODI | F56: =SUM(F44:F51) -> 1403 | G56: =+F56/$F$66 -> 0.051231558 | H56: =+F56/$D$60 -> 1403 | M56: DESECHO | O56: =O54*N56 -> 0
M57: COSTO PLANTA | O57: =SUM(O54:O56) -> 27653.455
B58: GRAMOS | D58: 10000 | H58: =+H56/61 -> 23 | M58: % GIF | O58: =+H59 -> 1334
B59: PESO POR UNIDAD | D59: 10000 | H59: =+H58*58 -> 1334 | M59: COSTO PLANTA | O59: =SUM(O57:O58) -> 28987.455
B60: UNIDADES TOTALES | D60: =+D58/D59 -> 1 | O60: =+O59*N60 -> 0
B61: UNIDAD MEDIDA | K61: PRECIO DE VENTA PLANTA A LOCAL | O61: =SUM(O59:O60) -> 28987.455 | P61: GR
E62: S/ COSTO | F62: TOTAL | L62: UNIDAD | O62: =+O61/D60 -> 28987.455 | P62: =+O62/D59 -> 2.8987455
B63: TOTAL MATERIAS P. + EMPAQUES | E63: =+F63/F63 -> 1 | F63: =SUM(F55) -> 26250.455 | G63: =+F63/$F$66 -> 0.95855432
B64: DESECHOS Y PERDIDAS | E64: 0.02 | F64: =+F53*E64 -> 525.0091 | G64: =+F64/$F$66 -> 0.019171086
B65: MANO OBRA DIRECTA | D65: 10 | E65: 61 | F65: =+E65*D65 -> 610 | G65: =+F65/$F$66 -> 0.022274591
B66: TOTAL COSTO PLANTA | F66: =SUM(F63:F65) -> 27385.464 | G66: =+F66/$F$66 -> 1 | M66: MODI 61 COLONES X MIN
M67: Gf 58 colones min
B68: COSTO POR GRAMO | M68: ,
B69: TOTAL COSTO MATERIA PRIMA | C69: =+F53 -> 26250.455 | D69: =+D58 -> 10000 | E69: =+C69/D69 -> 2.6250455
B71: TOTAL COSTO UNIDAD MP+DESECHO+EMPAQUE | C71: =SUM(F63:F64) -> 26775.464 | D71: =+D58 -> 10000 | E71: =+C71/D71 -> 2.6775464
B73: TOTAL MODI PREPARACION POR GRAMO | C73: =+F65 -> 610 | D73: =+D58 -> 10000 | E73: =+C73/D73 -> 0.061
B74: TOTAL MODI POR GRAMO | C74: =+F56 -> 1403 | D74: =+D73 -> 10000 | E74: =+C74/D74 -> 0.1403
B76: TOTAL EMPAQUE POR GRAMO | C76: =+F54 -> 0 | D76: =+D74 -> 10000 | E76: =+C76/D76 -> 0
B78: TOTAL GRAMO MP+MODI | E78: =+E69+E74 -> 2.7653455
B80: COSTO POR UNIDAD
B81: TOTAL COSTO MATERIA PRIMA | C81: =+C69 -> 26250.455 | D81: =+D60 -> 1 | E81: =+C81/D81 -> 26250.455
B83: TOTAL COSTO UNIDAD MP+DESECHO+EMPAQUE | C83: =+C71 -> 26775.464 | D83: =+D60 -> 1 | E83: =+C83/D83 -> 26775.464
B85: TOTAL MODI POR GRAMO | C85: =+C73 -> 610 | D85: =+D60 -> 1 | E85: =+C85/D85 -> 610
B86: TOTAL MODI POR GRAMO | C86: =+C74 -> 1403 | D86: =+D85 -> 1 | E86: =+C86/D86 -> 1403

Sheet Costo Crema Past Peruana
E1: Precio Local | F1: Costo MP | G1: Costo EM | H1: Costo MO
E2: =IFERROR(O62,"") -> 28628.2 | F2: =IFERROR(H53,"") -> 26248.2 | G2: =IFERROR(H54,"") -> 0 | H2: =IFERROR(H56,"") -> 1220
A5: ESTRUCTURA DE COSTOS
F6: Fecha: | H6: =TODAY() -> 45776
A7: UNIDADES | B7: DESCRIPCION MAT.PRIMA | C7: UNIDADES | D7: UND MEDIDA | E7: COSTO UNITARIO | F7: TOTAL COSTO | G7: % PREC. DEFINIDO | H7: CODIGOS
A8: 6540 | B8: =IFERROR(VLOOKUP(H8,'[1]Consolidado MP Planta'!$A$2:$M$823,3,0),"") -> LECHE EVAPORADA (UND: 1 L) | C8: =+A8 -> 6540 | D8: =IFERROR(VLOOKUP(H8,'[1]Consolidado MP Planta'!$A$2:$M$823,13,0),"") -> Mililitros | E8: 1.97 | F8: =IFERROR(C8*E8,"") -> 12883.8 | G8: =IFERROR(F8/$F$66,"") -> 0.46024808 | H8: 1110414
A9: 3230 | B9: =IFERROR(VLOOKUP(H9,'[1]Consolidado MP Planta'!$A$2:$M$823,3,0),"") -> LECHE CONDENSADA (PAQ:11 K) | C9: =+A9 -> 3230 | D9: =IFERROR(VLOOKUP(H9,'[1]Consolidado MP Planta'!$A$2:$M$823,13,0),"") -> Gramos | E9: 2.15 | F9: =IFERROR(C9*E9,"") -> 6944.5 | G9: =IFERROR(F9/$F$66,"") -> 0.24807842 | H9: 11400046
A10: 1100 | B10: =IFERROR(VLOOKUP(H10,'[1]Consolidado MP Planta'!$A$2:$M$823,3,0),"") -> YEMA DE HUEVO (UND: 8.34 K) | C10: =+A10 -> 1100 | D10: Gramos | E10: 2.29 | F10: =IFERROR(C10*E10,"") -> 2519 | G10: =IFERROR(F10/$F$66,"") -> 0.089986255 | H10: 11300011
A11: 380 | B11: =IFERROR(VLOOKUP(H11,'[1]Consolidado MP Planta'!$A$2:$M$823,3,0),"") -> ALMIDON MODIFICADO (SACO:25 K) | C11: =+A11 -> 380 | D11: =IFERROR(VLOOKUP(H11,'[1]Consolidado MP Planta'!$A$2:$M$823,13,0),"") -> Gramos | E11: 2.13 | F11: =IFERROR(C11*E11,"") -> 809.4 | G11: =IFERROR(F11/$F$66,"") -> 0.028914202 | H11: 510215
A12: 100 | B12: =IFERROR(VLOOKUP(H12,'[1]Consolidado MP Planta'!$A$2:$M$823,3,0),"") -> VAINILLA OSCURA (UND: 3.78 L) | C12: =+A12 -> 100 | D12: =IFERROR(VLOOKUP(H12,'[1]Consolidado MP Planta'!$A$2:$M$823,13,0),"") -> Mililitros | E12: 1.25 | F12: =IFERROR(C12*E12,"") -> 125 | G12: =IFERROR(F12/$F$66,"") -> 0.0044653759 | H12: 118000004
A13: 850 | B13: =IFERROR(VLOOKUP(H13,'[1]Consolidado MP Planta'!$A$2:$M$823,3,0),"") -> LACTOCREMA GRANEL (CAJA:25 KG) | C13: =+A13 -> 850 | D13: =IFERROR(VLOOKUP(H13,'[1]Consolidado MP Planta'!$A$2:$M$823,13,0),"") -> Gramos | E13: 3.49 | F13: =IFERROR(C13*E13,"") -> 2966.5 | G13: =IFERROR(F13/$F$66,"") -> 0.1059723 | H13: 0310107
B14: =IFERROR(VLOOKUP(H14,'[1]Consolidado MP Planta'!$A$2:$M$823,3,0),"") | C14: =+A14 -> 0 | D14: =IFERROR(VLOOKUP(H14,'[1]Consolidado MP Planta'!$A$2:$M$823,13,0),"") | E14: =IFERROR(VLOOKUP(H14,'[1]Consolidado MP Planta'!$A$2:$M$823,12,0),"") | F14: =IFERROR(C14*E14,"") | G14: =IFERROR(F14/$F$66,"")
B15: =IFERROR(VLOOKUP(H15,'[2]ARTICULOS MP PLANTA'!$A$2:$G$589,2,0),"")
A16: UNIDADES | B16: MATERIA PRIMA SEMIELABORADOS | C16: UNIDADES | D16: UND MEDIDA | E16: COSTO UNITARIO | F16: TOTAL COSTO | G16: % PREC. DEFINIDO | H16: CODIGOS
B17: =IFERROR(VLOOKUP(H17,[1]SEMIELABORADOS!$A$2:$M$6000,2,0),"") | C17: =+A17 -> 0 | D17: =IFERROR(VLOOKUP(H17,[1]SEMIELABORADOS!$A$2:$M$6000,6,0),"") | E17: =IFERROR(VLOOKUP(H17,[1]SEMIELABORADOS!$A$2:$H$65536,8,0),"") | F17: =IFERROR(E17*C17,"") | G17: =IFERROR(F17/$F$66,"")
B18: =IFERROR(VLOOKUP(H18,[1]SEMIELABORADOS!$A$2:$M$6000,2,0),"") | C18: =+A18 -> 0 | D18: =IFERROR(VLOOKUP(H18,[1]SEMIELABORADOS!$A$2:$M$6000,6,0),"") | E18: =IFERROR(VLOOKUP(H18,[1]SEMIELABORADOS!$A$2:$H$65536,8,0),"") | F18: =IFERROR(E18*C18,"") | G18: =IFERROR(F18/$F$66,"")
B19: =IFERROR(VLOOKUP(H19,[1]SEMIELABORADOS!$A$2:$M$6000,2,0),"") | C19: =+A19 -> 0 | D19: =IFERROR(VLOOKUP(H19,[1]SEMIELABORADOS!$A$2:$M$6000,6,0),"") | E19: =IFERROR(VLOOKUP(H19,[1]SEMIELABORADOS!$A$2:$H$65536,8,0),"") | F19: =IFERROR(E19*C19,"") | G19: =IFERROR(F19/$F$66,"")
B20: =IFERROR(VLOOKUP(H20,[1]SEMIELABORADOS!$A$2:$M$6000,2,0),"") | C20: =+A20 -> 0 | D20: =IFERROR(VLOOKUP(H20,[1]SEMIELABORADOS!$A$2:$M$6000,6,0),"") | E20: =IFERROR(VLOOKUP(H20,[1]SEMIELABORADOS!$A$2:$H$65536,8,0),"") | F20: =IFERROR(E20*C20,"") | G20: =IFERROR(F20/$F$66,"")
B21: =IFERROR(VLOOKUP(H21,[1]SEMIELABORADOS!$A$2:$M$6000,2,0),"") | C21: =+A21 -> 0 | D21: =IFERROR(VLOOKUP(H21,[1]SEMIELABORADOS!$A$2:$M$6000,6,0),"") | E21: =IFERROR(VLOOKUP(H21,[1]SEMIELABORADOS!$A$2:$H$65536,8,0),"") | F21: =IFERROR(E21*C21,"") | G21: =IFERROR(F21/$F$66,"")
B22: =IFERROR(VLOOKUP(H22,[1]SEMIELABORADOS!$A$2:$M$6000,2,0),"") | C22: =+A22 -> 0 | D22: =IFERROR(VLOOKUP(H22,[1]SEMIELABORADOS!$A$2:$M$6000,6,0),"") | E22: =IFERROR(VLOOKUP(H22,[1]SEMIELABORADOS!$A$2:$H$65536,8,0),"") | F22: =IFERROR(E22*C22,"") | G22: =IFERROR(F22/$F$66,"")
B23: =IFERROR(VLOOKUP(H23,[1]SEMIELABORADOS!$A$2:$M$6000,2,0),"") | C23: =+A23 -> 0 | D23: =IFERROR(VLOOKUP(H23,[1]SEMIELABORADOS!$A$2:$M$6000,6,0),"") | E23: =IFERROR(VLOOKUP(H23,[1]SEMIELABORADOS!$A$2:$H$65536,8,0),"") | F23: =IFERROR(E23*C23,"") | G23: =IFERROR(F23/$F$66,"")
B24: =IFERROR(VLOOKUP(H24,[1]SEMIELABORADOS!$A$2:$M$6000,2,0),"") | C24: =+A24 -> 0 | D24: =IFERROR(VLOOKUP(H24,[1]SEMIELABORADOS!$A$2:$M$6000,6,0),"") | E24: =IFERROR(VLOOKUP(H24,[1]SEMIELABORADOS!$A$2:$H$65536,8,0),"") | F24: =IFERROR(E24*C24,"") | G24: =IFERROR(F24/$F$66,"")
A26: UNIDADES | B26: EMPAQUE | C26: UNIDADES | D26: UND MEDIDA | E26: COSTO UNITARIO | F26: TOTAL COSTO | G26: % PREC. DEFINIDO | H26: CODIGOS
A27: 0 | B27: =IFERROR(VLOOKUP(H27,'[1]Consolidado MP Planta'!$A$2:$M$823,3,0),"") | C27: =+A27 -> 0 | D27: =IFERROR(VLOOKUP(H27,'[1]Consolidado MP Planta'!$A$2:$M$823,13,0),"") | E27: =IFERROR(VLOOKUP(H27,'[1]Consolidado MP Planta'!$A$2:$M$823,12,0),"") | F27: =IFERROR(C27*E27,"") | G27: =IFERROR(F27/$F$66,"")
B28: =IFERROR(VLOOKUP(H28,'[1]Consolidado MP Planta'!$A$2:$M$823,3,0),"") | C28: =+A28 -> 0 | D28: =IFERROR(VLOOKUP(H28,'[1]Consolidado MP Planta'!$A$2:$M$823,13,0),"") | E28: =IFERROR(VLOOKUP(H28,'[1]Consolidado MP Planta'!$A$2:$M$823,12,0),"") | F28: =IFERROR(C28*E28,"") | G28: =IFERROR(F28/$F$66,"")
B29: =IFERROR(VLOOKUP(H29,'[1]Consolidado MP Planta'!$A$2:$M$823,3,0),"") | C29: =+A29 -> 0 | D29: =IFERROR(VLOOKUP(H29,'[1]Consolidado MP Planta'!$A$2:$M$823,13,0),"") | E29: =IFERROR(VLOOKUP(H29,'[1]Consolidado MP Planta'!$A$2:$M$823,12,0),"") | F29: =IFERROR(C29*E29,"") | G29: =IFERROR(F29/$F$66,"")
B30: =IFERROR(VLOOKUP(H30,'[1]Consolidado MP Planta'!$A$2:$M$823,3,0),"") | C30: =+A30 -> 0 | D30: =IFERROR(VLOOKUP(H30,'[1]Consolidado MP Planta'!$A$2:$M$823,13,0),"") | E30: =IFERROR(VLOOKUP(H30,'[1]Consolidado MP Planta'!$A$2:$M$823,12,0),"") | F30: =IFERROR(C30*E30,"") | G30: =IFERROR(F30/$F$66,"")
B31: =IFERROR(VLOOKUP(H31,'[1]Consolidado MP Planta'!$A$2:$M$823,3,0),"") | C31: =+A31 -> 0 | D31: =IFERROR(VLOOKUP(H31,'[1]Consolidado MP Planta'!$A$2:$M$823,13,0),"") | E31: =IFERROR(VLOOKUP(H31,'[1]Consolidado MP Planta'!$A$2:$M$823,12,0),"") | F31: =IFERROR(C31*E31,"") | G31: =IFERROR(F31/$F$66,"")
B32: =IFERROR(VLOOKUP(H32,'[1]Consolidado MP Planta'!$A$2:$M$823,3,0),"") | C32: =+A32 -> 0 | D32: =IFERROR(VLOOKUP(H32,'[1]Consolidado MP Planta'!$A$2:$M$823,13,0),"") | E32: =IFERROR(VLOOKUP(H32,'[1]Consolidado MP Planta'!$A$2:$M$823,12,0),"") | F32: =IFERROR(C32*E32,"") | G32: =IFERROR(F32/$F$66,"")
A34: UNIDADES | B34: EMPAQUE SEMIELABORADOS | C34: UNIDADES | D34: UND MEDIDA | E34: COSTO UNITARIO | F34: TOTAL COSTO | G34: % PREC. DEFINIDO | H34: CODIGOS
A35: =+A17 -> 0 | B35: =IFERROR(VLOOKUP(H35,[1]SEMIELABORADOS!$A$2:$M$6000,2,0),"") | C35: =+A35 -> 0 | D35: =IFERROR(VLOOKUP(H35,[1]SEMIELABORADOS!$A$2:$M$6000,6,0),"") | E35: =IFERROR(VLOOKUP(H35,[1]SEMIELABORADOS!$A$2:$M$65536,10,0),"") | F35: =IFERROR(E35*C35,"") | G35: =IFERROR(F35/$F$66,"")
A36: =+A18 -> 0 | B36: =IFERROR(VLOOKUP(H36,[1]SEMIELABORADOS!$A$2:$M$6000,2,0),"") | C36: =+A36 -> 0 | D36: =IFERROR(VLOOKUP(H36,[1]SEMIELABORADOS!$A$2:$M$6000,6,0),"") | E36: =IFERROR(VLOOKUP(H36,[1]SEMIELABORADOS!$A$2:$M$65536,10,0),"") | F36: =IFERROR(E36*C36,"") | G36: =IFERROR(F36/$F$66,"")
A37: =+A19 -> 0 | B37: =IFERROR(VLOOKUP(H37,[1]SEMIELABORADOS!$A$2:$M$6000,2,0),"") | C37: =+A37 -> 0 | D37: =IFERROR(VLOOKUP(H37,[1]SEMIELABORADOS!$A$2:$M$6000,6,0),"") | E37: =IFERROR(VLOOKUP(H37,[1]SEMIELABORADOS!$A$2:$M$65536,10,0),"") | F37: =IFERROR(E37*C37,"") | G37: =IFERROR(F37/$F$66,"")
A38: =+A20 -> 0 | B38: =IFERROR(VLOOKUP(H38,[1]SEMIELABORADOS!$A$2:$M$6000,2,0),"") | C38: =+A38 -> 0 | D38: =IFERROR(VLOOKUP(H38,[1]SEMIELABORADOS!$A$2:$M$6000,6,0),"") | E38: =IFERROR(VLOOKUP(H38,[1]SEMIELABORADOS!$A$2:$M$65536,10,0),"") | F38: =IFERROR(E38*C38,"") | G38: =IFERROR(F38/$F$66,"")
A39: =+A21 -> 0 | B39: =IFERROR(VLOOKUP(H39,[1]SEMIELABORADOS!$A$2:$M$6000,2,0),"") | C39: =+A39 -> 0 | D39: =IFERROR(VLOOKUP(H39,[1]SEMIELABORADOS!$A$2:$M$6000,6,0),"") | E39: =IFERROR(VLOOKUP(H39,[1]SEMIELABORADOS!$A$2:$M$65536,10,0),"") | F39: =IFERROR(E39*C39,"") | G39: =IFERROR(F39/$F$66,"")
A40: =+A22 -> 0 | B40: =IFERROR(VLOOKUP(H40,[1]SEMIELABORADOS!$A$2:$M$6000,2,0),"") | C40: =+A40 -> 0 | D40: =IFERROR(VLOOKUP(H40,[1]SEMIELABORADOS!$A$2:$M$6000,6,0),"") | E40: =IFERROR(VLOOKUP(H40,[1]SEMIELABORADOS!$A$2:$M$65536,10,0),"") | F40: =IFERROR(E40*C40,"") | G40: =IFERROR(F40/$F$66,"")
A41: =+A23 -> 0 | B41: =IFERROR(VLOOKUP(H41,[1]SEMIELABORADOS!$A$2:$M$6000,2,0),"") | C41: =+A41 -> 0 | D41: =IFERROR(VLOOKUP(H41,[1]SEMIELABORADOS!$A$2:$M$6000,6,0),"") | E41: =IFERROR(VLOOKUP(H41,[1]SEMIELABORADOS!$A$2:$M$65536,10,0),"") | F41: =IFERROR(E41*C41,"") | G41: =IFERROR(F41/$F$66,"")
A43: UNIDADES | B43: MODI | C43: UNIDADES | D43: UND MEDIDA | E43: COSTO UNITARIO | F43: TOTAL COSTO | G43: % PREC. DEFINIDO | H43: CODIGOS
A44: =+A35 -> 0 | B44: =IFERROR(VLOOKUP(H44,[1]SEMIELABORADOS!$A$2:$M$6000,2,0),"") | C44: =+A44 -> 0 | D44: =IFERROR(VLOOKUP(H44,[1]SEMIELABORADOS!$A$2:$M$6000,6,0),"") | E44: =IFERROR(VLOOKUP(H44,[1]SEMIELABORADOS!$A$2:$M$65536,12,0),"") | F44: =IFERROR(E44*C44,"") | G44: =IFERROR(F44/$F$66,"")
A45: =+A36 -> 0 | B45: =IFERROR(VLOOKUP(H45,[1]SEMIELABORADOS!$A$2:$M$6000,2,0),"") | C45: =+A45 -> 0 | D45: =IFERROR(VLOOKUP(H45,[1]SEMIELABORADOS!$A$2:$M$6000,6,0),"") | E45: =IFERROR(VLOOKUP(H45,[1]SEMIELABORADOS!$A$2:$M$65536,12,0),"") | F45: =IFERROR(E45*C45,"") | G45: =IFERROR(F45/$F$66,"")
A46: =+A37 -> 0 | B46: =IFERROR(VLOOKUP(H46,[1]SEMIELABORADOS!$A$2:$M$6000,2,0),"") | C46: =+A46 -> 0 | D46: =IFERROR(VLOOKUP(H46,[1]SEMIELABORADOS!$A$2:$M$6000,6,0),"") | E46: =IFERROR(VLOOKUP(H46,[1]SEMIELABORADOS!$A$2:$M$65536,12,0),"") | F46: =IFERROR(E46*C46,"") | G46: =IFERROR(F46/$F$66,"")
A47: =+A38 -> 0 | B47: =IFERROR(VLOOKUP(H47,[1]SEMIELABORADOS!$A$2:$M$6000,2,0),"") | C47: =+A47 -> 0 | D47: =IFERROR(VLOOKUP(H47,[1]SEMIELABORADOS!$A$2:$M$6000,6,0),"") | E47: =IFERROR(VLOOKUP(H47,[1]SEMIELABORADOS!$A$2:$M$65536,12,0),"") | F47: =IFERROR(E47*C47,"") | G47: =IFERROR(F47/$F$66,"")
A48: =+A39 -> 0 | B48: =IFERROR(VLOOKUP(H48,[1]SEMIELABORADOS!$A$2:$M$6000,2,0),"") | C48: =+A48 -> 0 | D48: =IFERROR(VLOOKUP(H48,[1]SEMIELABORADOS!$A$2:$M$6000,6,0),"") | E48: =IFERROR(VLOOKUP(H48,[1]SEMIELABORADOS!$A$2:$M$65536,12,0),"") | F48: =IFERROR(E48*C48,"") | G48: =IFERROR(F48/$F$66,"")
A49: =+A40 -> 0 | B49: =IFERROR(VLOOKUP(H49,[1]SEMIELABORADOS!$A$2:$M$6000,2,0),"") | C49: =+A49 -> 0 | D49: =IFERROR(VLOOKUP(H49,[1]SEMIELABORADOS!$A$2:$M$6000,6,0),"") | E49: =IFERROR(VLOOKUP(H49,[1]SEMIELABORADOS!$A$2:$M$65536,12,0),"") | F49: =IFERROR(E49*C49,"") | G49: =IFERROR(F49/$F$66,"")
A50: =+A41 -> 0 | B50: =IFERROR(VLOOKUP(H50,[1]SEMIELABORADOS!$A$2:$M$6000,2,0),"") | C50: =+A50 -> 0 | D50: =IFERROR(VLOOKUP(H50,[1]SEMIELABORADOS!$A$2:$M$6000,6,0),"") | E50: =IFERROR(VLOOKUP(H50,[1]SEMIELABORADOS!$A$2:$M$65536,12,0),"") | F50: =IFERROR(E50*C50,"") | G50: =IFERROR(F50/$F$66,"")
A51: 1 | B51: MODI PREPARACION | C51: =+A51 -> 1 | D51: N/A | E51: =+F65 -> 1220 | F51: =IFERROR(C51*E51,"") -> 1220 | G51: =IFERROR(F51/$F$66,"") -> 0.043582069
B53: TOTAL MATERIA PRIMA | F53: =SUM(F8:F14,F17:F24) -> 26248.2 | G53: =+F53/$F$66 -> 0.93766464 | H53: =+F53/$D$60 -> 26248.2
B54: TOTAL EMPAQUE | F54: =SUM(F27:F32,F35:F41) -> 0 | G54: =+F54/$F$66 -> 0 | H54: =+F54/$D$60 -> 0 | K54: TOTAL MATERIA PRIMA + EMPAQUE | O54: =+F55 -> 26248.2
B55: TOTAL MATERIAS P. + EMPAQUES | F55: =+F53+F54 -> 26248.2 | G55: =+F55/$F$66 -> 0.93766464 | H55: =+F55/$D$60 -> 26248.2 | M55: MODI PLANTA | O55: =+H56 -> 1220
C56: TOTAL MODI | F56: =SUM(F44:F51) -> 1220 | G56: =+F56/$F$66 -> 0.043582069 | H56: =+F56/$D$60 -> 1220 | M56: DESECHO | O56: =O54*N56 -> 0
M57: COSTO PLANTA | O57: =SUM(O54:O56) -> 27468.2
B58: GRAMOS | D58: 10000 | H58: =+H56/61 -> 20 | M58: % GIF | O58: =+H59 -> 1160
B59: PESO POR UNIDAD | D59: 10000 | H59: =+H58*58 -> 1160 | M59: COSTO PLANTA | O59: =SUM(O57:O58) -> 28628.2
B60: UNIDADES TOTALES | D60: =+D58/D59 -> 1 | O60: =+O59*N60 -> 0
B61: UNIDAD MEDIDA | K61: PRECIO DE VENTA PLANTA A LOCAL | O61: =SUM(O59:O60) -> 28628.2 | P61: GR
E62: S/ COSTO | F62: TOTAL | L62: UNIDAD | O62: =+O61/D60 -> 28628.2 | P62: =+O62/D59 -> 2.86282
B63: TOTAL MATERIAS P. + EMPAQUES | E63: =+F63/F63 -> 1 | F63: =SUM(F55) -> 26248.2 | G63: =+F63/$F$66 -> 0.93766464
B64: DESECHOS Y PERDIDAS | E64: 0.02 | F64: =+F53*E64 -> 524.964 | G64: =+F64/$F$66 -> 0.018753293
B65: MANO OBRA DIRECTA | D65: 20 | E65: 61 | F65: =+E65*D65 -> 1220 | G65: =+F65/$F$66 -> 0.043582069
B66: TOTAL COSTO PLANTA | F66: =SUM(F63:F65) -> 27993.164 | G66: =+F66/$F$66 -> 1 | M66: MODI 61 COLONES X MIN
M67: Gf 58 colones min
B68: COSTO POR GRAMO | M68: ,
B69: TOTAL COSTO MATERIA PRIMA | C69: =+F53 -> 26248.2 | D69: =+D58 -> 10000 | E69: =+C69/D69 -> 2.62482
B71: TOTAL COSTO UNIDAD MP+DESECHO+EMPAQUE | C71: =SUM(F63:F64) -> 26773.164 | D71: =+D58 -> 10000 | E71: =+C71/D71 -> 2.6773164
B73: TOTAL MODI PREPARACION POR GRAMO | C73: =+F65 -> 1220 | D73: =+D58 -> 10000 | E73: =+C73/D73 -> 0.122
B74: TOTAL MODI POR GRAMO | C74: =+F56 -> 1220 | D74: =+D73 -> 10000 | E74: =+C74/D74 -> 0.122
B76: TOTAL EMPAQUE POR GRAMO | C76: =+F54 -> 0 | D76: =+D74 -> 10000 | E76: =+C76/D76 -> 0
B78: TOTAL GRAMO MP+MODI | E78: =+E69+E74 -> 2.74682
B80: COSTO POR UNIDAD
B81: TOTAL COSTO MATERIA PRIMA | C81: =+C69 -> 26248.2 | D81: =+D60 -> 1 | E81: =+C81/D81 -> 26248.2
B83: TOTAL COSTO UNIDAD MP+DESECHO+EMPAQUE | C83: =+C71 -> 26773.164 | D83: =+D60 -> 1 | E83: =+C83/D83 -> 26773.164
B85: TOTAL MODI POR GRAMO | C85: =+C73 -> 1220 | D85: =+D60 -> 1 | E85: =+C85/D85 -> 1220
B86: TOTAL MODI POR GRAMO | C86: =+C74 -> 1220 | D86: =+D85 -> 1 | E86: =+C86/D86 -> 1220
