Workbook

Sheet Hoja1
C1: SERVICIOS DE PASTELERIA S.A. | H1: CÓDIGO: | I1: ESP-RE-POS-039
C2: ESPECIFICACION DE RECETA | H2: REVISIÓN: | I2: 02
C3: 902000116(SE00299) Brittle de almendras | H3: FECHA DE APROBACIÓN: | I3: 45615
C4: Elaborado | D4: Javier Tong, Chef
C5: Aprobado | D5: Esteban Cartin, Gte Manufactura
A6: AREA QUE PRODUCE: | D6: Postres | G6: AREA QUE EMPACA: | I6: Postres
A7: # Código | B7: # Código Netsuite | C7: Descripción del ingrediente | D7: Marca | E7: Unidad Internacional | G7: Medida alternativa | I7: Costo - Referencia
E8: Cantidad | F8: Unidad medida | G8: Cantidad | H8: Unidad medida | I8: Colones
C9: Ensamble
A10: 90100131 | B10: SE00016 | C10: AZUCAR BLANCO INDUSTRIAL KILO | D10: FAS | E10: 1080 | F10: g
A11: 10100048 | B11: MP10573 | C11: SIROPE KARO DARK | D11: KARO | E11: 450 | F11: g
A12: 0310107 | B12: MP10022 | C12: LACTOCREMA GRANEL | D12: DOS PINOS | E12: 145 | F12: g
A13: 503000036 | B13: MP10085 | C13: BICARBONATO DE SODIO | D13: MAYCA | E13: 7 | F13: g
A14: 90100142 | B14: SE00104 | C14: EMPAQUE SAL KILO | D14: FAS | E14: 3 | F14: g
A15: 11900029 | B15: MP10591 | C15: ALMENDRA ENTERA | D15: NUECES INDUSTRIALES | E15: 630 | F15: g
C16: Agua | D16: FAS | E16: 180 | F16: g
C21: Decoración
C30: Empaque
A31: 512000002 | B31: EM10259 | C31: PLÁSTICO AUTOADERIBLE 1/ 18*2000 | E31: 1 | F31: metro
A32: 702067 | B32: EM10120 | C32: ETIQ.BLANCA 1 13/16 * 1 7/8 | D32: ETIPLAST | E32: 1 | F32: ud
D43: Cantidad | E43: Unidad
A44: PESO TOTAL OBTENIDO | D44: 2000 | E44: g | F44: Tiempo de Horneo:
A45: TIEMPO TOTAL DE PREPARACION | D45: 20 | E45: min | F45: Horno:
A46: CANTIDAD DE PORCIONES OBTENIDAS | D46: 1 | E46: tanda | F46: Temperatura de Horneo:
A47: PESO DE CADA PORCIÓN | D47: 2000 | E47: g | F47: Otros
A48: MERMA | D48: =SUM(E10:E16)-D44 -> 495
A49: PROCEDIMIENTO DE PREPARACION DE LA RECETA
A50: 1, Colocar el azucar junto con el agua, sirope en una olla y cocinar hasta tomar punto caramelo.
A51: 3, Agregar lactocrema, bicarbonato y sal y mezclar bien. Si le falta color seguir dandole punto.
A52: 3, Colocar sobre bandejas con lamina de silicon las almendras bien esparcidas, Agregar el caramelo anterior cubriendolas muy bien.
A53: 4, Dejar que enfrie a temp ambiente.
A54: 5, Pasar po la maquina para quebrar.
A55: 6,Etiquetar y emplasticar
A58: CONTROL DE CAMBIOS
A59: 2, Actualización ingredientes, se agrega agua a la receta y actualización merma

Sheet costeo brittle
E1: Precio Local | F1: Costo MP | G1: Costo EM | H1: Costo MO
E2: =IFERROR(O62,"") -> 8928.7531 | F2: =IFERROR(H53,"") -> 5531.4857 | G2: =IFERROR(H54,"") -> 75.675814 | H2: =IFERROR(H56,"") -> 1139.6264
A5: ESTRUCTURA DE COSTOS
F6: Fecha: | H6: =TODAY() -> 45754
A7: UNIDADES | B7: DESCRIPCION MAT.PRIMA | C7: UNIDADES | D7: UND MEDIDA | E7: COSTO UNITARIO | F7: TOTAL COSTO | G7: % PREC. DEFINIDO | H7: CODIGOS
A8: 180 | B8: =IFERROR(VLOOKUP(H8,'[1]Consolidado MP Planta'!$A$2:$M$823,3,0),"") -> AGUA PLANTA | C8: =+A8 -> 180 | D8: =IFERROR(VLOOKUP(H8,'[1]Consolidado MP Planta'!$A$2:$M$823,13,0),"") -> Mililitros | E8: =IFERROR(VLOOKUP(H8,'[1]Consolidado MP Planta'!$A$2:$M$823,12,0),"") -> 0.1 | F8: =IFERROR(C8*E8,"") -> 18 | G8: =IFERROR(F8/$F$66,"") -> 0.0026401512 | H8: 10415
A9: 450 | B9: =IFERROR(VLOOKUP(H9,'[1]Consolidado MP Planta'!$A$2:$M$823,3,0),"") -> SIROPE KARO DARK (UND: 3.78 K) | C9: =+A9 -> 450 | D9: =IFERROR(VLOOKUP(H9,'[1]Consolidado MP Planta'!$A$2:$M$823,13,0),"") -> Mililitros | E9: =IFERROR(VLOOKUP(H9,'[1]Consolidado MP Planta'!$A$2:$M$823,12,0),"") -> 2.5428571 | F9: =IFERROR(C9*E9,"") -> 1144.2857 | G9: =IFERROR(F9/$F$66,"") -> 0.16783819 | H9: 10100048
A10: 145 | B10: =IFERROR(VLOOKUP(H10,'[1]Consolidado MP Planta'!$A$2:$M$823,3,0),"") -> LACTOCREMA GRANEL (CAJA:25 KG) | C10: =+A10 -> 145 | D10: =IFERROR(VLOOKUP(H10,'[1]Consolidado MP Planta'!$A$2:$M$823,13,0),"") -> Gramos | E10: =IFERROR(VLOOKUP(H10,'[1]Consolidado MP Planta'!$A$2:$M$823,12,0),"") -> 3.055 | F10: =IFERROR(C10*E10,"") -> 442.975 | G10: =IFERROR(F10/$F$66,"") -> 0.064973389 | H10: 0310107
A11: 7 | B11: =IFERROR(VLOOKUP(H11,'[1]Consolidado MP Planta'!$A$2:$M$823,3,0),"") -> BICARBONATO DE SODIO (PAQ:2.5 K) | C11: =+A11 -> 7 | D11: =IFERROR(VLOOKUP(H11,'[1]Consolidado MP Planta'!$A$2:$M$823,13,0),"") -> Gramos | E11: =IFERROR(VLOOKUP(H11,'[1]Consolidado MP Planta'!$A$2:$M$823,12,0),"") -> 0.70658 | F11: =IFERROR(C11*E11,"") -> 4.94606 | G11: =IFERROR(F11/$F$66,"") -> 0.00072546369 | H11: 503000036
A12: 630 | B12: =IFERROR(VLOOKUP(H12,'[1]Consolidado MP Planta'!$A$2:$M$823,3,0),"") -> ALMENDRA ENTERA (CAJA:12 KG) | C12: =+A12 -> 630 | D12: =IFERROR(VLOOKUP(H12,'[1]Consolidado MP Planta'!$A$2:$M$823,13,0),"") -> Gramos | E12: =IFERROR(VLOOKUP(H12,'[1]Consolidado MP Planta'!$A$2:$M$823,12,0),"") -> 5.5533075 | F12: =IFERROR(C12*E12,"") -> 3498.5837 | G12: =IFERROR(F12/$F$66,"") -> 0.51315501 | H12: 510149
B13: =IFERROR(VLOOKUP(H13,'[1]Consolidado MP Planta'!$A$2:$M$823,3,0),"") | C13: =+A13 -> 0 | D13: =IFERROR(VLOOKUP(H13,'[1]Consolidado MP Planta'!$A$2:$M$823,13,0),"") | E13: =IFERROR(VLOOKUP(H13,'[1]Consolidado MP Planta'!$A$2:$M$823,12,0),"") | F13: =IFERROR(C13*E13,"") | G13: =IFERROR(F13/$F$66,"")
B14: =IFERROR(VLOOKUP(H14,'[1]Consolidado MP Planta'!$A$2:$M$823,3,0),"") | C14: =+A14 -> 0 | D14: =IFERROR(VLOOKUP(H14,'[1]Consolidado MP Planta'!$A$2:$M$823,13,0),"") | E14: =IFERROR(VLOOKUP(H14,'[1]Consolidado MP Planta'!$A$2:$M$823,12,0),"") | F14: =IFERROR(C14*E14,"") | G14: =IFERROR(F14/$F$66,"")
B15: =IFERROR(VLOOKUP(H15,'[2]ARTICULOS MP PLANTA'!$A$2:$G$589,2,0),"")
A16: UNIDADES | B16: MATERIA PRIMA SEMIELABORADOS | C16: UNIDADES | D16: UND MEDIDA | E16: COSTO UNITARIO | F16: TOTAL COSTO | G16: % PREC. DEFINIDO | H16: CODIGOS
A17: 1080 | B17: =IFERROR(VLOOKUP(H17,[1]SEMIELABORADOS!$A$2:$M$6000,2,0),"") -> AZUCAR BLANCO INDUSTRIAL KILO | C17: =+A17 -> 1080 | D17: =IFERROR(VLOOKUP(H17,[1]SEMIELABORADOS!$A$2:$M$6000,6,0),"") -> Gramo | E17: =IFERROR(VLOOKUP(H17,[1]SEMIELABORADOS!$A$2:$H$65536,8,0),"") -> 0.39034 | F17: =IFERROR(E17*C17,"") -> 421.5672 | G17: =IFERROR(F17/$F$66,"") -> 0.061833398 | H17: 90100131
A18: 3 | B18: =IFERROR(VLOOKUP(H18,[1]SEMIELABORADOS!$A$2:$M$6000,2,0),"") -> EMPAQUE SAL KILO | C18: =+A18 -> 3 | D18: =IFERROR(VLOOKUP(H18,[1]SEMIELABORADOS!$A$2:$M$6000,6,0),"") -> Gramo | E18: =IFERROR(VLOOKUP(H18,[1]SEMIELABORADOS!$A$2:$H$65536,8,0),"") -> 0.376 | F18: =IFERROR(E18*C18,"") -> 1.128 | G18: =IFERROR(F18/$F$66,"") -> 0.00016544948 | H18: 90100142
B19: =IFERROR(VLOOKUP(H19,[1]SEMIELABORADOS!$A$2:$M$6000,2,0),"") | C19: =+A19 -> 0 | D19: =IFERROR(VLOOKUP(H19,[1]SEMIELABORADOS!$A$2:$M$6000,6,0),"") | E19: =IFERROR(VLOOKUP(H19,[1]SEMIELABORADOS!$A$2:$H$65536,8,0),"") | F19: =IFERROR(E19*C19,"") | G19: =IFERROR(F19/$F$66,"")
B20: =IFERROR(VLOOKUP(H20,[1]SEMIELABORADOS!$A$2:$M$6000,2,0),"") | C20: =+A20 -> 0 | D20: =IFERROR(VLOOKUP(H20,[1]SEMIELABORADOS!$A$2:$M$6000,6,0),"") | E20: =IFERROR(VLOOKUP(H20,[1]SEMIELABORADOS!$A$2:$H$65536,8,0),"") | F20: =IFERROR(E20*C20,"") | G20: =IFERROR(F20/$F$66,"")
B21: =IFERROR(VLOOKUP(H21,[1]SEMIELABORADOS!$A$2:$M$6000,2,0),"") | C21: =+A21 -> 0 | D21: =IFERROR(VLOOKUP(H21,[1]SEMIELABORADOS!$A$2:$M$6000,6,0),"") | E21: =IFERROR(VLOOKUP(H21,[1]SEMIELABORADOS!$A$2:$H$65536,8,0),"") | F21: =IFERROR(E21*C21,"") | G21: =IFERROR(F21/$F$66,"")
B22: =IFERROR(VLOOKUP(H22,[1]SEMIELABORADOS!$A$2:$M$6000,2,0),"") | C22: =+A22 -> 0 | D22: =IFERROR(VLOOKUP(H22,[1]SEMIELABORADOS!$A$2:$M$6000,6,0),"") | E22: =IFERROR(VLOOKUP(H22,[1]SEMIELABORADOS!$A$2:$H$65536,8,0),"") | F22: =IFERROR(E22*C22,"") | G22: =IFERROR(F22/$F$66,"")
B23: =IFERROR(VLOOKUP(H23,[1]SEMIELABORADOS!$A$2:$M$6000,2,0),"") | C23: =+A23 -> 0 | D23: =IFERROR(VLOOKUP(H23,[1]SEMIELABORADOS!$A$2:$M$6000,6,0),"") | E23: =IFERROR(VLOOKUP(H23,[1]SEMIELABORADOS!$A$2:$H$65536,8,0),"") | F23: =IFERROR(E23*C23,"") | G23: =IFERROR(F23/$F$66,"")
B24: =IFERROR(VLOOKUP(H24,[1]SEMIELABORADOS!$A$2:$M$6000,2,0),"") | C24: =+A24 -> 0 | D24: =IFERROR(VLOOKUP(H24,[1]SEMIELABORADOS!$A$2:$M$6000,6,0),"") | E24: =IFERROR(VLOOKUP(H24,[1]SEMIELABORADOS!$A$2:$H$65536,8,0),"") | F24: =IFERROR(E24*C24,"") | G24: =IFERROR(F24/$F$66,"")
A26: UNIDADES | B26: EMPAQUE | C26: UNIDADES | D26: UND MEDIDA | E26: COSTO UNITARIO | F26: TOTAL COSTO | G26: % PREC. DEFINIDO | H26: CODIGOS
A27: 1 | B27: =IFERROR(VLOOKUP(H27,'[1]Consolidado MP Planta'!$A$2:$M$823,3,0),"") -> BOLSA TRANSPARENTE 56X96X1.80 KILO | C27: =+A27 -> 1 | D27: =IFERROR(VLOOKUP(H27,'[1]Consolidado MP Planta'!$A$2:$M$823,13,0),"") -> Und | E27: =IFERROR(VLOOKUP(H27,'[1]Consolidado MP Planta'!$A$2:$M$823,12,0),"") -> 50 | F27: =IFERROR(C27*E27,"") -> 50 | G27: =IFERROR(F27/$F$66,"") -> 0.0073337535 | H27: 1950928
B28: =IFERROR(VLOOKUP(H28,'[1]Consolidado MP Planta'!$A$2:$M$823,3,0),"") | C28: =+A28 -> 0 | D28: =IFERROR(VLOOKUP(H28,'[1]Consolidado MP Planta'!$A$2:$M$823,13,0),"") | E28: =IFERROR(VLOOKUP(H28,'[1]Consolidado MP Planta'!$A$2:$M$823,12,0),"") | F28: =IFERROR(C28*E28,"") | G28: =IFERROR(F28/$F$66,"")
B29: =IFERROR(VLOOKUP(H29,'[1]Consolidado MP Planta'!$A$2:$M$823,3,0),"") | C29: =+A29 -> 0 | D29: =IFERROR(VLOOKUP(H29,'[1]Consolidado MP Planta'!$A$2:$M$823,13,0),"") | E29: =IFERROR(VLOOKUP(H29,'[1]Consolidado MP Planta'!$A$2:$M$823,12,0),"") | F29: =IFERROR(C29*E29,"") | G29: =IFERROR(F29/$F$66,"")
B30: =IFERROR(VLOOKUP(H30,'[1]Consolidado MP Planta'!$A$2:$M$823,3,0),"") | C30: =+A30 -> 0 | D30: =IFERROR(VLOOKUP(H30,'[1]Consolidado MP Planta'!$A$2:$M$823,13,0),"") | E30: =IFERROR(VLOOKUP(H30,'[1]Consolidado MP Planta'!$A$2:$M$823,12,0),"") | F30: =IFERROR(C30*E30,"") | G30: =IFERROR(F30/$F$66,"")
B31: =IFERROR(VLOOKUP(H31,'[1]Consolidado MP Planta'!$A$2:$M$823,3,0),"") | C31: =+A31 -> 0 | D31: =IFERROR(VLOOKUP(H31,'[1]Consolidado MP Planta'!$A$2:$M$823,13,0),"") | E31: =IFERROR(VLOOKUP(H31,'[1]Consolidado MP Planta'!$A$2:$M$823,12,0),"") | F31: =IFERROR(C31*E31,"") | G31: =IFERROR(F31/$F$66,"")
B32: =IFERROR(VLOOKUP(H32,'[1]Consolidado MP Planta'!$A$2:$M$823,3,0),"") | C32: =+A32 -> 0 | D32: =IFERROR(VLOOKUP(H32,'[1]Consolidado MP Planta'!$A$2:$M$823,13,0),"") | E32: =IFERROR(VLOOKUP(H32,'[1]Consolidado MP Planta'!$A$2:$M$823,12,0),"") | F32: =IFERROR(C32*E32,"") | G32: =IFERROR(F32/$F$66,"")
A34: UNIDADES | B34: EMPAQUE SEMIELABORADOS | C34: UNIDADES | D34: UND MEDIDA | E34: COSTO UNITARIO | F34: TOTAL COSTO | G34: % PREC. DEFINIDO | H34: CODIGOS
A35: =+A17 -> 1080 | B35: =IFERROR(VLOOKUP(H35,[1]SEMIELABORADOS!$A$2:$M$6000,2,0),"") -> AZUCAR BLANCO INDUSTRIAL KILO | C35: =+A35 -> 1080 | D35: =IFERROR(VLOOKUP(H35,[1]SEMIELABORADOS!$A$2:$M$6000,6,0),"") -> Gramo | E35: =IFERROR(VLOOKUP(H35,[1]SEMIELABORADOS!$A$2:$M$65536,10,0),"") -> 0.023759093 | F35: =IFERROR(E35*C35,"") -> 25.659821 | G35: =IFERROR(F35/$F$66,"") -> 0.003763656 | H35: 90100131
A36: =+A18 -> 3 | B36: =IFERROR(VLOOKUP(H36,[1]SEMIELABORADOS!$A$2:$M$6000,2,0),"") -> EMPAQUE SAL KILO | C36: =+A36 -> 3 | D36: =IFERROR(VLOOKUP(H36,[1]SEMIELABORADOS!$A$2:$M$6000,6,0),"") -> Gramo | E36: =IFERROR(VLOOKUP(H36,[1]SEMIELABORADOS!$A$2:$M$65536,10,0),"") -> 0.0053312 | F36: =IFERROR(E36*C36,"") -> 0.0159936 | G36: =IFERROR(F36/$F$66,"") -> 2.3458624e-06 | H36: 90100142
A37: =+A19 -> 0 | B37: =IFERROR(VLOOKUP(H37,[1]SEMIELABORADOS!$A$2:$M$6000,2,0),"") | C37: =+A37 -> 0 | D37: =IFERROR(VLOOKUP(H37,[1]SEMIELABORADOS!$A$2:$M$6000,6,0),"") | E37: =IFERROR(VLOOKUP(H37,[1]SEMIELABORADOS!$A$2:$M$65536,10,0),"") | F37: =IFERROR(E37*C37,"") | G37: =IFERROR(F37/$F$66,"")
A38: =+A20 -> 0 | B38: =IFERROR(VLOOKUP(H38,[1]SEMIELABORADOS!$A$2:$M$6000,2,0),"") | C38: =+A38 -> 0 | D38: =IFERROR(VLOOKUP(H38,[1]SEMIELABORADOS!$A$2:$M$6000,6,0),"") | E38: =IFERROR(VLOOKUP(H38,[1]SEMIELABORADOS!$A$2:$M$65536,10,0),"") | F38: =IFERROR(E38*C38,"") | G38: =IFERROR(F38/$F$66,"")
A39: =+A21 -> 0 | B39: =IFERROR(VLOOKUP(H39,[1]SEMIELABORADOS!$A$2:$M$6000,2,0),"") | C39: =+A39 -> 0 | D39: =IFERROR(VLOOKUP(H39,[1]SEMIELABORADOS!$A$2:$M$6000,6,0),"") | E39: =IFERROR(VLOOKUP(H39,[1]SEMIELABORADOS!$A$2:$M$65536,10,0),"") | F39: =IFERROR(E39*C39,"") | G39: =IFERROR(F39/$F$66,"")
A40: =+A22 -> 0 | B40: =IFERROR(VLOOKUP(H40,[1]SEMIELABORADOS!$A$2:$M$6000,2,0),"") | C40: =+A40 -> 0 | D40: =IFERROR(VLOOKUP(H40,[1]SEMIELABORADOS!$A$2:$M$6000,6,0),"") | E40: =IFERROR(VLOOKUP(H40,[1]SEMIELABORADOS!$A$2:$M$65536,10,0),"") | F40: =IFERROR(E40*C40,"") | G40: =IFERROR(F40/$F$66,"")
A41: =+A23 -> 0 | B41: =IFERROR(VLOOKUP(H41,[1]SEMIELABORADOS!$A$2:$M$6000,2,0),"") | C41: =+A41 -> 0 | D41: =IFERROR(VLOOKUP(H41,[1]SEMIELABORADOS!$A$2:$M$6000,6,0),"") | E41: =IFERROR(VLOOKUP(H41,[1]SEMIELABORADOS!$A$2:$M$65536,10,0),"") | F41: =IFERROR(E41*C41,"") | G41: =IFERROR(F41/$F$66,"")
A43: UNIDADES | B43: MODI | C43: UNIDADES | D43: UND MEDIDA | E43: COSTO UNITARIO | F43: TOTAL COSTO | G43: % PREC. DEFINIDO | H43: CODIGOS
A44: =+A35 -> 1080 | B44: =IFERROR(VLOOKUP(H44,[1]SEMIELABORADOS!$A$2:$M$6000,2,0),"") -> AZUCAR BLANCO INDUSTRIAL KILO | C44: =+A44 -> 1080 | D44: =IFERROR(VLOOKUP(H44,[1]SEMIELABORADOS!$A$2:$M$6000,6,0),"") -> Gramo | E44: =IFERROR(VLOOKUP(H44,[1]SEMIELABORADOS!$A$2:$M$65536,12,0),"") -> 0.03663 | F44: =IFERROR(E44*C44,"") -> 39.5604 | G44: =IFERROR(F44/$F$66,"") -> 0.0058025244 | H44: 90100131
A45: =+A36 -> 3 | B45: =IFERROR(VLOOKUP(H45,[1]SEMIELABORADOS!$A$2:$M$6000,2,0),"") -> EMPAQUE SAL KILO | C45: =+A45 -> 3 | D45: =IFERROR(VLOOKUP(H45,[1]SEMIELABORADOS!$A$2:$M$6000,6,0),"") -> Gramo | E45: =IFERROR(VLOOKUP(H45,[1]SEMIELABORADOS!$A$2:$M$65536,12,0),"") -> 0.022 | F45: =IFERROR(E45*C45,"") -> 0.066 | G45: =IFERROR(F45/$F$66,"") -> 9.6805546e-06 | H45: 90100142
A46: =+A37 -> 0 | B46: =IFERROR(VLOOKUP(H46,[1]SEMIELABORADOS!$A$2:$M$6000,2,0),"") | C46: =+A46 -> 0 | D46: =IFERROR(VLOOKUP(H46,[1]SEMIELABORADOS!$A$2:$M$6000,6,0),"") | E46: =IFERROR(VLOOKUP(H46,[1]SEMIELABORADOS!$A$2:$M$65536,12,0),"") | F46: =IFERROR(E46*C46,"") | G46: =IFERROR(F46/$F$66,"")
A47: =+A38 -> 0 | B47: =IFERROR(VLOOKUP(H47,[1]SEMIELABORADOS!$A$2:$M$6000,2,0),"") | C47: =+A47 -> 0 | D47: =IFERROR(VLOOKUP(H47,[1]SEMIELABORADOS!$A$2:$M$6000,6,0),"") | E47: =IFERROR(VLOOKUP(H47,[1]SEMIELABORADOS!$A$2:$M$65536,12,0),"") | F47: =IFERROR(E47*C47,"") | G47: =IFERROR(F47/$F$66,"")
A48: =+A39 -> 0 | B48: =IFERROR(VLOOKUP(H48,[1]SEMIELABORADOS!$A$2:$M$6000,2,0),"") | C48: =+A48 -> 0 | D48: =IFERROR(VLOOKUP(H48,[1]SEMIELABORADOS!$A$2:$M$6000,6,0),"") | E48: =IFERROR(VLOOKUP(H48,[1]SEMIELABORADOS!$A$2:$M$65536,12,0),"") | F48: =IFERROR(E48*C48,"") | G48: =IFERROR(F48/$F$66,"")
A49: =+A40 -> 0 | B49: =IFERROR(VLOOKUP(H49,[1]SEMIELABORADOS!$A$2:$M$6000,2,0),"") | C49: =+A49 -> 0 | D49: =IFERROR(VLOOKUP(H49,[1]SEMIELABORADOS!$A$2:$M$6000,6,0),"") | E49: =IFERROR(VLOOKUP(H49,[1]SEMIELABORADOS!$A$2:$M$65536,12,0),"") | F49: =IFERROR(E49*C49,"") | G49: =IFERROR(F49/$F$66,"")
A50: =+A41 -> 0 | B50: =IFERROR(VLOOKUP(H50,[1]SEMIELABORADOS!$A$2:$M$6000,2,0),"") | C50: =+A50 -> 0 | D50: =IFERROR(VLOOKUP(H50,[1]SEMIELABORADOS!$A$2:$M$6000,6,0),"") | E50: =IFERROR(VLOOKUP(H50,[1]SEMIELABORADOS!$A$2:$M$65536,12,0),"") | F50: =IFERROR(E50*C50,"") | G50: =IFERROR(F50/$F$66,"")
A51: 1 | B51: MODI PREPARACION | C51: =+A51 -> 1 | D51: N/A | E51: =+F65 -> 1100 | F51: =IFERROR(C51*E51,"") -> 1100 | G51: =IFERROR(F51/$F$66,"") -> 0.16134258
B53: TOTAL MATERIA PRIMA | F53: =SUM(F8:F14,F17:F24) -> 5531.4857 | G53: =+F53/$F$66 -> 0.81133105 | H53: =+F53/$D$60 -> 5531.4857
B54: TOTAL EMPAQUE | F54: =SUM(F27:F32,F35:F41) -> 75.675814 | G54: =+F54/$F$66 -> 0.011099755 | H54: =+F54/$D$60 -> 75.675814 | K54: TOTAL MATERIA PRIMA + EMPAQUE | O54: =+F55 -> 5607.1615
B55: TOTAL MATERIAS P. + EMPAQUES | F55: =+F53+F54 -> 5607.1615 | G55: =+F55/$F$66 -> 0.8224308 | H55: =+F55/$D$60 -> 5607.1615 | L55: MODI PLANTA | O55: =+F56 -> 1139.6264
C56: TOTAL MODI | F56: =SUM(F44:F51) -> 1139.6264 | G56: =+F56/$F$66 -> 0.16715478 | H56: =+F56/$D$60 -> 1139.6264 | M56: DESECHO | N56: 0.01 | O56: =O54*N56 -> 56.071615
M57: COSTO PLANTA | O57: =SUM(O54:O56) -> 6802.8595
B58: GRAMOS | D58: 2000 | M58: % MK | N58: 0.25 | O58: =+O57*N58 -> 1700.7149
B59: PESO POR UNIDAD | D59: 2000 | M59: COSTO PLANTA | O59: =SUM(O57:O58) -> 8503.5744
B60: UNIDADES TOTALES | D60: =+D58/D59 -> 1 | L60: TRANSFERENCIA | N60: 0.05 | O60: =+O59*N60 -> 425.17872
B61: UNIDAD MEDIDA | D61: TANDA | K61: PRECIO DE VENTA PLANTA A LOCAL | O61: =SUM(O59:O60) -> 8928.7531 | P61: GR
E62: S/ COSTO | F62: TOTAL | L62: UNIDAD | O62: =+O61/D60 -> 8928.7531 | P62: =+O62/D59 -> 4.4643766
B63: TOTAL MATERIAS P. + EMPAQUES | E63: =+F63/F63 -> 1 | F63: =SUM(F55) -> 5607.1615 | G63: =+F63/$F$66 -> 0.8224308
B64: DESECHOS Y PERDIDAS | E64: 0.02 | F64: =+F53*E64 -> 110.62971 | G64: =+F64/$F$66 -> 0.016226621
B65: MANO OBRA DIRECTA | D65: 20 | E65: 55 | F65: =+E65*D65 -> 1100 | G65: =+F65/$F$66 -> 0.16134258
B66: TOTAL COSTO PLANTA | F66: =SUM(F63:F65) -> 6817.7912 | G66: =+F66/$F$66 -> 1
B68: COSTO POR GRAMO
B69: TOTAL COSTO MATERIA PRIMA | C69: =+F53 -> 5531.4857 | D69: =+D58 -> 2000 | E69: =+C69/D69 -> 2.7657428
B71: TOTAL COSTO UNIDAD MP+DESECHO+EMPAQUE | C71: =SUM(F63:F64) -> 5717.7912 | D71: =+D58 -> 2000 | E71: =+C71/D71 -> 2.8588956
B73: TOTAL MODI PREPARACION POR GRAMO | C73: =+F65 -> 1100 | D73: =+D58 -> 2000 | E73: =+C73/D73 -> 0.55
B74: TOTAL MODI POR GRAMO | C74: =+F56 -> 1139.6264 | D74: =+D73 -> 2000 | E74: =+C74/D74 -> 0.5698132
B76: TOTAL EMPAQUE POR GRAMO | C76: =+F54 -> 75.675814 | D76: =+D74 -> 2000 | E76: =+C76/D76 -> 0.037837907
B78: TOTAL GRAMO MP+MODI | E78: =+E69+E74 -> 3.335556
B80: COSTO POR UNIDAD
B81: TOTAL COSTO MATERIA PRIMA | C81: =+C69 -> 5531.4857 | D81: =+D60 -> 1 | E81: =+C81/D81 -> 5531.4857
B83: TOTAL COSTO UNIDAD MP+DESECHO+EMPAQUE | C83: =+C71 -> 5717.7912 | D83: =+D60 -> 1 | E83: =+C83/D83 -> 5717.7912
B85: TOTAL MODI POR GRAMO | C85: =+C73 -> 1100 | D85: =+D60 -> 1 | E85: =+C85/D85 -> 1100
B86: TOTAL MODI POR GRAMO | C86: =+C74 -> 1139.6264 | D86: =+D85 -> 1 | E86: =+C86/D86 -> 1139.6264

Sheet EMPAQUE BRITTLE
B1: SERVICIOS DE PASTELERIA S.A. | G1: CÓDIGO:
B2: ESPECIFICACION DE RECETA | G2: REVISIÓN:
B3: Empaque Brittle almendras 160g | G3: FECHA DE APROBACIÓN:
B4: Elaborado | C4: Javier Tong, Chef
B5: Aprobado | C5: Esteban Cartin, Gte Manufactura
A7: AREA QUE PRODUCE: | C7: Postre | F7: AREA QUE EMPACA: | H7: Postre
A8: # Código | B8: Descripción del ingrediente | C8: Marca | D8: Unidad Internacional | F8: Medida alternativa | H8: Costo - Referencia
D9: Cantidad | E9: Unidad medida | F9: Cantidad | G9: Unidad medida | H9: Colones
A10: 902000116 | B10: BRITTLE DE ALMENDRAS | C10: FAS | D10: 160 | E10: g
A13: 1950705 | B13: BOLSA 8x12 TRANSPARENTE KILO | C13: CEMUSA | D13: 1 | E13: ud
A14: 702069 | B14: ETIQ.BLANCA 1 1/4 * 3/4 (UND) | C14: CEMUSA | D14: 1 | E14: ud
A15: 701096 | B15: ETIQUETA BLANCA R-153 (UND) | C15: Cemusa | D15: 1 | E15: ud
A16: 702007 | B16: ETIQ.FECHA VENCIMIENTO BLANCO (ROLLO) | C16: CEMUSA | D16: 1 | E16: ud
C18: Cantidad | D18: Unidad
A19: PESO TOTAL OBTENIDO | C19: 160 | D19: g
A20: TIEMPO TOTAL DE PREPARACION | C20: 30 | D20: SEG
A21: CANTIDAD DE PORCIONES OBTENIDAS | C21: 1 | D21: ud
A22: PESO DE CADA PORCIÓN | C22: 160 | D22: g
A23: MERMA | C23: 0 | D23: g
A24: PROCEDIMIENTO DE PREPARACION DE LA RECETA
A25: 1, Empacar 160g de Brittle en una bolsa 8*12, hacer nudo
A26: 2, Etiquetar

Sheet COSTO EMPAQUE BRITTLE
E1: Precio Local | F1: Costo MP | G1: Costo EM | H1: Costo MO
E2: =IFERROR(O62,"") -> 691.90292 | F2: =IFERROR(H53,"") -> 442.51886 | G2: =IFERROR(H54,"") -> 14.204065 | H2: =IFERROR(H56,"") -> 118.67011
A5: ESTRUCTURA DE COSTOS
F6: Fecha: | H6: =TODAY() -> 45754
A7: UNIDADES | B7: DESCRIPCION MAT.PRIMA | C7: UNIDADES | D7: UND MEDIDA | E7: COSTO UNITARIO | F7: TOTAL COSTO | G7: % PREC. DEFINIDO | H7: CODIGOS
B8: =IFERROR(VLOOKUP(H8,'[1]Consolidado MP Planta'!$A$2:$M$823,3,0),"") | C8: =+A8 -> 0 | D8: =IFERROR(VLOOKUP(H8,'[1]Consolidado MP Planta'!$A$2:$M$823,13,0),"") | E8: =IFERROR(VLOOKUP(H8,'[1]Consolidado MP Planta'!$A$2:$M$823,12,0),"") | F8: =IFERROR(C8*E8,"") | G8: =IFERROR(F8/$F$66,"")
B9: =IFERROR(VLOOKUP(H9,'[1]Consolidado MP Planta'!$A$2:$M$823,3,0),"") | C9: =+A9 -> 0 | D9: =IFERROR(VLOOKUP(H9,'[1]Consolidado MP Planta'!$A$2:$M$823,13,0),"") | E9: =IFERROR(VLOOKUP(H9,'[1]Consolidado MP Planta'!$A$2:$M$823,12,0),"") | F9: =IFERROR(C9*E9,"") | G9: =IFERROR(F9/$F$66,"")
B10: =IFERROR(VLOOKUP(H10,'[1]Consolidado MP Planta'!$A$2:$M$823,3,0),"") | C10: =+A10 -> 0 | D10: =IFERROR(VLOOKUP(H10,'[1]Consolidado MP Planta'!$A$2:$M$823,13,0),"") | E10: =IFERROR(VLOOKUP(H10,'[1]Consolidado MP Planta'!$A$2:$M$823,12,0),"") | F10: =IFERROR(C10*E10,"") | G10: =IFERROR(F10/$F$66,"")
B11: =IFERROR(VLOOKUP(H11,'[1]Consolidado MP Planta'!$A$2:$M$823,3,0),"") | C11: =+A11 -> 0 | D11: =IFERROR(VLOOKUP(H11,'[1]Consolidado MP Planta'!$A$2:$M$823,13,0),"") | E11: =IFERROR(VLOOKUP(H11,'[1]Consolidado MP Planta'!$A$2:$M$823,12,0),"") | F11: =IFERROR(C11*E11,"") | G11: =IFERROR(F11/$F$66,"")
B12: =IFERROR(VLOOKUP(H12,'[1]Consolidado MP Planta'!$A$2:$M$823,3,0),"") | C12: =+A12 -> 0 | D12: =IFERROR(VLOOKUP(H12,'[1]Consolidado MP Planta'!$A$2:$M$823,13,0),"") | E12: =IFERROR(VLOOKUP(H12,'[1]Consolidado MP Planta'!$A$2:$M$823,12,0),"") | F12: =IFERROR(C12*E12,"") | G12: =IFERROR(F12/$F$66,"")
B13: =IFERROR(VLOOKUP(H13,'[1]Consolidado MP Planta'!$A$2:$M$823,3,0),"") | C13: =+A13 -> 0 | D13: =IFERROR(VLOOKUP(H13,'[1]Consolidado MP Planta'!$A$2:$M$823,13,0),"") | E13: =IFERROR(VLOOKUP(H13,'[1]Consolidado MP Planta'!$A$2:$M$823,12,0),"") | F13: =IFERROR(C13*E13,"") | G13: =IFERROR(F13/$F$66,"")
B14: =IFERROR(VLOOKUP(H14,'[1]Consolidado MP Planta'!$A$2:$M$823,3,0),"") | C14: =+A14 -> 0 | D14: =IFERROR(VLOOKUP(H14,'[1]Consolidado MP Planta'!$A$2:$M$823,13,0),"") | E14: =IFERROR(VLOOKUP(H14,'[1]Consolidado MP Planta'!$A$2:$M$823,12,0),"") | F14: =IFERROR(C14*E14,"") | G14: =IFERROR(F14/$F$66,"")
B15: =IFERROR(VLOOKUP(H15,'[2]ARTICULOS MP PLANTA'!$A$2:$G$589,2,0),"")
A16: UNIDADES | B16: MATERIA PRIMA SEMIELABORADOS | C16: UNIDADES | D16: UND MEDIDA | E16: COSTO UNITARIO | F16: TOTAL COSTO | G16: % PREC. DEFINIDO | H16: CODIGOS
A17: 160 | B17: BRITTLE DE ALMENDRAS | C17: =+A17 -> 160 | D17: Gramos | E17: =+'costeo brittle'!E69 -> 2.7657428 | F17: =IFERROR(E17*C17,"") -> 442.51886 | G17: =IFERROR(F17/$F$66,"") -> 0.89747074
B18: =IFERROR(VLOOKUP(H18,[1]SEMIELABORADOS!$A$2:$M$6000,2,0),"") | C18: =+A18 -> 0 | D18: =IFERROR(VLOOKUP(H18,[1]SEMIELABORADOS!$A$2:$M$6000,6,0),"") | E18: =IFERROR(VLOOKUP(H18,[1]SEMIELABORADOS!$A$2:$H$65536,8,0),"") | F18: =IFERROR(E18*C18,"") | G18: =IFERROR(F18/$F$66,"")
B19: =IFERROR(VLOOKUP(H19,[1]SEMIELABORADOS!$A$2:$M$6000,2,0),"") | C19: =+A19 -> 0 | D19: =IFERROR(VLOOKUP(H19,[1]SEMIELABORADOS!$A$2:$M$6000,6,0),"") | E19: =IFERROR(VLOOKUP(H19,[1]SEMIELABORADOS!$A$2:$H$65536,8,0),"") | F19: =IFERROR(E19*C19,"") | G19: =IFERROR(F19/$F$66,"")
B20: =IFERROR(VLOOKUP(H20,[1]SEMIELABORADOS!$A$2:$M$6000,2,0),"") | C20: =+A20 -> 0 | D20: =IFERROR(VLOOKUP(H20,[1]SEMIELABORADOS!$A$2:$M$6000,6,0),"") | E20: =IFERROR(VLOOKUP(H20,[1]SEMIELABORADOS!$A$2:$H$65536,8,0),"") | F20: =IFERROR(E20*C20,"") | G20: =IFERROR(F20/$F$66,"")
B21: =IFERROR(VLOOKUP(H21,[1]SEMIELABORADOS!$A$2:$M$6000,2,0),"") | C21: =+A21 -> 0 | D21: =IFERROR(VLOOKUP(H21,[1]SEMIELABORADOS!$A$2:$M$6000,6,0),"") | E21: =IFERROR(VLOOKUP(H21,[1]SEMIELABORADOS!$A$2:$H$65536,8,0),"") | F21: =IFERROR(E21*C21,"") | G21: =IFERROR(F21/$F$66,"")
B22: =IFERROR(VLOOKUP(H22,[1]SEMIELABORADOS!$A$2:$M$6000,2,0),"") | C22: =+A22 -> 0 | D22: =IFERROR(VLOOKUP(H22,[1]SEMIELABORADOS!$A$2:$M$6000,6,0),"") | E22: =IFERROR(VLOOKUP(H22,[1]SEMIELABORADOS!$A$2:$H$65536,8,0),"") | F22: =IFERROR(E22*C22,"") | G22: =IFERROR(F22/$F$66,"")
B23: =IFERROR(VLOOKUP(H23,[1]SEMIELABORADOS!$A$2:$M$6000,2,0),"") | C23: =+A23 -> 0 | D23: =IFERROR(VLOOKUP(H23,[1]SEMIELABORADOS!$A$2:$M$6000,6,0),"") | E23: =IFERROR(VLOOKUP(H23,[1]SEMIELABORADOS!$A$2:$H$65536,8,0),"") | F23: =IFERROR(E23*C23,"") | G23: =IFERROR(F23/$F$66,"")
B24: =IFERROR(VLOOKUP(H24,[1]SEMIELABORADOS!$A$2:$M$6000,2,0),"") | C24: =+A24 -> 0 | D24: =IFERROR(VLOOKUP(H24,[1]SEMIELABORADOS!$A$2:$M$6000,6,0),"") | E24: =IFERROR(VLOOKUP(H24,[1]SEMIELABORADOS!$A$2:$H$65536,8,0),"") | F24: =IFERROR(E24*C24,"") | G24: =IFERROR(F24/$F$66,"")
A26: UNIDADES | B26: EMPAQUE | C26: UNIDADES | D26: UND MEDIDA | E26: COSTO UNITARIO | F26: TOTAL COSTO | G26: % PREC. DEFINIDO | H26: CODIGOS
A27: 1 | B27: =IFERROR(VLOOKUP(H27,'[1]Consolidado MP Planta'!$A$2:$M$823,3,0),"") -> BOLSA 8x12 TRANSPARENTE KILO | C27: =+A27 -> 1 | D27: =IFERROR(VLOOKUP(H27,'[1]Consolidado MP Planta'!$A$2:$M$823,13,0),"") -> Und | E27: =IFERROR(VLOOKUP(H27,'[1]Consolidado MP Planta'!$A$2:$M$823,12,0),"") -> 7 | F27: =IFERROR(C27*E27,"") -> 7 | G27: =IFERROR(F27/$F$66,"") -> 0.014196672 | H27: 1950705
A28: 1 | B28: =IFERROR(VLOOKUP(H28,'[1]Consolidado MP Planta'!$A$2:$M$823,3,0),"") -> ETIQ.BLANCA 1 1/4 * 3/4 (UND) | C28: =+A28 -> 1 | D28: =IFERROR(VLOOKUP(H28,'[1]Consolidado MP Planta'!$A$2:$M$823,13,0),"") -> Und | E28: =IFERROR(VLOOKUP(H28,'[1]Consolidado MP Planta'!$A$2:$M$823,12,0),"") -> 0.58 | F28: =IFERROR(C28*E28,"") -> 0.58 | G28: =IFERROR(F28/$F$66,"") -> 0.0011762957 | H28: 0702069
A29: 1 | B29: =IFERROR(VLOOKUP(H29,'[1]Consolidado MP Planta'!$A$2:$M$823,3,0),"") -> ETIQUETA BLANCA R-153 (UND) | C29: =+A29 -> 1 | D29: =IFERROR(VLOOKUP(H29,'[1]Consolidado MP Planta'!$A$2:$M$823,13,0),"") -> Und | E29: =IFERROR(VLOOKUP(H29,'[1]Consolidado MP Planta'!$A$2:$M$823,12,0),"") -> 0.39 | F29: =IFERROR(C29*E29,"") -> 0.39 | G29: =IFERROR(F29/$F$66,"") -> 0.00079095745 | H29: 701096
A30: 1 | B30: ETIQ.FECHA VENCIMIENTO BLANCO (ROLLO) | C30: =+A30 -> 1 | D30: Und | E30: 0.18 | F30: =IFERROR(C30*E30,"") -> 0.18 | G30: =IFERROR(F30/$F$66,"") -> 0.00036505729 | H30: 702007
B31: =IFERROR(VLOOKUP(H31,'[1]Consolidado MP Planta'!$A$2:$M$823,3,0),"") | C31: =+A31 -> 0 | D31: =IFERROR(VLOOKUP(H31,'[1]Consolidado MP Planta'!$A$2:$M$823,13,0),"") | E31: =IFERROR(VLOOKUP(H31,'[1]Consolidado MP Planta'!$A$2:$M$823,12,0),"") | F31: =IFERROR(C31*E31,"") | G31: =IFERROR(F31/$F$66,"")
B32: =IFERROR(VLOOKUP(H32,'[1]Consolidado MP Planta'!$A$2:$M$823,3,0),"") | C32: =+A32 -> 0 | D32: =IFERROR(VLOOKUP(H32,'[1]Consolidado MP Planta'!$A$2:$M$823,13,0),"") | E32: =IFERROR(VLOOKUP(H32,'[1]Consolidado MP Planta'!$A$2:$M$823,12,0),"") | F32: =IFERROR(C32*E32,"") | G32: =IFERROR(F32/$F$66,"")
A34: UNIDADES | B34: EMPAQUE SEMIELABORADOS | C34: UNIDADES | D34: UND MEDIDA | E34: COSTO UNITARIO | F34: TOTAL COSTO | G34: % PREC. DEFINIDO | H34: CODIGOS
A35: =+A17 -> 160 | B35: BRITTLE DE ALMENDRAS | C35: =+A35 -> 160 | D35: Gramos | E35: =+'costeo brittle'!E76 -> 0.037837907 | F35: =IFERROR(E35*C35,"") -> 6.0540652 | G35: =IFERROR(F35/$F$66,"") -> 0.012278226
A36: =+A18 -> 0 | B36: =IFERROR(VLOOKUP(H36,[1]SEMIELABORADOS!$A$2:$M$6000,2,0),"") | C36: =+A36 -> 0 | D36: =IFERROR(VLOOKUP(H36,[1]SEMIELABORADOS!$A$2:$M$6000,6,0),"") | E36: =IFERROR(VLOOKUP(H36,[1]SEMIELABORADOS!$A$2:$M$65536,10,0),"") | F36: =IFERROR(E36*C36,"") | G36: =IFERROR(F36/$F$66,"")
A37: =+A19 -> 0 | B37: =IFERROR(VLOOKUP(H37,[1]SEMIELABORADOS!$A$2:$M$6000,2,0),"") | C37: =+A37 -> 0 | D37: =IFERROR(VLOOKUP(H37,[1]SEMIELABORADOS!$A$2:$M$6000,6,0),"") | E37: =IFERROR(VLOOKUP(H37,[1]SEMIELABORADOS!$A$2:$M$65536,10,0),"") | F37: =IFERROR(E37*C37,"") | G37: =IFERROR(F37/$F$66,"")
A38: =+A20 -> 0 | B38: =IFERROR(VLOOKUP(H38,[1]SEMIELABORADOS!$A$2:$M$6000,2,0),"") | C38: =+A38 -> 0 | D38: =IFERROR(VLOOKUP(H38,[1]SEMIELABORADOS!$A$2:$M$6000,6,0),"") | E38: =IFERROR(VLOOKUP(H38,[1]SEMIELABORADOS!$A$2:$M$65536,10,0),"") | F38: =IFERROR(E38*C38,"") | G38: =IFERROR(F38/$F$66,"")
A39: =+A21 -> 0 | B39: =IFERROR(VLOOKUP(H39,[1]SEMIELABORADOS!$A$2:$M$6000,2,0),"") | C39: =+A39 -> 0 | D39: =IFERROR(VLOOKUP(H39,[1]SEMIELABORADOS!$A$2:$M$6000,6,0),"") | E39: =IFERROR(VLOOKUP(H39,[1]SEMIELABORADOS!$A$2:$M$65536,10,0),"") | F39: =IFERROR(E39*C39,"") | G39: =IFERROR(F39/$F$66,"")
A40: =+A22 -> 0 | B40: =IFERROR(VLOOKUP(H40,[1]SEMIELABORADOS!$A$2:$M$6000,2,0),"") | C40: =+A40 -> 0 | D40: =IFERROR(VLOOKUP(H40,[1]SEMIELABORADOS!$A$2:$M$6000,6,0),"") | E40: =IFERROR(VLOOKUP(H40,[1]SEMIELABORADOS!$A$2:$M$65536,10,0),"") | F40: =IFERROR(E40*C40,"") | G40: =IFERROR(F40/$F$66,"")
A41: =+A23 -> 0 | B41: =IFERROR(VLOOKUP(H41,[1]SEMIELABORADOS!$A$2:$M$6000,2,0),"") | C41: =+A41 -> 0 | D41: =IFERROR(VLOOKUP(H41,[1]SEMIELABORADOS!$A$2:$M$6000,6,0),"") | E41: =IFERROR(VLOOKUP(H41,[1]SEMIELABORADOS!$A$2:$M$65536,10,0),"") | F41: =IFERROR(E41*C41,"") | G41: =IFERROR(F41/$F$66,"")
A43: UNIDADES | B43: MODI | C43: UNIDADES | D43: UND MEDIDA | E43: COSTO UNITARIO | F43: TOTAL COSTO | G43: % PREC. DEFINIDO | H43: CODIGOS
A44: =+A35 -> 160 | B44: BRITTLE DE ALMENDRAS | C44: =+A44 -> 160 | D44: Gramos | E44: =+'costeo brittle'!E74 -> 0.5698132 | F44: =IFERROR(E44*C44,"") -> 91.170112 | G44: =IFERROR(F44/$F$66,"") -> 0.18490174
A45: =+A36 -> 0 | B45: =IFERROR(VLOOKUP(H45,[1]SEMIELABORADOS!$A$2:$M$6000,2,0),"") | C45: =+A45 -> 0 | D45: =IFERROR(VLOOKUP(H45,[1]SEMIELABORADOS!$A$2:$M$6000,6,0),"") | E45: =IFERROR(VLOOKUP(H45,[1]SEMIELABORADOS!$A$2:$M$65536,12,0),"") | F45: =IFERROR(E45*C45,"") | G45: =IFERROR(F45/$F$66,"")
A46: =+A37 -> 0 | B46: =IFERROR(VLOOKUP(H46,[1]SEMIELABORADOS!$A$2:$M$6000,2,0),"") | C46: =+A46 -> 0 | D46: =IFERROR(VLOOKUP(H46,[1]SEMIELABORADOS!$A$2:$M$6000,6,0),"") | E46: =IFERROR(VLOOKUP(H46,[1]SEMIELABORADOS!$A$2:$M$65536,12,0),"") | F46: =IFERROR(E46*C46,"") | G46: =IFERROR(F46/$F$66,"")
A47: =+A38 -> 0 | B47: =IFERROR(VLOOKUP(H47,[1]SEMIELABORADOS!$A$2:$M$6000,2,0),"") | C47: =+A47 -> 0 | D47: =IFERROR(VLOOKUP(H47,[1]SEMIELABORADOS!$A$2:$M$6000,6,0),"") | E47: =IFERROR(VLOOKUP(H47,[1]SEMIELABORADOS!$A$2:$M$65536,12,0),"") | F47: =IFERROR(E47*C47,"") | G47: =IFERROR(F47/$F$66,"")
A48: =+A39 -> 0 | B48: =IFERROR(VLOOKUP(H48,[1]SEMIELABORADOS!$A$2:$M$6000,2,0),"") | C48: =+A48 -> 0 | D48: =IFERROR(VLOOKUP(H48,[1]SEMIELABORADOS!$A$2:$M$6000,6,0),"") | E48: =IFERROR(VLOOKUP(H48,[1]SEMIELABORADOS!$A$2:$M$65536,12,0),"") | F48: =IFERROR(E48*C48,"") | G48: =IFERROR(F48/$F$66,"")
A49: =+A40 -> 0 | B49: =IFERROR(VLOOKUP(H49,[1]SEMIELABORADOS!$A$2:$M$6000,2,0),"") | C49: =+A49 -> 0 | D49: =IFERROR(VLOOKUP(H49,[1]SEMIELABORADOS!$A$2:$M$6000,6,0),"") | E49: =IFERROR(VLOOKUP(H49,[1]SEMIELABORADOS!$A$2:$M$65536,12,0),"") | F49: =IFERROR(E49*C49,"") | G49: =IFERROR(F49/$F$66,"")
A50: =+A41 -> 0 | B50: =IFERROR(VLOOKUP(H50,[1]SEMIELABORADOS!$A$2:$M$6000,2,0),"") | C50: =+A50 -> 0 | D50: =IFERROR(VLOOKUP(H50,[1]SEMIELABORADOS!$A$2:$M$6000,6,0),"") | E50: =IFERROR(VLOOKUP(H50,[1]SEMIELABORADOS!$A$2:$M$65536,12,0),"") | F50: =IFERROR(E50*C50,"") | G50: =IFERROR(F50/$F$66,"")
A51: 1 | B51: MODI PREPARACION | C51: =+A51 -> 1 | D51: N/A | E51: =+F65 -> 27.5 | F51: =IFERROR(C51*E51,"") -> 27.5 | G51: =IFERROR(F51/$F$66,"") -> 0.055772641
B53: TOTAL MATERIA PRIMA | F53: =SUM(F8:F14,F17:F24) -> 442.51886 | G53: =+F53/$F$66 -> 0.89747074 | H53: =+F53/$D$60 -> 442.51886
B54: TOTAL EMPAQUE | F54: =SUM(F27:F32,F35:F41) -> 14.204065 | G54: =+F54/$F$66 -> 0.028807208 | H54: =+F54/$D$60 -> 14.204065 | K54: TOTAL MATERIA PRIMA + EMPAQUE | O54: =+F55 -> 456.72292
B55: TOTAL MATERIAS P. + EMPAQUES | F55: =+F53+F54 -> 456.72292 | G55: =+F55/$F$66 -> 0.92627794 | H55: =+F55/$D$60 -> 456.72292 | L55: MODI PLANTA | O55: 127.84
C56: TOTAL MODI | F56: =SUM(F44:F51) -> 118.67011 | G56: =+F56/$F$66 -> 0.24067438 | H56: =+F56/$D$60 -> 118.67011 | M56: DESECHO | O56: =O54*N56 -> 0
M57: COSTO PLANTA | O57: =SUM(O54:O56) -> 584.56292
B58: GRAMOS | D58: 160 | M58: GIF | O58: 107.34
B59: PESO POR UNIDAD | D59: 160 | M59: COSTO PLANTA | O59: =SUM(O57:O58) -> 691.90292
B60: UNIDADES TOTALES | D60: =+D58/D59 -> 1 | L60: TRANSFERENCIA | O60: =+O59*N60 -> 0
B61: UNIDAD MEDIDA | K61: PRECIO DE VENTA PLANTA A LOCAL | O61: =SUM(O59:O60) -> 691.90292 | P61: GR
E62: S/ COSTO | F62: TOTAL | L62: UNIDAD | O62: =+O61/D60 -> 691.90292 | P62: =+O62/D59 -> 4.3243933
B63: TOTAL MATERIAS P. + EMPAQUES | E63: =+F63/F63 -> 1 | F63: =SUM(F55) -> 456.72292 | G63: =+F63/$F$66 -> 0.92627794
B64: DESECHOS Y PERDIDAS | E64: 0.02 | F64: =+F53*E64 -> 8.8503771 | G64: =+F64/$F$66 -> 0.017949415
B65: MANO OBRA DIRECTA | D65: 0.5 | E65: 55 | F65: =+E65*D65 -> 27.5 | G65: =+F65/$F$66 -> 0.055772641
B66: TOTAL COSTO PLANTA | F66: =SUM(F63:F65) -> 493.0733 | G66: =+F66/$F$66 -> 1
B68: COSTO POR GRAMO
B69: TOTAL COSTO MATERIA PRIMA | C69: =+F53 -> 442.51886 | D69: =+D58 -> 160 | E69: =+C69/D69 -> 2.7657428
B71: TOTAL COSTO UNIDAD MP+DESECHO+EMPAQUE | C71: =SUM(F63:F64) -> 465.5733 | D71: =+D58 -> 160 | E71: =+C71/D71 -> 2.9098331
B73: TOTAL MODI PREPARACION POR GRAMO | C73: =+F65 -> 27.5 | D73: =+D58 -> 160 | E73: =+C73/D73 -> 0.171875
B74: TOTAL MODI POR GRAMO | C74: =+F56 -> 118.67011 | D74: =+D73 -> 160 | E74: =+C74/D74 -> 0.7416882
B76: TOTAL EMPAQUE POR GRAMO | C76: =+F54 -> 14.204065 | D76: =+D74 -> 160 | E76: =+C76/D76 -> 0.088775407
B78: TOTAL GRAMO MP+MODI | E78: =+E69+E74 -> 3.507431
B80: COSTO POR UNIDAD
B81: TOTAL COSTO MATERIA PRIMA | C81: =+C69 -> 442.51886 | D81: =+D60 -> 1 | E81: =+C81/D81 -> 442.51886
B83: TOTAL COSTO UNIDAD MP+DESECHO+EMPAQUE | C83: =+C71 -> 465.5733 | D83: =+D60 -> 1 | E83: =+C83/D83 -> 465.5733
B85: TOTAL MODI POR GRAMO | C85: =+C73 -> 27.5 | D85: =+D60 -> 1 | E85: =+C85/D85 -> 27.5
B86: TOTAL MODI POR GRAMO | C86: =+C74 -> 118.67011 | D86: =+D85 -> 1 | E86: =+C86/D86 -> 118.67011

Sheet ENSAMBLE 2
B1: SERVICIOS DE PASTELERIA S.A. | G1: CÓDIGO:
B2: ESPECIFICACION DE RECETA | G2: REVISIÓN:
B3: Postre caramelo y almendras (dia de la madre 2021) | G3: FECHA DE APROBACIÓN:
B4: Elaborado | C4: Javier Tong, Chef
B5: Aprobado | C5: Esteban Cartin, Gte Manufactura
A7: AREA QUE PRODUCE: | C7: Postre | F7: AREA QUE EMPACA: | H7: Postre
A8: # Código | B8: Descripción del ingrediente | C8: Marca | D8: Unidad Internacional | F8: Medida alternativa | H8: Costo - Referencia
D9: Cantidad | E9: Unidad medida | F9: Cantidad | G9: Unidad medida | H9: Colones
A10: 907000002 | B10: BASE GALLETA P/CHEESE CAKE (KILO) | C10: FAS | D10: 200 | E10: g
A11: 90200029 | B11: RELLENO CHEESECAKE KILO | C11: FAS | D11: 300 | E11: g
A12: 410154 | B12: RELLENO CARAMELO (KILO) | C12: CONEXU | D12: 120 | E12: g
A13: 90200029 | B13: RELLENO CHEESECAKE KILO | C13: FAS | D13: 300 | E13: g
B14: DECORACION
A15: 901000111 | B15: GANACHE DE DULCE LECHE (4800g) | C15: FAS | D15: 90 | E15: g | F15: Espejo
E16: g | F16: 3/4 tz
B17: CHOCOLATE CORAZON DORADO | C17: Karol | D17: 1 | E17: ud
A18: 1112431 | B18: MANJAR LECHE CONDENSADA (PAQ: 4.5 K) | C18: NESTLE | D18: 20 | E18: g | F18: Para pegar
B19: EMPAQUE
A20: 702182 | B20: ETIQUETA IMP. SPOON MEDIANA V-273 (UND) | C20: ETIPLAST | D20: 1 | E20: ud
A21: 703020 | B21: CINTA ADHESIVA TRANSPARENT 2*100 M (UND) | C21: ETIPLAST | D21: 60 | E21: cm
A22: 1950693 | B22: ORLA CARTON 9" DORADA (UND ) | C22: RAPIBOX | D22: 1 | E22: ud
A23: 51400021 | B23: QUEQUERA RED C/BASE ALTA 9" (CAJA:100 U) | C23: Exp PMT | D23: 1 | E23: ud
A24: 702123 | B24: ETIQUETA BLANCA 2 5/8X1 15/16 (UND) | C24: Cemusa | D24: 1 | E24: ud
A25: 701096 | B25: ETIQUETA BLANCA R-153 (UND) | C25: Cemusa | D25: 1 | E25: ud
A26: 702007 | B26: ETIQ.FECHA VENCIMIENTO BLANCO (ROLLO) | C26: CEMUSA | D26: 1 | E26: ud
C28: Cantidad | D28: Unidad
A29: PESO TOTAL OBTENIDO | C29: 950 | D29: g
A30: TIEMPO TOTAL DE PREPARACION | C30: 5 | D30: min
A31: CANTIDAD DE PORCIONES OBTENIDAS | C31: 1 | D31: ud
A32: PESO DE CADA PORCIÓN | C32: 950 | D32: g
A33: MERMA | C33: 191 | D33: g
A34: PROCEDIMIENTO DE PREPARACION DE LA RECETA
A35: 1.- Colocar dentro del molde desarmable redondo 21 cm ,previamente ensagrasado la base de galleta presionar y hornear a 175°C por 7 min en el Argental, a 175°C por 8 min en el Dicte 1 y Dicte 2, a 170°C en el Dicte 3 y a 175°C por 7 min en el Marshal
A36: 2.- Una vez fria la galleta, dosificar en el molde 275g de mezcla de cheesecake, 120g de caramelo y 275g de mezcla de cheesecake. Dejar enfriar al menos 6 horas en Refrigeracion
A37: 3.- Desmoldar con ayuda de una espatula.
A38: 4.- Pegar a la orla con manjar, decorar con ganache en el hacinedo espejo y dejar chorrear. sobre este ganache colocar el brittle de almednras.
A39: 5.- Decorar con un corazon de chocolate, tapar y etiquetar

Sheet Hoja5

Sheet COSTEO ENSAMBLE
E1: Precio Local | F1: Costo MP | G1: Costo EM | H1: Costo MO
E2: =IFERROR(O67,"") -> 3912.1697 | F2: =IFERROR(H58,"") -> 2227.3038 | G2: =IFERROR(H59,"") -> 393.7941 | H2: =IFERROR(H61,"") -> 386.06712
A5: ESTRUCTURA DE COSTOS
F6: Fecha: | H6: =TODAY() -> 45754
A7: UNIDADES | B7: DESCRIPCION MAT.PRIMA | C7: UNIDADES | D7: UND MEDIDA | E7: COSTO UNITARIO | F7: TOTAL COSTO | G7: % PREC. DEFINIDO | H7: CODIGOS
A8: 120 | B8: =IFERROR(VLOOKUP(H8,'[1]Consolidado MP Planta'!$A$2:$M$823,3,0),"") -> RELLENO CARAMELO KILO | C8: =+A8 -> 120 | D8: =IFERROR(VLOOKUP(H8,'[1]Consolidado MP Planta'!$A$2:$M$823,13,0),"") -> Gramos | E8: =IFERROR(VLOOKUP(H8,'[1]Consolidado MP Planta'!$A$2:$M$823,12,0),"") -> 3.335 | F8: =IFERROR(C8*E8,"") -> 400.2 | G8: =IFERROR(F8/$F$71,"") -> 0.13609264 | H8: 0410154
B9: =IFERROR(VLOOKUP(H9,'[1]Consolidado MP Planta'!$A$2:$M$823,3,0),"") -> CHOCOLATE CORAZON ROJO PASION (CAJA:200) | C9: =+A9 -> 0 | D9: =IFERROR(VLOOKUP(H9,'[1]Consolidado MP Planta'!$A$2:$M$823,13,0),"") -> Und | E9: =IFERROR(VLOOKUP(H9,'[1]Consolidado MP Planta'!$A$2:$M$823,12,0),"") -> 38.25 | F9: =IFERROR(C9*E9,"") -> 0 | G9: =IFERROR(F9/$F$71,"") -> 0 | H9: 10700029
A10: 20 | B10: =IFERROR(VLOOKUP(H10,'[1]Consolidado MP Planta'!$A$2:$M$823,3,0),"") -> MANJAR LECHE CONDENSADA (PAQ: 4.5 K) | C10: =+A10 -> 20 | D10: =IFERROR(VLOOKUP(H10,'[1]Consolidado MP Planta'!$A$2:$M$823,13,0),"") -> Gramos | E10: =IFERROR(VLOOKUP(H10,'[1]Consolidado MP Planta'!$A$2:$M$823,12,0),"") -> 2.142 | F10: =IFERROR(C10*E10,"") -> 42.84 | G10: =IFERROR(F10/$F$71,"") -> 0.014568237 | H10: 1112431
B11: =IFERROR(VLOOKUP(H11,'[1]Consolidado MP Planta'!$A$2:$M$823,3,0),"") | C11: =+A11 -> 0 | D11: =IFERROR(VLOOKUP(H11,'[1]Consolidado MP Planta'!$A$2:$M$823,13,0),"") | E11: =IFERROR(VLOOKUP(H11,'[1]Consolidado MP Planta'!$A$2:$M$823,12,0),"") | F11: =IFERROR(C11*E11,"") | G11: =IFERROR(F11/$F$71,"")
B12: =IFERROR(VLOOKUP(H12,'[1]Consolidado MP Planta'!$A$2:$M$823,3,0),"") | C12: =+A12 -> 0 | D12: =IFERROR(VLOOKUP(H12,'[1]Consolidado MP Planta'!$A$2:$M$823,13,0),"") | E12: =IFERROR(VLOOKUP(H12,'[1]Consolidado MP Planta'!$A$2:$M$823,12,0),"") | F12: =IFERROR(C12*E12,"") | G12: =IFERROR(F12/$F$71,"")
B13: =IFERROR(VLOOKUP(H13,'[1]Consolidado MP Planta'!$A$2:$M$823,3,0),"") | C13: =+A13 -> 0 | D13: =IFERROR(VLOOKUP(H13,'[1]Consolidado MP Planta'!$A$2:$M$823,13,0),"") | E13: =IFERROR(VLOOKUP(H13,'[1]Consolidado MP Planta'!$A$2:$M$823,12,0),"") | F13: =IFERROR(C13*E13,"") | G13: =IFERROR(F13/$F$71,"")
B14: =IFERROR(VLOOKUP(H14,'[1]Consolidado MP Planta'!$A$2:$M$823,3,0),"") | C14: =+A14 -> 0 | D14: =IFERROR(VLOOKUP(H14,'[1]Consolidado MP Planta'!$A$2:$M$823,13,0),"") | E14: =IFERROR(VLOOKUP(H14,'[1]Consolidado MP Planta'!$A$2:$M$823,12,0),"") | F14: =IFERROR(C14*E14,"") | G14: =IFERROR(F14/$F$71,"")
B15: =IFERROR(VLOOKUP(H15,'[2]ARTICULOS MP PLANTA'!$A$2:$G$589,2,0),"")
A16: UNIDADES | B16: MATERIA PRIMA SEMIELABORADOS | C16: UNIDADES | D16: UND MEDIDA | E16: COSTO UNITARIO | F16: TOTAL COSTO | G16: % PREC. DEFINIDO | H16: CODIGOS
A17: 200 | B17: =IFERROR(VLOOKUP(H17,[1]SEMIELABORADOS!$A$2:$M$6000,2,0),"") -> BASE GALLETA P/CHEESE CAKE (KILO) | C17: =+A17 -> 200 | D17: =IFERROR(VLOOKUP(H17,[1]SEMIELABORADOS!$A$2:$M$6000,6,0),"") -> Gramo | E17: =IFERROR(VLOOKUP(H17,[1]SEMIELABORADOS!$A$2:$H$65536,8,0),"") -> 2.0071033 | F17: =IFERROR(E17*C17,"") -> 401.42065 | G17: =IFERROR(F17/$F$71,"") -> 0.13650773 | H17: 907000002
A18: 600 | B18: =IFERROR(VLOOKUP(H18,[1]SEMIELABORADOS!$A$2:$M$6000,2,0),"") -> RELLENO CHEESECAKE KILO | C18: =+A18 -> 600 | D18: =IFERROR(VLOOKUP(H18,[1]SEMIELABORADOS!$A$2:$M$6000,6,0),"") -> Gramo | E18: =IFERROR(VLOOKUP(H18,[1]SEMIELABORADOS!$A$2:$H$65536,8,0),"") -> 1.8699122 | F18: =IFERROR(E18*C18,"") -> 1121.9473 | G18: =IFERROR(F18/$F$71,"") -> 0.38153117 | H18: 90200029
A19: 90 | B19: GANACHE DE DULCE LECHE (4800g) | C19: =+A19 -> 90 | D19: Gramo | E19: =+'[3]COSTEO GANACHE'!$E$69 -> 2.8988426 | F19: =IFERROR(E19*C19,"") -> 260.89583 | G19: =IFERROR(F19/$F$71,"") -> 0.088720645 | H19: 901000111
A20: 0 | B20: =IFERROR(VLOOKUP(H20,[1]SEMIELABORADOS!$A$2:$M$6000,2,0),"") -> CREMA DULCE LECHE KILO | C20: =+A20 -> 0 | D20: =IFERROR(VLOOKUP(H20,[1]SEMIELABORADOS!$A$2:$M$6000,6,0),"") -> Gramo | E20: =IFERROR(VLOOKUP(H20,[1]SEMIELABORADOS!$A$2:$H$65536,8,0),"") -> 1.9863913 | F20: =IFERROR(E20*C20,"") -> 0 | G20: =IFERROR(F20/$F$71,"") -> 0 | H20: 96344
B22: =IFERROR(VLOOKUP(H22,[1]SEMIELABORADOS!$A$2:$M$6000,2,0),"") | C22: =+A22 -> 0 | D22: =IFERROR(VLOOKUP(H22,[1]SEMIELABORADOS!$A$2:$M$6000,6,0),"") | E22: =IFERROR(VLOOKUP(H22,[1]SEMIELABORADOS!$A$2:$H$65536,8,0),"") | F22: =IFERROR(E22*C22,"") | G22: =IFERROR(F22/$F$71,"")
B23: =IFERROR(VLOOKUP(H23,[1]SEMIELABORADOS!$A$2:$M$6000,2,0),"") | C23: =+A23 -> 0 | D23: =IFERROR(VLOOKUP(H23,[1]SEMIELABORADOS!$A$2:$M$6000,6,0),"") | E23: =IFERROR(VLOOKUP(H23,[1]SEMIELABORADOS!$A$2:$H$65536,8,0),"") | F23: =IFERROR(E23*C23,"") | G23: =IFERROR(F23/$F$71,"")
B24: =IFERROR(VLOOKUP(H24,[1]SEMIELABORADOS!$A$2:$M$6000,2,0),"") | C24: =+A24 -> 0 | D24: =IFERROR(VLOOKUP(H24,[1]SEMIELABORADOS!$A$2:$M$6000,6,0),"") | E24: =IFERROR(VLOOKUP(H24,[1]SEMIELABORADOS!$A$2:$H$65536,8,0),"") | F24: =IFERROR(E24*C24,"") | G24: =IFERROR(F24/$F$71,"")
A26: UNIDADES | B26: EMPAQUE | C26: UNIDADES | D26: UND MEDIDA | E26: COSTO UNITARIO | F26: TOTAL COSTO | G26: % PREC. DEFINIDO | H26: CODIGOS
A27: 1 | B27: =IFERROR(VLOOKUP(H27,'[1]Consolidado MP Planta'!$A$2:$M$823,3,0),"") -> ETIQUETA IMP. SPOON MEDIANA V-273 (UND) | C27: =+A27 -> 1 | D27: =IFERROR(VLOOKUP(H27,'[1]Consolidado MP Planta'!$A$2:$M$823,13,0),"") -> Und | E27: =IFERROR(VLOOKUP(H27,'[1]Consolidado MP Planta'!$A$2:$M$823,12,0),"") -> 32.49 | F27: =IFERROR(C27*E27,"") -> 32.49 | G27: =IFERROR(F27/$F$71,"") -> 0.0110486 | H27: 702182
A28: 60 | B28: =IFERROR(VLOOKUP(H28,'[1]Consolidado MP Planta'!$A$2:$M$823,3,0),"") -> CINTA ADHESIVA TRANSPARENT 2*100 M (UND) | C28: =+A28 -> 60 | D28: =IFERROR(VLOOKUP(H28,'[1]Consolidado MP Planta'!$A$2:$M$823,13,0),"") -> Cm | E28: =IFERROR(VLOOKUP(H28,'[1]Consolidado MP Planta'!$A$2:$M$823,12,0),"") -> 0.145 | F28: =IFERROR(C28*E28,"") -> 8.7 | G28: =IFERROR(F28/$F$71,"") -> 0.0029585356 | H28: 703020
A29: 1 | B29: =IFERROR(VLOOKUP(H29,'[1]Consolidado MP Planta'!$A$2:$M$823,3,0),"") -> ORLA #9 DORADA (UND) | C29: =+A29 -> 1 | D29: =IFERROR(VLOOKUP(H29,'[1]Consolidado MP Planta'!$A$2:$M$823,13,0),"") -> Und | E29: =IFERROR(VLOOKUP(H29,'[1]Consolidado MP Planta'!$A$2:$M$823,12,0),"") -> 105 | F29: =IFERROR(C29*E29,"") -> 105 | G29: =IFERROR(F29/$F$71,"") -> 0.035706464 | H29: 1950693
A30: 1 | B30: =IFERROR(VLOOKUP(H30,'[1]Consolidado MP Planta'!$A$2:$M$823,3,0),"") -> QUEQUERA RED C/BASE ALTA 9" (CAJA:100 U) | C30: =+A30 -> 1 | D30: =IFERROR(VLOOKUP(H30,'[1]Consolidado MP Planta'!$A$2:$M$823,13,0),"") -> Und | E30: =IFERROR(VLOOKUP(H30,'[1]Consolidado MP Planta'!$A$2:$M$823,12,0),"") -> 244.36 | F30: =IFERROR(C30*E30,"") -> 244.36 | G30: =IFERROR(F30/$F$71,"") -> 0.083097444 | H30: 51400021
A31: 1 | B31: =IFERROR(VLOOKUP(H31,'[1]Consolidado MP Planta'!$A$2:$M$823,3,0),"") -> ETIQUETA BLANCA 2 5/8X1 15/16 (UND) | C31: =+A31 -> 1 | D31: =IFERROR(VLOOKUP(H31,'[1]Consolidado MP Planta'!$A$2:$M$823,13,0),"") -> Und | E31: =IFERROR(VLOOKUP(H31,'[1]Consolidado MP Planta'!$A$2:$M$823,12,0),"") -> 2.128 | F31: =IFERROR(C31*E31,"") -> 2.128 | G31: =IFERROR(F31/$F$71,"") -> 0.00072365101 | H31: 0702123
A32: 1 | B32: =IFERROR(VLOOKUP(H32,'[1]Consolidado MP Planta'!$A$2:$M$823,3,0),"") -> ETIQUETA BLANCA R-153 (UND) | C32: =+A32 -> 1 | D32: =IFERROR(VLOOKUP(H32,'[1]Consolidado MP Planta'!$A$2:$M$823,13,0),"") -> Und | E32: =IFERROR(VLOOKUP(H32,'[1]Consolidado MP Planta'!$A$2:$M$823,12,0),"") -> 0.39 | F32: =IFERROR(C32*E32,"") -> 0.39 | G32: =IFERROR(F32/$F$71,"") -> 0.00013262401 | H32: 701096
A33: 1 | B33: =IFERROR(VLOOKUP(H33,'[1]Consolidado MP Planta'!$A$2:$M$823,3,0),"") -> ETIQ.FECHA VENCIMIENTO AMARILLO (ROLLO) | C33: =+A33 -> 1 | D33: =IFERROR(VLOOKUP(H33,'[1]Consolidado MP Planta'!$A$2:$M$823,13,0),"") -> Und | E33: =IFERROR(VLOOKUP(H33,'[1]Consolidado MP Planta'!$A$2:$M$823,12,0),"") -> 0.2 | F33: =IFERROR(C33*E33,"") -> 0.2 | G33: =IFERROR(F33/$F$71,"") -> 6.8012313e-05 | H33: 0702006
B34: =IFERROR(VLOOKUP(H34,'[1]Consolidado MP Planta'!$A$2:$M$823,3,0),"") | C34: =+A34 -> 0 | D34: =IFERROR(VLOOKUP(H34,'[1]Consolidado MP Planta'!$A$2:$M$823,13,0),"") | E34: =IFERROR(VLOOKUP(H34,'[1]Consolidado MP Planta'!$A$2:$M$823,12,0),"") | F34: =IFERROR(C34*E34,"") | G34: =IFERROR(F34/$F$71,"")
B35: =IFERROR(VLOOKUP(H35,'[1]Consolidado MP Planta'!$A$2:$M$823,3,0),"") | C35: =+A35 -> 0 | D35: =IFERROR(VLOOKUP(H35,'[1]Consolidado MP Planta'!$A$2:$M$823,13,0),"") | E35: =IFERROR(VLOOKUP(H35,'[1]Consolidado MP Planta'!$A$2:$M$823,12,0),"") | F35: =IFERROR(C35*E35,"") | G35: =IFERROR(F35/$F$71,"")
B36: =IFERROR(VLOOKUP(H36,'[1]Consolidado MP Planta'!$A$2:$M$823,3,0),"") | C36: =+A36 -> 0 | D36: =IFERROR(VLOOKUP(H36,'[1]Consolidado MP Planta'!$A$2:$M$823,13,0),"") | E36: =IFERROR(VLOOKUP(H36,'[1]Consolidado MP Planta'!$A$2:$M$823,12,0),"") | F36: =IFERROR(C36*E36,"") | G36: =IFERROR(F36/$F$71,"")
B37: =IFERROR(VLOOKUP(H37,'[1]Consolidado MP Planta'!$A$2:$M$823,3,0),"") | C37: =+A37 -> 0 | D37: =IFERROR(VLOOKUP(H37,'[1]Consolidado MP Planta'!$A$2:$M$823,13,0),"") | E37: =IFERROR(VLOOKUP(H37,'[1]Consolidado MP Planta'!$A$2:$M$823,12,0),"") | F37: =IFERROR(C37*E37,"") | G37: =IFERROR(F37/$F$71,"")
A39: UNIDADES | B39: EMPAQUE SEMIELABORADOS | C39: UNIDADES | D39: UND MEDIDA | E39: COSTO UNITARIO | F39: TOTAL COSTO | G39: % PREC. DEFINIDO | H39: CODIGOS
A40: =+A17 -> 200 | B40: =IFERROR(VLOOKUP(H40,[1]SEMIELABORADOS!$A$2:$M$6000,2,0),"") -> BASE GALLETA P/CHEESE CAKE (KILO) | C40: =+A40 -> 200 | D40: =IFERROR(VLOOKUP(H40,[1]SEMIELABORADOS!$A$2:$M$6000,6,0),"") -> Gramo | E40: =IFERROR(VLOOKUP(H40,[1]SEMIELABORADOS!$A$2:$M$65536,10,0),"") -> 0.0011524699 | F40: =IFERROR(E40*C40,"") -> 0.23049398 | G40: =IFERROR(F40/$F$71,"") -> 7.8382144e-05 | H40: 907000002
A41: =+A18 -> 600 | B41: =IFERROR(VLOOKUP(H41,[1]SEMIELABORADOS!$A$2:$M$6000,2,0),"") -> RELLENO CHEESECAKE KILO | C41: =+A41 -> 600 | D41: =IFERROR(VLOOKUP(H41,[1]SEMIELABORADOS!$A$2:$M$6000,6,0),"") -> Gramo | E41: =IFERROR(VLOOKUP(H41,[1]SEMIELABORADOS!$A$2:$M$65536,10,0),"") -> 7.4358974e-06 | F41: =IFERROR(E41*C41,"") -> 0.0044615385 | G41: =IFERROR(F41/$F$71,"") -> 1.5171977e-06 | H41: 90200029
A42: =+A19 -> 90 | B42: GANACHE DE DULCE LECHE (4800g) | C42: =+A42 -> 90 | D42: Gramo | E42: =+'[3]COSTEO GANACHE'!$E$76 -> 0.0032348958 | F42: =IFERROR(E42*C42,"") -> 0.29114063 | G42: =IFERROR(F42/$F$71,"") -> 9.9005736e-05 | H42: 901000111
A43: =+A20 -> 0 | B43: =IFERROR(VLOOKUP(H43,[1]SEMIELABORADOS!$A$2:$M$6000,2,0),"") -> CREMA DULCE LECHE KILO | C43: =+A43 -> 0 | D43: =IFERROR(VLOOKUP(H43,[1]SEMIELABORADOS!$A$2:$M$6000,6,0),"") -> Gramo | E43: =IFERROR(VLOOKUP(H43,[1]SEMIELABORADOS!$A$2:$M$65536,10,0),"") -> 8.512e-05 | F43: =IFERROR(E43*C43,"") -> 0 | G43: =IFERROR(F43/$F$71,"") -> 0 | H43: 96344
A44: =+A21 -> 0 | B44: BRITTLE DE ALMENDRAS | C44: =+A44 -> 0 | D44: Gramo | E44: =+'costeo brittle'!E76 -> 0.037837907 | F44: =IFERROR(E44*C44,"") -> 0 | G44: =IFERROR(F44/$F$71,"") -> 0
A45: =+A22 -> 0 | B45: =IFERROR(VLOOKUP(H45,[1]SEMIELABORADOS!$A$2:$M$6000,2,0),"") | C45: =+A45 -> 0 | D45: =IFERROR(VLOOKUP(H45,[1]SEMIELABORADOS!$A$2:$M$6000,6,0),"") | E45: =IFERROR(VLOOKUP(H45,[1]SEMIELABORADOS!$A$2:$M$65536,10,0),"") | F45: =IFERROR(E45*C45,"") | G45: =IFERROR(F45/$F$71,"")
A46: =+A23 -> 0 | B46: =IFERROR(VLOOKUP(H46,[1]SEMIELABORADOS!$A$2:$M$6000,2,0),"") | C46: =+A46 -> 0 | D46: =IFERROR(VLOOKUP(H46,[1]SEMIELABORADOS!$A$2:$M$6000,6,0),"") | E46: =IFERROR(VLOOKUP(H46,[1]SEMIELABORADOS!$A$2:$M$65536,10,0),"") | F46: =IFERROR(E46*C46,"") | G46: =IFERROR(F46/$F$71,"")
A48: UNIDADES | B48: MODI | C48: UNIDADES | D48: UND MEDIDA | E48: COSTO UNITARIO | F48: TOTAL COSTO | G48: % PREC. DEFINIDO | H48: CODIGOS
A49: =+A40 -> 200 | B49: =IFERROR(VLOOKUP(H49,[1]SEMIELABORADOS!$A$2:$M$6000,2,0),"") -> BASE GALLETA P/CHEESE CAKE (KILO) | C49: =+A49 -> 200 | D49: =IFERROR(VLOOKUP(H49,[1]SEMIELABORADOS!$A$2:$M$6000,6,0),"") -> Gramo | E49: =IFERROR(VLOOKUP(H49,[1]SEMIELABORADOS!$A$2:$M$65536,12,0),"") -> 0.2087223 | F49: =IFERROR(E49*C49,"") -> 41.74446 | G49: =IFERROR(F49/$F$71,"") -> 0.014195686 | H49: 907000002
A50: =+A41 -> 600 | B50: =IFERROR(VLOOKUP(H50,[1]SEMIELABORADOS!$A$2:$M$6000,2,0),"") -> RELLENO CHEESECAKE KILO | C50: =+A50 -> 600 | D50: =IFERROR(VLOOKUP(H50,[1]SEMIELABORADOS!$A$2:$M$6000,6,0),"") -> Gramo | E50: =IFERROR(VLOOKUP(H50,[1]SEMIELABORADOS!$A$2:$M$65536,12,0),"") -> 0.098350267 | F50: =IFERROR(E50*C50,"") -> 59.01016 | G50: =IFERROR(F50/$F$71,"") -> 0.020067087 | H50: 90200029
A51: =+A42 -> 90 | B51: GANACHE DE DULCE LECHE (4800g) | C51: =+A51 -> 90 | D51: Gramo | E51: =+'[3]COSTEO GANACHE'!$E$74 -> 0.11458333 | F51: =IFERROR(E51*C51,"") -> 10.3125 | G51: =IFERROR(F51/$F$71,"") -> 0.0035068849 | H51: 901000111
A52: =+A43 -> 0 | B52: =IFERROR(VLOOKUP(H52,[1]SEMIELABORADOS!$A$2:$M$6000,2,0),"") -> CREMA DULCE LECHE KILO | C52: =+A52 -> 0 | D52: =IFERROR(VLOOKUP(H52,[1]SEMIELABORADOS!$A$2:$M$6000,6,0),"") -> Gramo | E52: =IFERROR(VLOOKUP(H52,[1]SEMIELABORADOS!$A$2:$M$65536,12,0),"") -> 0.01122 | F52: =IFERROR(E52*C52,"") -> 0 | G52: =IFERROR(F52/$F$71,"") -> 0 | H52: 96344
A53: =+A44 -> 0 | B53: BRITTLE DE ALMENDRAS | C53: =+A53 -> 0 | D53: Gramo | E53: =+'costeo brittle'!E74 -> 0.5698132 | F53: =IFERROR(E53*C53,"") -> 0 | G53: =IFERROR(F53/$F$71,"") -> 0
A54: =+A45 -> 0 | B54: =IFERROR(VLOOKUP(H54,[1]SEMIELABORADOS!$A$2:$M$6000,2,0),"") | C54: =+A54 -> 0 | D54: =IFERROR(VLOOKUP(H54,[1]SEMIELABORADOS!$A$2:$M$6000,6,0),"") | E54: =IFERROR(VLOOKUP(H54,[1]SEMIELABORADOS!$A$2:$M$65536,12,0),"") | F54: =IFERROR(E54*C54,"") | G54: =IFERROR(F54/$F$71,"")
A55: =+A46 -> 0 | B55: =IFERROR(VLOOKUP(H55,[1]SEMIELABORADOS!$A$2:$M$6000,2,0),"") | C55: =+A55 -> 0 | D55: =IFERROR(VLOOKUP(H55,[1]SEMIELABORADOS!$A$2:$M$6000,6,0),"") | E55: =IFERROR(VLOOKUP(H55,[1]SEMIELABORADOS!$A$2:$M$65536,12,0),"") | F55: =IFERROR(E55*C55,"") | G55: =IFERROR(F55/$F$71,"")
A56: 1 | B56: MODI PREPARACION | C56: =+A56 -> 1 | D56: N/A | E56: =+F70 -> 275 | F56: =IFERROR(C56*E56,"") -> 275 | G56: =IFERROR(F56/$F$71,"") -> 0.09351693
B58: TOTAL MATERIA PRIMA | F58: =SUM(F8:F14,F17:F24) -> 2227.3038 | G58: =+F58/$F$71 -> 0.75742043 | H58: =+F58/$D$65 -> 2227.3038
B59: TOTAL EMPAQUE | F59: =SUM(F27:F37,F40:F46) -> 393.7941 | G59: =+F59/$F$71 -> 0.13391424 | H59: =+F59/$D$65 -> 393.7941 | K59: TOTAL MATERIA PRIMA + EMPAQUE | O59: =+F60 -> 2621.0979
B60: TOTAL MATERIAS P. + EMPAQUES | F60: =+F58+F59 -> 2621.0979 | G60: =+F60/$F$71 -> 0.89133466 | H60: =+F60/$D$65 -> 2621.0979 | L60: MODI PLANTA | O60: 508.47
C61: TOTAL MODI | F61: =SUM(F49:F56) -> 386.06712 | G61: =+F61/$F$71 -> 0.13128659 | H61: =+F61/$D$65 -> 386.06712 | M61: DESECHO | O61: =O59*N61 -> 0
M62: COSTO PLANTA | O62: =SUM(O59:O61) -> 3129.5679
B63: GRAMOS | D63: 950 | M63: GIF | O63: 426.95
B64: PESO POR UNIDAD | D64: 950 | M64: COSTO PLANTA | O64: =SUM(O62:O63) -> 3556.5179
B65: UNIDADES TOTALES | D65: =+D63/D64 -> 1 | L65: TRANSFERENCIA | N65: 0.1 | O65: =+O64*N65 -> 355.65179
B66: UNIDAD MEDIDA | D66: UND | K66: PRECIO DE VENTA PLANTA A LOCAL | O66: =+O65+O64 -> 3912.1697 | P66: GR
E67: S/ COSTO | F67: TOTAL | L67: UNIDAD | O67: =+O66/D65 -> 3912.1697 | P67: =+O67/D64 -> 4.1180734
B68: TOTAL MATERIAS P. + EMPAQUES | E68: =+F68/F68 -> 1 | F68: =SUM(F60) -> 2621.0979 | G68: =+F68/$F$71 -> 0.89133466
B69: DESECHOS Y PERDIDAS | E69: 0.02 | F69: =+F58*E69 -> 44.546077 | G69: =+F69/$F$71 -> 0.015148409 | O69: 3556.52
B70: MANO OBRA DIRECTA | D70: 5 | E70: 55 | F70: =+E70*D70 -> 275 | G70: =+F70/$F$71 -> 0.09351693
B71: TOTAL COSTO PLANTA | F71: =SUM(F68:F70) -> 2940.644 | G71: =+F71/$F$71 -> 1 | N71: =+O69*10% -> 355.652
N72: =3556.52+N71 -> 3912.172
B73: COSTO POR GRAMO
B74: TOTAL COSTO MATERIA PRIMA | C74: =+F58 -> 2227.3038 | D74: =+D63 -> 950 | E74: =+C74/D74 -> 2.3445304 | N74: Se le aumenta el 10 % costo por distribucion volumen GIF
B76: TOTAL COSTO UNIDAD MP+DESECHO+EMPAQUE | C76: =SUM(F68:F69) -> 2665.644 | D76: =+D63 -> 950 | E76: =+C76/D76 -> 2.8059411
B78: TOTAL MODI PREPARACION POR GRAMO | C78: =+F70 -> 275 | D78: =+D63 -> 950 | E78: =+C78/D78 -> 0.28947368
B79: TOTAL MODI POR GRAMO | C79: =+F61 -> 386.06712 | D79: =+D78 -> 950 | E79: =+C79/D79 -> 0.40638644
B81: TOTAL EMPAQUE POR GRAMO | C81: =+F59 -> 393.7941 | D81: =+D79 -> 950 | E81: =+C81/D81 -> 0.4145201
B83: TOTAL GRAMO MP+MODI | E83: =+E74+E79 -> 2.7509168
B85: COSTO POR UNIDAD
B86: TOTAL COSTO MATERIA PRIMA | C86: =+C74 -> 2227.3038 | D86: =+D65 -> 1 | E86: =+C86/D86 -> 2227.3038
B88: TOTAL COSTO UNIDAD MP+DESECHO+EMPAQUE | C88: =+C76 -> 2665.644 | D88: =+D65 -> 1 | E88: =+C88/D88 -> 2665.644
B90: TOTAL MODI POR GRAMO | C90: =+C78 -> 275 | D90: =+D65 -> 1 | E90: =+C90/D90 -> 275
B91: TOTAL MODI POR GRAMO | C91: =+C79 -> 386.06712 | D91: =+D90 -> 1 | E91: =+C91/D91 -> 386.06712

Sheet INS
B1: SERVICIOS DE PASTELERIA S.A. | G1: CÓDIGO
B2: INSTRUCTIVO | G2: REVISION
B3: Postre Cumbrel almendra | G3: FECHA APROBACION
B4: ELABORADO: | D4: Enmanuel Madrigal, Chef | F4: APROBADO: | G4: Yenny Castro Q, Calidad
A6: # Código | B6: Descrip. - Componentes | C6: ALÉRGENOS | D6: Cantidades | E6: Vida Útil | F6: Tipo Almacenamiento | G6: Tiempo Calentamiento
B7: Postre caramelo y almendras locales | D7: 1 ud | E7: Ver empaque | F7: Refrigeracion | G7: N.A.
B8: Empaque caramelo almendras 160g | D8: 1 bolsa -160g | E8: Ver empaque | F8: Refrigeracion | G8: N.A.
A13: 702182 | B13: ETIQUETA IMP. SPOON MEDIANA V-273 (UND) | D13: 1 | E13: ud | F13: N/A | G13: N/A
A16: 1. DIAGRAMA Y/O FOTOGRAFIA DE PRODUCTO
A18: PRESENTACIÓN SALON | E18: LLEVAR / DOMICILIO
A29: 2. DESCRIPCIÓN DE ACTIVIDADES
A30: 1, Colocar sobre el postre 1 bolsa del caramelo almendras, esparciendo sobre toda la superficie.
A31: 2, Se porciona en 6 porc.
A34: 3. ESPECIFICACIONES DEL PLATO
A35: Postre frio de queso relleno con caramelo, con caramelo crujiente de almendras

Sheet PRECIO 2
H1: TOTAL COSTO | I1: =+G51 -> 4719.1745
B5: ESTRUCTURA DE COSTOS
B6: LOCALES
G7: Fecha: | I7: =TODAY() -> 45754
B8: UNIDADES | C8: DESCRIPCION SEMIELABORADOS PLANTA | D8: UNIDADES | E8: UND MEDIDA | F8: COSTO UNITARIO | G8: TOTAL COSTO | H8: % PREC. DEFINIDO | I8: CODIGOS
B9: 1 | C9: POSTRE CARAMELO Y ALMENDRAS | D9: =+B9 -> 1 | E9: UND | F9: =+'COSTEO ENSAMBLE'!O67 -> 3912.1697 | G9: =IFERROR(D9*F9,"") -> 3912.1697 | H9: =IFERROR(G9/$G$53,"") -> 0.34137478
B10: 1 | C10: Bolsa Brittle 160 g | D10: =+B10 -> 1 | E10: UND | F10: =+'COSTO EMPAQUE BRITTLE'!O62 -> 691.90292 | G10: =IFERROR(D10*F10,"") -> 691.90292 | H10: =IFERROR(G10/$G$53,"") -> 0.060375245
C11: =VLOOKUP(I11,'[1]COMPRAS LOCALES'!$A$2:$F$380,2,0) -> #N/A | D11: =+B11 -> 0 | E11: =VLOOKUP(I11,'[1]COMPRAS LOCALES'!$A$2:$F$380,5,0) -> #N/A | F11: =VLOOKUP(I11,'[1]COMPRAS LOCALES'!$A$2:$F$380,6,0) -> #N/A | G11: =IFERROR(D11*F11,"") | H11: =IFERROR(G11/$G$53,"")
C12: =VLOOKUP(I12,'[1]COMPRAS LOCALES'!$A$2:$F$380,2,0) -> #N/A | D12: =+B12 -> 0 | E12: =VLOOKUP(I12,'[1]COMPRAS LOCALES'!$A$2:$F$380,5,0) -> #N/A | F12: =VLOOKUP(I12,'[1]COMPRAS LOCALES'!$A$2:$F$380,6,0) -> #N/A | G12: =IFERROR(D12*F12,"") | H12: =IFERROR(G12/$G$53,"")
C13: =VLOOKUP(I13,'[1]COMPRAS LOCALES'!$A$2:$F$380,2,0) -> #N/A | D13: =+B13 -> 0 | E13: =VLOOKUP(I13,'[1]COMPRAS LOCALES'!$A$2:$F$380,5,0) -> #N/A | F13: =VLOOKUP(I13,'[1]COMPRAS LOCALES'!$A$2:$F$380,6,0) -> #N/A | G13: =IFERROR(D13*F13,"") | H13: =IFERROR(G13/$G$53,"")
C14: =VLOOKUP(I14,'[1]COMPRAS LOCALES'!$A$2:$F$380,2,0) -> #N/A | D14: =+B14 -> 0 | E14: =VLOOKUP(I14,'[1]COMPRAS LOCALES'!$A$2:$F$380,5,0) -> #N/A | F14: =VLOOKUP(I14,'[1]COMPRAS LOCALES'!$A$2:$F$380,6,0) -> #N/A | G14: =IFERROR(D14*F14,"") | H14: =IFERROR(G14/$G$53,"")
B16: UNIDADES | C16: DESCRIPCION MAT.PRIMA LOCAL | D16: UNIDADES | E16: UND MEDIDA | F16: COSTO UNITARIO | G16: TOTAL COSTO | H16: % PREC. DEFINIDO | I16: CODIGOS
C17: =VLOOKUP(I17,'[1]COMPRAS LOCALES'!$A$2:$F$380,2,0) -> #N/A | D17: =+B17 -> 0 | E17: =VLOOKUP(I17,'[1]COMPRAS LOCALES'!$A$2:$F$380,5,0) -> #N/A | F17: =VLOOKUP(I17,'[1]COMPRAS LOCALES'!$A$2:$F$380,6,0) -> #N/A | G17: =IFERROR(D17*F17,"") | H17: =IFERROR(G17/$G$53,"")
C18: =VLOOKUP(I18,'[1]COMPRAS LOCALES'!$A$2:$F$380,2,0) -> #N/A | D18: =+B18 -> 0 | E18: =VLOOKUP(I18,'[1]COMPRAS LOCALES'!$A$2:$F$380,5,0) -> #N/A | F18: =VLOOKUP(I18,'[1]COMPRAS LOCALES'!$A$2:$F$380,6,0) -> #N/A | G18: =IFERROR(D18*F18,"") | H18: =IFERROR(G18/$G$53,"")
C19: =VLOOKUP(I19,'[1]COMPRAS LOCALES'!$A$2:$F$380,2,0) -> #N/A | D19: =+B19 -> 0 | E19: =VLOOKUP(I19,'[1]COMPRAS LOCALES'!$A$2:$F$380,5,0) -> #N/A | F19: =VLOOKUP(I19,'[1]COMPRAS LOCALES'!$A$2:$F$380,6,0) -> #N/A | G19: =IFERROR(D19*F19,"") | H19: =IFERROR(G19/$G$53,"")
C20: =VLOOKUP(I20,'[1]COMPRAS LOCALES'!$A$2:$F$380,2,0) -> #N/A | D20: =+B20 -> 0 | E20: =VLOOKUP(I20,'[1]COMPRAS LOCALES'!$A$2:$F$380,5,0) -> #N/A | F20: =VLOOKUP(I20,'[1]COMPRAS LOCALES'!$A$2:$F$380,6,0) -> #N/A | G20: =IFERROR(D20*F20,"") | H20: =IFERROR(G20/$G$53,"")
B22: UNIDAD | C22: EMPAQUE | D22: UNIDAD | E22: UND MEDIDA | F22: COSTO UNITARIO | G22: TOTAL COSTO | H22: % PREC. DEFINIDO | I22: CÓDIGOS
C23: DOMICILIO Y LLEVAR
B24: 0.55 | C24: =VLOOKUP(I24,'[4]COMPRAS LOCALES'!$A$1:$F$380,2,0) -> #N/A | D24: =+B24 -> 0.55 | E24: =VLOOKUP(I24,'[1]COMPRAS LOCALES'!$A$2:$F$380,5,0) -> #N/A | F24: =VLOOKUP(I24,'[1]COMPRAS LOCALES'!$A$2:$F$380,6,0) -> #N/A | G24: =IFERROR(F24*D24,"") | H24: =IFERROR(G24/$G$53,"")
B25: 0.55 | C25: =VLOOKUP(I25,'[4]COMPRAS LOCALES'!$A$1:$F$380,2,0) -> #N/A | D25: =+B25 -> 0.55 | E25: =VLOOKUP(I25,'[1]COMPRAS LOCALES'!$A$2:$F$380,5,0) -> #N/A | F25: =VLOOKUP(I25,'[1]COMPRAS LOCALES'!$A$2:$F$380,6,0) -> #N/A | G25: =IFERROR(F25*D25,"") | H25: =IFERROR(G25/$G$53,"")
B26: 0.55 | C26: =VLOOKUP(I26,'[4]COMPRAS LOCALES'!$A$1:$F$380,2,0) -> #N/A | D26: =+B26 -> 0.55 | E26: =VLOOKUP(I26,'[1]COMPRAS LOCALES'!$A$2:$F$380,5,0) -> #N/A | F26: =VLOOKUP(I26,'[1]COMPRAS LOCALES'!$A$2:$F$380,6,0) -> #N/A | G26: =IFERROR(F26*D26,"") | H26: =IFERROR(G26/$G$53,"")
B27: 0.55 | C27: =VLOOKUP(I27,'[4]COMPRAS LOCALES'!$A$1:$F$380,2,0) -> #N/A | D27: =+B27 -> 0.55 | E27: =VLOOKUP(I27,'[1]COMPRAS LOCALES'!$A$2:$F$380,5,0) -> #N/A | F27: =VLOOKUP(I27,'[1]COMPRAS LOCALES'!$A$2:$F$380,6,0) -> #N/A | G27: =IFERROR(F27*D27,"") | H27: =IFERROR(G27/$G$53,"")
B28: 0.55 | C28: =VLOOKUP(I28,'[4]COMPRAS LOCALES'!$A$1:$F$380,2,0) -> #N/A | D28: =+B28 -> 0.55 | E28: =VLOOKUP(I28,'[1]COMPRAS LOCALES'!$A$2:$F$380,5,0) -> #N/A | F28: =VLOOKUP(I28,'[1]COMPRAS LOCALES'!$A$2:$F$380,6,0) -> #N/A | G28: =IFERROR(F28*D28,"") | H28: =IFERROR(G28/$G$53,"")
B29: 0.55 | C29: =VLOOKUP(I29,'[4]COMPRAS LOCALES'!$A$1:$F$380,2,0) -> #N/A | D29: =+B29 -> 0.55 | E29: =VLOOKUP(I29,'[1]COMPRAS LOCALES'!$A$2:$F$380,5,0) -> #N/A | F29: =VLOOKUP(I29,'[1]COMPRAS LOCALES'!$A$2:$F$380,6,0) -> #N/A | G29: =IFERROR(F29*D29,"") | H29: =IFERROR(G29/$G$53,"")
B30: 0.55 | C30: =VLOOKUP(I30,'[4]COMPRAS LOCALES'!$A$1:$F$380,2,0) -> #N/A | D30: =+B30 -> 0.55 | E30: =VLOOKUP(I30,'[1]COMPRAS LOCALES'!$A$2:$F$380,5,0) -> #N/A | F30: =VLOOKUP(I30,'[1]COMPRAS LOCALES'!$A$2:$F$380,6,0) -> #N/A | G30: =IFERROR(F30*D30,"") | H30: =IFERROR(G30/$G$53,"")
B31: 0.55 | C31: =VLOOKUP(I31,'[4]COMPRAS LOCALES'!$A$1:$F$380,2,0) -> #N/A | D31: =+B31 -> 0.55 | E31: =VLOOKUP(I31,'[1]COMPRAS LOCALES'!$A$2:$F$380,5,0) -> #N/A | F31: =VLOOKUP(I31,'[1]COMPRAS LOCALES'!$A$2:$F$380,6,0) -> #N/A | G31: =IFERROR(F31*D31,"") | H31: =IFERROR(G31/$G$53,"")
C32: FOOD COURT
B33: 0.05 | C33: =IFERROR(VLOOKUP(I33,'[2]EMP LOCALES'!$A$2:$G$119,2,0),"") | D33: =+B33 -> 0.05 | E33: =IFERROR(VLOOKUP(I33,'[2]EMP LOCALES'!$A$2:$G$119,6,0),"") | F33: =IFERROR(VLOOKUP(I33,'[2]EMP LOCALES'!$A$2:$G$119,7,0),"") | G33: =IFERROR(F33*D33,"") | H33: =IFERROR(G33/$G$53,"")
B34: 0.05 | C34: =IFERROR(VLOOKUP(I34,'[2]EMP LOCALES'!$A$2:$G$119,2,0),"") | D34: =+B34 -> 0.05 | E34: =IFERROR(VLOOKUP(I34,'[2]EMP LOCALES'!$A$2:$G$119,6,0),"") | F34: =IFERROR(VLOOKUP(I34,'[2]EMP LOCALES'!$A$2:$G$119,7,0),"") | G34: =IFERROR(F34*D34,"") | H34: =IFERROR(G34/$G$53,"")
B35: 0.05 | C35: =IFERROR(VLOOKUP(I35,'[2]EMP LOCALES'!$A$2:$G$119,2,0),"") | D35: =+B35 -> 0.05 | E35: =IFERROR(VLOOKUP(I35,'[2]EMP LOCALES'!$A$2:$G$119,6,0),"") | F35: =IFERROR(VLOOKUP(I35,'[2]EMP LOCALES'!$A$2:$G$119,7,0),"") | G35: =IFERROR(F35*D35,"") | H35: =IFERROR(G35/$G$53,"")
B36: 0.05 | C36: =IFERROR(VLOOKUP(I36,'[2]EMP LOCALES'!$A$2:$G$119,2,0),"") | D36: =+B36 -> 0.05 | E36: =IFERROR(VLOOKUP(I36,'[2]EMP LOCALES'!$A$2:$G$119,6,0),"") | F36: =IFERROR(VLOOKUP(I36,'[2]EMP LOCALES'!$A$2:$G$119,7,0),"") | G36: =IFERROR(F36*D36,"") | H36: =IFERROR(G36/$G$53,"")
B37: 0.05 | C37: =IFERROR(VLOOKUP(I37,'[2]EMP LOCALES'!$A$2:$G$119,2,0),"") | D37: =+B37 -> 0.05 | E37: =IFERROR(VLOOKUP(I37,'[2]EMP LOCALES'!$A$2:$G$119,6,0),"") | F37: =IFERROR(VLOOKUP(I37,'[2]EMP LOCALES'!$A$2:$G$119,7,0),"") | G37: =IFERROR(F37*D37,"") | H37: =IFERROR(G37/$G$53,"")
B38: 0.05 | C38: =IFERROR(VLOOKUP(I38,'[2]EMP LOCALES'!$A$2:$G$119,2,0),"") | D38: =+B38 -> 0.05 | E38: =IFERROR(VLOOKUP(I38,'[2]EMP LOCALES'!$A$2:$G$119,6,0),"") | F38: =IFERROR(VLOOKUP(I38,'[2]EMP LOCALES'!$A$2:$G$119,7,0),"") | G38: =IFERROR(F38*D38,"") | H38: =IFERROR(G38/$G$53,"")
B40: TOTAL MATERIA PRIMA PLANTA | G40: =SUM(G9:G14) -> 4604.0726 | H40: =+G40/$G$53 -> 0.40175002
B41: TOTAL MATERIA PRIMA LOCAL | F41: =SUM(F17:F20) -> #N/A | G41: =SUM(G17:G20) -> 0 | H41: =+G41/$G$53 -> 0
B42: TOTAL MATERIA PRIMA | G42: =SUM(G40:G41) -> 4604.0726 | H42: =+G42/$G$53 -> 0.40175002
B43: TOTAL EMPAQUE | G43: =SUM(G24:G38) -> 0 | H43: =+G43/$G$53 -> 0
B44: TOTAL MATERIA PRIMA + EMPAQUE | G44: =SUM(G42:G43) -> 4604.0726 | H44: =+G44/$G$53 -> 0.40175002
B48: TOTAL MATERIA PRIMA | G48: =+G42 -> 4604.0726 | H48: =+G48/$G$53 -> 0.40175002
B49: EMPAQUE | F49: Local | G49: =+G43 -> 0 | H49: =+G49/$G$53 -> 0
B50: DESECHO | F50: 0.025 | G50: =+(G49+G48)*F50 -> 115.10182 | H50: =+G50/$G$53 -> 0.010043751
B51: COSTO TOTAL LOCAL | G51: =SUM(G48:G50) -> 4719.1745 | H51: =+G51/$G$53 -> 0.41179377
B52: MARK UP LOCAL | F52: 1.4284 | G52: =+G51*F52 -> 6740.8688
B53: PRECIO VENTA SIN IMP | G53: =SUM(G51:G52) -> 11460.043 | I53: =+I55/1.13 -> 11460.177 | J53: =+(I53-G51)/G51 -> 1.4284283
B54: PRECIO VENTA IVI | F54: 0.13 | G54: =+G53*(1+F54) -> 12949.849 | I54: =+I53*1.13 -> 12950
B55: PRECIO VENTA II | F55: 0.23 | G55: =+G53*(1+F55) -> 14095.853 | I55: 12950
A57: Esteban Ramírez S. / Costos

Sheet ENSAMBLE INDUSTRIA 
B1: SERVICIOS DE PASTELERIA S.A. | G1: CÓDIGO:
B2: ESPECIFICACION DE RECETA | G2: REVISIÓN:
B3: 30800096 Postre caramelo y almendras (dia de la madre 2021) INDUSTRIA | G3: FECHA DE APROBACIÓN:
B4: Elaborado | C4: Javier Tong, Chef
B5: Aprobado | C5: Esteban Cartin, Gte Manufactura
A7: AREA QUE PRODUCE: | C7: Postre | F7: AREA QUE EMPACA: | H7: Postre
A8: # Código | B8: Descripción del ingrediente | C8: Marca | D8: Unidad Internacional | F8: Medida alternativa | H8: Costo - Referencia
D9: Cantidad | E9: Unidad medida | F9: Cantidad | G9: Unidad medida | H9: Colones
A10: 907000002 | B10: BASE GALLETA P/CHEESE CAKE (KILO) | C10: FAS | D10: 200 | E10: g
A11: 90200029 | B11: RELLENO CHEESECAKE KILO | C11: FAS | D11: 300 | E11: g
A12: 410154 | B12: RELLENO CARAMELO (KILO) | C12: CONEXU | D12: 120 | E12: g
A13: 90200029 | B13: RELLENO CHEESECAKE KILO | C13: FAS | D13: 300 | E13: g
B14: DECORACION
A15: 901000111 | B15: GANACHE DE DULCE LECHE (4800g) | C15: FAS | D15: 90 | E15: g | F15: Espejo
A16: 902000116 | B16: BRITTLE DE ALMENDRAS | C16: FAS | D16: 160 | E16: g | F16: 3/4 tz
A17: 1112431 | B17: MANJAR LECHE CONDENSADA (PAQ: 4.5 K) | C17: NESTLE | D17: 20 | E17: g | F17: Para pegar
B18: EMPAQUE
A19: 702182 | B19: ETIQUETA IMP. SPOON MEDIANA V-273 (UND) | C19: ETIPLAST | D19: 1 | E19: ud
A20: 703020 | B20: CINTA ADHESIVA TRANSPARENT 2*100 M (UND) | C20: ETIPLAST | D20: 60 | E20: cm
A21: 1950693 | B21: ORLA CARTON 9" DORADA (UND ) | C21: RAPIBOX | D21: 1 | E21: ud
A22: 51400021 | B22: QUEQUERA RED C/BASE ALTA 9" (CAJA:100 U) | C22: Exp PMT | D22: 1 | E22: ud
A23: 702123 | B23: ETIQUETA BLANCA 2 5/8X1 15/16 (UND) | C23: Cemusa | D23: 1 | E23: ud
A24: 701096 | B24: ETIQUETA BLANCA R-153 (UND) | C24: Cemusa | D24: 1 | E24: ud
A25: 702007 | B25: ETIQ.FECHA VENCIMIENTO BLANCO (ROLLO) | C25: CEMUSA | D25: 1 | E25: ud
C27: Cantidad | D27: Unidad
A28: PESO TOTAL OBTENIDO | C28: 1000 | D28: g
A29: TIEMPO TOTAL DE PREPARACION | C29: 5 | D29: min
A30: CANTIDAD DE PORCIONES OBTENIDAS | C30: 1 | D30: ud
A31: PESO DE CADA PORCIÓN | C31: =+C28 -> 1000 | D31: g
A32: MERMA | C32: =SUM(D10:D18)-C28 -> 190 | D32: g
A33: PROCEDIMIENTO DE PREPARACION DE LA RECETA
A34: 1.- Colocar dentro del molde desarmable redondo 21 cm ,previamente ensagrasado la base de galleta presionar y hornear a 175°C por 7 min en el Argental, a 175°C por 8 min en el Dicte 1 y Dicte 2, a 170°C en el Dicte 3 y a 175°C por 7 min en el Marshal
A35: 2.- Una vez fria la galleta, dosificar en el molde 275g de mezcla de cheesecake, 120g de caramelo y 275g de mezcla de cheesecake. Dejar enfriar al menos 6 horas en Refrigeracion
A36: 3.- Desmoldar con ayuda de una espatula.
A37: 4.- Pegar a la orla con manjar, decorar con ganache en el hacinedo espejo y dejar chorrear. sobre este ganache colocar el brittle de almednras.
A38: 5.- Decorar con un corazon de chocolate, tapar y etiquetar

Sheet COSTO ENSAM IND
E1: Precio Local | F1: Costo MP | G1: Costo EM | H1: Costo MO
E2: =IFERROR(O67,"") -> 4405.5999 | F2: =IFERROR(H58,"") -> 2669.8227 | G2: =IFERROR(H59,"") -> 399.84816 | H2: =IFERROR(H61,"") -> 477.23723
A5: ESTRUCTURA DE COSTOS
F6: Fecha: | H6: =TODAY() -> 45754
A7: UNIDADES | B7: DESCRIPCION MAT.PRIMA | C7: UNIDADES | D7: UND MEDIDA | E7: COSTO UNITARIO | F7: TOTAL COSTO | G7: % PREC. DEFINIDO | H7: CODIGOS
A8: 120 | B8: =IFERROR(VLOOKUP(H8,'[1]Consolidado MP Planta'!$A$2:$M$823,3,0),"") -> RELLENO CARAMELO KILO | C8: =+A8 -> 120 | D8: =IFERROR(VLOOKUP(H8,'[1]Consolidado MP Planta'!$A$2:$M$823,13,0),"") -> Gramos | E8: =IFERROR(VLOOKUP(H8,'[1]Consolidado MP Planta'!$A$2:$M$823,12,0),"") -> 3.335 | F8: =IFERROR(C8*E8,"") -> 400.2 | G8: =IFERROR(F8/$F$71,"") -> 0.11777283 | H8: 0410154
B9: =IFERROR(VLOOKUP(H9,'[1]Consolidado MP Planta'!$A$2:$M$823,3,0),"") -> CHOCOLATE CORAZON ROJO PASION (CAJA:200) | C9: =+A9 -> 0 | D9: =IFERROR(VLOOKUP(H9,'[1]Consolidado MP Planta'!$A$2:$M$823,13,0),"") -> Und | E9: =IFERROR(VLOOKUP(H9,'[1]Consolidado MP Planta'!$A$2:$M$823,12,0),"") -> 38.25 | F9: =IFERROR(C9*E9,"") -> 0 | G9: =IFERROR(F9/$F$71,"") -> 0 | H9: 10700029
A10: 20 | B10: =IFERROR(VLOOKUP(H10,'[1]Consolidado MP Planta'!$A$2:$M$823,3,0),"") -> MANJAR LECHE CONDENSADA (PAQ: 4.5 K) | C10: =+A10 -> 20 | D10: =IFERROR(VLOOKUP(H10,'[1]Consolidado MP Planta'!$A$2:$M$823,13,0),"") -> Gramos | E10: =IFERROR(VLOOKUP(H10,'[1]Consolidado MP Planta'!$A$2:$M$823,12,0),"") -> 2.142 | F10: =IFERROR(C10*E10,"") -> 42.84 | G10: =IFERROR(F10/$F$71,"") -> 0.012607166 | H10: 1112431
B11: =IFERROR(VLOOKUP(H11,'[1]Consolidado MP Planta'!$A$2:$M$823,3,0),"") | C11: =+A11 -> 0 | D11: =IFERROR(VLOOKUP(H11,'[1]Consolidado MP Planta'!$A$2:$M$823,13,0),"") | E11: =IFERROR(VLOOKUP(H11,'[1]Consolidado MP Planta'!$A$2:$M$823,12,0),"") | F11: =IFERROR(C11*E11,"") | G11: =IFERROR(F11/$F$71,"")
B12: =IFERROR(VLOOKUP(H12,'[1]Consolidado MP Planta'!$A$2:$M$823,3,0),"") | C12: =+A12 -> 0 | D12: =IFERROR(VLOOKUP(H12,'[1]Consolidado MP Planta'!$A$2:$M$823,13,0),"") | E12: =IFERROR(VLOOKUP(H12,'[1]Consolidado MP Planta'!$A$2:$M$823,12,0),"") | F12: =IFERROR(C12*E12,"") | G12: =IFERROR(F12/$F$71,"")
B13: =IFERROR(VLOOKUP(H13,'[1]Consolidado MP Planta'!$A$2:$M$823,3,0),"") | C13: =+A13 -> 0 | D13: =IFERROR(VLOOKUP(H13,'[1]Consolidado MP Planta'!$A$2:$M$823,13,0),"") | E13: =IFERROR(VLOOKUP(H13,'[1]Consolidado MP Planta'!$A$2:$M$823,12,0),"") | F13: =IFERROR(C13*E13,"") | G13: =IFERROR(F13/$F$71,"")
B14: =IFERROR(VLOOKUP(H14,'[1]Consolidado MP Planta'!$A$2:$M$823,3,0),"") | C14: =+A14 -> 0 | D14: =IFERROR(VLOOKUP(H14,'[1]Consolidado MP Planta'!$A$2:$M$823,13,0),"") | E14: =IFERROR(VLOOKUP(H14,'[1]Consolidado MP Planta'!$A$2:$M$823,12,0),"") | F14: =IFERROR(C14*E14,"") | G14: =IFERROR(F14/$F$71,"")
B15: =IFERROR(VLOOKUP(H15,'[2]ARTICULOS MP PLANTA'!$A$2:$G$589,2,0),"")
A16: UNIDADES | B16: MATERIA PRIMA SEMIELABORADOS | C16: UNIDADES | D16: UND MEDIDA | E16: COSTO UNITARIO | F16: TOTAL COSTO | G16: % PREC. DEFINIDO | H16: CODIGOS
A17: 200 | B17: =IFERROR(VLOOKUP(H17,[1]SEMIELABORADOS!$A$2:$M$6000,2,0),"") -> BASE GALLETA P/CHEESE CAKE (KILO) | C17: =+A17 -> 200 | D17: =IFERROR(VLOOKUP(H17,[1]SEMIELABORADOS!$A$2:$M$6000,6,0),"") -> Gramo | E17: =IFERROR(VLOOKUP(H17,[1]SEMIELABORADOS!$A$2:$H$65536,8,0),"") -> 2.0071033 | F17: =IFERROR(E17*C17,"") -> 401.42065 | G17: =IFERROR(F17/$F$71,"") -> 0.11813205 | H17: 907000002
A18: 600 | B18: =IFERROR(VLOOKUP(H18,[1]SEMIELABORADOS!$A$2:$M$6000,2,0),"") -> RELLENO CHEESECAKE KILO | C18: =+A18 -> 600 | D18: =IFERROR(VLOOKUP(H18,[1]SEMIELABORADOS!$A$2:$M$6000,6,0),"") -> Gramo | E18: =IFERROR(VLOOKUP(H18,[1]SEMIELABORADOS!$A$2:$H$65536,8,0),"") -> 1.8699122 | F18: =IFERROR(E18*C18,"") -> 1121.9473 | G18: =IFERROR(F18/$F$71,"") -> 0.3301722 | H18: 90200029
A19: 90 | B19: GANACHE DE DULCE LECHE (4800g) | C19: =+A19 -> 90 | D19: Gramo | E19: =+'[3]COSTEO GANACHE'!$E$69 -> 2.8988426 | F19: =IFERROR(E19*C19,"") -> 260.89583 | G19: =IFERROR(F19/$F$71,"") -> 0.076777712 | H19: 901000111
A20: 0 | B20: =IFERROR(VLOOKUP(H20,[1]SEMIELABORADOS!$A$2:$M$6000,2,0),"") -> COCCION PICADILLO PLATANO CON CHORIZO KILO | C20: =+A20 -> 0 | D20: Gramo | E20: =+'[3]COSTEO GANACHE'!$E$69 -> 2.8988426 | F20: =IFERROR(E20*C20,"") -> 0 | G20: =IFERROR(F20/$F$71,"") -> 0 | H20: 901000112
A21: 160 | B21: BRITTLE DE ALMENDRAS | C21: =+A21 -> 160 | D21: Gramo | E21: =+'costeo brittle'!E69 -> 2.7657428 | F21: =IFERROR(E21*C21,"") -> 442.51886 | G21: =IFERROR(F21/$F$71,"") -> 0.13022663
B22: =IFERROR(VLOOKUP(H22,[1]SEMIELABORADOS!$A$2:$M$6000,2,0),"") | C22: =+A22 -> 0 | D22: =IFERROR(VLOOKUP(H22,[1]SEMIELABORADOS!$A$2:$M$6000,6,0),"") | E22: =IFERROR(VLOOKUP(H22,[1]SEMIELABORADOS!$A$2:$H$65536,8,0),"") | F22: =IFERROR(E22*C22,"") | G22: =IFERROR(F22/$F$71,"")
B23: =IFERROR(VLOOKUP(H23,[1]SEMIELABORADOS!$A$2:$M$6000,2,0),"") | C23: =+A23 -> 0 | D23: =IFERROR(VLOOKUP(H23,[1]SEMIELABORADOS!$A$2:$M$6000,6,0),"") | E23: =IFERROR(VLOOKUP(H23,[1]SEMIELABORADOS!$A$2:$H$65536,8,0),"") | F23: =IFERROR(E23*C23,"") | G23: =IFERROR(F23/$F$71,"")
B24: =IFERROR(VLOOKUP(H24,[1]SEMIELABORADOS!$A$2:$M$6000,2,0),"") | C24: =+A24 -> 0 | D24: =IFERROR(VLOOKUP(H24,[1]SEMIELABORADOS!$A$2:$M$6000,6,0),"") | E24: =IFERROR(VLOOKUP(H24,[1]SEMIELABORADOS!$A$2:$H$65536,8,0),"") | F24: =IFERROR(E24*C24,"") | G24: =IFERROR(F24/$F$71,"")
A26: UNIDADES | B26: EMPAQUE | C26: UNIDADES | D26: UND MEDIDA | E26: COSTO UNITARIO | F26: TOTAL COSTO | G26: % PREC. DEFINIDO | H26: CODIGOS
A27: 1 | B27: =IFERROR(VLOOKUP(H27,'[1]Consolidado MP Planta'!$A$2:$M$823,3,0),"") -> ETIQUETA IMP. SPOON MEDIANA V-273 (UND) | C27: =+A27 -> 1 | D27: =IFERROR(VLOOKUP(H27,'[1]Consolidado MP Planta'!$A$2:$M$823,13,0),"") -> Und | E27: =IFERROR(VLOOKUP(H27,'[1]Consolidado MP Planta'!$A$2:$M$823,12,0),"") -> 32.49 | F27: =IFERROR(C27*E27,"") -> 32.49 | G27: =IFERROR(F27/$F$71,"") -> 0.0095613174 | H27: 702182
A28: 60 | B28: =IFERROR(VLOOKUP(H28,'[1]Consolidado MP Planta'!$A$2:$M$823,3,0),"") -> CINTA ADHESIVA TRANSPARENT 2*100 M (UND) | C28: =+A28 -> 60 | D28: =IFERROR(VLOOKUP(H28,'[1]Consolidado MP Planta'!$A$2:$M$823,13,0),"") -> Cm | E28: =IFERROR(VLOOKUP(H28,'[1]Consolidado MP Planta'!$A$2:$M$823,12,0),"") -> 0.145 | F28: =IFERROR(C28*E28,"") -> 8.7 | G28: =IFERROR(F28/$F$71,"") -> 0.0025602789 | H28: 703020
A29: 1 | B29: =IFERROR(VLOOKUP(H29,'[1]Consolidado MP Planta'!$A$2:$M$823,3,0),"") -> ORLA #9 DORADA (UND) | C29: =+A29 -> 1 | D29: =IFERROR(VLOOKUP(H29,'[1]Consolidado MP Planta'!$A$2:$M$823,13,0),"") -> Und | E29: =IFERROR(VLOOKUP(H29,'[1]Consolidado MP Planta'!$A$2:$M$823,12,0),"") -> 105 | F29: =IFERROR(C29*E29,"") -> 105 | G29: =IFERROR(F29/$F$71,"") -> 0.030899918 | H29: 1950693
A30: 1 | B30: =IFERROR(VLOOKUP(H30,'[1]Consolidado MP Planta'!$A$2:$M$823,3,0),"") -> QUEQUERA RED C/BASE ALTA 9" (CAJA:100 U) | C30: =+A30 -> 1 | D30: =IFERROR(VLOOKUP(H30,'[1]Consolidado MP Planta'!$A$2:$M$823,13,0),"") -> Und | E30: =IFERROR(VLOOKUP(H30,'[1]Consolidado MP Planta'!$A$2:$M$823,12,0),"") -> 244.36 | F30: =IFERROR(C30*E30,"") -> 244.36 | G30: =IFERROR(F30/$F$71,"") -> 0.071911466 | H30: 51400021
A31: 1 | B31: =IFERROR(VLOOKUP(H31,'[1]Consolidado MP Planta'!$A$2:$M$823,3,0),"") -> ETIQUETA BLANCA 2 5/8X1 15/16 (UND) | C31: =+A31 -> 1 | D31: =IFERROR(VLOOKUP(H31,'[1]Consolidado MP Planta'!$A$2:$M$823,13,0),"") -> Und | E31: =IFERROR(VLOOKUP(H31,'[1]Consolidado MP Planta'!$A$2:$M$823,12,0),"") -> 2.128 | F31: =IFERROR(C31*E31,"") -> 2.128 | G31: =IFERROR(F31/$F$71,"") -> 0.00062623833 | H31: 0702123
A32: 1 | B32: =IFERROR(VLOOKUP(H32,'[1]Consolidado MP Planta'!$A$2:$M$823,3,0),"") -> ETIQUETA BLANCA R-153 (UND) | C32: =+A32 -> 1 | D32: =IFERROR(VLOOKUP(H32,'[1]Consolidado MP Planta'!$A$2:$M$823,13,0),"") -> Und | E32: =IFERROR(VLOOKUP(H32,'[1]Consolidado MP Planta'!$A$2:$M$823,12,0),"") -> 0.39 | F32: =IFERROR(C32*E32,"") -> 0.39 | G32: =IFERROR(F32/$F$71,"") -> 0.00011477112 | H32: 701096
A33: 1 | B33: =IFERROR(VLOOKUP(H33,'[1]Consolidado MP Planta'!$A$2:$M$823,3,0),"") -> ETIQ.FECHA VENCIMIENTO AMARILLO (ROLLO) | C33: =+A33 -> 1 | D33: =IFERROR(VLOOKUP(H33,'[1]Consolidado MP Planta'!$A$2:$M$823,13,0),"") -> Und | E33: =IFERROR(VLOOKUP(H33,'[1]Consolidado MP Planta'!$A$2:$M$823,12,0),"") -> 0.2 | F33: =IFERROR(C33*E33,"") -> 0.2 | G33: =IFERROR(F33/$F$71,"") -> 5.8856986e-05 | H33: 0702006
B34: =IFERROR(VLOOKUP(H34,'[1]Consolidado MP Planta'!$A$2:$M$823,3,0),"") | C34: =+A34 -> 0 | D34: =IFERROR(VLOOKUP(H34,'[1]Consolidado MP Planta'!$A$2:$M$823,13,0),"") | E34: =IFERROR(VLOOKUP(H34,'[1]Consolidado MP Planta'!$A$2:$M$823,12,0),"") | F34: =IFERROR(C34*E34,"") | G34: =IFERROR(F34/$F$71,"")
B35: =IFERROR(VLOOKUP(H35,'[1]Consolidado MP Planta'!$A$2:$M$823,3,0),"") | C35: =+A35 -> 0 | D35: =IFERROR(VLOOKUP(H35,'[1]Consolidado MP Planta'!$A$2:$M$823,13,0),"") | E35: =IFERROR(VLOOKUP(H35,'[1]Consolidado MP Planta'!$A$2:$M$823,12,0),"") | F35: =IFERROR(C35*E35,"") | G35: =IFERROR(F35/$F$71,"")
B36: =IFERROR(VLOOKUP(H36,'[1]Consolidado MP Planta'!$A$2:$M$823,3,0),"") | C36: =+A36 -> 0 | D36: =IFERROR(VLOOKUP(H36,'[1]Consolidado MP Planta'!$A$2:$M$823,13,0),"") | E36: =IFERROR(VLOOKUP(H36,'[1]Consolidado MP Planta'!$A$2:$M$823,12,0),"") | F36: =IFERROR(C36*E36,"") | G36: =IFERROR(F36/$F$71,"")
B37: =IFERROR(VLOOKUP(H37,'[1]Consolidado MP Planta'!$A$2:$M$823,3,0),"") | C37: =+A37 -> 0 | D37: =IFERROR(VLOOKUP(H37,'[1]Consolidado MP Planta'!$A$2:$M$823,13,0),"") | E37: =IFERROR(VLOOKUP(H37,'[1]Consolidado MP Planta'!$A$2:$M$823,12,0),"") | F37: =IFERROR(C37*E37,"") | G37: =IFERROR(F37/$F$71,"")
A39: UNIDADES | B39: EMPAQUE SEMIELABORADOS | C39: UNIDADES | D39: UND MEDIDA | E39: COSTO UNITARIO | F39: TOTAL COSTO | G39: % PREC. DEFINIDO | H39: CODIGOS
A40: =+A17 -> 200 | B40: =IFERROR(VLOOKUP(H40,[1]SEMIELABORADOS!$A$2:$M$6000,2,0),"") -> BASE GALLETA P/CHEESE CAKE (KILO) | C40: =+A40 -> 200 | D40: =IFERROR(VLOOKUP(H40,[1]SEMIELABORADOS!$A$2:$M$6000,6,0),"") -> Gramo | E40: =IFERROR(VLOOKUP(H40,[1]SEMIELABORADOS!$A$2:$M$65536,10,0),"") -> 0.0011524699 | F40: =IFERROR(E40*C40,"") -> 0.23049398 | G40: =IFERROR(F40/$F$71,"") -> 6.7830906e-05 | H40: 907000002
A41: =+A18 -> 600 | B41: =IFERROR(VLOOKUP(H41,[1]SEMIELABORADOS!$A$2:$M$6000,2,0),"") -> RELLENO CHEESECAKE KILO | C41: =+A41 -> 600 | D41: =IFERROR(VLOOKUP(H41,[1]SEMIELABORADOS!$A$2:$M$6000,6,0),"") -> Gramo | E41: =IFERROR(VLOOKUP(H41,[1]SEMIELABORADOS!$A$2:$M$65536,10,0),"") -> 7.4358974e-06 | F41: =IFERROR(E41*C41,"") -> 0.0044615385 | G41: =IFERROR(F41/$F$71,"") -> 1.3129635e-06 | H41: 90200029
A42: =+A19 -> 90 | B42: GANACHE DE DULCE LECHE (4800g) | C42: =+A42 -> 90 | D42: Gramo | E42: =+'[3]COSTEO GANACHE'!$E$76 -> 0.0032348958 | F42: =IFERROR(E42*C42,"") -> 0.29114063 | G42: =IFERROR(F42/$F$71,"") -> 8.5678299e-05 | H42: 901000111
A43: =+A20 -> 0 | B43: =IFERROR(VLOOKUP(H43,[1]SEMIELABORADOS!$A$2:$M$6000,2,0),"") -> CREMA DULCE LECHE KILO | C43: =+A43 -> 0 | D43: =IFERROR(VLOOKUP(H43,[1]SEMIELABORADOS!$A$2:$M$6000,6,0),"") -> Gramo | E43: =IFERROR(VLOOKUP(H43,[1]SEMIELABORADOS!$A$2:$M$65536,10,0),"") -> 8.512e-05 | F43: =IFERROR(E43*C43,"") -> 0 | G43: =IFERROR(F43/$F$71,"") -> 0 | H43: 96344
A44: =+A21 -> 160 | B44: BRITTLE DE ALMENDRAS | C44: =+A44 -> 160 | D44: Gramo | E44: =+'costeo brittle'!E76 -> 0.037837907 | F44: =IFERROR(E44*C44,"") -> 6.0540652 | G44: =IFERROR(F44/$F$71,"") -> 0.0017816201
A45: =+A22 -> 0 | B45: =IFERROR(VLOOKUP(H45,[1]SEMIELABORADOS!$A$2:$M$6000,2,0),"") | C45: =+A45 -> 0 | D45: =IFERROR(VLOOKUP(H45,[1]SEMIELABORADOS!$A$2:$M$6000,6,0),"") | E45: =IFERROR(VLOOKUP(H45,[1]SEMIELABORADOS!$A$2:$M$65536,10,0),"") | F45: =IFERROR(E45*C45,"") | G45: =IFERROR(F45/$F$71,"")
A46: =+A23 -> 0 | B46: =IFERROR(VLOOKUP(H46,[1]SEMIELABORADOS!$A$2:$M$6000,2,0),"") | C46: =+A46 -> 0 | D46: =IFERROR(VLOOKUP(H46,[1]SEMIELABORADOS!$A$2:$M$6000,6,0),"") | E46: =IFERROR(VLOOKUP(H46,[1]SEMIELABORADOS!$A$2:$M$65536,10,0),"") | F46: =IFERROR(E46*C46,"") | G46: =IFERROR(F46/$F$71,"")
A48: UNIDADES | B48: MODI | C48: UNIDADES | D48: UND MEDIDA | E48: COSTO UNITARIO | F48: TOTAL COSTO | G48: % PREC. DEFINIDO | H48: CODIGOS
A49: =+A40 -> 200 | B49: =IFERROR(VLOOKUP(H49,[1]SEMIELABORADOS!$A$2:$M$6000,2,0),"") -> BASE GALLETA P/CHEESE CAKE (KILO) | C49: =+A49 -> 200 | D49: =IFERROR(VLOOKUP(H49,[1]SEMIELABORADOS!$A$2:$M$6000,6,0),"") -> Gramo | E49: =IFERROR(VLOOKUP(H49,[1]SEMIELABORADOS!$A$2:$M$65536,12,0),"") -> 0.2087223 | F49: =IFERROR(E49*C49,"") -> 41.74446 | G49: =IFERROR(F49/$F$71,"") -> 0.012284765 | H49: 907000002
A50: =+A41 -> 600 | B50: =IFERROR(VLOOKUP(H50,[1]SEMIELABORADOS!$A$2:$M$6000,2,0),"") -> RELLENO CHEESECAKE KILO | C50: =+A50 -> 600 | D50: =IFERROR(VLOOKUP(H50,[1]SEMIELABORADOS!$A$2:$M$6000,6,0),"") -> Gramo | E50: =IFERROR(VLOOKUP(H50,[1]SEMIELABORADOS!$A$2:$M$65536,12,0),"") -> 0.098350267 | F50: =IFERROR(E50*C50,"") -> 59.01016 | G50: =IFERROR(F50/$F$71,"") -> 0.017365801 | H50: 90200029
A51: =+A42 -> 90 | B51: GANACHE DE DULCE LECHE (4800g) | C51: =+A51 -> 90 | D51: Gramo | E51: =+'[3]COSTEO GANACHE'!$E$74 -> 0.11458333 | F51: =IFERROR(E51*C51,"") -> 10.3125 | G51: =IFERROR(F51/$F$71,"") -> 0.0030348133 | H51: 901000111
A52: =+A43 -> 0 | B52: =IFERROR(VLOOKUP(H52,[1]SEMIELABORADOS!$A$2:$M$6000,2,0),"") -> CREMA DULCE LECHE KILO | C52: =+A52 -> 0 | D52: =IFERROR(VLOOKUP(H52,[1]SEMIELABORADOS!$A$2:$M$6000,6,0),"") -> Gramo | E52: =IFERROR(VLOOKUP(H52,[1]SEMIELABORADOS!$A$2:$M$65536,12,0),"") -> 0.01122 | F52: =IFERROR(E52*C52,"") -> 0 | G52: =IFERROR(F52/$F$71,"") -> 0 | H52: 96344
A53: =+A44 -> 160 | B53: BRITTLE DE ALMENDRAS | C53: =+A53 -> 160 | D53: Gramo | E53: =+'costeo brittle'!E74 -> 0.5698132 | F53: =IFERROR(E53*C53,"") -> 91.170112 | G53: =IFERROR(F53/$F$71,"") -> 0.02682999
A54: =+A45 -> 0 | B54: =IFERROR(VLOOKUP(H54,[1]SEMIELABORADOS!$A$2:$M$6000,2,0),"") | C54: =+A54 -> 0 | D54: =IFERROR(VLOOKUP(H54,[1]SEMIELABORADOS!$A$2:$M$6000,6,0),"") | E54: =IFERROR(VLOOKUP(H54,[1]SEMIELABORADOS!$A$2:$M$65536,12,0),"") | F54: =IFERROR(E54*C54,"") | G54: =IFERROR(F54/$F$71,"")
A55: =+A46 -> 0 | B55: =IFERROR(VLOOKUP(H55,[1]SEMIELABORADOS!$A$2:$M$6000,2,0),"") | C55: =+A55 -> 0 | D55: =IFERROR(VLOOKUP(H55,[1]SEMIELABORADOS!$A$2:$M$6000,6,0),"") | E55: =IFERROR(VLOOKUP(H55,[1]SEMIELABORADOS!$A$2:$M$65536,12,0),"") | F55: =IFERROR(E55*C55,"") | G55: =IFERROR(F55/$F$71,"")
A56: 1 | B56: MODI PREPARACION | C56: =+A56 -> 1 | D56: N/A | E56: =+F70 -> 275 | F56: =IFERROR(C56*E56,"") -> 275 | G56: =IFERROR(F56/$F$71,"") -> 0.080928356
B58: TOTAL MATERIA PRIMA | F58: =SUM(F8:F14,F17:F24) -> 2669.8227 | G58: =+F58/$F$71 -> 0.78568858 | H58: =+F58/$D$65 -> 2669.8227
B59: TOTAL EMPAQUE | F59: =SUM(F27:F37,F40:F46) -> 399.84816 | G59: =+F59/$F$71 -> 0.11766929 | H59: =+F59/$D$65 -> 399.84816 | K59: TOTAL MATERIA PRIMA + EMPAQUE | O59: =+F60 -> 3069.6709
B60: TOTAL MATERIAS P. + EMPAQUES | F60: =+F58+F59 -> 3069.6709 | G60: =+F60/$F$71 -> 0.90335787 | H60: =+F60/$D$65 -> 3069.6709 | L60: MODI PLANTA | O60: 508.47
C61: TOTAL MODI | F61: =SUM(F49:F56) -> 477.23723 | G61: =+F61/$F$71 -> 0.14044373 | H61: =+F61/$D$65 -> 477.23723 | M61: DESECHO | O61: =O59*N61 -> 0
M62: COSTO PLANTA | O62: =SUM(O59:O61) -> 3578.1409
B63: GRAMOS | D63: 950 | M63: GIF | O63: 426.95
B64: PESO POR UNIDAD | D64: 950 | M64: COSTO PLANTA | O64: =SUM(O62:O63) -> 4005.0909
B65: UNIDADES TOTALES | D65: =+D63/D64 -> 1 | L65: TRANSFERENCIA | N65: 0.1 | O65: =+O64*N65 -> 400.50909
B66: UNIDAD MEDIDA | D66: UND | K66: PRECIO DE VENTA PLANTA A LOCAL | O66: =+O64+O65 -> 4405.5999 | P66: GR
E67: S/ COSTO | F67: TOTAL | L67: UNIDAD | O67: =+O66/D65 -> 4405.5999 | P67: =+O67/D64 -> 4.6374736
B68: TOTAL MATERIAS P. + EMPAQUES | E68: =+F68/F68 -> 1 | F68: =SUM(F60) -> 3069.6709 | G68: =+F68/$F$71 -> 0.90335787
B69: DESECHOS Y PERDIDAS | E69: 0.02 | F69: =+F58*E69 -> 53.396454 | G69: =+F69/$F$71 -> 0.015713772 | O69: 3556.52
B70: MANO OBRA DIRECTA | D70: 5 | E70: 55 | F70: =+E70*D70 -> 275 | G70: =+F70/$F$71 -> 0.080928356
B71: TOTAL COSTO PLANTA | F71: =SUM(F68:F70) -> 3398.0673 | G71: =+F71/$F$71 -> 1 | N71: =+O69*10% -> 355.652
N72: =3501.27+N71 -> 3856.922
B73: COSTO POR GRAMO
B74: TOTAL COSTO MATERIA PRIMA | C74: =+F58 -> 2669.8227 | D74: =+D63 -> 950 | E74: =+C74/D74 -> 2.8103397 | N74: Se le aumenta el 10 % costo por distribucion volumen GIF
B76: TOTAL COSTO UNIDAD MP+DESECHO+EMPAQUE | C76: =SUM(F68:F69) -> 3123.0673 | D76: =+D63 -> 950 | E76: =+C76/D76 -> 3.2874393
B78: TOTAL MODI PREPARACION POR GRAMO | C78: =+F70 -> 275 | D78: =+D63 -> 950 | E78: =+C78/D78 -> 0.28947368
B79: TOTAL MODI POR GRAMO | C79: =+F61 -> 477.23723 | D79: =+D78 -> 950 | E79: =+C79/D79 -> 0.50235498
B81: TOTAL EMPAQUE POR GRAMO | C81: =+F59 -> 399.84816 | D81: =+D79 -> 950 | E81: =+C81/D81 -> 0.4208928
B83: TOTAL GRAMO MP+MODI | E83: =+E74+E79 -> 3.3126947
B85: COSTO POR UNIDAD
B86: TOTAL COSTO MATERIA PRIMA | C86: =+C74 -> 2669.8227 | D86: =+D65 -> 1 | E86: =+C86/D86 -> 2669.8227
B88: TOTAL COSTO UNIDAD MP+DESECHO+EMPAQUE | C88: =+C76 -> 3123.0673 | D88: =+D65 -> 1 | E88: =+C88/D88 -> 3123.0673
B90: TOTAL MODI POR GRAMO | C90: =+C78 -> 275 | D90: =+D65 -> 1 | E90: =+C90/D90 -> 275
B91: TOTAL MODI POR GRAMO | C91: =+C79 -> 477.23723 | D91: =+D90 -> 1 | E91: =+C91/D91 -> 477.23723

Sheet PRECIO INDUSTRIA 
B2: ESTRUCTURA DE COSTOS
B3: INDUSTRIA
F4: Fecha:
B5: UNIDAD | C5: DESCRIPCION MAT.PRIMA | D5: UNIDAD | E5: COSTO UNITARIO | F5: TOTAL COSTO | G5: % PREC. DEFINIDO | H5: CÓDIGOS
B6: 1 | C6: POSTRE CARAMELO Y ALMENDRAS | D6: =+B6 -> 1 | E6: =+'COSTO ENSAM IND'!H58 -> 2669.8227 | F6: =+D6*E6 -> 2669.8227 | G6: =+F6/$F$23 -> 0.60600661 | H6: SPOON
B8: UNIDAD | C8: EMPAQUE | D8: UNIDAD | E8: COSTO UNITARIO | F8: TOTAL COSTO | G8: % PREC. DEFINIDO | H8: CÓDIGOS
B9: 1 | C9: EMPAQUE PLANTA | D9: =+B9 -> 1 | E9: =+'COSTO ENSAM IND'!H59 -> 399.84816 | F9: =+D9*E9 -> 399.84816 | G9: =+F9/$F$23 -> 0.090759072 | H9: PLANTA
C11: TOTAL MATERIA PRIMA | F11: =SUM(F6) -> 2669.8227 | G11: =+F11/$F$23 -> 0.60600661
C12: TOTAL EMPAQUE | F12: =SUM(F9) -> 399.84816 | G12: =+F12/$F$23 -> 0.090759072
C13: TOTAL MATERIA PRIMA + EMPAQUE | F13: =SUM(F11:F12) -> 3069.6709 | G13: =+F13/$F$23 -> 0.69676568
B15: TOTAL MATERIA PRIMA + EMPAQUE | E15: Planta | F15: =+F13 -> 3069.6709 | G15: =+F15/$F$23 -> 0.69676568
C16: MODI PLANTA | F16: =+'COSTO ENSAM IND'!O60 -> 508.47 | G16: =+F16/$F$23 -> 0.11541447
C17: DESECHO | E17: 0 | F17: =+(F15+F16)*E17 -> 0 | G17: =+F17/$F$23 -> 0
C18: GAF | E18: 0 | F18: =+F16*E18 -> 0 | G18: =+F18/$F$23 -> 0
F19: =SUM(F15:F18) -> 3578.1409 | G19: =+F19/$F$21 -> 0.89339817
C20: GIF | F20: =+'COSTO ENSAM IND'!O63 -> 426.95 | G20: =+F20/$F$23 -> 0.096910751
C21: COSTO PLANTA | F21: =SUM(F19:F20) -> 4005.0909 | G21: =+F21/$F$23 -> 0.90909091
C22: VARIACION | E22: 0.1 | F22: =+F21*E22 -> 400.50909 | G22: =+F22/$F$23 -> 0.090909091
C23: PRECIO DE VENTA PLANTA A LOCAL | F23: =SUM(F21:F22) -> 4405.5999 | G23: =+F23/$F$23 -> 1
C27: PRECIO DE VENTA PLANTA A LOCAL | F27: =+F23 -> 4405.5999
C28: CAMIONES | D28: LOGISTICA | E28: 0.1 | F28: =+F27*E28 -> 440.55999 | G28: Costo | H28: % Margen
C29: COSTO TOTAL | F29: =SUM(F27:F28) -> 4846.1599 | G29: =+F29/$F$31 -> 0.8 | H29: =1-(F29/F31) -> 0.2
C30: MARK UP LOCAL | E30: 0.25 | F30: =+F29*E30 -> 1211.54
C31: PRECIO VENTA SIN IMP | F31: =SUM(F29:F30) -> 6057.6999
C32: PRECIO VENTA IVI | E32: 0.13 | F32: =+F31*(1+E32) -> 6845.2009
C34: MARGEN SUPERMERCADO | E34: 0.65 | F34: =+F31/0.65 -> 9319.5383
C35: PRECIO IVI | E35: 0.13 | F35: =+F34*1.13 -> 10531.078
A37: Esteban Ramírez S. / Costos

Sheet PRECIO
B2: ESTRUCTURA DE COSTOS
B3: LOCALES
F4: Fecha:
B5: UNIDAD | C5: DESCRIPCION MAT.PRIMA | D5: UNIDAD | E5: COSTO UNITARIO | F5: TOTAL COSTO | G5: % PREC. DEFINIDO | H5: CÓDIGOS
B6: 1 | D6: =+B6 -> 1 | F6: =+'COSTEO ENSAMBLE'!H58 -> 2227.3038 | G6: =+F6/$F$27 -> 0.50874916 | H6: SPOON
B8: UNIDAD | C8: EMPAQUE | D8: UNIDAD | E8: COSTO UNITARIO | F8: TOTAL COSTO | G8: % PREC. DEFINIDO | H8: CÓDIGOS
B9: 1 | C9: EMPAQUE PLANTA | D9: =+B9 -> 1 | F9: =+'COSTEO ENSAMBLE'!H59 -> 393.7941 | G9: =+F9/$F$27 -> 0.0899484 | H9: PLANTA
B10: 1 | C10: EMPAQUE LOCAL | D10: =SUM(D11:D13) -> 3 | E10: =SUM(E11:E13) -> 32.03876 | F10: =SUM(F11:F13) -> 19.855641 | G10: =+F10/$F$36 -> 0.0017325759 | H10: LOCAL
B11: 0.5 | C11: BOLSA IMP. SPOON CAMI 10* 20 | D11: =+B11 -> 0.5 | E11: 18.181818 | F11: =+E11*D11 -> 9.0909091 | G11: =+F11/$F$36 -> 0.00079326023 | H11: L1950709
B12: 0.5 | C12: BOLSA IMP. SPOON CAMI 8 * 16 | D12: =+B12 -> 0.5 | E12: 11.299435 | F12: =+E12*D12 -> 5.6497175 | G12: =+F12/$F$36 -> 0.00049298658 | H12: L1950703
B13: 2 | C13: SERVILLETA | D13: =+B13 -> 2 | E13: 2.5575071 | F13: =+E13*D13 -> 5.1150142 | G13: =+F13/$F$36 -> 0.00044632911 | H13: 1950785
C15: TOTAL MATERIA PRIMA | F15: =SUM(F6) -> 2227.3038 | G15: =+F15/$F$27 -> 0.50874916
C16: TOTAL EMPAQUE | F16: =SUM(F9) -> 393.7941 | G16: =+F16/$F$27 -> 0.0899484
C17: TOTAL MATERIA PRIMA + EMPAQUE | F17: =SUM(F15:F16) -> 2621.0979 | G17: =+F17/$F$27 -> 0.59869756
B19: TOTAL MATERIA PRIMA + EMPAQUE | E19: Planta | F19: =+F17 -> 2621.0979 | G19: =+F19/$F$27 -> 0.59869756
C20: MODI PLANTA | F20: =+'COSTEO ENSAMBLE'!O60 -> 508.47 | G20: =+F20/$F$27 -> 0.11614207
C21: DESECHO | E21: 0.01 | F21: =+(F19)*E21 -> 26.210979 | G21: =+F21/$F$27 -> 0.0059869756
C22: GAF | E22: 0 | F22: =+F20*E22 -> 0 | G22: =+F22/$F$27 -> 0
F23: =SUM(F19:F22) -> 3155.7789 | G23: =+F23/$F$27 -> 0.72082661
C24: % MK | F24: =+'COSTEO ENSAMBLE'!O63 -> 426.95 | G24: =+F24/$F$27 -> 0.097521699
C25: COSTO PLANTA | F25: =SUM(F23:F24) -> 3582.7289 | G25: =+F25/$F$27 -> 0.81834831
C26: TRANSFERENCIA | F26: =+F25*E26 -> 0 | G26: =+F26/$F$27 -> 0
C27: PRECIO DE VENTA PLANTA A LOCAL | F27: 4378 | G27: =+F27/$F$27 -> 1 | J27: 3979.99 | L27: Se le incrementa un 10 % por volumen
E28: PORC. | J28: =+J27*10% -> 397.999
J29: =+J27+J28 -> 4377.989
C31: PRECIO DE VENTA PLANTA A LOCAL | F31: =+F27 -> 4378 | G31: =+F31/$F$36 -> 0.38201826
C32: EMPAQUE | E32: Local | F32: =+F10 -> 19.855641 | G32: =+F32/$F$36 -> 0.0017325759
C33: DESECHO | E33: 0.025 | F33: =+(F32+F31)*E33 -> 109.94639 | G33: =+F33/$F$36 -> 0.009593771
C34: COSTO TOTAL LOCAL | F34: =SUM(F31:F33) -> 4507.802 | G34: =+F34/$F$36 -> 0.39334461
C35: MARK UP LOCAL | E35: 1.5423 | F35: =+F34*E35 -> 6952.3831
C36: PRECIO VENTA SIN IMP | F36: =SUM(F34:F35) -> 11460.185 | H36: =+H37/1.13 -> 11460.177 | I36: =+(H36-F34)/F34 -> 1.5422982
C37: PRECIO VENTA IVI | E37: 0.13 | F37: =+F36*(1+E37) -> 12950.009 | H37: 12950
B38: PRECIO VENTA II | E38: 0.23 | F38: =+F36*(1+E38) -> 14096.028
A40: Alejandro Rodriguez S. / Costos

Sheet Ensamble
B1: SERVICIOS DE PASTELERIA S.A. | G1: CÓDIGO:
B2: ESPECIFICACION DE RECETA | G2: REVISIÓN:
B3: Postre caramelo y almendras (dia de la madre 2021) | G3: FECHA DE APROBACIÓN:
B4: Elaborado | C4: Javier Tong, Chef
B5: Aprobado | C5: Esteban Cartin, Gte Manufactura
A7: AREA QUE PRODUCE: | F7: AREA QUE EMPACA:
A8: # Código | B8: Descripción del ingrediente | C8: Marca | D8: Unidad Internacional | F8: Medida alternativa | H8: Costo - Referencia
D9: Cantidad | E9: Unidad medida | F9: Cantidad | G9: Unidad medida | H9: Colones
A10: 907000002 | B10: BASE GALLETA P/CHEESE CAKE (KILO) | C10: FAS | D10: 200 | E10: g
A11: 90200029 | B11: RELLENO CHEESECAKE KILO | C11: FAS | D11: 275 | E11: g
A12: 410154 | B12: RELLENO CARAMELO (KILO) | C12: CONEXU | D12: 120 | E12: g
A13: 90200029 | B13: RELLENO CHEESECAKE KILO | C13: FAS | D13: 275 | E13: g
B14: DECORACION
A15: 901000111 | B15: GANACHE DE DULCE LECHE (4800g) | C15: FAS | D15: 55 | E15: g | F15: Bordes
A16: 910000016 | B16: CREMA BLANCA DULCE LECHE (KILO) | C16: FAS | D16: 100 | E16: g | F16: Colochos boq #22
A17: 901000111 | B17: GANACHE DE DULCE LECHE (4800g) | C17: FAS | D17: 20g | E17: g | F17: Centro
B18: BRITTLE DE ALMENDRAS | C18: FAS | D18: 100 | E18: g | F18: 1/2 tz
A19: 10700029 | B19: CHOCOLATE CORAZON ROJO PASION (CAJA:200) | C19: Karol | D19: 1 | E19: ud
A20: 1112431 | B20: MANJAR LECHE CONDENSADA (PAQ: 4.5 K) | C20: NESTLE | D20: 20 | E20: g | F20: Para pegar
B21: EMPAQUE
A22: 702182 | B22: ETIQUETA IMP. SPOON MEDIANA V-273 (UND) | C22: ETIPLAST | D22: 1 | E22: ud
A23: 703020 | B23: CINTA ADHESIVA TRANSPARENT 2*100 M (UND) | C23: ETIPLAST | D23: 60 | E23: cm
A24: 1950693 | B24: ORLA CARTON 9" DORADA (UND ) | C24: RAPIBOX | D24: 1 | E24: ud
A25: 51400021 | B25: QUEQUERA RED C/BASE ALTA 9" (CAJA:100 U) | C25: Exp PMT | D25: 1 | E25: ud
A26: 702123 | B26: ETIQUETA BLANCA 2 5/8X1 15/16 (UND) | C26: Cemusa | D26: 1 | E26: ud
A27: 701096 | B27: ETIQUETA BLANCA R-153 (UND) | C27: Cemusa | D27: 1 | E27: ud
A28: 702007 | B28: ETIQ.FECHA VENCIMIENTO BLANCO (ROLLO) | C28: CEMUSA | D28: 1 | E28: ud
C30: Cantidad | D30: Unidad
A31: PESO TOTAL OBTENIDO | C31: 2000 | D31: g
A32: TIEMPO TOTAL DE PREPARACION | C32: 20 | D32: min
A33: CANTIDAD DE PORCIONES OBTENIDAS | C33: 1 | D33: tanda
A34: PESO DE CADA PORCIÓN | C34: 2000 | D34: g
A35: MERMA | C35: =SUM(D10:D21)-C31 -> -854
A36: PROCEDIMIENTO DE PREPARACION DE LA RECETA
A37: 1.- Colocar dentro del molde desarmable redondo 21 cm ,previamente ensagrasado la base de galleta presionar y hornear a 175°C por 7 min en el Argental, a 175°C por 8 min en el Dicte 1 y Dicte 2, a 170°C en el Dicte 3 y a 175°C por 7 min en el Marshal
A38: 2.- Una vez fria la galleta, dosificar en el molde 275g de mezcla de cheesecake, 120g de caramelo y 275g de mezcla de cheesecake. Dejar enfriar al menos 6 horas en Refrigeracion
A39: 3.- Desmoldar con ayuda de una espatula.
A40: 4.- Pegar a la orla con manjar, decorar con ganache en el borde y dejar chorrear. Hacer colocho en el centro, rellenar con ganache el centro y sobre este ganache colocar el brittle de almednras.
A41: 5.- Decorar con un corazon de chocolate, tapar y etiquetar
